Workbook
Name 采光: 【1】定价因子!$D$45:$D$50
Name 床型: 【1】定价因子!$D$52:$D$57
Name 地铁站步行时间: 【1】定价因子!#REF!
Name 电梯房楼层: 【1】定价因子!$D$29:$D$37
Name 公区步行距离: 【1】定价因子!$D$2:$D$6
Name 功能: 【1】定价因子!$D$39:$D$44
Name 户型格局: 【1】定价因子!#REF!
Name 楼栋外观: 【1】定价因子!#REF!
Name 楼梯房楼层: 【1】定价因子!$D$19:$D$28
Name 套内空间: 【1】定价因子!$D$9:$D$13
Name 梯户比: 【1】定价因子!#REF!
Name 阳台: 【1】定价因子!$D$14:$D$18
Name 有无电梯: 【1】定价因子!$D$7:$D$8

Sheet 更新日志
B2: 版本号 | C2: 更新日期 | D2: 主要更新内容 | E2: 决议方式 | F2: 启用时间
B3: v1.0 | C3: 44036 | D3: 1. 创建了xlsx格式的模型，便于过程数据留存 | F3: 44039
B4: v1.01 | C4: 44056 | D4: 1. 优化了【楼栋公区距离】因子下的调价系数，使公区距离的影响力扩大，更符合市场需求； 2. 新增了定价模型的【更新日志】 | E4: 公寓例会 | F4: 44056
B5: v1.10 | C5: 44131 | D5: 1. 对各个格局的【套内空间】分档明确面积范围； 2. 【地铁站距离】测量方式改为步行时长（百度地图）； 3. 深化完善【户型】【功能】【采光】等因子各分档的标准描述，减小主观误差； | E5: 定价小组会议 | F5: 44132
B6: v1.11 | C6: 44281 | D6: 1. 更新了两个项目的基准价：元芬上早1468.41元，创业花园1763元，以及各个格局的基准价； 2. 删除“高架床/窄床开间”格局，使格局类型与实际业务名词体系一致，新增【床型】因子，用于描述不同床型对定价的影响； 3. 调整了【采光】【地铁站距离】【有无电梯】【楼层】【功能】因子的分档和系数； 4. 删除了【公交站距离】【噪音】【污染】【视野】等极少使用或影响力极小的因子； 5. 深化完善各个因子各分档的标准描述； | F6: 44287
B7: v1.12 | C7: 44670 | D7: 1.更新采光因素量化标准，并增加采光因素填写sheet，需填写房间窗户数量，根据楼间距填写遮挡信息 2.增加审批条件，整体均价≥模型均价，实际定价在模型价格的-5%~15%之间 | F7: 44670
B8: v2.2 | C8: 45127 | D8: 1.将很狭小的折价从0.91修正为0.9； 2.将较宽敞的溢价由1.05提高到1.06，很宽敞溢价由1.09提高到1.10； 3.将楼梯一层的折价由0.9，提高到0.91；将电梯一层的折价由0.85，提高到0.87； | F8: 45127
B9: v2.3 | C9: 45468 | D9: 1.增加房间面积，增加自动取值逻辑 | F9: 45468
B10: v2.4 | C10: 45482 | D10: 1.更新了一下村成本算法，增加自动取值逻辑 | F10: 45482
B11: V2.5 | C11: 45483 | D11: 增加二居室相关配置信息

Sheet 【1】定价因子
B1: 序号 | C1: 定价因子 | D1: 分档 | E1: 数列 | F1: 调价倍数 | G1: 备注 | L1: 项目基准价 | M1: =VLOOKUP('【2】运营中心填-基本信息&审核标准'!C2,[1]Sheet1!$E:$G,3,FALSE) -> 1612.1
A2: 基准格局定价因子 | B2: 1 | C2: 区位 | D2: 交通很便利 | E2: =$C$2&D2 -> 区位交通很便利 | F2: 1.04 | G2: 距离中心楼栋步行300米以上，且为方向交通更便利，如更靠近地铁，更靠近主干道 | I2: =J2*#REF!-J2 -> #REF! | J2: 1350 | L2: 基准格局 | M2: 套均价
D3: 交通较便利 | E3: =$C$2&D3 -> 区位交通较便利 | F3: 1.02 | G3: 距离中心楼栋步行150米以上，且为方向交通更便利，如更靠近地铁，更靠近主干道 | I3: =J3*#REF!-J3 -> #REF! | J3: 1350 | K3: 1 | L3: 开间 | M3: =$M$1*K3 -> 1612.1
D4: 中心位置 | E4: =$C$2&D4 -> 区位中心位置 | F4: 1 | G4: 在中心楼栋步行半径150米的位置范围内 | I4: =J4*F2-J4 -> 54 | J4: 1350 | K4: 1.5 | L4: 一居室 | M4: =VLOOKUP('【2】运营中心填-基本信息&审核标准'!C2,[1]Sheet1!$E:$H,4,FALSE) -> 2402.5
D5: 交通较不便 | E5: =$C$2&D5 -> 区位交通较不便 | F5: 0.98 | G5: 距离中心楼栋步行150米以上，且为方向交通更不便，如更远离地铁，距离村口位置更远 | I5: =J5*F3-J5 -> 27 | J5: 1350 | K5: 2 | L5: 二居室 | M5: =$M$1*K5 -> 3224.2
D6: 交通很不便 | E6: =$C$2&D6 -> 区位交通很不便 | F6: 0.96 | G6: 距离中心楼栋步行300米以上，且为方向交通更不便，如更远离地铁，距离村口位置更远 | I6: 100 | J6: 1350 | K6: 1 | L6: 轻复式 | M6: =$M$1*K6 -> 1612.1
B7: 2 | C7: 有无电梯 | D7: 有 | E7: =$C$7&D7 -> 有无电梯有 | F7: 1.05 | G7: 只比较楼梯4F和电梯4F | I7: 80 | J7: 1350 | K7: 1 | L7: 二人宿舍 | M7: =$M$1*K7 -> 1612.1
D8: 无 | E8: =$C$7&D8 -> 有无电梯无 | F8: 1 | I8: =J8*F6-J8 -> -54 | J8: 1350 | K8: 1.5 | L8: 四人宿舍 | M8: =M4 -> 2402.5
A9: 房间定价因子 | B9: 1 | C9: 套内空间 | D9: 很宽敞 | E9: =$C$9&D9 -> 套内空间很宽敞 | F9: 1.1 | G9: 权重：客厅>卧室>＞卫生间/洗漱区； 空间为住户实际使用感知的空间，如：（1）裸露地板的面积（2）床周边通行宽度（3）高架床、LOFT利用了立体空间，套内面积狭小但可能套内空间适中 | I9: =J9*F7-J9 -> 0 | K9: 2 | L9: 六人宿舍 | M9: =$M$1*K9 -> 3224.2
D10: 较宽敞 | E10: =$C$9&D10 -> 套内空间较宽敞 | F10: 1.06 | I10: =J10*F8-J10 -> 0 | K10: 2 | L10: 八人宿舍 | M10: =$M$1*K10 -> 3224.2
D11: 适中 | E11: =$C$9&D11 -> 套内空间适中 | F11: 1 | I11: =J11*#REF!-J11 -> #REF! | K11: 2 | L11: 二居轻复式 | M11: =$M$1*K11 -> 3224.2
D12: 较狭小 | E12: =$C$9&D12 -> 套内空间较狭小 | F12: 0.95 | I12: =J12*#REF!-J12 -> #REF!
D13: 很狭小 | E13: =$C$9&D13 -> 套内空间很狭小 | F13: 0.9 | I13: =J13*#REF!-J13 -> #REF!
B14: 3 | C14: 阳台 | I14: =J14*#REF!-J14 -> #REF!
D16: 有 | E16: =$C$14&D16 -> 阳台有 | F16: 1.07 | K16: 套内空间类型 | L16: 高架床/窄床 | M16: 正常开间 | N16: 正常一居室 | O16: 两居室
I17: =J17*F9-J17 -> 135 | J17: 1350 | K17: 很宽敞 | L17: >18 | M17: >20㎡ | N17: >28㎡ | O17: >45㎡
D18: 无 | E18: =$C$14&D18 -> 阳台无 | F18: 1 | I18: =J18*F10-J18 -> 81 | J18: 1350 | K18: 较宽敞 | L18: 15-18㎡ | M18: 17-20㎡ | N18: 26-28㎡ | O18: 40-45㎡
B19: 4 | C19: 楼梯房楼层 | D19: 无 | E19: =$C$19&D19 -> 楼梯房楼层无 | F19: 1 | G19: 不考虑采光和视野的差异 | I19: =J19*F11-J19 -> 0 | J19: 1350 | K19: 适中 | L19: 11-15㎡ | M19: 13-17㎡ | N19: 23-26㎡ | O19: 35-40㎡
D20: 1F | E20: =$C$19&D20 -> 楼梯房楼层1F | F20: 0.91 | I20: =J20*F12-J20 -> -67.5 | J20: 1350 | K20: 较狭小 | L20: 9-11㎡ | M20: 10-13㎡ | N20: 20-23㎡ | O20: 30-35㎡
D21: 2F | E21: =$C$19&D21 -> 楼梯房楼层2F | F21: 1.02 | I21: =J21*F13-J21 -> -135 | J21: 1350 | K21: 很狭小 | L21: <9㎡ | M21: <10㎡ | N21: <20㎡ | O21: <30㎡
D22: 3F | E22: =$C$19&D22 -> 楼梯房楼层3F | F22: 1.01 | I22: =J22*#REF!-J22 -> #REF! | J22: 1350
D23: 4F | E23: =$C$19&D23 -> 楼梯房楼层4F | F23: 1 | I23: =J23*#REF!-J23 -> #REF! | J23: 1350
D24: 5F | E24: =$C$19&D24 -> 楼梯房楼层5F | F24: 0.99 | I24: =J24*#REF!-J24 -> #REF! | J24: 1350
D25: 6F | E25: =$C$19&D25 -> 楼梯房楼层6F | F25: 0.98 | I25: =J25*#REF!-J25 -> #REF! | J25: 1350
D26: 7F | E26: =$C$19&D26 -> 楼梯房楼层7F | F26: 0.96 | I26: =J26*#REF!-J26 -> #REF! | J26: 1350
D27: 8F | E27: =$C$19&D27 -> 楼梯房楼层8F | F27: 0.93 | I27: =J27*F14-J27 -> -1350 | J27: 1350
D28: 9F | E28: =$C$19&D28 -> 楼梯房楼层9F | F28: 0.9 | I28: =J28*F15-J28 -> -1350 | J28: 1350
B29: 5 | C29: 电梯房楼层 | D29: 无 | E29: =$C$29&D29 -> 电梯房楼层无 | F29: 1 | I29: =J29*F16-J29 -> 94.5 | J29: 1350
D30: 1F | E30: =$C$29&D30 -> 电梯房楼层1F | F30: 0.87 | G30: 不考虑采光和视野的差异
D31: 2-3F | E31: =$C$29&D31 -> 电梯房楼层2-3F | F31: 0.99 | I31: =J31*F18-J31 -> 0
D32: 4F | E32: =$C$29&D32 -> 电梯房楼层4F | F32: 1 | I32: =1325*F19-1325 -> 0
D33: 5-6F | E33: =$C$29&D33 -> 电梯房楼层5-6F | F33: 1.01
D34: 7-8F | E34: =$C$29&D34 -> 电梯房楼层7-8F | F34: 1.02 | I34: =1325*F21-1325 -> 26.5
D35: 9-10F | E35: =$C$29&D35 -> 电梯房楼层9-10F | F35: 1.03 | I35: =1325*F22-1325 -> 13.25
D36: 11-12F | E36: =$C$29&D36 -> 电梯房楼层11-12F | F36: 1.04 | I36: =1325*F23-1325 -> 0
D37: 13以上F | E37: =$C$29&D37 -> 电梯房楼层13以上F | F37: 1.05 | I37: =1325*F24-1325 -> -13.25
B38: 6 | C38: 功能配置（开间） | D38: 缺失 | E38: =$C$38&D38 -> 功能配置（开间）缺失 | F38: 0.93
D39: 缺失（书桌） | E39: =$C$38&D39 -> 功能配置（开间）缺失（书桌） | F39: 0.98 | I39: =1325*F25-1325 -> -26.5
D40: 缺失（操作台） | E40: =$C$38&D40 -> 功能配置（开间）缺失（操作台） | F40: 0.96 | I40: =1325*F26-1325 -> -53
D41: 适中 | E41: =$C$38&D41 -> 功能配置（开间）适中 | F41: 1 | I41: =1325*F27-1325 -> -92.75
D42: 充足（油烟机/沙发） | E42: =$C$38&D42 -> 功能配置（开间）充足（油烟机/沙发） | F42: 1.04 | I42: =1325*F28-1325 -> -132.5
D43: 充足（单人沙发/餐桌椅） | E43: =$C$38&D43 -> 功能配置（开间）充足（单人沙发/餐桌椅） | F43: 1.03
D44: 非常充足 | E44: =$C$38&D44 -> 功能配置（开间）非常充足 | F44: 1.06 | I44: =1325*F30-1325 -> -172.25
B45: 7 | C45: 采光 | I45: =1325*F31-1325 -> -13.25
D46: 5 | E46: =$C$45&D46 -> 采光5 | F46: 1.06 | G46: 根据采光模型
D47: 4 | E47: =$C$45&D47 -> 采光4 | F47: 1.03
D48: 3 | E48: =$C$45&D48 -> 采光3 | F48: 1 | I48: =1325*F34-1325 -> 26.5
D49: 2 | E49: =$C$45&D49 -> 采光2 | F49: 0.96 | I49: =1325*F35-1325 -> 39.75
D50: 1 | E50: =$C$45&D50 -> 采光1 | F50: 0.91 | I50: =1325*F36-1325 -> 53
B51: 8 | C51: 功能配置（一居） | D51: 缺失 | E51: =$C$51&D51 -> 功能配置（一居）缺失 | F51: 0.93
D52: 缺失（操作台/双人沙发） | E52: =$C$51&D52 -> 功能配置（一居）缺失（操作台/双人沙发） | F52: 0.96 | K52: 各格局功能分档说明 | L52: 开间（含窄床） | M52: 正常一居室 | N52: 两居室
D53: 缺失（餐桌） | E53: =$C$51&D53 -> 功能配置（一居）缺失（餐桌） | F53: 0.98 | I53: =J53*F39-J53 -> -27 | J53: 1350 | K53: 缺失 | L53: 无操作台或无书桌 | M53: 沙发/餐桌/操作台任意缺一 | N53: 缺失沙发、餐桌、操作台
D54: 适中 | E54: =$C$51&D54 -> 功能配置（一居）适中 | F54: 1 | K54: 适中 | L54: 操作台+书桌 | M54: 沙发+餐桌+操作台 | N54: 沙发+4人餐桌+操作台+电视柜
D55: 充配（书桌） | E55: =$C$51&D55 -> 功能配置（一居）充配（书桌） | F55: 1.02 | I55: =J55*F41-J55 -> 0 | J55: 1350 | K55: 充足 | L55: 操作台+书桌+沙发/餐桌 | M55: 沙发+餐桌+操作台+电视柜/卧室书桌 | N55: 客厅（沙发、4人餐桌、茶几、电视柜、油烟机/冰箱）
D56: 充配（油烟机） | E56: =$C$51&D56 -> 功能配置（一居）充配（油烟机） | F56: 1.04 | I56: =J56*F42-J56 -> 54 | J56: 1350 | K56: 非常充足 | L56: 操作台+书桌+沙发+餐桌 | M56: 沙发+餐桌+操作台+厨房（含油烟机） | N56: 充足+油烟机+冰箱
D57: 非常充配 | E57: =$C$51&D57 -> 功能配置（一居）非常充配 | F57: 1.06
B58: 9 | C58: 功能配置（二居） | D58: 缺失 | E58: =$C$58&D58 -> 功能配置（二居）缺失 | F58: 0.93
D59: 缺失（沙发/餐桌） | E59: =$C$58&D59 -> 功能配置（二居）缺失（沙发/餐桌） | F59: 0.96
D60: 缺失（电视柜/操作台） | E60: =$C$58&D60 -> 功能配置（二居）缺失（电视柜/操作台） | F60: 0.98
D61: 适中 | E61: =$C$58&D61 -> 功能配置（二居）适中 | F61: 1
D62: 充配（油烟机/冰箱） | E62: =$C$58&D62 -> 功能配置（二居）充配（油烟机/冰箱） | F62: 1.04
D63: 非常充配 | E63: =$C$58&D63 -> 功能配置（二居）非常充配 | F63: 1.06
C64: 公交站步行距离 | D64: <0.5km | F64: 1 | H64: 从定价因子中剔除，正常收集标签
D65: 0.5~1km | F65: 0.975 | H65: 从定价因子中剔除，正常收集标签 | I65: =J65*F45-J65 -> -1350 | J65: 1350
D66: 1~1.5km | F66: 0.95 | H66: 从定价因子中剔除，正常收集标签 | I66: =J66*F46-J66 -> 81 | J66: 1350
D67: >1.5km | F67: 0.91 | H67: 从定价因子中剔除，正常收集标签 | I67: =J67*F47-J67 -> 40.5 | J67: 1350
C68: 视野 | D68: 很好 | F68: 1.045 | G68: 如：窗前有水景、山景、花园等 | H68: 从定价因子中剔除，正常收集标签 | I68: =J68*F48-J68 -> 0 | J68: 1350
D69: 较好 | F69: 1.02 | G69: 如：视野开阔，无遮挡 | H69: 从定价因子中剔除，正常收集标签 | I69: =J69*F49-J69 -> -54 | J69: 1350
D70: 适中 | F70: 1 | G70: 看的是邻栋楼 | H70: 从定价因子中剔除，正常收集标签
D71: 差 | F71: 0.95 | G71: 如：窗前有垃圾站、烂尾建筑等 | H71: 从定价因子中剔除，正常收集标签 | I71: =J71*F52-J71 -> -58 | J71: 1450
C72: 噪音影响度 | D72: 无 | F72: 1 | G72: 如：马路行车、商业喧嚣等（主要考虑噪音发生时间是否客户经常在家，如：早晨、夜间、周末；相邻马路车流量、隔音情况等） | H72: 从定价因子中剔除，正常收集标签 | I72: =J72*F53-J72 -> -29 | J72: 1450
D73: 小 | F73: 0.975 | H73: 从定价因子中剔除，正常收集标签 | I73: =J73*F54-J73 -> 0 | J73: 1450
D74: 中 | F74: 0.95 | H74: 从定价因子中剔除，正常收集标签
D75: 大 | F75: 0.91 | H75: 从定价因子中剔除，正常收集标签
C76: 污染 | D76: 无 | F76: 1 | G76: 如:臭气等 | H76: 从定价因子中剔除，正常收集标签 | I76: =J76*F57-J76 -> 180 | J76: 3000
D77: 小 | F77: 0.975 | H77: 从定价因子中剔除，正常收集标签
D78: 中 | F78: 0.945 | H78: 从定价因子中剔除，正常收集标签
D79: 大 | F79: 0.9 | H79: 从定价因子中剔除，正常收集标签
I85: =J85*F72-J85 -> 0
I86: =J86*F73-J86 -> 0
I87: =J87*F74-J87 -> 0
I88: =J88*F75-J88 -> 0
I89: =J89*F76-J89 -> 0
I90: =J90*F77-J90 -> 0
I91: =J91*F78-J91 -> 0
I92: =J92*F79-J92 -> 0

Sheet 各村基准价
A1: 村 | B1: 开间 | C1: 一居室
A2: 马蹄山村 | B2: 2075.1 | C2: 2847.2
A3: 禾坪岗村 | B3: 2080.7 | C3: 2851.9
A4: 中心围村 | B4: 2075.2 | C4: 2847.3
A5: 白石龙老村 | B5: 2200.7 | C5: 2945.6
A6: 东边新村 | B6: 1889.9 | C6: 2669.3
A7: 陶吓新村 | B7: 1585.3 | C7: 2353.9
A8: 元芬新村 | B8: 1707.9 | C8: 2486.2
A9: 塘水围二区 | B9: 1943.3 | C9: 2720.1
A10: 三合华侨新村 | B10: 1530.2 | C10: 2292.2
A11: 谭罗华侨新村 | B11: 1530.7 | C11: 2292.8
A12: 下早新村 | B12: 1624.6 | C12: 2397.1
A13: 赤岭头村 | B13: 1748.1 | C13: 2528
... A88: 74区布心二村 | B88: 2306.2 | C88: 3032.4

Sheet piovt_各村均价
C3: 成本 | E3: 实际
B4: 村 | C4: 收楼坪效 | D4: 标准成本坪效 | E4: 挂牌坪效 | F4: 签约坪效 | G4: 总面积
B5: 31区水口花园 | C5: 76.488565 | D5: 84.393728 | E5: 114.57053 | G5: 893.31 | H5: =C5*G5 -> 68328
B6: 坳下村 | C6: 62.262344 | D6: 104.98889 | E6: 95.122886 | G6: 4959.9 | H6: =C6*G6 -> 308815
B7: 白石龙二区 | C7: 59.762105 | D7: 79.955556 | E7: 102.00649 | G7: 832.3 | H7: =C7*G7 -> 49740
B8: 白石龙老村 | C8: 58.724033 | D8: 79.2 | E8: 91.136763 | G8: 10909.22 | H8: =C8*G8 -> 640633.4
B9: 白石龙一区 | C9: 60.200836 | E9: 109.89186 | G9: 1100.4 | H9: =C9*G9 -> 66245
B10: 宝安永丰八区 | C10: 86.996901 | E10: 118.2469 | G10: 968 | H10: =C10*G10 -> 84213
B11: 赤岭头新村 | C11: 47.829279 | E11: 82.290041 | G11: 1089.5 | H11: =C11*G11 -> 52110
B12: 东边坑 | C12: 31.947913 | E12: 60.09364 | G12: 1025.2 | H12: =C12*G12 -> 32753
B13: 东边新村 | C13: 59.711601 | E13: 91.020319 | G13: 915.4 | H13: =C13*G13 -> 54660
B14: 东方二街 | C14: 28.062348 | E14: 52.03701 | G14: 2487.96 | H14: =C14*G14 -> 69818
B15: 福围广生 | C15: 51.940645 | E15: 77.358156 | G15: 2540.65 | H15: =C15*G15 -> 131963
B16: 福永新村 | C16: 46.077623 | E16: 73.4127 | G16: 2825.71 | H16: =C16*G16 -> 130202
B17: 弓村 | C17: 44.838467 | E17: 79.876688 | G17: 3584.4 | H17: =C17*G17 -> 160719
B18: 和顺新村 | C18: 38.974508 | E18: 64.761258 | G18: 1545.6 | H18: =C18*G18 -> 60239
B19: 后瑞村 | C19: 53.272104 | E19: 83.713307 | G19: 338.62 | H19: =C19*G19 -> 18039
B20: 后亭村 | C20: 32.113961 | E20: 63.069143 | G20: 1512.8 | H20: =C20*G20 -> 48582
... B39: 元芬新村 | C39: 43.566971 | E39: 86.429829 | G39: 624.9 | H39: =C39*G39 -> 27225

Sheet 【2】运营中心填-基本信息&审核标准
B2: 小区（村） | C2: 福围村 | D2: 楼栋号 | E2: 福围广生1-41栋
B3: 楼栋基本画像 | C3: 屋面晾晒区 | D3: 电梯 | E3: 格局 | F3: 公寓楼层 | G3: 总销售单元数 | H3: 标准层单元数 | I3: 开间均价 | J3: 一居均价 | K3: 单元均价 | L3: 开间均面积 | M3: 一居室均面积 | N3: 标准层面积 | O3: 公寓面积 | P3: 月租金 | Q3: 村公寓面积
C4: 是 | D4: 否 | E4: {=_xlfn.TEXTJOIN("&",TRUE,_xlfn._xlws.FILTER('【3-2】大区&运营中心填-房间模型价'!K2:K10,'【3-2】大区&运营中心填-房间模型价'!K2:K10<>""))} -> 开间&一居室 | F4: {=INT(LOOKUP(2,1/(NOT(ISBLANK('【3-2】大区&运营中心填-房间模型价'!H:H))),'【3-2】大区&运营中心填-房间模型价'!H:H)/100)} -> 6 | G4: =SUMPRODUCT(('【3-2】大区&运营中心填-房间模型价'!J:J="开间")*1+('【3-2】大区&运营中心填-房间模型价'!J:J="二人宿舍")*1+('【3-2】大区&运营中心填-房间模型价'!J:J="一居室")*1.5+('【3-2】大区&运营中心填-房间模型价'!J:J="四人宿舍")*1.5+('【3-2】大区&运营中心填-房间模型价'!J:J="二居室")*2+('【3-2】大区&运营中心填-房间模型价'!J:J="六人宿舍")*2) -> 23.5 | H4: ='【3-2】大区&运营中心填-房间模型价'!G2 -> 4 | I4: =AVERAGEIF('【3-2】大区&运营中心填-房间模型价'!J:J,"开间",'【3-2】大区&运营中心填-房间模型价'!AE:AE) -> 1176.34 | J4: =AVERAGEIF('【3-2】大区&运营中心填-房间模型价'!J:J,"一居室",'【3-2】大区&运营中心填-房间模型价'!AE:AE) -> 1765.6667 | K4: =SUMIF('【3-2】大区&运营中心填-房间模型价'!A:A,E2,'【3-2】大区&运营中心填-房间模型价'!AE:AE)/G4 -> 1176.783 | L4: =AVERAGEIF('【3-2】大区&运营中心填-房间模型价'!J:J,"开间",'【3-2】大区&运营中心填-房间模型价'!N:N) -> 13.475 | M4: =AVERAGEIF('【3-2】大区&运营中心填-房间模型价'!J:J,"一居室",'【3-2】大区&运营中心填-房间模型价'!N:N) -> 22.152222 | N4: 99.2 | O4: 522.39 | P4: 27617 | Q4: =VLOOKUP(C2,piovt_各村均价!B:G,6,0) -> #N/A
B7: 审批标准
B8: 成本线指标 | C8: 楼栋成本线 | D8: 收楼成本单价 | E8: 成本标准单价 | F8: 定价坪效 | G8: 收楼溢价率 | H8: 成本溢价率 | I8: check
D9: =P4/O4 -> 52.866632 | E9: =(D9+13)/0.9 -> 73.185147 | F9: =SUMIF('【3-2】大区&运营中心填-房间模型价'!A:A,E2,'【3-2】大区&运营中心填-房间模型价'!AE:AE)/O4 -> 52.938226 | G9: =F9/D9 -> 1.0013542 | H9: =F9/E9 -> 0.72334659 | I9: =IF(H9<1,"不通过","通过") -> 不通过
C11: 村成本线 | D11: 收楼成本均价 | E11: 成本标准均价 | F11: 项目整体定价坪效 | G11: 收楼溢价率 | H11: 成本溢价率 | I11: check
D12: =D9 -> 52.866632 | E12: =(D12+13)/0.9 -> 73.185147 | F12: =F9 -> 52.938226 | G12: =F12/D12 -> 1.0013542 | H12: =F12/E12 -> 0.72334659 | I12: =IF(H12<1.05,"不通过","通过") -> 不通过
B15: 竞争线指标 | C15: 村竞争线 | D15: 项目 | E15: 标签属性 | J15: 挂牌均价 | K15: 签约均价 | L15: 本楼栋同标签定价均价 | M15: check
M17: =L17/J17 -> #DIV/0!
M18: =L18/J18 -> #DIV/0!
M19: =L19/J19 -> #DIV/0!
B21: 模型线指标 | C21: 房间模型线 | D21: 房间偏差最小值 | E21: 房间偏差最大值 | F21: check
D22: =MIN('【3-2】大区&运营中心填-房间模型价'!AF:AF) -> -0.17094576 | E22: =MAX('【3-2】大区&运营中心填-房间模型价'!AF:AF) -> 0.091447371 | F22: =IF(OR(D22<-10%,E22>10%),"不通过","通过") -> 不通过
C25: 楼栋模型线 | D25: 模型均价 | E25: 定价均价 | F25: check
D26: =AVERAGE('【3-2】大区&运营中心填-房间模型价'!AD:AD) -> 1494.7989 | E26: =AVERAGE('【3-2】大区&运营中心填-房间模型价'!AE:AE) -> 1455.4947 | F26: =E26/D26 -> 0.97370605

Sheet 【1】楼栋基本信息
B2: 楼栋号： | C2: A28栋
B3: 房源基本画像 | C3: 电梯 | D3: 公区 | E3: 格局
C4: 无 | D4: 无 | E4: 开间&一居室
B6: 公寓楼层 | C6: 总销售单元数 | D6: 标准层单元数 | E6: 开间均价 | F6: 一居均价 | G6: 单元均价 | H6: 标准层面积 | I6: 公寓面积 | J6: 模型均价
B7: 5 | C7: 34 | D7: 7.5 | E7: =AVERAGEIF('【3-2】大区&运营中心填-房间模型价'!J:J,"开间",'【3-2】大区&运营中心填-房间模型价'!AE:AE) -> 1176.34 | F7: =AVERAGEIF('【3-2】大区&运营中心填-房间模型价'!J:J,"一居室",'【3-2】大区&运营中心填-房间模型价'!AE:AE) -> 1765.6667 | G7: 1681.0588 | H7: 135.73 | I7: 662 | J7: =SUMIF('【3-2】大区&运营中心填-房间模型价'!A:A,C2,'【3-2】大区&运营中心填-房间模型价'!AD:AD)/C7 -> 0
C9: 收楼-楼梯（元/㎡） | D9: 收楼-电梯(元/㎡） | E9: 成本坪效 （含建设按出租率96%） | F9: 定价坪效 | G9: 收楼溢价率 | H9: 成本溢价率
B10: 坪效 | C10: 45 | D10: 55 | E10: =(C10+21)/0.96 -> 68.75 | F10: =SUMIF('【3-2】大区&运营中心填-房间模型价'!A:A,C2,'【3-2】大区&运营中心填-房间模型价'!AE:AE)/I7 -> 0 | G10: =F10/C10 -> 0 | H10: =F10/E10 -> 0
B11: 备注 | C11: 成本坪效=（收入成本+建设成本）/ 96%
B12: 项目 | C12: 属性 | G12: 挂牌价 | H12: 同房型对比
B13: 元芬村 | C13: 10-15平 | D13: 标配 | E13: 无电梯 | F13: 无阳台 | G13: 1533 | H13: =E7/G13 -> 0.76734508
B14: 元芬村 | C14: 15-20平 | D14: 标配 | E14: 无电梯 | F14: 无阳台 | G14: 1619 | H14: =E7/G14 -> 0.72658431
B15: 元芬村 | C15: 20-25平 | D15: 标配 | E15: 无电梯 | F15: 无阳台 | G15: 2202 | H15: =F7/G15 -> 0.80184681
C21: 成本线 | D21: 单楼栋
D22: 全项目

Sheet 项目基准价
A1: 项目 | B1: 单位 | C1: 数值
A2: 租金成本坪效 | B2: 元/㎡/月 | C2: 46.3
A3: 单元平均面积 | B3: ㎡/单元 | C3: 18.9
A4: 单位面积装修成本 | B4: 元/㎡ | C4: 2500
A5: 装修线性折旧年限 | B5: 年 | C5: 10
A6: 稳定出租率 | B6: % | C6: 0.98
A7: 成本法基准价 | B7: 元/单元/月 | C7: =(C2*C3+C4*C3/C5/12)/C6 -> 1294.7143
A8: 成本法权重 | B8: % | C8: 1
A9: 市场法基准价 | B9: 元/单元/月
A10: 市场法权重 | B10: % | C10: =1-C8 -> 0
A11: 项目基准价 | B11: 元/单元/月 | C11: =C7*C8+C9*C10 -> 1294.7143
C12: 套均价 | D12: 单元均价 | F12: 基准价条件 | G12: 地铁站步行距离 | H12: 公交站步行距离 | I12: 公区步行距离 | J12: 噪音 | K12: 污染 | L12: 4楼有无电梯 | M12: 梯户比 | N12: 楼栋外观 | O12: 套内空间 | P12: 户型 | Q12: 阳台 | R12: 楼梯房楼层 | S12: 功能 | T12: 采光 | U12: 视野
A13: 普通开间基准价 | B13: 元/套 | C13: 1325 | D13: =C13/1 -> 1325 | F13: 分档 | G13: 1~1.5km | H13: <0.5km | I13: 0~0.2km | J13: 无 | K13: 无 | L13: 无 | M13: 5~8 | N13: 适中 | O13: 适中 | P13: 适中 | Q13: 无 | R13: 4楼 | S13: 适中 | T13: 适中 | U13: 适中
A14: 高架床/窄床开间基准价 | B14: 元/套 | C14: 1200 | D14: =C14/1 -> 1200
A15: 普通1居基准价 | B15: 元/套 | C15: 1850 | D15: =C15/1.5 -> 1233.3333
A16: 客厅功能性弱的1居基准价 | B16: 元/套 | C16: 1650 | D16: =C16/1.5 -> 1100
A17: LOFT基准价 | B17: 元/套 | D17: =C17/1.5 -> 0
A18: 2居基准价 | B18: 元/套 | D18: =C18/2 -> 0
A19: 2人间宿舍基准价 | B19: 元/套 | D19: =C19/1 -> 0

Sheet 赋权表
F1: 运营中心 | N1: 营销中心
E2: =MEDIAN(E8:E54) -> #REF! | F2: 地铁站步行距离 | G2: 公交站步行距离 | H2: 公区步行距离 | I2: 噪音 | J2: 污染 | K2: 4楼有无电梯 | L2: 梯户比 | M2: 楼栋外观 | N2: 套内空间 | O2: 户型 | P2: 阳台 | Q2: 楼梯房楼层 | R2: 功能 | S2: 采光 | T2: 视野
B3: 基准条件 | F3: 1~1.5km | G3: <0.5km | H3: 0~0.2km | I3: 无 | J3: 无 | K3: 无 | L3: 5~8 | M3: 适中 | N3: 适中 | O3: 适中 | P3: 无 | Q3: 4楼 | R3: 适中 | S3: 适中 | T3: 适中
B4: 相对优 | F4: 0.5~1km | G4: <0.5km | H4: 0~0.2km | I4: 无 | J4: 无 | K4: 无 | L4: 5~8 | M4: 优 | N4: 较宽敞 | O4: 适中 | P4: 小 | Q4: 4楼 | R4: 充足 | S4: 很好 | T4: 优
B5: 相对差 | E5: 差异率 | F5: 1~1.5km | G5: 0.5~1km | H5: 0.2~0.5km | I5: 中 | J5: 中 | K5: 有 | L5: >8 | M5: 适中 | N5: 适中 | O5: 差 | P5: 无 | Q5: 5楼 | R5: 适中 | S5: 适中 | T5: 适中
B7: V59-406 | C7: 定价租金 | D7: 1419 | F7: 1~1.5km | G7: <0.5km | H7: 0~0.2km | I7: 无 | J7: 无 | K7: 无 | L7: 5~8 | M7: 适中 | N7: 较宽敞 | O7: 适中 | P7: 无 | Q7: 4楼 | R7: 适中 | S7: 较差 | T7: 适中
C8: 模型租金 | D8: =项目基准价!C13*PRODUCT(赋权表!F8:T8) -> #REF! | E8: =D7/D8-1 -> #REF! | F8: =【1】定价因子!#REF! -> #REF! | G8: =【1】定价因子!F64 -> 1 | H8: =【1】定价因子!F6 -> 0.96 | I8: =【1】定价因子!F72 -> 1 | J8: =【1】定价因子!F76 -> 1 | K8: =【1】定价因子!F8 -> 1 | L8: =【1】定价因子!#REF! -> #REF! | M8: =【1】定价因子!#REF! -> #REF! | N8: =【1】定价因子!F10 -> 1.06 | O8: =【1】定价因子!#REF! -> #REF! | P8: =【1】定价因子!F18 -> 1 | Q8: =【1】定价因子!F23 -> 1 | R8: =【1】定价因子!F41 -> 1 | S8: =【1】定价因子!F48 -> 1 | T8: =【1】定价因子!F70 -> 1
B9: N258-305 | C9: 定价租金 | D9: 1469 | F9: >1.5km | G9: <0.5km | H9: 0.2~0.5km | I9: 无 | J9: 无 | K9: 无 | L9: 5~8 | M9: 适中 | N9: 较宽敞 | O9: 适中 | P9: 无 | Q9: 3楼 | R9: 充足 | S9: 好 | T9: 优
C10: 模型租金 | D10: =项目基准价!C13*PRODUCT(赋权表!F10:T10) -> #REF! | E10: =D9/D10-1 -> #REF! | F10: =【1】定价因子!#REF! -> #REF! | G10: =【1】定价因子!F64 -> 1 | H10: =【1】定价因子!#REF! -> #REF! | I10: =I8 -> 1 | J10: =J8 -> 1 | K10: =K8 -> 1 | L10: =L8 -> #REF! | M10: =M8 -> #REF! | N10: =N8 -> 1.06 | O10: =O8 -> #REF! | P10: =P8 -> 1 | Q10: =【1】定价因子!F22 -> 1.01 | R10: =【1】定价因子!F42 -> 1.04 | S10: =【1】定价因子!F46 -> 1.06 | T10: =【1】定价因子!F68 -> 1.045
B11: T78-1404 | C11: 定价租金 | D11: 1470 | F11: 1~1.5km | G11: <0.5km | H11: 楼内 | I11: 无 | J11: 无 | K11: 有 | L11: >8 | M11: 适中 | N11: 适中 | O11: 适中 | P11: 小 | Q11: 14楼 | R11: 适中 | S11: 好 | T11: 适中
C12: 模型租金 | D12: =项目基准价!$C$13*PRODUCT(赋权表!F12:T12) -> #REF! | E12: =D11/D12-1 -> #REF! | F12: =F8 -> #REF! | G12: =G8 -> 1 | H12: =【1】定价因子!F2 -> 1.04 | I12: =I8 -> 1 | J12: =J8 -> 1 | K12: =【1】定价因子!F7 -> 1.05 | L12: =【1】定价因子!#REF! -> #REF! | M12: =M8 -> #REF! | N12: 1 | O12: =O8 -> #REF! | P12: =【1】定价因子!F16 -> 1.07 | Q12: =【1】定价因子!F35 -> 1.03 | R12: =R8 -> 1 | S12: =【1】定价因子!F46 -> 1.06 | T12: =T8 -> 1
B13: V20-410 | C13: 定价租金 | D13: 1509 | F13: 1~1.5km | G13: <0.5km | H13: 0~0.2km | I13: 无 | J13: 无 | K13: 无 | L13: >8 | M13: 适中 | N13: 很宽敞 | O13: 适中 | P13: 无 | Q13: 4楼 | R13: 充足 | S13: 好 | T13: 适中 | U13: =70/1300 -> 0.053846154
C14: 模型租金 | D14: =项目基准价!$C$13*PRODUCT(赋权表!F14:T14) -> #REF! | E14: =D13/D14-1 -> #REF! | F14: =F8 -> #REF! | G14: =G8 -> 1 | H14: =H8 -> 0.96 | I14: =I8 -> 1 | J14: =J8 -> 1 | K14: =K8 -> 1 | L14: =L12 -> #REF! | M14: =M8 -> #REF! | N14: =【1】定价因子!F9 -> 1.1 | O14: =O8 -> #REF! | P14: =P8 -> 1 | Q14: =Q8 -> 1 | R14: =R10 -> 1.04 | S14: =S10 -> 1.06 | T14: =T8 -> 1
B15: V17-105 | C15: 定价租金 | D15: 1519 | F15: 1~1.5km | G15: <0.5km | H15: 0.2~0.5km | I15: 无 | J15: 无 | K15: 无 | L15: 5~8 | M15: 适中 | N15: 较宽敞 | O15: 适中 | P15: 无 | Q15: 1楼 | R15: 适中 | S15: 很差 | T15: 适中
C16: 模型租金 | D16: =项目基准价!$C$15*PRODUCT(赋权表!F16:T16) -> #REF! | E16: =D15/D16-1 -> #REF! | F16: =F14 -> #REF! | G16: =G14 -> 1 | H16: =H10 -> #REF! | I16: =I10 -> 1 | J16: =J10 -> 1 | K16: =K10 -> 1 | L16: =L10 -> #REF! | M16: =M10 -> #REF! | N16: =N10 -> 1.06 | O16: =O10 -> #REF! | P16: =P10 -> 1 | Q16: =【1】定价因子!F30 -> 0.87 | R16: =R8 -> 1 | S16: =【1】定价因子!F49 -> 0.96 | T16: =T8 -> 1
B17: V17-104 | C17: 定价租金 | D17: 1099 | F17: 1~1.5km | G17: <0.5km | H17: 0.2~0.5km | I17: 无 | J17: 无 | K17: 无 | L17: 5~8 | M17: 适中 | N17: 较狭小 | O17: 适中 | P17: 无 | Q17: 1楼 | R17: 适中 | S17: 很差 | T17: 适中
C18: 模型租金 | D18: =项目基准价!$C$13*PRODUCT(赋权表!F18:T18) -> #REF! | E18: =D17/D18-1 -> #REF! | F18: =F16 -> #REF! | G18: =G16 -> 1 | H18: =H16 -> #REF! | I18: =I16 -> 1 | J18: =J16 -> 1 | K18: =K16 -> 1 | L18: =L16 -> #REF! | M18: =M16 -> #REF! | N18: =【1】定价因子!F12 -> 0.95 | O18: =O16 -> #REF! | P18: =P16 -> 1 | Q18: =Q16 -> 0.87 | R18: =R16 -> 1 | S18: =S16 -> 0.96 | T18: =T16 -> 1
B19: X20-1020 | C19: 定价租金 | D19: 2199 | F19: 1~1.5km | G19: <0.5km | H19: >0.5km | I19: 无 | J19: 无 | K19: 有 | L19: >8 | M19: 适中 | N19: 很宽敞 | O19: 适中 | P19: 无 | Q19: 10楼 | R19: 适中 | S19: 好 | T19: 较好
C20: 模型租金 | D20: =项目基准价!$C$15*PRODUCT(赋权表!F20:T20) -> #REF! | E20: =D19/D20-1 -> #REF! | F20: =F18 -> #REF! | G20: =G18 -> 1 | H20: =【1】定价因子!#REF! -> #REF! | I20: =I12 -> 1 | J20: =J12 -> 1 | K20: =K12 -> 1.05 | L20: =L12 -> #REF! | M20: =M12 -> #REF! | N20: =N14 -> 1.1 | O20: =O14 -> #REF! | P20: =P14 -> 1 | Q20: =Q12 -> 1.03 | R20: =R12 -> 1 | S20: =S14 -> 1.06 | T20: =【1】定价因子!F69 -> 1.02
B21: X20-1001 | C21: 定价租金 | D21: 839 | F21: 1~1.5km | G21: <0.5km | H21: >0.5km | I21: 无 | J21: 无 | K21: 有 | L21: >8 | M21: 适中 | N21: 非常狭小 | O21: 适中 | P21: 无 | Q21: 10楼 | R21: 非常缺失 | S21: 好 | T21: 较好
C22: 模型租金 | D22: =项目基准价!$C$14*PRODUCT(赋权表!F22:T22) -> #REF! | E22: =D21/D22-1 -> #REF! | F22: =F20 -> #REF! | G22: =G20 -> 1 | H22: =H20 -> #REF! | I22: =I20 -> 1 | J22: =J20 -> 1 | K22: =K20 -> 1.05 | L22: =L20 -> #REF! | M22: =M20 -> #REF! | N22: 0.86 | O22: =O20 -> #REF! | P22: =P20 -> 1 | Q22: =Q20 -> 1.03 | R22: 0.9 | S22: =S20 -> 1.06 | T22: =T20 -> 1.02
B23: T78-815 | C23: 定价租金 | D23: 1379 | F23: 1~1.5km | G23: <0.5km | H23: 楼内 | I23: 无 | J23: 无 | K23: 有 | L23: >8 | M23: 适中 | N23: 适中 | O23: 适中 | P23: 小 | Q23: 8楼 | R23: 适中 | S23: 好 | T23: 适中
C24: 模型租金 | D24: =项目基准价!$C$14*PRODUCT(赋权表!F24:T24) -> #REF! | E24: =D23/D24-1 -> #REF! | F24: =F12 -> #REF! | G24: =G12 -> 1 | H24: =H12 -> 1.04 | I24: =I12 -> 1 | J24: =J12 -> 1 | K24: =K12 -> 1.05 | L24: =L12 -> #REF! | M24: =M12 -> #REF! | N24: =N12 -> 1 | O24: =O22 -> #REF! | P24: =P12 -> 1.07 | Q24: =【1】定价因子!F34 -> 1.02 | R24: =R12 -> 1 | S24: =S12 -> 1.06 | T24: =T12 -> 1
A25: 高架 | B25: V21-301 | C25: 定价租金 | D25: 1439 | F25: 1~1.5km | G25: <0.5km | H25: 0~0.2km | I25: 无 | J25: 无 | K25: 无 | L25: 5~8 | M25: 适中 | N25: 较宽敞 | O25: 适中 | P25: 超大 | Q25: 3楼 | R25: 适中 | S25: 好 | T25: 适中
C26: 模型租金 | D26: =项目基准价!$C$14*PRODUCT(赋权表!F26:T26) -> #REF! | E26: =D25/D26-1 -> #REF! | F26: =F14 -> #REF! | G26: =G14 -> 1 | H26: =H14 -> 0.96 | I26: =I14 -> 1 | J26: =J14 -> 1 | K26: =K14 -> 1 | L26: =L18 -> #REF! | M26: =M14 -> #REF! | N26: =N16 -> 1.06 | O26: =O16 -> #REF! | P26: =【1】定价因子!F14 -> 0 | Q26: =【1】定价因子!F22 -> 1.01 | R26: =R24 -> 1 | S26: =S24 -> 1.06 | T26: =T24 -> 1
B27: V46-204 | C27: 定价租金 | D27: 1799 | F27: 1~1.5km | G27: <0.5km | H27: 0~0.2km | I27: 无 | J27: 无 | K27: 无 | L27: 5~8 | M27: 优 | N27: 适中 | O27: 适中 | P27: 无 | Q27: 2楼 | R27: 适中 | S27: 适中 | T27: 适中
C28: 模型租金 | D28: =项目基准价!$C$15*PRODUCT(赋权表!F28:T28) -> #REF! | E28: =D27/D28-1 -> #REF! | F28: =F26 -> #REF! | G28: =G26 -> 1 | H28: =H26 -> 0.96 | I28: =I26 -> 1 | J28: =J26 -> 1 | K28: =K26 -> 1 | L28: =L26 -> #REF! | M28: =【1】定价因子!#REF! -> #REF! | N28: =N24 -> 1 | O28: =O24 -> #REF! | P28: =P22 -> 1 | Q28: =【1】定价因子!F21 -> 1.02 | R28: =R26 -> 1 | S28: =【1】定价因子!F47 -> 1.03 | T28: =T26 -> 1
B29: V46-304 | C29: 定价租金 | D29: 1999 | F29: 1~1.5km | G29: <0.5km | H29: 0~0.2km | I29: 无 | J29: 无 | K29: 无 | L29: 5~8 | M29: 优 | N29: 适中 | O29: 适中 | P29: 大 | Q29: 2楼 | R29: 适中 | S29: 适中 | T29: 很好
C30: 模型租金 | D30: =项目基准价!$C$15*PRODUCT(赋权表!F30:T30) -> #REF! | E30: =D29/D30-1 -> #REF! | F30: =F28 -> #REF! | G30: =G28 -> 1 | H30: =H28 -> 0.96 | I30: =I28 -> 1 | J30: =J28 -> 1 | K30: =K28 -> 1 | L30: =L28 -> #REF! | M30: =M28 -> #REF! | ... O30: =O28 -> #REF! | P30: =【1】定价因子!F15 -> 0 | Q30: =Q28 -> 1.02 | R30: =R28 -> 1 | S30: =S28 -> 1.03 | T30: =【1】定价因子!F68 -> 1.045
B31: V17-301 | C31: 定价租金 | D31: 1569 | F31: 1~1.5km | G31: <0.5km | H31: 0.2~0.5km | I31: 无 | J31: 无 | K31: 无 | L31: 5~8 | M31: 适中 | N31: 适中 | O31: 适中 | P31: 大 | Q31: 3楼 | R31: 缺失 | S31: 较差 | T31: 适中
A32: 弱1居 | C32: 模型租金 | D32: =项目基准价!$C$16*PRODUCT(赋权表!F32:T32) -> #REF! | E32: =D31/D32-1 -> #REF! | F32: =F18 -> #REF! | G32: =G18 -> 1 | H32: =H18 -> #REF! | I32: =I18 -> 1 | J32: =J18 -> 1 | K32: =K18 -> 1 | L32: =L18 -> #REF! | M32: =M18 -> #REF! | N32: =N30 -> 1 | O32: =O30 -> #REF! | P32: =P30 -> 0 | Q32: =Q30 -> 1.02 | S32: =S8 -> 1 | T32: =T28 -> 1
B33: T78-1401 | C33: 定价租金 | D33: 2299 | F33: 1~1.5km | G33: <0.5km | H33: 楼内 | I33: 无 | J33: 无 | K33: 有 | L33: >8 | M33: 适中 | N33: 较宽敞 | O33: 适中 | P33: 小 | Q33: 14楼 | R33: 适中 | S33: 好 | T33: 较好
C34: 模型租金 | D34: =项目基准价!$C$15*PRODUCT(赋权表!F34:T34) -> #REF! | E34: =D33/D34-1 -> #REF! | F34: =F24 -> #REF! | G34: =G24 -> 1 | H34: =H24 -> 1.04 | I34: =I24 -> 1 | J34: =J24 -> 1 | K34: =K24 -> 1.05 | L34: =L24 -> #REF! | M34: =M24 -> #REF! | N34: =N26 -> 1.06 | O34: =O26 -> #REF! | P34: =P24 -> 1.07 | Q34: =【1】定价因子!F35 -> 1.03 | R34: =R30 -> 1 | S34: =S10 -> 1.06 | T34: =T20 -> 1.02
A35: 高架 | B35: V46-606 | C35: 定价租金 | D35: 1249 | F35: 1~1.5km | G35: <0.5km | H35: 0~0.2km | I35: 无 | J35: 无 | K35: 无 | L35: 5~8 | M35: 优 | N35: 适中 | O35: 适中 | P35: 无 | Q35: 6楼 | R35: 适中 | S35: 好 | T35: 适中
C36: 模型租金 | D36: =项目基准价!$C$14*PRODUCT(赋权表!F36:T36) -> #REF! | E36: =D35/D36-1 -> #REF! | F36: =F30 -> #REF! | G36: =G30 -> 1 | H36: =H30 -> 0.96 | I36: =I34 -> 1 | J36: =J30 -> 1 | K36: =K30 -> 1 | L36: =L32 -> #REF! | M36: =M30 -> #REF! | N36: =N30 -> 1 | O36: =O34 -> #REF! | P36: =P28 -> 1 | Q36: =【1】定价因子!F25 -> 0.98 | R36: =R34 -> 1 | S36: =S34 -> 1.06 | T36: =T32 -> 1
A37: 高架 | B37: V60-504 | C37: 定价租金 | D37: 1299 | F37: 1~1.5km | G37: <0.5km | H37: 0~0.2km | I37: 无 | J37: 无 | K37: 无 | L37: 5~8 | M37: 适中 | N37: 适中 | O37: 适中 | P37: 无 | Q37: 5楼 | R37: 适中 | S37: 适中 | T37: 适中
C38: 模型租金 | D38: =项目基准价!$C$14*PRODUCT(赋权表!F38:T38) -> #REF! | E38: =D37/D38-1 -> #REF! | F38: =F8 -> #REF! | G38: =G8 -> 1 | H38: =H8 -> 0.96 | I38: =I36 -> 1 | J38: =J8 -> 1 | K38: =K8 -> 1 | L38: =L8 -> #REF! | M38: =M8 -> #REF! | N38: =N36 -> 1 | O38: =O36 -> #REF! | P38: =P36 -> 1 | Q38: =【1】定价因子!F24 -> 0.99 | R38: =R36 -> 1 | S38: =S28 -> 1.03 | T38: =T28 -> 1
B39: V19-505 | C39: 定价租金 | D39: 1239 | F39: 1~1.5km | G39: <0.5km | H39: 0.2~0.5km | I39: 无 | J39: 无 | K39: 无 | L39: 5~8 | M39: 适中 | N39: 适中 | O39: 适中 | P39: 无 | Q39: 5楼 | R39: 充足 | S39: 较差 | T39: 适中
C40: 模型租金 | D40: =项目基准价!$C$13*PRODUCT(赋权表!F40:T40) -> #REF! | E40: =D39/D40-1 -> #REF! | F40: =F32 -> #REF! | G40: =G32 -> 1 | H40: =H32 -> #REF! | I40: =I38 -> 1 | J40: =J32 -> 1 | K40: =K32 -> 1 | L40: =L32 -> #REF! | M40: =M32 -> #REF! | N40: =N38 -> 1 | O40: =O38 -> #REF! | P40: =P38 -> 1 | Q40: =Q38 -> 0.99 | R40: =R14 -> 1.04 | S40: =S32 -> 1 | T40: =T38 -> 1
A41: 弱1居 | B41: V60-303 | C41: 定价租金 | D41: 1699 | F41: 1~1.5km | G41: <0.5km | H41: 0~0.2km | I41: 无 | J41: 无 | K41: 无 | L41: 5~8 | M41: 适中 | N41: 适中 | O41: 适中 | P41: 无 | Q41: 3楼 | R41: 缺失 | S41: 适中 | T41: 适中
C42: 模型租金 | D42: =项目基准价!$C$16*PRODUCT(赋权表!F42:T42) -> #REF! | E42: =D41/D42-1 -> #REF! | F42: =F38 -> #REF! | G42: =G38 -> 1 | H42: =H38 -> 0.96 | I42: =I38 -> 1 | J42: =J38 -> 1 | K42: =K38 -> 1 | L42: =L38 -> #REF! | M42: =M38 -> #REF! | N42: =N38 -> 1 | O42: =O40 -> #REF! | P42: =P40 -> 1 | Q42: =Q32 -> 1.02 | S42: =S38 -> 1.03 | T42: =T40 -> 1
B43: T133-505 | C43: 定价租金 | D43: 1239 | F43: 1~1.5km | G43: <0.5km | H43: 0.2~0.5km | I43: 小 | J43: 无 | K43: 无 | L43: 5~8 | M43: 适中 | N43: 较宽敞 | O43: 适中 | P43: 无 | Q43: 5楼 | R43: 充足 | S43: 较差 | T43: 适中
C44: 模型租金 | D44: =项目基准价!$C$13*PRODUCT(赋权表!F44:T44) -> #REF! | E44: =D43/D44-1 -> #REF! | F44: =F42 -> #REF! | G44: =G42 -> 1 | H44: =H40 -> #REF! | I44: =【1】定价因子!F73 -> 0.975 | J44: =J34 -> 1 | K44: =K38 -> 1 | L44: =L36 -> #REF! | M44: =M34 -> #REF! | N44: =N34 -> 1.06 | O44: =O40 -> #REF! | P44: =P40 -> 1 | Q44: =Q40 -> 0.99 | R44: =R40 -> 1.04 | S44: =S32 -> 1 | T44: =T40 -> 1
B45: N248-306 | C45: 定价租金 | D45: 1239 | F45: >1.5km | G45: <0.5km | H45: 0.2~0.5km | I45: 无 | J45: 无 | K45: 无 | L45: 5~8 | M45: 适中 | N45: 较宽敞 | O45: 适中 | P45: 无 | Q45: 3楼 | R45: 充足 | S45: 适中 | T45: 适中
C46: 模型租金 | D46: =项目基准价!$C$13*PRODUCT(赋权表!F46:T46) -> #REF! | E46: =D45/D46-1 -> #REF! | F46: =F10 -> #REF! | G46: =G10 -> 1 | H46: =H10 -> #REF! | I46: =I10 -> 1 | J46: =J10 -> 1 | K46: =K10 -> 1 | L46: =L10 -> #REF! | M46: =M10 -> #REF! | N46: =N34 -> 1.06 | O46: =O44 -> #REF! | P46: =P44 -> 1 | Q46: =Q42 -> 1.02 | R46: =R44 -> 1.04 | S46: =S42 -> 1.03 | T46: =T44 -> 1
B47: V43-1101 | C47: 定价租金 | D47: 1629 | F47: 1~1.5km | G47: <0.5km | H47: 0~0.2km | I47: 无 | J47: 无 | K47: 有 | L47: 5~8 | M47: 适中 | N47: 适中 | O47: 适中 | P47: 无 | Q47: 11楼 | R47: 适中 | S47: 适中 | T47: 较好
C48: 模型租金 | D48: =项目基准价!$C$13*PRODUCT(赋权表!F48:T48) -> #REF! | E48: =D47/D48-1 -> #REF! | F48: =F34 -> #REF! | G48: =G34 -> 1 | H48: =H42 -> 0.96 | I48: =I34 -> 1 | J48: =J34 -> 1 | K48: =K34 -> 1.05 | L48: =L46 -> #REF! | M48: =M34 -> #REF! | N48: =N40 -> 1 | O48: =O40 -> #REF! | P48: =P40 -> 1 | Q48: =【1】定价因子!F35 -> 1.03 | R48: =R38 -> 1 | S48: =S38 -> 1.03 | T48: =T20 -> 1.02
A49: 对标T133-505 | B49: V21-304 | C49: 定价租金 | D49: 1449 | F49: 1~1.5km | G49: <0.5km | H49: 0~0.2km | I49: 无 | J49: 无 | K49: 有 | L49: 5~8 | M49: 适中 | N49: 适中 | O49: 适中 | P49: 无 | Q49: 3楼 | R49: 充足 | S49: 较差 | T49: 适中
C50: 模型租金 | D50: =项目基准价!$C$13*PRODUCT(赋权表!F50:T50) -> #REF! | E50: =D49/D50-1 -> #REF! | F50: =F26 -> #REF! | G50: =G26 -> 1 | H50: =H26 -> 0.96 | I50: =I26 -> 1 | J50: =J26 -> 1 | K50: =K26 -> 1 | L50: =L26 -> #REF! | M50: =M26 -> #REF! | N50: =N48 -> 1 | O50: =O48 -> #REF! | P50: =P48 -> 1 | Q50: =Q46 -> 1.02 | R50: =R46 -> 1.04 | S50: =S44 -> 1 | T50: =T46 -> 1
B51: V20-404 | C51: 定价租金 | D51: 1449 | F51: 1~1.5km | G51: <0.5km | H51: 0~0.2km | I51: 无 | J51: 无 | K51: 无 | L51: >8 | M51: 适中 | N51: 适中 | O51: 适中 | P51: 无 | Q51: 4楼 | R51: 适中 | S51: 适中 | T51: 适中
C52: 模型租金 | D52: =项目基准价!$C$13*PRODUCT(赋权表!F52:T52) -> #REF! | E52: =D51/D52-1 -> #REF! | F52: =F14 -> #REF! | G52: =G14 -> 1 | H52: =H14 -> 0.96 | I52: =I14 -> 1 | J52: =J14 -> 1 | K52: =K14 -> 1 | L52: =L14 -> #REF! | M52: =M14 -> #REF! | N52: =N50 -> 1 | O52: =O50 -> #REF! | P52: =P50 -> 1 | Q52: =Q8 -> 1 | R52: =R48 -> 1 | S52: =S48 -> 1.03 | T52: =T46 -> 1
B53: 合计 | F53: =SUM(F55:F71) -> 152 | G53: =SUM(G55:G71) -> 65 | H53: =SUM(H55:H71) -> 32 | I53: =SUM(I55:I71) -> 125 | J53: =SUM(J55:J71) -> 139 | K53: =SUM(K55:K71) -> 51 | L53: =SUM(L55:L71) -> 38 | M53: =SUM(M55:M71) -> 26 | ... T53: =SUM(T55:T71) -> 100
A54: =6%/150 -> 0.0004 | B54: 调价系数 | F54: 0.06 | G54: 0.025 | H54: 0.015 | I54: 0.05 | J54: 0.055 | K54: 0.02 | L54: 0.015 | M54: 0.01 | N54: 0.06 | O54: 0.05 | P54: 0.06 | Q54: 0.015 | R54: 0.035 | S54: 0.065 | T54: 0.04
A55: 李晓阳 | F55: 20 | G55: 2 | H55: 12 | I55: 20 | J55: 10 | K55: 8 | L55: 12 | M55: 0 | N55: 26 | O55: 18 | P55: 26 | Q55: 10 | R55: 4 | S55: 26 | T55: 16
A56: 姚欢 | F56: 13 | G56: 7 | H56: 1 | I56: 10 | J56: 14 | K56: 2 | L56: 3 | M56: 0 | N56: 9 | O56: 8 | P56: 11 | Q56: 4 | R56: 6 | S56: 11 | T56: 6
A57: 孙铭馗 | F57: 20 | G57: 4 | H57: 8 | I57: 12 | J57: 18 | K57: 6 | L57: 0 | M57: 2 | N57: 26 | O57: 12 | P57: 24 | Q57: 20 | R57: 16 | S57: 28 | T57: 14
A58: 王漫柔 | F58: 14 | G58: 13 | H58: 4 | I58: 5 | J58: 5 | K58: 8 | L58: 1 | M58: 2 | N58: 4 | O58: 10 | P58: 12 | Q58: 0 | R58: 7 | S58: 11 | T58: 9
A59: 邓彬彬 | F59: 13 | G59: 5 | H59: 3 | I59: 12 | J59: 14 | K59: 2 | L59: 0 | M59: 1 | N59: 7 | O59: 6 | P59: 9 | Q59: 4 | R59: 10 | S59: 10 | T59: 9
A60: 胡文竹 | F60: 24 | G60: 8 | H60: 0 | I60: 20 | J60: 26 | K60: 4 | L60: 8 | M60: 10 | N60: 18 | O60: 20 | P60: 16 | Q60: 8 | R60: 8 | S60: 24 | T60: 16
A61: 贾矿营 | F61: 22 | G61: 10 | H61: 2 | I61: 10 | J61: 10 | K61: 6 | L61: 4 | M61: 0 | N61: 26 | O61: 28 | P61: 22 | Q61: 14 | R61: 18 | S61: 22 | T61: 16
A62: 戚梓茵 | F62: 8 | G62: 2 | H62: 0 | I62: 10 | J62: 14 | K62: 1 | L62: 4 | M62: 9 | N62: 6 | O62: 11 | P62: 6 | Q62: 4 | R62: 5 | S62: 13 | T62: 12
A63: 庹凯 | F63: 18 | G63: 14 | H63: 2 | I63: 26 | J63: 28 | K63: 14 | L63: 6 | M63: 2 | N63: 32 | O63: 10 | P63: 18 | Q63: 10 | R63: 12 | S63: 16 | T63: 2

Sheet 目录
A1: 地铁站步行距离
A2: 公交站步行距离
A3: 公区步行距离
A4: 噪音影响度
A5: 污染
A6: 四楼有无电梯
A7: 梯户比
A8: 楼栋外观
A9: 套内空间
A10: 户型
A11: 阳台
A12: 楼梯房楼层
... A16: 视野

Sheet 【3】大区填-楼栋基准格局定价
A1: 楼栋 | B1: 基准格局 | C1: 基准格局基准价 | D1: 区位 | E1: 调价倍数1 | F1: 有无电梯 | G1: 调价倍数2 | H1: 是否简装 | I1: 调价倍数3 | J1: 基准格局定价
A2: ='【2】运营中心填-基本信息&审核标准'!$E$2 -> 福围广生1-41栋 | B2: ='【3-2】大区&运营中心填-房间模型价'!K2 -> 开间 | C2: =VLOOKUP(B2,【1】定价因子!L:M,2,0) -> 1612.1 | D2: 交通很不便 | E2: =VLOOKUP(D2,【1】定价因子!$D:$F,3,0) -> 0.96 | F2: 无 | G2: =VLOOKUP(F2,【1】定价因子!D:F,3,0) -> 1 | H2: 是 | I2: 0.8 | J2: =C2*PRODUCT(G2,,E2,I2) -> 1238.0928
A3: ='【2】运营中心填-基本信息&审核标准'!$E$2 -> 福围广生1-41栋 | B3: ='【3-2】大区&运营中心填-房间模型价'!K3 -> 一居室 | C3: =VLOOKUP(B3,【1】定价因子!L:M,2,0) -> 2402.5 | D3: 交通很不便 | E3: =VLOOKUP(D3,【1】定价因子!$D:$F,3,0) -> 0.96 | F3: 无 | G3: =VLOOKUP(F3,【1】定价因子!D:F,3,0) -> 1 | H3: 是 | I3: 0.8 | J3: =C3*PRODUCT(G3,,E3,I3) -> 1845.12
A4: ='【2】运营中心填-基本信息&审核标准'!$E$2 -> 福围广生1-41栋 | B4: ='【3-2】大区&运营中心填-房间模型价'!K4 | C4: =VLOOKUP(B4,【1】定价因子!L:M,2,0) -> #N/A | D4: 交通很便利 | E4: =VLOOKUP(D4,【1】定价因子!$D:$F,3,0) -> 1.04 | F4: =IF('【2】运营中心填-基本信息&审核标准'!$C$4="否","无",IF('【2】运营中心填-基本信息&审核标准'!$C$4="是","有")) -> 有 | G4: =VLOOKUP(F4,【1】定价因子!D:F,3,0) -> 1.05 | H4: 是 | I4: 0.8 | J4: =C4*PRODUCT(G4,,E4,I4) -> #N/A
A5: ='【2】运营中心填-基本信息&审核标准'!$E$2 -> 福围广生1-41栋 | B5: ='【3-2】大区&运营中心填-房间模型价'!K5 | C5: =VLOOKUP(B5,【1】定价因子!L:M,2,0) -> #N/A | D5: 交通很便利 | E5: =VLOOKUP(D5,【1】定价因子!$D:$F,3,0) -> 1.04 | F5: =IF('【2】运营中心填-基本信息&审核标准'!$C$4="否","无",IF('【2】运营中心填-基本信息&审核标准'!$C$4="是","有")) -> 有 | G5: =VLOOKUP(F5,【1】定价因子!D:F,3,0) -> 1.05 | H5: 是 | I5: 0.8 | J5: =C5*PRODUCT(G5,,E5,I5) -> #N/A
A6: ='【2】运营中心填-基本信息&审核标准'!$E$2 -> 福围广生1-41栋 | B6: ='【3-2】大区&运营中心填-房间模型价'!K6 | C6: =VLOOKUP(B6,【1】定价因子!L:M,2,0) -> #N/A | D6: 交通很便利 | E6: =VLOOKUP(D6,【1】定价因子!$D:$F,3,0) -> 1.04 | F6: =IF('【2】运营中心填-基本信息&审核标准'!$C$4="否","无",IF('【2】运营中心填-基本信息&审核标准'!$C$4="是","有")) -> 有 | G6: =VLOOKUP(F6,【1】定价因子!D:F,3,0) -> 1.05 | H6: 是 | I6: 0.8 | J6: =C6*PRODUCT(G6,,E6,I6) -> #N/A
A7: ='【2】运营中心填-基本信息&审核标准'!$E$2 -> 福围广生1-41栋 | B7: ='【3-2】大区&运营中心填-房间模型价'!K7 | C7: =VLOOKUP(B7,【1】定价因子!L:M,2,0) -> #N/A | D7: 交通很便利 | E7: =VLOOKUP(D7,【1】定价因子!$D:$F,3,0) -> 1.04 | F7: =IF('【2】运营中心填-基本信息&审核标准'!$C$4="否","无",IF('【2】运营中心填-基本信息&审核标准'!$C$4="是","有")) -> 有 | G7: =VLOOKUP(F7,【1】定价因子!D:F,3,0) -> 1.05 | H7: 是 | I7: 0.8 | J7: =C7*PRODUCT(G7,,E7,I7) -> #N/A
A8: ='【2】运营中心填-基本信息&审核标准'!$E$2 -> 福围广生1-41栋 | B8: ='【3-2】大区&运营中心填-房间模型价'!K8 | C8: =VLOOKUP(B8,【1】定价因子!L:M,2,0) -> #N/A | D8: 交通很便利 | E8: =VLOOKUP(D8,【1】定价因子!$D:$F,3,0) -> 1.04 | F8: =IF('【2】运营中心填-基本信息&审核标准'!$C$4="否","无",IF('【2】运营中心填-基本信息&审核标准'!$C$4="是","有")) -> 有 | G8: =VLOOKUP(F8,【1】定价因子!D:F,3,0) -> 1.05 | H8: 是 | I8: 0.8 | J8: =C8*PRODUCT(G8,,E8,I8) -> #N/A
A9: ='【2】运营中心填-基本信息&审核标准'!$E$2 -> 福围广生1-41栋 | B9: ='【3-2】大区&运营中心填-房间模型价'!K9 | C9: =VLOOKUP(B9,【1】定价因子!L:M,2,0) -> #N/A | D9: 交通很便利 | E9: =VLOOKUP(D9,【1】定价因子!$D:$F,3,0) -> 1.04 | F9: =IF('【2】运营中心填-基本信息&审核标准'!$C$4="否","无",IF('【2】运营中心填-基本信息&审核标准'!$C$4="是","有")) -> 有 | G9: =VLOOKUP(F9,【1】定价因子!D:F,3,0) -> 1.05 | H9: 是 | I9: 0.8 | J9: =C9*PRODUCT(G9,,E9,I9) -> #N/A
A10: ='【2】运营中心填-基本信息&审核标准'!$E$2 -> 福围广生1-41栋 | B10: ='【3-2】大区&运营中心填-房间模型价'!K10 | C10: =VLOOKUP(B10,【1】定价因子!L:M,2,0) -> #N/A | D10: 交通很便利 | E10: =VLOOKUP(D10,【1】定价因子!$D:$F,3,0) -> 1.04 | F10: =IF('【2】运营中心填-基本信息&审核标准'!$C$4="否","无",IF('【2】运营中心填-基本信息&审核标准'!$C$4="是","有")) -> 有 | G10: =VLOOKUP(F10,【1】定价因子!D:F,3,0) -> 1.05 | H10: 是 | I10: 0.8 | J10: =C10*PRODUCT(G10,,E10,I10) -> #N/A

Sheet 【3-1】大区填-采光基本要素
D1: 仅需填写绿色部分，其余部分自动带出
A2: 房间号 | B2: 户型 | C2: 格局 | D2: 房间窗户数量（不含卫生间窗户） | E2: 阳台数量 | F2: 阳台面积（有阳台填写） | G2: 窗户遮挡数量 | H2: 采光判断 | I2: 有无玄关 | L2: 窗户遮挡填写标准
A3: ='【3-2】大区&运营中心填-房间模型价'!H2 -> 101 | B3: ='【3-2】大区&运营中心填-房间模型价'!I2 -> 1-41A | C3: =VLOOKUP(A3,'【3-2】大区&运营中心填-房间模型价'!H:J,3,0) -> 开间 | D3: 1.5 | E3: 0 | G3: 1.5 | H3: =IF(C3="开间",IF(D3+E3*2-G3<=0,"1",IF(D3+E3*2-G3<=1,"2",IF(D3+E3*2-G3<=2,"3",IF(D3+E3*2-G3<=3,"4","5")))),IF(D3+E3*2-G3<1.1,"1",IF(D3+E3*2-G3<=2,"2",IF(D3+E3*2-G3<=3,"3",IF(D3+E3*2-G3<=4,"4","5"))))) -> 1 | I3: 无 | L3: 情况 | O3: 填写值
A4: ='【3-2】大区&运营中心填-房间模型价'!H3 -> 102 | B4: ='【3-2】大区&运营中心填-房间模型价'!I3 -> 1-41B | C4: =VLOOKUP(A4,'【3-2】大区&运营中心填-房间模型价'!H:J,3,0) -> 一居室 | D4: 1.5 | E4: 0 | G4: 1.5 | H4: =IF(C4="开间",IF(D4+E4*2-G4<=0,"1",IF(D4+E4*2-G4<=1,"2",IF(D4+E4*2-G4<=2,"3",IF(D4+E4*2-G4<=3,"4","5")))),IF(D4+E4*2-G4<1.1,"1",IF(D4+E4*2-G4<=2,"2",IF(D4+E4*2-G4<=3,"3",IF(D4+E4*2-G4<=4,"4","5"))))) -> 1 | I4: 无 | L4: 窗户所面对的完全无楼栋或楼间距＞10米 | O4: -1
A5: ='【3-2】大区&运营中心填-房间模型价'!H4 -> 201 | B5: ='【3-2】大区&运营中心填-房间模型价'!I4 -> 1-41C | C5: =VLOOKUP(A5,'【3-2】大区&运营中心填-房间模型价'!H:J,3,0) -> 开间 | D5: 2 | E5: 0 | G5: 2 | H5: =IF(C5="开间",IF(D5+E5*2-G5<=0,"1",IF(D5+E5*2-G5<=1,"2",IF(D5+E5*2-G5<=2,"3",IF(D5+E5*2-G5<=3,"4","5")))),IF(D5+E5*2-G5<1.1,"1",IF(D5+E5*2-G5<=2,"2",IF(D5+E5*2-G5<=3,"3",IF(D5+E5*2-G5<=4,"4","5"))))) -> 1 | I5: 无 | L5: 窗户对面有楼 | M5: 1-4楼窗户所对楼间距＞3米 | O5: 0
A6: ='【3-2】大区&运营中心填-房间模型价'!H5 -> 202 | B6: ='【3-2】大区&运营中心填-房间模型价'!I5 -> 1-41D | C6: =VLOOKUP(A6,'【3-2】大区&运营中心填-房间模型价'!H:J,3,0) -> 一居室 | D6: 2 | E6: 0 | G6: 1 | H6: =IF(C6="开间",IF(D6+E6*2-G6<=0,"1",IF(D6+E6*2-G6<=1,"2",IF(D6+E6*2-G6<=2,"3",IF(D6+E6*2-G6<=3,"4","5")))),IF(D6+E6*2-G6<1.1,"1",IF(D6+E6*2-G6<=2,"2",IF(D6+E6*2-G6<=3,"3",IF(D6+E6*2-G6<=4,"4","5"))))) -> 1 | I6: 无 | M6: 4楼以上窗户所对楼间距＞2米 | O6: 0
A7: ='【3-2】大区&运营中心填-房间模型价'!H6 -> 203 | B7: ='【3-2】大区&运营中心填-房间模型价'!I6 -> 1-41E | C7: =VLOOKUP(A7,'【3-2】大区&运营中心填-房间模型价'!H:J,3,0) -> 一居室 | D7: 3 | E7: 1 | F7: 3 | G7: 1 | H7: =IF(C7="开间",IF(D7+E7*2-G7<=0,"1",IF(D7+E7*2-G7<=1,"2",IF(D7+E7*2-G7<=2,"3",IF(D7+E7*2-G7<=3,"4","5")))),IF(D7+E7*2-G7<1.1,"1",IF(D7+E7*2-G7<=2,"2",IF(D7+E7*2-G7<=3,"3",IF(D7+E7*2-G7<=4,"4","5"))))) -> 4 | I7: 无 | M7: 1-4楼窗户所对楼间距＜3米 | O7: 1*窗户遮挡数量
A8: ='【3-2】大区&运营中心填-房间模型价'!H7 -> 301 | B8: ='【3-2】大区&运营中心填-房间模型价'!I7 -> 1-41F | C8: =VLOOKUP(A8,'【3-2】大区&运营中心填-房间模型价'!H:J,3,0) -> 开间 | D8: 1.5 | E8: 0 | G8: 1.5 | H8: =IF(C8="开间",IF(D8+E8*2-G8<=0,"1",IF(D8+E8*2-G8<=1,"2",IF(D8+E8*2-G8<=2,"3",IF(D8+E8*2-G8<=3,"4","5")))),IF(D8+E8*2-G8<1.1,"1",IF(D8+E8*2-G8<=2,"2",IF(D8+E8*2-G8<=3,"3",IF(D8+E8*2-G8<=4,"4","5"))))) -> 1 | I8: 无 | M8: 4楼以上窗户所对楼间距＜2米 | O8: 1*窗户遮挡数量
A9: ='【3-2】大区&运营中心填-房间模型价'!H8 -> 302 | B9: ='【3-2】大区&运营中心填-房间模型价'!I8 -> 1-41G | C9: =VLOOKUP(A9,'【3-2】大区&运营中心填-房间模型价'!H:J,3,0) -> 一居室 | D9: 3 | E9: 1 | F9: 3 | G9: 2 | H9: =IF(C9="开间",IF(D9+E9*2-G9<=0,"1",IF(D9+E9*2-G9<=1,"2",IF(D9+E9*2-G9<=2,"3",IF(D9+E9*2-G9<=3,"4","5")))),IF(D9+E9*2-G9<1.1,"1",IF(D9+E9*2-G9<=2,"2",IF(D9+E9*2-G9<=3,"3",IF(D9+E9*2-G9<=4,"4","5"))))) -> 3 | I9: 无
A10: ='【3-2】大区&运营中心填-房间模型价'!H9 -> 303 | B10: ='【3-2】大区&运营中心填-房间模型价'!I9 -> 1-41G | C10: =VLOOKUP(A10,'【3-2】大区&运营中心填-房间模型价'!H:J,3,0) -> 一居室 | D10: 3 | E10: 1 | F10: 3 | G10: 1 | H10: =IF(C10="开间",IF(D10+E10*2-G10<=0,"1",IF(D10+E10*2-G10<=1,"2",IF(D10+E10*2-G10<=2,"3",IF(D10+E10*2-G10<=3,"4","5")))),IF(D10+E10*2-G10<1.1,"1",IF(D10+E10*2-G10<=2,"2",IF(D10+E10*2-G10<=3,"3",IF(D10+E10*2-G10<=4,"4","5"))))) -> 4 | I10: 无
A11: ='【3-2】大区&运营中心填-房间模型价'!H10 -> 304 | B11: ='【3-2】大区&运营中心填-房间模型价'!I10 -> 1-41F | C11: =VLOOKUP(A11,'【3-2】大区&运营中心填-房间模型价'!H:J,3,0) -> 开间 | D11: 1.5 | E11: 0 | G11: -0.5 | H11: =IF(C11="开间",IF(D11+E11*2-G11<=0,"1",IF(D11+E11*2-G11<=1,"2",IF(D11+E11*2-G11<=2,"3",IF(D11+E11*2-G11<=3,"4","5")))),IF(D11+E11*2-G11<1.1,"1",IF(D11+E11*2-G11<=2,"2",IF(D11+E11*2-G11<=3,"3",IF(D11+E11*2-G11<=4,"4","5"))))) -> 3 | I11: 无
A12: ='【3-2】大区&运营中心填-房间模型价'!H11 -> 401 | B12: ='【3-2】大区&运营中心填-房间模型价'!I11 -> 1-41F | C12: =VLOOKUP(A12,'【3-2】大区&运营中心填-房间模型价'!H:J,3,0) -> 开间 | D12: 1.5 | E12: 0 | G12: 1.5 | H12: =IF(C12="开间",IF(D12+E12*2-G12<=0,"1",IF(D12+E12*2-G12<=1,"2",IF(D12+E12*2-G12<=2,"3",IF(D12+E12*2-G12<=3,"4","5")))),IF(D12+E12*2-G12<1.1,"1",IF(D12+E12*2-G12<=2,"2",IF(D12+E12*2-G12<=3,"3",IF(D12+E12*2-G12<=4,"4","5"))))) -> 1 | I12: 无
A13: ='【3-2】大区&运营中心填-房间模型价'!H12 -> 402 | B13: ='【3-2】大区&运营中心填-房间模型价'!I12 -> 1-41G | C13: =VLOOKUP(A13,'【3-2】大区&运营中心填-房间模型价'!H:J,3,0) -> 一居室 | D13: 3 | E13: 1 | F13: 3 | G13: 2 | H13: =IF(C13="开间",IF(D13+E13*2-G13<=0,"1",IF(D13+E13*2-G13<=1,"2",IF(D13+E13*2-G13<=2,"3",IF(D13+E13*2-G13<=3,"4","5")))),IF(D13+E13*2-G13<1.1,"1",IF(D13+E13*2-G13<=2,"2",IF(D13+E13*2-G13<=3,"3",IF(D13+E13*2-G13<=4,"4","5"))))) -> 3 | I13: 无
A14: ='【3-2】大区&运营中心填-房间模型价'!H13 -> 403 | B14: ='【3-2】大区&运营中心填-房间模型价'!I13 -> 1-41G | C14: =VLOOKUP(A14,'【3-2】大区&运营中心填-房间模型价'!H:J,3,0) -> 一居室 | D14: 3 | E14: 1 | F14: 3 | G14: 1 | H14: =IF(C14="开间",IF(D14+E14*2-G14<=0,"1",IF(D14+E14*2-G14<=1,"2",IF(D14+E14*2-G14<=2,"3",IF(D14+E14*2-G14<=3,"4","5")))),IF(D14+E14*2-G14<1.1,"1",IF(D14+E14*2-G14<=2,"2",IF(D14+E14*2-G14<=3,"3",IF(D14+E14*2-G14<=4,"4","5"))))) -> 4 | I14: 无
A15: ='【3-2】大区&运营中心填-房间模型价'!H14 -> 404 | B15: ='【3-2】大区&运营中心填-房间模型价'!I14 -> 1-41F | C15: =VLOOKUP(A15,'【3-2】大区&运营中心填-房间模型价'!H:J,3,0) -> 开间 | D15: 1.5 | E15: 0 | G15: -0.5 | H15: =IF(C15="开间",IF(D15+E15*2-G15<=0,"1",IF(D15+E15*2-G15<=1,"2",IF(D15+E15*2-G15<=2,"3",IF(D15+E15*2-G15<=3,"4","5")))),IF(D15+E15*2-G15<1.1,"1",IF(D15+E15*2-G15<=2,"2",IF(D15+E15*2-G15<=3,"3",IF(D15+E15*2-G15<=4,"4","5"))))) -> 3 | I15: 无
A16: ='【3-2】大区&运营中心填-房间模型价'!H15 -> 501 | B16: ='【3-2】大区&运营中心填-房间模型价'!I15 -> 1-41F | C16: =VLOOKUP(A16,'【3-2】大区&运营中心填-房间模型价'!H:J,3,0) -> 开间 | D16: 1.5 | E16: 0 | G16: 1.5 | H16: =IF(C16="开间",IF(D16+E16*2-G16<=0,"1",IF(D16+E16*2-G16<=1,"2",IF(D16+E16*2-G16<=2,"3",IF(D16+E16*2-G16<=3,"4","5")))),IF(D16+E16*2-G16<1.1,"1",IF(D16+E16*2-G16<=2,"2",IF(D16+E16*2-G16<=3,"3",IF(D16+E16*2-G16<=4,"4","5"))))) -> 1 | I16: 无 | L16: 以下规格，窗户数按0.5算 | R16: 以下规格，窗户数按1算 | AB16: 以下规格，按窗户数2计算
A17: ='【3-2】大区&运营中心填-房间模型价'!H16 -> 502 | B17: ='【3-2】大区&运营中心填-房间模型价'!I16 -> 1-41G | C17: =VLOOKUP(A17,'【3-2】大区&运营中心填-房间模型价'!H:J,3,0) -> 一居室 | D17: 3 | E17: 1 | F17: 3 | G17: 2 | H17: =IF(C17="开间",IF(D17+E17*2-G17<=0,"1",IF(D17+E17*2-G17<=1,"2",IF(D17+E17*2-G17<=2,"3",IF(D17+E17*2-G17<=3,"4","5")))),IF(D17+E17*2-G17<1.1,"1",IF(D17+E17*2-G17<=2,"2",IF(D17+E17*2-G17<=3,"3",IF(D17+E17*2-G17<=4,"4","5"))))) -> 3 | I17: 无
A18: ='【3-2】大区&运营中心填-房间模型价'!H17 -> 503 | B18: ='【3-2】大区&运营中心填-房间模型价'!I17 -> 1-41G | C18: =VLOOKUP(A18,'【3-2】大区&运营中心填-房间模型价'!H:J,3,0) -> 一居室 | D18: 3 | E18: 1 | F18: 3 | G18: 1 | H18: =IF(C18="开间",IF(D18+E18*2-G18<=0,"1",IF(D18+E18*2-G18<=1,"2",IF(D18+E18*2-G18<=2,"3",IF(D18+E18*2-G18<=3,"4","5")))),IF(D18+E18*2-G18<1.1,"1",IF(D18+E18*2-G18<=2,"2",IF(D18+E18*2-G18<=3,"3",IF(D18+E18*2-G18<=4,"4","5"))))) -> 4 | I18: 无
A19: ='【3-2】大区&运营中心填-房间模型价'!H18 -> 504 | B19: ='【3-2】大区&运营中心填-房间模型价'!I18 -> 1-41F | C19: =VLOOKUP(A19,'【3-2】大区&运营中心填-房间模型价'!H:J,3,0) -> 开间 | D19: 1.5 | E19: 0 | G19: -0.5 | H19: =IF(C19="开间",IF(D19+E19*2-G19<=0,"1",IF(D19+E19*2-G19<=1,"2",IF(D19+E19*2-G19<=2,"3",IF(D19+E19*2-G19<=3,"4","5")))),IF(D19+E19*2-G19<1.1,"1",IF(D19+E19*2-G19<=2,"2",IF(D19+E19*2-G19<=3,"3",IF(D19+E19*2-G19<=4,"4","5"))))) -> 3 | I19: 无
A20: ='【3-2】大区&运营中心填-房间模型价'!H19 -> 601 | B20: ='【3-2】大区&运营中心填-房间模型价'!I19 -> 1-41F | C20: =VLOOKUP(A20,'【3-2】大区&运营中心填-房间模型价'!H:J,3,0) -> 开间 | D20: 1.5 | E20: 0 | G20: 0.5 | H20: =IF(C20="开间",IF(D20+E20*2-G20<=0,"1",IF(D20+E20*2-G20<=1,"2",IF(D20+E20*2-G20<=2,"3",IF(D20+E20*2-G20<=3,"4","5")))),IF(D20+E20*2-G20<1.1,"1",IF(D20+E20*2-G20<=2,"2",IF(D20+E20*2-G20<=3,"3",IF(D20+E20*2-G20<=4,"4","5"))))) -> 2 | I20: 无
A21: ='【3-2】大区&运营中心填-房间模型价'!H20 -> 602 | B21: ='【3-2】大区&运营中心填-房间模型价'!I20 -> 1-41F | C21: =VLOOKUP(A21,'【3-2】大区&运营中心填-房间模型价'!H:J,3,0) -> 开间 | D21: 1.5 | E21: 0 | G21: -1.5 | H21: =IF(C21="开间",IF(D21+E21*2-G21<=0,"1",IF(D21+E21*2-G21<=1,"2",IF(D21+E21*2-G21<=2,"3",IF(D21+E21*2-G21<=3,"4","5")))),IF(D21+E21*2-G21<1.1,"1",IF(D21+E21*2-G21<=2,"2",IF(D21+E21*2-G21<=3,"3",IF(D21+E21*2-G21<=4,"4","5"))))) -> 4 | I21: 无
A22: ='【3-2】大区&运营中心填-房间模型价'!#REF! -> #REF! | B22: ='【3-2】大区&运营中心填-房间模型价'!#REF! -> #REF! | C22: =VLOOKUP(A22,'【3-2】大区&运营中心填-房间模型价'!H:J,3,0) -> #REF! | H22: =IF(C22="开间",IF(D22+E22*2-G22<=0,"1",IF(D22+E22*2-G22<=1,"2",IF(D22+E22*2-G22<=2,"3",IF(D22+E22*2-G22<=3,"4","5")))),IF(D22+E22*2-G22<1.1,"1",IF(D22+E22*2-G22<=2,"2",IF(D22+E22*2-G22<=3,"3",IF(D22+E22*2-G22<=4,"4","5"))))) -> #REF!
A23: ='【3-2】大区&运营中心填-房间模型价'!#REF! -> #REF! | B23: ='【3-2】大区&运营中心填-房间模型价'!#REF! -> #REF! | C23: =VLOOKUP(A23,'【3-2】大区&运营中心填-房间模型价'!H:J,3,0) -> #REF! | H23: =IF(C23="开间",IF(D23+E23*2-G23<=0,"1",IF(D23+E23*2-G23<=1,"2",IF(D23+E23*2-G23<=2,"3",IF(D23+E23*2-G23<=3,"4","5")))),IF(D23+E23*2-G23<1.1,"1",IF(D23+E23*2-G23<=2,"2",IF(D23+E23*2-G23<=3,"3",IF(D23+E23*2-G23<=4,"4","5"))))) -> #REF!
A24: ='【3-2】大区&运营中心填-房间模型价'!#REF! -> #REF! | B24: ='【3-2】大区&运营中心填-房间模型价'!#REF! -> #REF! | C24: =VLOOKUP(A24,'【3-2】大区&运营中心填-房间模型价'!H:J,3,0) -> #REF! | H24: =IF(C24="开间",IF(D24+E24*2-G24<=0,"1",IF(D24+E24*2-G24<=1,"2",IF(D24+E24*2-G24<=2,"3",IF(D24+E24*2-G24<=3,"4","5")))),IF(D24+E24*2-G24<1.1,"1",IF(D24+E24*2-G24<=2,"2",IF(D24+E24*2-G24<=3,"3",IF(D24+E24*2-G24<=4,"4","5"))))) -> #REF!
A25: ='【3-2】大区&运营中心填-房间模型价'!#REF! -> #REF! | B25: ='【3-2】大区&运营中心填-房间模型价'!#REF! -> #REF! | C25: =VLOOKUP(A25,'【3-2】大区&运营中心填-房间模型价'!H:J,3,0) -> #REF! | H25: =IF(C25="开间",IF(D25+E25*2-G25<=0,"1",IF(D25+E25*2-G25<=1,"2",IF(D25+E25*2-G25<=2,"3",IF(D25+E25*2-G25<=3,"4","5")))),IF(D25+E25*2-G25<1.1,"1",IF(D25+E25*2-G25<=2,"2",IF(D25+E25*2-G25<=3,"3",IF(D25+E25*2-G25<=4,"4","5"))))) -> #REF!
A26: ='【3-2】大区&运营中心填-房间模型价'!#REF! -> #REF! | B26: ='【3-2】大区&运营中心填-房间模型价'!#REF! -> #REF! | C26: =VLOOKUP(A26,'【3-2】大区&运营中心填-房间模型价'!H:J,3,0) -> #REF! | H26: =IF(C26="开间",IF(D26+E26*2-G26<=0,"1",IF(D26+E26*2-G26<=1,"2",IF(D26+E26*2-G26<=2,"3",IF(D26+E26*2-G26<=3,"4","5")))),IF(D26+E26*2-G26<1.1,"1",IF(D26+E26*2-G26<=2,"2",IF(D26+E26*2-G26<=3,"3",IF(D26+E26*2-G26<=4,"4","5"))))) -> #REF!
A27: ='【3-2】大区&运营中心填-房间模型价'!#REF! -> #REF! | B27: ='【3-2】大区&运营中心填-房间模型价'!#REF! -> #REF! | C27: =VLOOKUP(A27,'【3-2】大区&运营中心填-房间模型价'!H:J,3,0) -> #REF! | H27: =IF(C27="开间",IF(D27+E27*2-G27<=0,"1",IF(D27+E27*2-G27<=1,"2",IF(D27+E27*2-G27<=2,"3",IF(D27+E27*2-G27<=3,"4","5")))),IF(D27+E27*2-G27<1.1,"1",IF(D27+E27*2-G27<=2,"2",IF(D27+E27*2-G27<=3,"3",IF(D27+E27*2-G27<=4,"4","5"))))) -> #REF!
A28: ='【3-2】大区&运营中心填-房间模型价'!#REF! -> #REF! | B28: ='【3-2】大区&运营中心填-房间模型价'!#REF! -> #REF! | C28: =VLOOKUP(A28,'【3-2】大区&运营中心填-房间模型价'!H:J,3,0) -> #REF! | H28: =IF(C28="开间",IF(D28+E28*2-G28<=0,"1",IF(D28+E28*2-G28<=1,"2",IF(D28+E28*2-G28<=2,"3",IF(D28+E28*2-G28<=3,"4","5")))),IF(D28+E28*2-G28<1.1,"1",IF(D28+E28*2-G28<=2,"2",IF(D28+E28*2-G28<=3,"3",IF(D28+E28*2-G28<=4,"4","5"))))) -> #REF!
A29: ='【3-2】大区&运营中心填-房间模型价'!#REF! -> #REF! | B29: ='【3-2】大区&运营中心填-房间模型价'!#REF! -> #REF! | C29: =VLOOKUP(A29,'【3-2】大区&运营中心填-房间模型价'!H:J,3,0) -> #REF! | H29: =IF(C29="开间",IF(D29+E29*2-G29<=0,"1",IF(D29+E29*2-G29<=1,"2",IF(D29+E29*2-G29<=2,"3",IF(D29+E29*2-G29<=3,"4","5")))),IF(D29+E29*2-G29<1.1,"1",IF(D29+E29*2-G29<=2,"2",IF(D29+E29*2-G29<=3,"3",IF(D29+E29*2-G29<=4,"4","5"))))) -> #REF!
A30: ='【3-2】大区&运营中心填-房间模型价'!#REF! -> #REF! | B30: ='【3-2】大区&运营中心填-房间模型价'!#REF! -> #REF! | C30: =VLOOKUP(A30,'【3-2】大区&运营中心填-房间模型价'!H:J,3,0) -> #REF! | H30: =IF(C30="开间",IF(D30+E30*2-G30<=0,"1",IF(D30+E30*2-G30<=1,"2",IF(D30+E30*2-G30<=2,"3",IF(D30+E30*2-G30<=3,"4","5")))),IF(D30+E30*2-G30<1.1,"1",IF(D30+E30*2-G30<=2,"2",IF(D30+E30*2-G30<=3,"3",IF(D30+E30*2-G30<=4,"4","5"))))) -> #REF!
A31: ='【3-2】大区&运营中心填-房间模型价'!#REF! -> #REF! | B31: ='【3-2】大区&运营中心填-房间模型价'!#REF! -> #REF! | C31: =VLOOKUP(A31,'【3-2】大区&运营中心填-房间模型价'!H:J,3,0) -> #REF! | H31: =IF(C31="开间",IF(D31+E31*2-G31<=0,"1",IF(D31+E31*2-G31<=1,"2",IF(D31+E31*2-G31<=2,"3",IF(D31+E31*2-G31<=3,"4","5")))),IF(D31+E31*2-G31<1.1,"1",IF(D31+E31*2-G31<=2,"2",IF(D31+E31*2-G31<=3,"3",IF(D31+E31*2-G31<=4,"4","5"))))) -> #REF!
A32: ='【3-2】大区&运营中心填-房间模型价'!#REF! -> #REF! | B32: ='【3-2】大区&运营中心填-房间模型价'!#REF! -> #REF! | C32: =VLOOKUP(A32,'【3-2】大区&运营中心填-房间模型价'!H:J,3,0) -> #REF! | H32: =IF(C32="开间",IF(D32+E32*2-G32<=0,"1",IF(D32+E32*2-G32<=1,"2",IF(D32+E32*2-G32<=2,"3",IF(D32+E32*2-G32<=3,"4","5")))),IF(D32+E32*2-G32<1.1,"1",IF(D32+E32*2-G32<=2,"2",IF(D32+E32*2-G32<=3,"3",IF(D32+E32*2-G32<=4,"4","5"))))) -> #REF!
A33: ='【3-2】大区&运营中心填-房间模型价'!#REF! -> #REF! | B33: ='【3-2】大区&运营中心填-房间模型价'!#REF! -> #REF! | C33: =VLOOKUP(A33,'【3-2】大区&运营中心填-房间模型价'!H:J,3,0) -> #REF! | H33: =IF(C33="开间",IF(D33+E33*2-G33<=0,"1",IF(D33+E33*2-G33<=1,"2",IF(D33+E33*2-G33<=2,"3",IF(D33+E33*2-G33<=3,"4","5")))),IF(D33+E33*2-G33<1.1,"1",IF(D33+E33*2-G33<=2,"2",IF(D33+E33*2-G33<=3,"3",IF(D33+E33*2-G33<=4,"4","5"))))) -> #REF!
... A201: ='【3-2】大区&运营中心填-房间模型价'!#REF! -> #REF! | B201: ='【3-2】大区&运营中心填-房间模型价'!#REF! -> #REF! | C201: =VLOOKUP(A201,'【3-2】大区&运营中心填-房间模型价'!H:J,3,0) -> #REF! | H201: =IF(C201="开间",IF(D201+E201*2-G201<=0,"1",IF(D201+E201*2-G201<=1,"2",IF(D201+E201*2-G201<=2,"3",IF(D201+E201*2-G201<=3,"4","5")))),IF(D201+E201*2-G201<1.1,"1",IF(D201+E201*2-G201<=2,"2",IF(D201+E201*2-G201<=3,"3",IF(D201+E201*2-G201<=4,"4","5"))))) -> #REF!
A202: ='【3-2】大区&运营中心填-房间模型价'!H21 -> 0 | B202: ='【3-2】大区&运营中心填-房间模型价'!I21 -> 0 | C202: =VLOOKUP(A202,'【3-2】大区&运营中心填-房间模型价'!H:J,3,0) -> #N/A | H202: =IF(C202="开间",IF(D202+E202*2-G202<=0,"1",IF(D202+E202*2-G202<=1,"2",IF(D202+E202*2-G202<=2,"3",IF(D202+E202*2-G202<=3,"4","5")))),IF(D202+E202*2-G202<1.1,"1",IF(D202+E202*2-G202<=2,"2",IF(D202+E202*2-G202<=3,"3",IF(D202+E202*2-G202<=4,"4","5"))))) -> #N/A
A203: ='【3-2】大区&运营中心填-房间模型价'!H22 -> 0 | B203: ='【3-2】大区&运营中心填-房间模型价'!I22 -> 0 | C203: =VLOOKUP(A203,'【3-2】大区&运营中心填-房间模型价'!H:J,3,0) -> #N/A | H203: =IF(C203="开间",IF(D203+E203*2-G203<=0,"1",IF(D203+E203*2-G203<=1,"2",IF(D203+E203*2-G203<=2,"3",IF(D203+E203*2-G203<=3,"4","5")))),IF(D203+E203*2-G203<1.1,"1",IF(D203+E203*2-G203<=2,"2",IF(D203+E203*2-G203<=3,"3",IF(D203+E203*2-G203<=4,"4","5"))))) -> #N/A
A204: ='【3-2】大区&运营中心填-房间模型价'!H23 -> 0 | B204: ='【3-2】大区&运营中心填-房间模型价'!I23 -> 0 | C204: =VLOOKUP(A204,'【3-2】大区&运营中心填-房间模型价'!H:J,3,0) -> #N/A | H204: =IF(C204="开间",IF(D204+E204*2-G204<=0,"1",IF(D204+E204*2-G204<=1,"2",IF(D204+E204*2-G204<=2,"3",IF(D204+E204*2-G204<=3,"4","5")))),IF(D204+E204*2-G204<1.1,"1",IF(D204+E204*2-G204<=2,"2",IF(D204+E204*2-G204<=3,"3",IF(D204+E204*2-G204<=4,"4","5"))))) -> #N/A
A205: ='【3-2】大区&运营中心填-房间模型价'!H24 -> 0 | B205: ='【3-2】大区&运营中心填-房间模型价'!I24 -> 0 | C205: =VLOOKUP(A205,'【3-2】大区&运营中心填-房间模型价'!H:J,3,0) -> #N/A | H205: =IF(C205="开间",IF(D205+E205*2-G205<=0,"1",IF(D205+E205*2-G205<=1,"2",IF(D205+E205*2-G205<=2,"3",IF(D205+E205*2-G205<=3,"4","5")))),IF(D205+E205*2-G205<1.1,"1",IF(D205+E205*2-G205<=2,"2",IF(D205+E205*2-G205<=3,"3",IF(D205+E205*2-G205<=4,"4","5"))))) -> #N/A
A206: ='【3-2】大区&运营中心填-房间模型价'!H25 -> 0 | B206: ='【3-2】大区&运营中心填-房间模型价'!I25 -> 0 | C206: =VLOOKUP(A206,'【3-2】大区&运营中心填-房间模型价'!H:J,3,0) -> #N/A | H206: =IF(C206="开间",IF(D206+E206*2-G206<=0,"1",IF(D206+E206*2-G206<=1,"2",IF(D206+E206*2-G206<=2,"3",IF(D206+E206*2-G206<=3,"4","5")))),IF(D206+E206*2-G206<1.1,"1",IF(D206+E206*2-G206<=2,"2",IF(D206+E206*2-G206<=3,"3",IF(D206+E206*2-G206<=4,"4","5"))))) -> #N/A
A207: ='【3-2】大区&运营中心填-房间模型价'!H26 -> 0 | B207: ='【3-2】大区&运营中心填-房间模型价'!I26 -> 0 | C207: =VLOOKUP(A207,'【3-2】大区&运营中心填-房间模型价'!H:J,3,0) -> #N/A | H207: =IF(C207="开间",IF(D207+E207*2-G207<=0,"1",IF(D207+E207*2-G207<=1,"2",IF(D207+E207*2-G207<=2,"3",IF(D207+E207*2-G207<=3,"4","5")))),IF(D207+E207*2-G207<1.1,"1",IF(D207+E207*2-G207<=2,"2",IF(D207+E207*2-G207<=3,"3",IF(D207+E207*2-G207<=4,"4","5"))))) -> #N/A
A208: ='【3-2】大区&运营中心填-房间模型价'!H27 -> 0 | B208: ='【3-2】大区&运营中心填-房间模型价'!I27 -> 0 | C208: =VLOOKUP(A208,'【3-2】大区&运营中心填-房间模型价'!H:J,3,0) -> #N/A | H208: =IF(C208="开间",IF(D208+E208*2-G208<=0,"1",IF(D208+E208*2-G208<=1,"2",IF(D208+E208*2-G208<=2,"3",IF(D208+E208*2-G208<=3,"4","5")))),IF(D208+E208*2-G208<1.1,"1",IF(D208+E208*2-G208<=2,"2",IF(D208+E208*2-G208<=3,"3",IF(D208+E208*2-G208<=4,"4","5"))))) -> #N/A
A209: ='【3-2】大区&运营中心填-房间模型价'!H28 -> 0 | B209: ='【3-2】大区&运营中心填-房间模型价'!I28 -> 0 | C209: =VLOOKUP(A209,'【3-2】大区&运营中心填-房间模型价'!H:J,3,0) -> #N/A | H209: =IF(C209="开间",IF(D209+E209*2-G209<=0,"1",IF(D209+E209*2-G209<=1,"2",IF(D209+E209*2-G209<=2,"3",IF(D209+E209*2-G209<=3,"4","5")))),IF(D209+E209*2-G209<1.1,"1",IF(D209+E209*2-G209<=2,"2",IF(D209+E209*2-G209<=3,"3",IF(D209+E209*2-G209<=4,"4","5"))))) -> #N/A
A210: ='【3-2】大区&运营中心填-房间模型价'!H29 -> 0 | B210: ='【3-2】大区&运营中心填-房间模型价'!I29 -> 0 | C210: =VLOOKUP(A210,'【3-2】大区&运营中心填-房间模型价'!H:J,3,0) -> #N/A | H210: =IF(C210="开间",IF(D210+E210*2-G210<=0,"1",IF(D210+E210*2-G210<=1,"2",IF(D210+E210*2-G210<=2,"3",IF(D210+E210*2-G210<=3,"4","5")))),IF(D210+E210*2-G210<1.1,"1",IF(D210+E210*2-G210<=2,"2",IF(D210+E210*2-G210<=3,"3",IF(D210+E210*2-G210<=4,"4","5"))))) -> #N/A
A211: ='【3-2】大区&运营中心填-房间模型价'!H30 -> 0 | B211: ='【3-2】大区&运营中心填-房间模型价'!I30 -> 0 | C211: =VLOOKUP(A211,'【3-2】大区&运营中心填-房间模型价'!H:J,3,0) -> #N/A | H211: =IF(C211="开间",IF(D211+E211*2-G211<=0,"1",IF(D211+E211*2-G211<=1,"2",IF(D211+E211*2-G211<=2,"3",IF(D211+E211*2-G211<=3,"4","5")))),IF(D211+E211*2-G211<1.1,"1",IF(D211+E211*2-G211<=2,"2",IF(D211+E211*2-G211<=3,"3",IF(D211+E211*2-G211<=4,"4","5"))))) -> #N/A
A212: ='【3-2】大区&运营中心填-房间模型价'!H31 -> 0 | B212: ='【3-2】大区&运营中心填-房间模型价'!I31 -> 0 | C212: =VLOOKUP(A212,'【3-2】大区&运营中心填-房间模型价'!H:J,3,0) -> #N/A | H212: =IF(C212="开间",IF(D212+E212*2-G212<=0,"1",IF(D212+E212*2-G212<=1,"2",IF(D212+E212*2-G212<=2,"3",IF(D212+E212*2-G212<=3,"4","5")))),IF(D212+E212*2-G212<1.1,"1",IF(D212+E212*2-G212<=2,"2",IF(D212+E212*2-G212<=3,"3",IF(D212+E212*2-G212<=4,"4","5"))))) -> #N/A
A213: ='【3-2】大区&运营中心填-房间模型价'!H32 -> 0 | B213: ='【3-2】大区&运营中心填-房间模型价'!I32 -> 0 | C213: =VLOOKUP(A213,'【3-2】大区&运营中心填-房间模型价'!H:J,3,0) -> #N/A | H213: =IF(C213="开间",IF(D213+E213*2-G213<=0,"1",IF(D213+E213*2-G213<=1,"2",IF(D213+E213*2-G213<=2,"3",IF(D213+E213*2-G213<=3,"4","5")))),IF(D213+E213*2-G213<1.1,"1",IF(D213+E213*2-G213<=2,"2",IF(D213+E213*2-G213<=3,"3",IF(D213+E213*2-G213<=4,"4","5"))))) -> #N/A
... A276: ='【3-2】大区&运营中心填-房间模型价'!H95 -> 0 | B276: ='【3-2】大区&运营中心填-房间模型价'!I95 -> 0 | C276: =VLOOKUP(A276,'【3-2】大区&运营中心填-房间模型价'!H:J,3,0) -> #N/A | H276: =IF(C276="开间",IF(D276+E276*2-G276<=0,"1",IF(D276+E276*2-G276<=1,"2",IF(D276+E276*2-G276<=2,"3",IF(D276+E276*2-G276<=3,"4","5")))),IF(D276+E276*2-G276<1.1,"1",IF(D276+E276*2-G276<=2,"2",IF(D276+E276*2-G276<=3,"3",IF(D276+E276*2-G276<=4,"4","5"))))) -> #N/A

Sheet 【3-2】大区&运营中心填-房间模型价
A1: 楼栋 | B1: 标准层1 | C1: 标准层2 | D1: 标准层3 | E1: 标准层4 | F1: 标准层5 | G1: 标准层6 | H1: 房间号 | I1: 户型 | J1: 基准格局 | K1: 格局 | L1: 基准格局定价 | M1: 套内空间 | N1: 套内面积 | O1: 调价倍数1 | P1: 阳台 | Q1: 调价倍数2 | R1: 楼梯房楼层 | S1: 调价倍数3 | T1: 电梯房楼层 | U1: 调价倍数4 | V1: =【1】定价因子!$C$38 -> 功能配置（开间） | W1: 调价倍数5 | X1: =【1】定价因子!$C$51 -> 功能配置（一居） | Y1: 调价倍数6 | Z1: =【1】定价因子!$C$58 -> 功能配置（二居） | AA1: 调价倍数7 | AB1: 采光 | AC1: 调价倍数8 | AD1: 房间模型价 | AE1: 实际定价 | AF1: 差距 | AG1: 原实际定价
A2: ='【2】运营中心填-基本信息&审核标准'!$E$2 -> 福围广生1-41栋 | B2: =INT(H2/100) -> 1 | C2: =COUNTIF($B$2:$B$20,B2) -> 2 | D2: =COUNTIF(C$2:C$20,C2) -> 4 | E2: =MAX(D2:D20) -> 12 | F2: =IF(D2=$E$2,C2,"") | G2: =MAX(F2:F20) -> 4 | H2: 101 | I2: 1-41A | J2: 开间 | K2: {=IFERROR(INDEX($J$2:$J$20,MATCH(0,IF(ISBLANK($J$2:$J$20),1,COUNTIF($K$1:K1,$J$2:$J$20)),0)),"")} -> 开间 | L2: =VLOOKUP(J2,'【3】大区填-楼栋基准格局定价'!B:J,9,0) -> 1238.0928 | M2: =IF(OR(J2="开间",J2="二人宿舍"),IF(N2<10,"很狭小",IF(N2<13,"较狭小",IF(N2<17,"适中",IF(N2<20,"较宽敞","很宽敞")))),IF(OR(J2="一居室",J2="四人宿舍"),IF(N2<20,"很狭小",IF(N2<23,"较狭小",IF(N2<26,"适中",IF(N2<28,"较宽敞","很宽敞")))),IF(OR(J2="二居室",J2="六人宿舍"),IF(N2<30,"很狭小",IF(N2<35,"较狭小",IF(N2<40,"适中",IF(N2<45,"较宽敞","很宽敞")))),""))) -> 适中 | N2: 13.3 | O2: =VLOOKUP($M$1&M2,【1】定价因子!E:F,2,0) -> 1 | P2: =IF(VLOOKUP(H2,'【3-1】大区填-采光基本要素'!A:E,5,FALSE)=0,"无","有") -> 无 | Q2: =VLOOKUP($P$1&P2,【1】定价因子!E:F,2,0) -> 1 | R2: =IF('【2】运营中心填-基本信息&审核标准'!$D$4="是","无",IF(INT(H2/100)>9,"9F",INT(H2/100)&"F")) -> 1F | S2: =VLOOKUP(R2,【1】定价因子!D:F,3,0) -> 0.91 | T2: =IF('【2】运营中心填-基本信息&审核标准'!$D$4="否","无",IF(INT(H2/100)=1,"1F",IF(AND(INT(H2/100)>=2,INT(H2/100)<=3),"2-3F",IF(INT(H2/100)=4,"4F",IF(AND(INT(H2/100)>=5,INT(H2/100)<=6),"5-6F",IF(AND(INT(H2/100)>=7,INT(H2/100)<=8),"7-8F",IF(AND(INT(H2/100)>=9,INT(H2/100)<=10),"9-10F",IF(AND(INT(H2/100)>=11,INT(H2/100)<=12),"11-12F",IF(INT(H2/100)>=13,"13以上F",""))))))))) -> 无 | U2: =VLOOKUP($T$1&T2,【1】定价因子!E:F,2,0) -> 1 | V2: 适中 | W2: =VLOOKUP($V$1&V2,【1】定价因子!E:F,2,0) -> 1 | X2: 适中 | Y2: =VLOOKUP($X$1&X2,【1】定价因子!$E:$F,2,0) -> 1 | Z2: 适中 | AA2: =VLOOKUP($Z$1&Z2,【1】定价因子!$E:$F,2,0) -> 1 | AB2: =VLOOKUP(H2,'【3-1】大区填-采光基本要素'!A:H,8,0) -> 1 | AC2: =VLOOKUP($AB$1&AB2,【1】定价因子!$E:$F,2,0) -> 0.91 | AD2: =L2*PRODUCT(Y2,AC2,W2,U2,S2,Q2,O2) -> 1025.2646 | AE2: 850 | AF2: =AE2/AD2-1 -> -0.17094576 | AG2: 938
A3: ='【2】运营中心填-基本信息&审核标准'!$E$2 -> 福围广生1-41栋 | B3: =INT(H3/100) -> 1 | C3: =COUNTIF($B$2:$B$20,B3) -> 2 | D3: =COUNTIF(C$2:C$20,C3) -> 4 | F3: =IF(D3=$E$2,C3,"") | H3: 102 | I3: 1-41B | J3: 一居室 | K3: {=IFERROR(INDEX($J$2:$J$20,MATCH(0,IF(ISBLANK($J$2:$J$20),1,COUNTIF($K$1:K2,$J$2:$J$20)),0)),"")} -> 一居室 | L3: =VLOOKUP(J3,'【3】大区填-楼栋基准格局定价'!B:J,9,0) -> 1845.12 | M3: =IF(OR(J3="开间",J3="二人宿舍"),IF(N3<10,"很狭小",IF(N3<13,"较狭小",IF(N3<17,"适中",IF(N3<20,"较宽敞","很宽敞")))),IF(OR(J3="一居室",J3="四人宿舍"),IF(N3<20,"很狭小",IF(N3<23,"较狭小",IF(N3<26,"适中",IF(N3<28,"较宽敞","很宽敞")))),IF(OR(J3="二居室",J3="六人宿舍"),IF(N3<30,"很狭小",IF(N3<35,"较狭小",IF(N3<40,"适中",IF(N3<45,"较宽敞","很宽敞")))),""))) -> 很狭小 | N3: 19.12 | O3: =VLOOKUP($M$1&M3,【1】定价因子!E:F,2,0) -> 0.9 | P3: =IF(VLOOKUP(H3,'【3-1】大区填-采光基本要素'!A:E,5,FALSE)=0,"无","有") -> 无 | Q3: =VLOOKUP($P$1&P3,【1】定价因子!E:F,2,0) -> 1 | R3: =IF('【2】运营中心填-基本信息&审核标准'!$D$4="是","无",IF(INT(H3/100)>9,"9F",INT(H3/100)&"F")) -> 1F | S3: =VLOOKUP(R3,【1】定价因子!D:F,3,0) -> 0.91 | T3: =IF('【2】运营中心填-基本信息&审核标准'!$D$4="否","无",IF(INT(H3/100)=1,"1F",IF(AND(INT(H3/100)>=2,INT(H3/100)<=3),"2-3F",IF(INT(H3/100)=4,"4F",IF(AND(INT(H3/100)>=5,INT(H3/100)<=6),"5-6F",IF(AND(INT(H3/100)>=7,INT(H3/100)<=8),"7-8F",IF(AND(INT(H3/100)>=9,INT(H3/100)<=10),"9-10F",IF(AND(INT(H3/100)>=11,INT(H3/100)<=12),"11-12F",IF(INT(H3/100)>=13,"13以上F",""))))))))) -> 无 | U3: =VLOOKUP($T$1&T3,【1】定价因子!E:F,2,0) -> 1 | V3: 适中 | W3: =VLOOKUP($V$1&V3,【1】定价因子!E:F,2,0) -> 1 | X3: 适中 | Y3: =VLOOKUP($X$1&X3,【1】定价因子!$E:$F,2,0) -> 1 | Z3: 适中 | AA3: =VLOOKUP($Z$1&Z3,【1】定价因子!$E:$F,2,0) -> 1 | AB3: =VLOOKUP(H3,'【3-1】大区填-采光基本要素'!A:H,8,0) -> 1 | AC3: =VLOOKUP($AB$1&AB3,【1】定价因子!$E:$F,2,0) -> 0.91 | AD3: =L3*PRODUCT(Y3,AC3,W3,U3,S3,Q3,O3) -> 1375.1495 | AE3: 1407.8 | AF3: =AE3/AD3-1 -> 0.023743248
A4: ='【2】运营中心填-基本信息&审核标准'!$E$2 -> 福围广生1-41栋 | B4: =INT(H4/100) -> 2 | C4: =COUNTIF($B$2:$B$20,B4) -> 3 | D4: =COUNTIF(C$2:C$20,C4) -> 3 | F4: =IF(D4=$E$2,C4,"") | H4: 201 | I4: 1-41C | J4: 开间 | K4: {=IFERROR(INDEX($J$2:$J$20,MATCH(0,IF(ISBLANK($J$2:$J$20),1,COUNTIF($K$1:K3,$J$2:$J$20)),0)),"")} | L4: =VLOOKUP(J4,'【3】大区填-楼栋基准格局定价'!B:J,9,0) -> 1238.0928 | M4: =IF(OR(J4="开间",J4="二人宿舍"),IF(N4<10,"很狭小",IF(N4<13,"较狭小",IF(N4<17,"适中",IF(N4<20,"较宽敞","很宽敞")))),IF(OR(J4="一居室",J4="四人宿舍"),IF(N4<20,"很狭小",IF(N4<23,"较狭小",IF(N4<26,"适中",IF(N4<28,"较宽敞","很宽敞")))),IF(OR(J4="二居室",J4="六人宿舍"),IF(N4<30,"很狭小",IF(N4<35,"较狭小",IF(N4<40,"适中",IF(N4<45,"较宽敞","很宽敞")))),""))) -> 适中 | N4: 14.72 | O4: =VLOOKUP($M$1&M4,【1】定价因子!E:F,2,0) -> 1 | P4: =IF(VLOOKUP(H4,'【3-1】大区填-采光基本要素'!A:E,5,FALSE)=0,"无","有") -> 无 | Q4: =VLOOKUP($P$1&P4,【1】定价因子!E:F,2,0) -> 1 | R4: =IF('【2】运营中心填-基本信息&审核标准'!$D$4="是","无",IF(INT(H4/100)>9,"9F",INT(H4/100)&"F")) -> 2F | S4: =VLOOKUP(R4,【1】定价因子!D:F,3,0) -> 1.02 | T4: =IF('【2】运营中心填-基本信息&审核标准'!$D$4="否","无",IF(INT(H4/100)=1,"1F",IF(AND(INT(H4/100)>=2,INT(H4/100)<=3),"2-3F",IF(INT(H4/100)=4,"4F",IF(AND(INT(H4/100)>=5,INT(H4/100)<=6),"5-6F",IF(AND(INT(H4/100)>=7,INT(H4/100)<=8),"7-8F",IF(AND(INT(H4/100)>=9,INT(H4/100)<=10),"9-10F",IF(AND(INT(H4/100)>=11,INT(H4/100)<=12),"11-12F",IF(INT(H4/100)>=13,"13以上F",""))))))))) -> 无 | U4: =VLOOKUP($T$1&T4,【1】定价因子!E:F,2,0) -> 1 | V4: 适中 | W4: =VLOOKUP($V$1&V4,【1】定价因子!E:F,2,0) -> 1 | X4: 适中 | Y4: =VLOOKUP($X$1&X4,【1】定价因子!$E:$F,2,0) -> 1 | Z4: 适中 | AA4: =VLOOKUP($Z$1&Z4,【1】定价因子!$E:$F,2,0) -> 1 | AB4: =VLOOKUP(H4,'【3-1】大区填-采光基本要素'!A:H,8,0) -> 1 | AC4: =VLOOKUP($AB$1&AB4,【1】定价因子!$E:$F,2,0) -> 0.91 | AD4: =L4*PRODUCT(Y4,AC4,W4,U4,S4,Q4,O4) -> 1149.1977 | AE4: 1137.8 | AF4: =AE4/AD4-1 -> -0.0099179946
A5: ='【2】运营中心填-基本信息&审核标准'!$E$2 -> 福围广生1-41栋 | B5: =INT(H5/100) -> 2 | C5: =COUNTIF($B$2:$B$20,B5) -> 3 | D5: =COUNTIF(C$2:C$20,C5) -> 3 | F5: =IF(D5=$E$2,C5,"") | H5: 202 | I5: 1-41D | J5: 一居室 | K5: {=IFERROR(INDEX($J$2:$J$20,MATCH(0,IF(ISBLANK($J$2:$J$20),1,COUNTIF($K$1:K4,$J$2:$J$20)),0)),"")} | L5: =VLOOKUP(J5,'【3】大区填-楼栋基准格局定价'!B:J,9,0) -> 1845.12 | M5: =IF(OR(J5="开间",J5="二人宿舍"),IF(N5<10,"很狭小",IF(N5<13,"较狭小",IF(N5<17,"适中",IF(N5<20,"较宽敞","很宽敞")))),IF(OR(J5="一居室",J5="四人宿舍"),IF(N5<20,"很狭小",IF(N5<23,"较狭小",IF(N5<26,"适中",IF(N5<28,"较宽敞","很宽敞")))),IF(OR(J5="二居室",J5="六人宿舍"),IF(N5<30,"很狭小",IF(N5<35,"较狭小",IF(N5<40,"适中",IF(N5<45,"较宽敞","很宽敞")))),""))) -> 很狭小 | N5: 19.74 | O5: =VLOOKUP($M$1&M5,【1】定价因子!E:F,2,0) -> 0.9 | P5: =IF(VLOOKUP(H5,'【3-1】大区填-采光基本要素'!A:E,5,FALSE)=0,"无","有") -> 无 | Q5: =VLOOKUP($P$1&P5,【1】定价因子!E:F,2,0) -> 1 | R5: =IF('【2】运营中心填-基本信息&审核标准'!$D$4="是","无",IF(INT(H5/100)>9,"9F",INT(H5/100)&"F")) -> 2F | S5: =VLOOKUP(R5,【1】定价因子!D:F,3,0) -> 1.02 | T5: =IF('【2】运营中心填-基本信息&审核标准'!$D$4="否","无",IF(INT(H5/100)=1,"1F",IF(AND(INT(H5/100)>=2,INT(H5/100)<=3),"2-3F",IF(INT(H5/100)=4,"4F",IF(AND(INT(H5/100)>=5,INT(H5/100)<=6),"5-6F",IF(AND(INT(H5/100)>=7,INT(H5/100)<=8),"7-8F",IF(AND(INT(H5/100)>=9,INT(H5/100)<=10),"9-10F",IF(AND(INT(H5/100)>=11,INT(H5/100)<=12),"11-12F",IF(INT(H5/100)>=13,"13以上F",""))))))))) -> 无 | U5: =VLOOKUP($T$1&T5,【1】定价因子!E:F,2,0) -> 1 | V5: 适中 | W5: =VLOOKUP($V$1&V5,【1】定价因子!E:F,2,0) -> 1 | X5: 适中 | Y5: =VLOOKUP($X$1&X5,【1】定价因子!$E:$F,2,0) -> 1 | Z5: 适中 | AA5: =VLOOKUP($Z$1&Z5,【1】定价因子!$E:$F,2,0) -> 1 | AB5: =VLOOKUP(H5,'【3-1】大区填-采光基本要素'!A:H,8,0) -> 1 | AC5: =VLOOKUP($AB$1&AB5,【1】定价因子!$E:$F,2,0) -> 0.91 | AD5: =L5*PRODUCT(Y5,AC5,W5,U5,S5,Q5,O5) -> 1541.3763 | AE5: 1517.8 | AF5: =AE5/AD5-1 -> -0.015295645
A6: ='【2】运营中心填-基本信息&审核标准'!$E$2 -> 福围广生1-41栋 | B6: =INT(H6/100) -> 2 | C6: =COUNTIF($B$2:$B$20,B6) -> 3 | D6: =COUNTIF(C$2:C$20,C6) -> 3 | F6: =IF(D6=$E$2,C6,"") | H6: 203 | I6: 1-41E | J6: 一居室 | K6: {=IFERROR(INDEX($J$2:$J$20,MATCH(0,IF(ISBLANK($J$2:$J$20),1,COUNTIF($K$1:K5,$J$2:$J$20)),0)),"")} | L6: =VLOOKUP(J6,'【3】大区填-楼栋基准格局定价'!B:J,9,0) -> 1845.12 | M6: =IF(OR(J6="开间",J6="二人宿舍"),IF(N6<10,"很狭小",IF(N6<13,"较狭小",IF(N6<17,"适中",IF(N6<20,"较宽敞","很宽敞")))),IF(OR(J6="一居室",J6="四人宿舍"),IF(N6<20,"很狭小",IF(N6<23,"较狭小",IF(N6<26,"适中",IF(N6<28,"较宽敞","很宽敞")))),IF(OR(J6="二居室",J6="六人宿舍"),IF(N6<30,"很狭小",IF(N6<35,"较狭小",IF(N6<40,"适中",IF(N6<45,"较宽敞","很宽敞")))),""))) -> 适中 | N6: 23.35 | O6: =VLOOKUP($M$1&M6,【1】定价因子!E:F,2,0) -> 1 | P6: =IF(VLOOKUP(H6,'【3-1】大区填-采光基本要素'!A:E,5,FALSE)=0,"无","有") -> 有 | Q6: =VLOOKUP($P$1&P6,【1】定价因子!E:F,2,0) -> 1.07 | R6: =IF('【2】运营中心填-基本信息&审核标准'!$D$4="是","无",IF(INT(H6/100)>9,"9F",INT(H6/100)&"F")) -> 2F | S6: =VLOOKUP(R6,【1】定价因子!D:F,3,0) -> 1.02 | T6: =IF('【2】运营中心填-基本信息&审核标准'!$D$4="否","无",IF(INT(H6/100)=1,"1F",IF(AND(INT(H6/100)>=2,INT(H6/100)<=3),"2-3F",IF(INT(H6/100)=4,"4F",IF(AND(INT(H6/100)>=5,INT(H6/100)<=6),"5-6F",IF(AND(INT(H6/100)>=7,INT(H6/100)<=8),"7-8F",IF(AND(INT(H6/100)>=9,INT(H6/100)<=10),"9-10F",IF(AND(INT(H6/100)>=11,INT(H6/100)<=12),"11-12F",IF(INT(H6/100)>=13,"13以上F",""))))))))) -> 无 | U6: =VLOOKUP($T$1&T6,【1】定价因子!E:F,2,0) -> 1 | V6: 适中 | W6: =VLOOKUP($V$1&V6,【1】定价因子!E:F,2,0) -> 1 | X6: 适中 | Y6: =VLOOKUP($X$1&X6,【1】定价因子!$E:$F,2,0) -> 1 | Z6: 适中 | AA6: =VLOOKUP($Z$1&Z6,【1】定价因子!$E:$F,2,0) -> 1 | AB6: =VLOOKUP(H6,'【3-1】大区填-采光基本要素'!A:H,8,0) -> 4 | AC6: =VLOOKUP($AB$1&AB6,【1】定价因子!$E:$F,2,0) -> 1.03 | AD6: =L6*PRODUCT(Y6,AC6,W6,U6,S6,Q6,O6) -> 2074.1769 | AE6: 1878 | AF6: =AE6/AD6-1 -> -0.094580596
A7: ='【2】运营中心填-基本信息&审核标准'!$E$2 -> 福围广生1-41栋 | B7: =INT(H7/100) -> 3 | C7: =COUNTIF($B$2:$B$20,B7) -> 4 | D7: =COUNTIF(C$2:C$20,C7) -> 12 | F7: =IF(D7=$E$2,C7,"") -> 4 | H7: 301 | I7: 1-41F | J7: 开间 | K7: {=IFERROR(INDEX($J$2:$J$20,MATCH(0,IF(ISBLANK($J$2:$J$20),1,COUNTIF($K$1:K6,$J$2:$J$20)),0)),"")} | L7: =VLOOKUP(J7,'【3】大区填-楼栋基准格局定价'!B:J,9,0) -> 1238.0928 | M7: =IF(OR(J7="开间",J7="二人宿舍"),IF(N7<10,"很狭小",IF(N7<13,"较狭小",IF(N7<17,"适中",IF(N7<20,"较宽敞","很宽敞")))),IF(OR(J7="一居室",J7="四人宿舍"),IF(N7<20,"很狭小",IF(N7<23,"较狭小",IF(N7<26,"适中",IF(N7<28,"较宽敞","很宽敞")))),IF(OR(J7="二居室",J7="六人宿舍"),IF(N7<30,"很狭小",IF(N7<35,"较狭小",IF(N7<40,"适中",IF(N7<45,"较宽敞","很宽敞")))),""))) -> 适中 | N7: 13.12 | O7: =VLOOKUP($M$1&M7,【1】定价因子!E:F,2,0) -> 1 | P7: =IF(VLOOKUP(H7,'【3-1】大区填-采光基本要素'!A:E,5,FALSE)=0,"无","有") -> 无 | Q7: =VLOOKUP($P$1&P7,【1】定价因子!E:F,2,0) -> 1 | R7: =IF('【2】运营中心填-基本信息&审核标准'!$D$4="是","无",IF(INT(H7/100)>9,"9F",INT(H7/100)&"F")) -> 3F | S7: =VLOOKUP(R7,【1】定价因子!D:F,3,0) -> 1.01 | T7: =IF('【2】运营中心填-基本信息&审核标准'!$D$4="否","无",IF(INT(H7/100)=1,"1F",IF(AND(INT(H7/100)>=2,INT(H7/100)<=3),"2-3F",IF(INT(H7/100)=4,"4F",IF(AND(INT(H7/100)>=5,INT(H7/100)<=6),"5-6F",IF(AND(INT(H7/100)>=7,INT(H7/100)<=8),"7-8F",IF(AND(INT(H7/100)>=9,INT(H7/100)<=10),"9-10F",IF(AND(INT(H7/100)>=11,INT(H7/100)<=12),"11-12F",IF(INT(H7/100)>=13,"13以上F",""))))))))) -> 无 | U7: =VLOOKUP($T$1&T7,【1】定价因子!E:F,2,0) -> 1 | V7: 适中 | W7: =VLOOKUP($V$1&V7,【1】定价因子!E:F,2,0) -> 1 | X7: 适中 | Y7: =VLOOKUP($X$1&X7,【1】定价因子!$E:$F,2,0) -> 1 | Z7: 适中 | AA7: =VLOOKUP($Z$1&Z7,【1】定价因子!$E:$F,2,0) -> 1 | AB7: =VLOOKUP(H7,'【3-1】大区填-采光基本要素'!A:H,8,0) -> 1 | AC7: =VLOOKUP($AB$1&AB7,【1】定价因子!$E:$F,2,0) -> 0.91 | AD7: =L7*PRODUCT(Y7,AC7,W7,U7,S7,Q7,O7) -> 1137.9311 | AE7: 1150 | AF7: =AE7/AD7-1 -> 0.010606009 | AG7: 1238
A8: ='【2】运营中心填-基本信息&审核标准'!$E$2 -> 福围广生1-41栋 | B8: =INT(H8/100) -> 3 | C8: =COUNTIF($B$2:$B$20,B8) -> 4 | D8: =COUNTIF(C$2:C$20,C8) -> 12 | F8: =IF(D8=$E$2,C8,"") -> 4 | H8: 302 | I8: 1-41G | J8: 一居室 | K8: {=IFERROR(INDEX($J$2:$J$20,MATCH(0,IF(ISBLANK($J$2:$J$20),1,COUNTIF($K$1:K7,$J$2:$J$20)),0)),"")} | L8: =VLOOKUP(J8,'【3】大区填-楼栋基准格局定价'!B:J,9,0) -> 1845.12 | M8: =IF(OR(J8="开间",J8="二人宿舍"),IF(N8<10,"很狭小",IF(N8<13,"较狭小",IF(N8<17,"适中",IF(N8<20,"较宽敞","很宽敞")))),IF(OR(J8="一居室",J8="四人宿舍"),IF(N8<20,"很狭小",IF(N8<23,"较狭小",IF(N8<26,"适中",IF(N8<28,"较宽敞","很宽敞")))),IF(OR(J8="二居室",J8="六人宿舍"),IF(N8<30,"很狭小",IF(N8<35,"较狭小",IF(N8<40,"适中",IF(N8<45,"较宽敞","很宽敞")))),""))) -> 较狭小 | N8: 22.5 | O8: =VLOOKUP($M$1&M8,【1】定价因子!E:F,2,0) -> 0.95 | P8: =IF(VLOOKUP(H8,'【3-1】大区填-采光基本要素'!A:E,5,FALSE)=0,"无","有") -> 有 | Q8: =VLOOKUP($P$1&P8,【1】定价因子!E:F,2,0) -> 1.07 | R8: =IF('【2】运营中心填-基本信息&审核标准'!$D$4="是","无",IF(INT(H8/100)>9,"9F",INT(H8/100)&"F")) -> 3F | S8: =VLOOKUP(R8,【1】定价因子!D:F,3,0) -> 1.01 | T8: =IF('【2】运营中心填-基本信息&审核标准'!$D$4="否","无",IF(INT(H8/100)=1,"1F",IF(AND(INT(H8/100)>=2,INT(H8/100)<=3),"2-3F",IF(INT(H8/100)=4,"4F",IF(AND(INT(H8/100)>=5,INT(H8/100)<=6),"5-6F",IF(AND(INT(H8/100)>=7,INT(H8/100)<=8),"7-8F",IF(AND(INT(H8/100)>=9,INT(H8/100)<=10),"9-10F",IF(AND(INT(H8/100)>=11,INT(H8/100)<=12),"11-12F",IF(INT(H8/100)>=13,"13以上F",""))))))))) -> 无 | U8: =VLOOKUP($T$1&T8,【1】定价因子!E:F,2,0) -> 1 | V8: 适中 | W8: =VLOOKUP($V$1&V8,【1】定价因子!E:F,2,0) -> 1 | X8: 适中 | Y8: =VLOOKUP($X$1&X8,【1】定价因子!$E:$F,2,0) -> 1 | Z8: 适中 | AA8: =VLOOKUP($Z$1&Z8,【1】定价因子!$E:$F,2,0) -> 1 | AB8: =VLOOKUP(H8,'【3-1】大区填-采光基本要素'!A:H,8,0) -> 3 | AC8: =VLOOKUP($AB$1&AB8,【1】定价因子!$E:$F,2,0) -> 1 | AD8: =L8*PRODUCT(Y8,AC8,W8,U8,S8,Q8,O8) -> 1894.3201 | AE8: 1837.8 | AF8: =AE8/AD8-1 -> -0.029836628
A9: ='【2】运营中心填-基本信息&审核标准'!$E$2 -> 福围广生1-41栋 | B9: =INT(H9/100) -> 3 | C9: =COUNTIF($B$2:$B$20,B9) -> 4 | D9: =COUNTIF(C$2:C$20,C9) -> 12 | F9: =IF(D9=$E$2,C9,"") -> 4 | H9: 303 | I9: 1-41G | J9: 一居室 | K9: {=IFERROR(INDEX($J$2:$J$20,MATCH(0,IF(ISBLANK($J$2:$J$20),1,COUNTIF($K$1:K8,$J$2:$J$20)),0)),"")} | L9: =VLOOKUP(J9,'【3】大区填-楼栋基准格局定价'!B:J,9,0) -> 1845.12 | M9: =IF(OR(J9="开间",J9="二人宿舍"),IF(N9<10,"很狭小",IF(N9<13,"较狭小",IF(N9<17,"适中",IF(N9<20,"较宽敞","很宽敞")))),IF(OR(J9="一居室",J9="四人宿舍"),IF(N9<20,"很狭小",IF(N9<23,"较狭小",IF(N9<26,"适中",IF(N9<28,"较宽敞","很宽敞")))),IF(OR(J9="二居室",J9="六人宿舍"),IF(N9<30,"很狭小",IF(N9<35,"较狭小",IF(N9<40,"适中",IF(N9<45,"较宽敞","很宽敞")))),""))) -> 适中 | N9: 23.22 | O9: =VLOOKUP($M$1&M9,【1】定价因子!E:F,2,0) -> 1 | P9: =IF(VLOOKUP(H9,'【3-1】大区填-采光基本要素'!A:E,5,FALSE)=0,"无","有") -> 有 | Q9: =VLOOKUP($P$1&P9,【1】定价因子!E:F,2,0) -> 1.07 | R9: =IF('【2】运营中心填-基本信息&审核标准'!$D$4="是","无",IF(INT(H9/100)>9,"9F",INT(H9/100)&"F")) -> 3F | S9: =VLOOKUP(R9,【1】定价因子!D:F,3,0) -> 1.01 | T9: =IF('【2】运营中心填-基本信息&审核标准'!$D$4="否","无",IF(INT(H9/100)=1,"1F",IF(AND(INT(H9/100)>=2,INT(H9/100)<=3),"2-3F",IF(INT(H9/100)=4,"4F",IF(AND(INT(H9/100)>=5,INT(H9/100)<=6),"5-6F",IF(AND(INT(H9/100)>=7,INT(H9/100)<=8),"7-8F",IF(AND(INT(H9/100)>=9,INT(H9/100)<=10),"9-10F",IF(AND(INT(H9/100)>=11,INT(H9/100)<=12),"11-12F",IF(INT(H9/100)>=13,"13以上F",""))))))))) -> 无 | U9: =VLOOKUP($T$1&T9,【1】定价因子!E:F,2,0) -> 1 | V9: 适中 | W9: =VLOOKUP($V$1&V9,【1】定价因子!E:F,2,0) -> 1 | X9: 适中 | Y9: =VLOOKUP($X$1&X9,【1】定价因子!$E:$F,2,0) -> 1 | Z9: 适中 | AA9: =VLOOKUP($Z$1&Z9,【1】定价因子!$E:$F,2,0) -> 1 | AB9: =VLOOKUP(H9,'【3-1】大区填-采光基本要素'!A:H,8,0) -> 4 | AC9: =VLOOKUP($AB$1&AB9,【1】定价因子!$E:$F,2,0) -> 1.03 | AD9: =L9*PRODUCT(Y9,AC9,W9,U9,S9,Q9,O9) -> 2053.8418 | AE9: 1868 | AF9: =AE9/AD9-1 -> -0.090484972
A10: ='【2】运营中心填-基本信息&审核标准'!$E$2 -> 福围广生1-41栋 | B10: =INT(H10/100) -> 3 | C10: =COUNTIF($B$2:$B$20,B10) -> 4 | D10: =COUNTIF(C$2:C$20,C10) -> 12 | F10: =IF(D10=$E$2,C10,"") -> 4 | H10: 304 | I10: 1-41F | J10: 开间 | K10: {=IFERROR(INDEX($J$2:$J$20,MATCH(0,IF(ISBLANK($J$2:$J$20),1,COUNTIF($K$1:K9,$J$2:$J$20)),0)),"")} | L10: =VLOOKUP(J10,'【3】大区填-楼栋基准格局定价'!B:J,9,0) -> 1238.0928 | M10: =IF(OR(J10="开间",J10="二人宿舍"),IF(N10<10,"很狭小",IF(N10<13,"较狭小",IF(N10<17,"适中",IF(N10<20,"较宽敞","很宽敞")))),IF(OR(J10="一居室",J10="四人宿舍"),IF(N10<20,"很狭小",IF(N10<23,"较狭小",IF(N10<26,"适中",IF(N10<28,"较宽敞","很宽敞")))),IF(OR(J10="二居室",J10="六人宿舍"),IF(N10<30,"很狭小",IF(N10<35,"较狭小",IF(N10<40,"适中",IF(N10<45,"较宽敞","很宽敞")))),""))) -> 适中 | N10: 13.35 | O10: =VLOOKUP($M$1&M10,【1】定价因子!E:F,2,0) -> 1 | P10: =IF(VLOOKUP(H10,'【3-1】大区填-采光基本要素'!A:E,5,FALSE)=0,"无","有") -> 无 | Q10: =VLOOKUP($P$1&P10,【1】定价因子!E:F,2,0) -> 1 | R10: =IF('【2】运营中心填-基本信息&审核标准'!$D$4="是","无",IF(INT(H10/100)>9,"9F",INT(H10/100)&"F")) -> 3F | S10: =VLOOKUP(R10,【1】定价因子!D:F,3,0) -> 1.01 | T10: =IF('【2】运营中心填-基本信息&审核标准'!$D$4="否","无",IF(INT(H10/100)=1,"1F",IF(AND(INT(H10/100)>=2,INT(H10/100)<=3),"2-3F",IF(INT(H10/100)=4,"4F",IF(AND(INT(H10/100)>=5,INT(H10/100)<=6),"5-6F",IF(AND(INT(H10/100)>=7,INT(H10/100)<=8),"7-8F",IF(AND(INT(H10/100)>=9,INT(H10/100)<=10),"9-10F",IF(AND(INT(H10/100)>=11,INT(H10/100)<=12),"11-12F",IF(INT(H10/100)>=13,"13以上F",""))))))))) -> 无 | U10: =VLOOKUP($T$1&T10,【1】定价因子!E:F,2,0) -> 1 | V10: 适中 | W10: =VLOOKUP($V$1&V10,【1】定价因子!E:F,2,0) -> 1 | X10: 适中 | Y10: =VLOOKUP($X$1&X10,【1】定价因子!$E:$F,2,0) -> 1 | Z10: 适中 | AA10: =VLOOKUP($Z$1&Z10,【1】定价因子!$E:$F,2,0) -> 1 | AB10: =VLOOKUP(H10,'【3-1】大区填-采光基本要素'!A:H,8,0) -> 3 | AC10: =VLOOKUP($AB$1&AB10,【1】定价因子!$E:$F,2,0) -> 1 | AD10: =L10*PRODUCT(Y10,AC10,W10,U10,S10,Q10,O10) -> 1250.4737 | AE10: 1337.8 | AF10: =AE10/AD10-1 -> 0.069834552
A11: ='【2】运营中心填-基本信息&审核标准'!$E$2 -> 福围广生1-41栋 | B11: =INT(H11/100) -> 4 | C11: =COUNTIF($B$2:$B$20,B11) -> 4 | D11: =COUNTIF(C$2:C$20,C11) -> 12 | F11: =IF(D11=$E$2,C11,"") -> 4 | H11: 401 | I11: 1-41F | J11: 开间 | L11: =VLOOKUP(J11,'【3】大区填-楼栋基准格局定价'!B:J,9,0) -> 1238.0928 | M11: =IF(OR(J11="开间",J11="二人宿舍"),IF(N11<10,"很狭小",IF(N11<13,"较狭小",IF(N11<17,"适中",IF(N11<20,"较宽敞","很宽敞")))),IF(OR(J11="一居室",J11="四人宿舍"),IF(N11<20,"很狭小",IF(N11<23,"较狭小",IF(N11<26,"适中",IF(N11<28,"较宽敞","很宽敞")))),IF(OR(J11="二居室",J11="六人宿舍"),IF(N11<30,"很狭小",IF(N11<35,"较狭小",IF(N11<40,"适中",IF(N11<45,"较宽敞","很宽敞")))),""))) -> 适中 | N11: 13.12 | O11: =VLOOKUP($M$1&M11,【1】定价因子!E:F,2,0) -> 1 | P11: =IF(VLOOKUP(H11,'【3-1】大区填-采光基本要素'!A:E,5,FALSE)=0,"无","有") -> 无 | Q11: =VLOOKUP($P$1&P11,【1】定价因子!E:F,2,0) -> 1 | R11: =IF('【2】运营中心填-基本信息&审核标准'!$D$4="是","无",IF(INT(H11/100)>9,"9F",INT(H11/100)&"F")) -> 4F | S11: =VLOOKUP(R11,【1】定价因子!D:F,3,0) -> 1 | T11: =IF('【2】运营中心填-基本信息&审核标准'!$D$4="否","无",IF(INT(H11/100)=1,"1F",IF(AND(INT(H11/100)>=2,INT(H11/100)<=3),"2-3F",IF(INT(H11/100)=4,"4F",IF(AND(INT(H11/100)>=5,INT(H11/100)<=6),"5-6F",IF(AND(INT(H11/100)>=7,INT(H11/100)<=8),"7-8F",IF(AND(INT(H11/100)>=9,INT(H11/100)<=10),"9-10F",IF(AND(INT(H11/100)>=11,INT(H11/100)<=12),"11-12F",IF(INT(H11/100)>=13,"13以上F",""))))))))) -> 无 | U11: =VLOOKUP($T$1&T11,【1】定价因子!E:F,2,0) -> 1 | V11: 适中 | W11: =VLOOKUP($V$1&V11,【1】定价因子!E:F,2,0) -> 1 | X11: 适中 | Y11: =VLOOKUP($X$1&X11,【1】定价因子!$E:$F,2,0) -> 1 | Z11: 适中 | AA11: =VLOOKUP($Z$1&Z11,【1】定价因子!$E:$F,2,0) -> 1 | AB11: =VLOOKUP(H11,'【3-1】大区填-采光基本要素'!A:H,8,0) -> 1 | AC11: =VLOOKUP($AB$1&AB11,【1】定价因子!$E:$F,2,0) -> 0.91 | AD11: =L11*PRODUCT(Y11,AC11,W11,U11,S11,Q11,O11) -> 1126.6644 | AE11: 1150 | AF11: =AE11/AD11-1 -> 0.020712069 | AG11: 1238
A12: ='【2】运营中心填-基本信息&审核标准'!$E$2 -> 福围广生1-41栋 | B12: =INT(H12/100) -> 4 | C12: =COUNTIF($B$2:$B$20,B12) -> 4 | D12: =COUNTIF(C$2:C$20,C12) -> 12 | F12: =IF(D12=$E$2,C12,"") -> 4 | H12: 402 | I12: 1-41G | J12: 一居室 | L12: =VLOOKUP(J12,'【3】大区填-楼栋基准格局定价'!B:J,9,0) -> 1845.12 | M12: =IF(OR(J12="开间",J12="二人宿舍"),IF(N12<10,"很狭小",IF(N12<13,"较狭小",IF(N12<17,"适中",IF(N12<20,"较宽敞","很宽敞")))),IF(OR(J12="一居室",J12="四人宿舍"),IF(N12<20,"很狭小",IF(N12<23,"较狭小",IF(N12<26,"适中",IF(N12<28,"较宽敞","很宽敞")))),IF(OR(J12="二居室",J12="六人宿舍"),IF(N12<30,"很狭小",IF(N12<35,"较狭小",IF(N12<40,"适中",IF(N12<45,"较宽敞","很宽敞")))),""))) -> 较狭小 | N12: 22.5 | O12: =VLOOKUP($M$1&M12,【1】定价因子!E:F,2,0) -> 0.95 | P12: =IF(VLOOKUP(H12,'【3-1】大区填-采光基本要素'!A:E,5,FALSE)=0,"无","有") -> 有 | Q12: =VLOOKUP($P$1&P12,【1】定价因子!E:F,2,0) -> 1.07 | R12: =IF('【2】运营中心填-基本信息&审核标准'!$D$4="是","无",IF(INT(H12/100)>9,"9F",INT(H12/100)&"F")) -> 4F | S12: =VLOOKUP(R12,【1】定价因子!D:F,3,0) -> 1 | T12: =IF('【2】运营中心填-基本信息&审核标准'!$D$4="否","无",IF(INT(H12/100)=1,"1F",IF(AND(INT(H12/100)>=2,INT(H12/100)<=3),"2-3F",IF(INT(H12/100)=4,"4F",IF(AND(INT(H12/100)>=5,INT(H12/100)<=6),"5-6F",IF(AND(INT(H12/100)>=7,INT(H12/100)<=8),"7-8F",IF(AND(INT(H12/100)>=9,INT(H12/100)<=10),"9-10F",IF(AND(INT(H12/100)>=11,INT(H12/100)<=12),"11-12F",IF(INT(H12/100)>=13,"13以上F",""))))))))) -> 无 | U12: =VLOOKUP($T$1&T12,【1】定价因子!E:F,2,0) -> 1 | V12: 适中 | W12: =VLOOKUP($V$1&V12,【1】定价因子!E:F,2,0) -> 1 | X12: 适中 | Y12: =VLOOKUP($X$1&X12,【1】定价因子!$E:$F,2,0) -> 1 | Z12: 适中 | AA12: =VLOOKUP($Z$1&Z12,【1】定价因子!$E:$F,2,0) -> 1 | AB12: =VLOOKUP(H12,'【3-1】大区填-采光基本要素'!A:H,8,0) -> 3 | AC12: =VLOOKUP($AB$1&AB12,【1】定价因子!$E:$F,2,0) -> 1 | AD12: =L12*PRODUCT(Y12,AC12,W12,U12,S12,Q12,O12) -> 1875.5645 | AE12: 1837.8 | AF12: =AE12/AD12-1 -> -0.020134994
A13: ='【2】运营中心填-基本信息&审核标准'!$E$2 -> 福围广生1-41栋 | B13: =INT(H13/100) -> 4 | C13: =COUNTIF($B$2:$B$20,B13) -> 4 | D13: =COUNTIF(C$2:C$20,C13) -> 12 | F13: =IF(D13=$E$2,C13,"") -> 4 | H13: 403 | I13: 1-41G | J13: 一居室 | L13: =VLOOKUP(J13,'【3】大区填-楼栋基准格局定价'!B:J,9,0) -> 1845.12 | M13: =IF(OR(J13="开间",J13="二人宿舍"),IF(N13<10,"很狭小",IF(N13<13,"较狭小",IF(N13<17,"适中",IF(N13<20,"较宽敞","很宽敞")))),IF(OR(J13="一居室",J13="四人宿舍"),IF(N13<20,"很狭小",IF(N13<23,"较狭小",IF(N13<26,"适中",IF(N13<28,"较宽敞","很宽敞")))),IF(OR(J13="二居室",J13="六人宿舍"),IF(N13<30,"很狭小",IF(N13<35,"较狭小",IF(N13<40,"适中",IF(N13<45,"较宽敞","很宽敞")))),""))) -> 适中 | N13: 23.22 | O13: =VLOOKUP($M$1&M13,【1】定价因子!E:F,2,0) -> 1 | P13: =IF(VLOOKUP(H13,'【3-1】大区填-采光基本要素'!A:E,5,FALSE)=0,"无","有") -> 有 | Q13: =VLOOKUP($P$1&P13,【1】定价因子!E:F,2,0) -> 1.07 | R13: =IF('【2】运营中心填-基本信息&审核标准'!$D$4="是","无",IF(INT(H13/100)>9,"9F",INT(H13/100)&"F")) -> 4F | S13: =VLOOKUP(R13,【1】定价因子!D:F,3,0) -> 1 | T13: =IF('【2】运营中心填-基本信息&审核标准'!$D$4="否","无",IF(INT(H13/100)=1,"1F",IF(AND(INT(H13/100)>=2,INT(H13/100)<=3),"2-3F",IF(INT(H13/100)=4,"4F",IF(AND(INT(H13/100)>=5,INT(H13/100)<=6),"5-6F",IF(AND(INT(H13/100)>=7,INT(H13/100)<=8),"7-8F",IF(AND(INT(H13/100)>=9,INT(H13/100)<=10),"9-10F",IF(AND(INT(H13/100)>=11,INT(H13/100)<=12),"11-12F",IF(INT(H13/100)>=13,"13以上F",""))))))))) -> 无 | U13: =VLOOKUP($T$1&T13,【1】定价因子!E:F,2,0) -> 1 | V13: 适中 | W13: =VLOOKUP($V$1&V13,【1】定价因子!E:F,2,0) -> 1 | X13: 适中 | Y13: =VLOOKUP($X$1&X13,【1】定价因子!$E:$F,2,0) -> 1 | Z13: 适中 | AA13: =VLOOKUP($Z$1&Z13,【1】定价因子!$E:$F,2,0) -> 1 | AB13: =VLOOKUP(H13,'【3-1】大区填-采光基本要素'!A:H,8,0) -> 4 | AC13: =VLOOKUP($AB$1&AB13,【1】定价因子!$E:$F,2,0) -> 1.03 | AD13: =L13*PRODUCT(Y13,AC13,W13,U13,S13,Q13,O13) -> 2033.5068 | AE13: 1868 | AF13: =AE13/AD13-1 -> -0.081389822
A14: ='【2】运营中心填-基本信息&审核标准'!$E$2 -> 福围广生1-41栋 | B14: =INT(H14/100) -> 4 | C14: =COUNTIF($B$2:$B$20,B14) -> 4 | D14: =COUNTIF(C$2:C$20,C14) -> 12 | F14: =IF(D14=$E$2,C14,"") -> 4 | H14: 404 | I14: 1-41F | J14: 开间 | L14: =VLOOKUP(J14,'【3】大区填-楼栋基准格局定价'!B:J,9,0) -> 1238.0928 | M14: =IF(OR(J14="开间",J14="二人宿舍"),IF(N14<10,"很狭小",IF(N14<13,"较狭小",IF(N14<17,"适中",IF(N14<20,"较宽敞","很宽敞")))),IF(OR(J14="一居室",J14="四人宿舍"),IF(N14<20,"很狭小",IF(N14<23,"较狭小",IF(N14<26,"适中",IF(N14<28,"较宽敞","很宽敞")))),IF(OR(J14="二居室",J14="六人宿舍"),IF(N14<30,"很狭小",IF(N14<35,"较狭小",IF(N14<40,"适中",IF(N14<45,"较宽敞","很宽敞")))),""))) -> 适中 | N14: 13.35 | O14: =VLOOKUP($M$1&M14,【1】定价因子!E:F,2,0) -> 1 | P14: =IF(VLOOKUP(H14,'【3-1】大区填-采光基本要素'!A:E,5,FALSE)=0,"无","有") -> 无 | Q14: =VLOOKUP($P$1&P14,【1】定价因子!E:F,2,0) -> 1 | R14: =IF('【2】运营中心填-基本信息&审核标准'!$D$4="是","无",IF(INT(H14/100)>9,"9F",INT(H14/100)&"F")) -> 4F | S14: =VLOOKUP(R14,【1】定价因子!D:F,3,0) -> 1 | T14: =IF('【2】运营中心填-基本信息&审核标准'!$D$4="否","无",IF(INT(H14/100)=1,"1F",IF(AND(INT(H14/100)>=2,INT(H14/100)<=3),"2-3F",IF(INT(H14/100)=4,"4F",IF(AND(INT(H14/100)>=5,INT(H14/100)<=6),"5-6F",IF(AND(INT(H14/100)>=7,INT(H14/100)<=8),"7-8F",IF(AND(INT(H14/100)>=9,INT(H14/100)<=10),"9-10F",IF(AND(INT(H14/100)>=11,INT(H14/100)<=12),"11-12F",IF(INT(H14/100)>=13,"13以上F",""))))))))) -> 无 | U14: =VLOOKUP($T$1&T14,【1】定价因子!E:F,2,0) -> 1 | V14: 适中 | W14: =VLOOKUP($V$1&V14,【1】定价因子!E:F,2,0) -> 1 | X14: 适中 | Y14: =VLOOKUP($X$1&X14,【1】定价因子!$E:$F,2,0) -> 1 | Z14: 适中 | AA14: =VLOOKUP($Z$1&Z14,【1】定价因子!$E:$F,2,0) -> 1 | AB14: =VLOOKUP(H14,'【3-1】大区填-采光基本要素'!A:H,8,0) -> 3 | AC14: =VLOOKUP($AB$1&AB14,【1】定价因子!$E:$F,2,0) -> 1 | AD14: =L14*PRODUCT(Y14,AC14,W14,U14,S14,Q14,O14) -> 1238.0928 | AE14: 1250 | AF14: =AE14/AD14-1 -> 0.0096173728 | AG14: 1338
A15: ='【2】运营中心填-基本信息&审核标准'!$E$2 -> 福围广生1-41栋 | B15: =INT(H15/100) -> 5 | C15: =COUNTIF($B$2:$B$20,B15) -> 4 | D15: =COUNTIF(C$2:C$20,C15) -> 12 | F15: =IF(D15=$E$2,C15,"") -> 4 | H15: 501 | I15: 1-41F | J15: 开间 | L15: =VLOOKUP(J15,'【3】大区填-楼栋基准格局定价'!B:J,9,0) -> 1238.0928 | M15: =IF(OR(J15="开间",J15="二人宿舍"),IF(N15<10,"很狭小",IF(N15<13,"较狭小",IF(N15<17,"适中",IF(N15<20,"较宽敞","很宽敞")))),IF(OR(J15="一居室",J15="四人宿舍"),IF(N15<20,"很狭小",IF(N15<23,"较狭小",IF(N15<26,"适中",IF(N15<28,"较宽敞","很宽敞")))),IF(OR(J15="二居室",J15="六人宿舍"),IF(N15<30,"很狭小",IF(N15<35,"较狭小",IF(N15<40,"适中",IF(N15<45,"较宽敞","很宽敞")))),""))) -> 适中 | N15: 13.12 | O15: =VLOOKUP($M$1&M15,【1】定价因子!E:F,2,0) -> 1 | P15: =IF(VLOOKUP(H15,'【3-1】大区填-采光基本要素'!A:E,5,FALSE)=0,"无","有") -> 无 | Q15: =VLOOKUP($P$1&P15,【1】定价因子!E:F,2,0) -> 1 | R15: =IF('【2】运营中心填-基本信息&审核标准'!$D$4="是","无",IF(INT(H15/100)>9,"9F",INT(H15/100)&"F")) -> 5F | S15: =VLOOKUP(R15,【1】定价因子!D:F,3,0) -> 0.99 | T15: =IF('【2】运营中心填-基本信息&审核标准'!$D$4="否","无",IF(INT(H15/100)=1,"1F",IF(AND(INT(H15/100)>=2,INT(H15/100)<=3),"2-3F",IF(INT(H15/100)=4,"4F",IF(AND(INT(H15/100)>=5,INT(H15/100)<=6),"5-6F",IF(AND(INT(H15/100)>=7,INT(H15/100)<=8),"7-8F",IF(AND(INT(H15/100)>=9,INT(H15/100)<=10),"9-10F",IF(AND(INT(H15/100)>=11,INT(H15/100)<=12),"11-12F",IF(INT(H15/100)>=13,"13以上F",""))))))))) -> 无 | U15: =VLOOKUP($T$1&T15,【1】定价因子!E:F,2,0) -> 1 | V15: 适中 | W15: =VLOOKUP($V$1&V15,【1】定价因子!E:F,2,0) -> 1 | X15: 适中 | Y15: =VLOOKUP($X$1&X15,【1】定价因子!$E:$F,2,0) -> 1 | Z15: 适中 | AA15: =VLOOKUP($Z$1&Z15,【1】定价因子!$E:$F,2,0) -> 1 | AB15: =VLOOKUP(H15,'【3-1】大区填-采光基本要素'!A:H,8,0) -> 1 | AC15: =VLOOKUP($AB$1&AB15,【1】定价因子!$E:$F,2,0) -> 0.91 | AD15: =L15*PRODUCT(Y15,AC15,W15,U15,S15,Q15,O15) -> 1115.3978 | AE15: 1150 | AF15: =AE15/AD15-1 -> 0.031022292 | AG15: 1238
A16: ='【2】运营中心填-基本信息&审核标准'!$E$2 -> 福围广生1-41栋 | B16: =INT(H16/100) -> 5 | C16: =COUNTIF($B$2:$B$20,B16) -> 4 | D16: =COUNTIF(C$2:C$20,C16) -> 12 | F16: =IF(D16=$E$2,C16,"") -> 4 | H16: 502 | I16: 1-41G | J16: 一居室 | L16: =VLOOKUP(J16,'【3】大区填-楼栋基准格局定价'!B:J,9,0) -> 1845.12 | M16: =IF(OR(J16="开间",J16="二人宿舍"),IF(N16<10,"很狭小",IF(N16<13,"较狭小",IF(N16<17,"适中",IF(N16<20,"较宽敞","很宽敞")))),IF(OR(J16="一居室",J16="四人宿舍"),IF(N16<20,"很狭小",IF(N16<23,"较狭小",IF(N16<26,"适中",IF(N16<28,"较宽敞","很宽敞")))),IF(OR(J16="二居室",J16="六人宿舍"),IF(N16<30,"很狭小",IF(N16<35,"较狭小",IF(N16<40,"适中",IF(N16<45,"较宽敞","很宽敞")))),""))) -> 较狭小 | N16: 22.5 | O16: =VLOOKUP($M$1&M16,【1】定价因子!E:F,2,0) -> 0.95 | P16: =IF(VLOOKUP(H16,'【3-1】大区填-采光基本要素'!A:E,5,FALSE)=0,"无","有") -> 有 | Q16: =VLOOKUP($P$1&P16,【1】定价因子!E:F,2,0) -> 1.07 | R16: =IF('【2】运营中心填-基本信息&审核标准'!$D$4="是","无",IF(INT(H16/100)>9,"9F",INT(H16/100)&"F")) -> 5F | S16: =VLOOKUP(R16,【1】定价因子!D:F,3,0) -> 0.99 | T16: =IF('【2】运营中心填-基本信息&审核标准'!$D$4="否","无",IF(INT(H16/100)=1,"1F",IF(AND(INT(H16/100)>=2,INT(H16/100)<=3),"2-3F",IF(INT(H16/100)=4,"4F",IF(AND(INT(H16/100)>=5,INT(H16/100)<=6),"5-6F",IF(AND(INT(H16/100)>=7,INT(H16/100)<=8),"7-8F",IF(AND(INT(H16/100)>=9,INT(H16/100)<=10),"9-10F",IF(AND(INT(H16/100)>=11,INT(H16/100)<=12),"11-12F",IF(INT(H16/100)>=13,"13以上F",""))))))))) -> 无 | U16: =VLOOKUP($T$1&T16,【1】定价因子!E:F,2,0) -> 1 | V16: 适中 | W16: =VLOOKUP($V$1&V16,【1】定价因子!E:F,2,0) -> 1 | X16: 适中 | Y16: =VLOOKUP($X$1&X16,【1】定价因子!$E:$F,2,0) -> 1 | Z16: 适中 | AA16: =VLOOKUP($Z$1&Z16,【1】定价因子!$E:$F,2,0) -> 1 | AB16: =VLOOKUP(H16,'【3-1】大区填-采光基本要素'!A:H,8,0) -> 3 | AC16: =VLOOKUP($AB$1&AB16,【1】定价因子!$E:$F,2,0) -> 1 | AD16: =L16*PRODUCT(Y16,AC16,W16,U16,S16,Q16,O16) -> 1856.8088 | AE16: 1837.8 | AF16: =AE16/AD16-1 -> -0.010237368
A17: ='【2】运营中心填-基本信息&审核标准'!$E$2 -> 福围广生1-41栋 | B17: =INT(H17/100) -> 5 | C17: =COUNTIF($B$2:$B$20,B17) -> 4 | D17: =COUNTIF(C$2:C$20,C17) -> 12 | F17: =IF(D17=$E$2,C17,"") -> 4 | H17: 503 | I17: 1-41G | J17: 一居室 | L17: =VLOOKUP(J17,'【3】大区填-楼栋基准格局定价'!B:J,9,0) -> 1845.12 | M17: =IF(OR(J17="开间",J17="二人宿舍"),IF(N17<10,"很狭小",IF(N17<13,"较狭小",IF(N17<17,"适中",IF(N17<20,"较宽敞","很宽敞")))),IF(OR(J17="一居室",J17="四人宿舍"),IF(N17<20,"很狭小",IF(N17<23,"较狭小",IF(N17<26,"适中",IF(N17<28,"较宽敞","很宽敞")))),IF(OR(J17="二居室",J17="六人宿舍"),IF(N17<30,"很狭小",IF(N17<35,"较狭小",IF(N17<40,"适中",IF(N17<45,"较宽敞","很宽敞")))),""))) -> 适中 | N17: 23.22 | O17: =VLOOKUP($M$1&M17,【1】定价因子!E:F,2,0) -> 1 | P17: =IF(VLOOKUP(H17,'【3-1】大区填-采光基本要素'!A:E,5,FALSE)=0,"无","有") -> 有 | Q17: =VLOOKUP($P$1&P17,【1】定价因子!E:F,2,0) -> 1.07 | R17: =IF('【2】运营中心填-基本信息&审核标准'!$D$4="是","无",IF(INT(H17/100)>9,"9F",INT(H17/100)&"F")) -> 5F | S17: =VLOOKUP(R17,【1】定价因子!D:F,3,0) -> 0.99 | T17: =IF('【2】运营中心填-基本信息&审核标准'!$D$4="否","无",IF(INT(H17/100)=1,"1F",IF(AND(INT(H17/100)>=2,INT(H17/100)<=3),"2-3F",IF(INT(H17/100)=4,"4F",IF(AND(INT(H17/100)>=5,INT(H17/100)<=6),"5-6F",IF(AND(INT(H17/100)>=7,INT(H17/100)<=8),"7-8F",IF(AND(INT(H17/100)>=9,INT(H17/100)<=10),"9-10F",IF(AND(INT(H17/100)>=11,INT(H17/100)<=12),"11-12F",IF(INT(H17/100)>=13,"13以上F",""))))))))) -> 无 | U17: =VLOOKUP($T$1&T17,【1】定价因子!E:F,2,0) -> 1 | V17: 适中 | W17: =VLOOKUP($V$1&V17,【1】定价因子!E:F,2,0) -> 1 | X17: 适中 | Y17: =VLOOKUP($X$1&X17,【1】定价因子!$E:$F,2,0) -> 1 | Z17: 适中 | AA17: =VLOOKUP($Z$1&Z17,【1】定价因子!$E:$F,2,0) -> 1 | AB17: =VLOOKUP(H17,'【3-1】大区填-采光基本要素'!A:H,8,0) -> 4 | AC17: =VLOOKUP($AB$1&AB17,【1】定价因子!$E:$F,2,0) -> 1.03 | AD17: =L17*PRODUCT(Y17,AC17,W17,U17,S17,Q17,O17) -> 2013.1717 | AE17: 1838 | AF17: =AE17/AD17-1 -> -0.08701279
A18: ='【2】运营中心填-基本信息&审核标准'!$E$2 -> 福围广生1-41栋 | B18: =INT(H18/100) -> 5 | C18: =COUNTIF($B$2:$B$20,B18) -> 4 | D18: =COUNTIF(C$2:C$20,C18) -> 12 | F18: =IF(D18=$E$2,C18,"") -> 4 | H18: 504 | I18: 1-41F | J18: 开间 | L18: =VLOOKUP(J18,'【3】大区填-楼栋基准格局定价'!B:J,9,0) -> 1238.0928 | M18: =IF(OR(J18="开间",J18="二人宿舍"),IF(N18<10,"很狭小",IF(N18<13,"较狭小",IF(N18<17,"适中",IF(N18<20,"较宽敞","很宽敞")))),IF(OR(J18="一居室",J18="四人宿舍"),IF(N18<20,"很狭小",IF(N18<23,"较狭小",IF(N18<26,"适中",IF(N18<28,"较宽敞","很宽敞")))),IF(OR(J18="二居室",J18="六人宿舍"),IF(N18<30,"很狭小",IF(N18<35,"较狭小",IF(N18<40,"适中",IF(N18<45,"较宽敞","很宽敞")))),""))) -> 适中 | N18: 13.35 | O18: =VLOOKUP($M$1&M18,【1】定价因子!E:F,2,0) -> 1 | P18: =IF(VLOOKUP(H18,'【3-1】大区填-采光基本要素'!A:E,5,FALSE)=0,"无","有") -> 无 | Q18: =VLOOKUP($P$1&P18,【1】定价因子!E:F,2,0) -> 1 | R18: =IF('【2】运营中心填-基本信息&审核标准'!$D$4="是","无",IF(INT(H18/100)>9,"9F",INT(H18/100)&"F")) -> 5F | S18: =VLOOKUP(R18,【1】定价因子!D:F,3,0) -> 0.99 | T18: =IF('【2】运营中心填-基本信息&审核标准'!$D$4="否","无",IF(INT(H18/100)=1,"1F",IF(AND(INT(H18/100)>=2,INT(H18/100)<=3),"2-3F",IF(INT(H18/100)=4,"4F",IF(AND(INT(H18/100)>=5,INT(H18/100)<=6),"5-6F",IF(AND(INT(H18/100)>=7,INT(H18/100)<=8),"7-8F",IF(AND(INT(H18/100)>=9,INT(H18/100)<=10),"9-10F",IF(AND(INT(H18/100)>=11,INT(H18/100)<=12),"11-12F",IF(INT(H18/100)>=13,"13以上F",""))))))))) -> 无 | U18: =VLOOKUP($T$1&T18,【1】定价因子!E:F,2,0) -> 1 | V18: 适中 | W18: =VLOOKUP($V$1&V18,【1】定价因子!E:F,2,0) -> 1 | X18: 适中 | Y18: =VLOOKUP($X$1&X18,【1】定价因子!$E:$F,2,0) -> 1 | Z18: 适中 | AA18: =VLOOKUP($Z$1&Z18,【1】定价因子!$E:$F,2,0) -> 1 | AB18: =VLOOKUP(H18,'【3-1】大区填-采光基本要素'!A:H,8,0) -> 3 | AC18: =VLOOKUP($AB$1&AB18,【1】定价因子!$E:$F,2,0) -> 1 | AD18: =L18*PRODUCT(Y18,AC18,W18,U18,S18,Q18,O18) -> 1225.7119 | AE18: 1337.8 | AF18: =AE18/AD18-1 -> 0.091447371
A19: ='【2】运营中心填-基本信息&审核标准'!$E$2 -> 福围广生1-41栋 | B19: =INT(H19/100) -> 6 | C19: =COUNTIF($B$2:$B$20,B19) -> 2 | D19: =COUNTIF(C$2:C$20,C19) -> 4 | F19: =IF(D19=$E$2,C19,"") | H19: 601 | I19: 1-41F | J19: 开间 | L19: =VLOOKUP(J19,'【3】大区填-楼栋基准格局定价'!B:J,9,0) -> 1238.0928 | M19: =IF(OR(J19="开间",J19="二人宿舍"),IF(N19<10,"很狭小",IF(N19<13,"较狭小",IF(N19<17,"适中",IF(N19<20,"较宽敞","很宽敞")))),IF(OR(J19="一居室",J19="四人宿舍"),IF(N19<20,"很狭小",IF(N19<23,"较狭小",IF(N19<26,"适中",IF(N19<28,"较宽敞","很宽敞")))),IF(OR(J19="二居室",J19="六人宿舍"),IF(N19<30,"很狭小",IF(N19<35,"较狭小",IF(N19<40,"适中",IF(N19<45,"较宽敞","很宽敞")))),""))) -> 适中 | N19: 13.66 | O19: =VLOOKUP($M$1&M19,【1】定价因子!E:F,2,0) -> 1 | P19: =IF(VLOOKUP(H19,'【3-1】大区填-采光基本要素'!A:E,5,FALSE)=0,"无","有") -> 无 | Q19: =VLOOKUP($P$1&P19,【1】定价因子!E:F,2,0) -> 1 | R19: =IF('【2】运营中心填-基本信息&审核标准'!$D$4="是","无",IF(INT(H19/100)>9,"9F",INT(H19/100)&"F")) -> 6F | S19: =VLOOKUP(R19,【1】定价因子!D:F,3,0) -> 0.98 | T19: =IF('【2】运营中心填-基本信息&审核标准'!$D$4="否","无",IF(INT(H19/100)=1,"1F",IF(AND(INT(H19/100)>=2,INT(H19/100)<=3),"2-3F",IF(INT(H19/100)=4,"4F",IF(AND(INT(H19/100)>=5,INT(H19/100)<=6),"5-6F",IF(AND(INT(H19/100)>=7,INT(H19/100)<=8),"7-8F",IF(AND(INT(H19/100)>=9,INT(H19/100)<=10),"9-10F",IF(AND(INT(H19/100)>=11,INT(H19/100)<=12),"11-12F",IF(INT(H19/100)>=13,"13以上F",""))))))))) -> 无 | U19: =VLOOKUP($T$1&T19,【1】定价因子!E:F,2,0) -> 1 | V19: 适中 | W19: =VLOOKUP($V$1&V19,【1】定价因子!E:F,2,0) -> 1 | X19: 适中 | Y19: =VLOOKUP($X$1&X19,【1】定价因子!$E:$F,2,0) -> 1 | Z19: 适中 | AA19: =VLOOKUP($Z$1&Z19,【1】定价因子!$E:$F,2,0) -> 1 | AB19: =VLOOKUP(H19,'【3-1】大区填-采光基本要素'!A:H,8,0) -> 2 | AC19: =VLOOKUP($AB$1&AB19,【1】定价因子!$E:$F,2,0) -> 0.96 | AD19: =L19*PRODUCT(Y19,AC19,W19,U19,S19,Q19,O19) -> 1164.7977 | AE19: 1150 | AF19: =AE19/AD19-1 -> -0.0127041 | AG19: 1238
A20: ='【2】运营中心填-基本信息&审核标准'!$E$2 -> 福围广生1-41栋 | B20: =INT(H20/100) -> 6 | C20: =COUNTIF($B$2:$B$20,B20) -> 2 | D20: =COUNTIF(C$2:C$20,C20) -> 4 | F20: =IF(D20=$E$2,C20,"") | H20: 602 | I20: 1-41F | J20: 开间 | L20: =VLOOKUP(J20,'【3】大区填-楼栋基准格局定价'!B:J,9,0) -> 1238.0928 | M20: =IF(OR(J20="开间",J20="二人宿舍"),IF(N20<10,"很狭小",IF(N20<13,"较狭小",IF(N20<17,"适中",IF(N20<20,"较宽敞","很宽敞")))),IF(OR(J20="一居室",J20="四人宿舍"),IF(N20<20,"很狭小",IF(N20<23,"较狭小",IF(N20<26,"适中",IF(N20<28,"较宽敞","很宽敞")))),IF(OR(J20="二居室",J20="六人宿舍"),IF(N20<30,"很狭小",IF(N20<35,"较狭小",IF(N20<40,"适中",IF(N20<45,"较宽敞","很宽敞")))),""))) -> 适中 | N20: 13.66 | O20: =VLOOKUP($M$1&M20,【1】定价因子!E:F,2,0) -> 1 | P20: =IF(VLOOKUP(H20,'【3-1】大区填-采光基本要素'!A:E,5,FALSE)=0,"无","有") -> 无 | Q20: =VLOOKUP($P$1&P20,【1】定价因子!E:F,2,0) -> 1 | R20: =IF('【2】运营中心填-基本信息&审核标准'!$D$4="是","无",IF(INT(H20/100)>9,"9F",INT(H20/100)&"F")) -> 6F | S20: =VLOOKUP(R20,【1】定价因子!D:F,3,0) -> 0.98 | T20: =IF('【2】运营中心填-基本信息&审核标准'!$D$4="否","无",IF(INT(H20/100)=1,"1F",IF(AND(INT(H20/100)>=2,INT(H20/100)<=3),"2-3F",IF(INT(H20/100)=4,"4F",IF(AND(INT(H20/100)>=5,INT(H20/100)<=6),"5-6F",IF(AND(INT(H20/100)>=7,INT(H20/100)<=8),"7-8F",IF(AND(INT(H20/100)>=9,INT(H20/100)<=10),"9-10F",IF(AND(INT(H20/100)>=11,INT(H20/100)<=12),"11-12F",IF(INT(H20/100)>=13,"13以上F",""))))))))) -> 无 | U20: =VLOOKUP($T$1&T20,【1】定价因子!E:F,2,0) -> 1 | V20: 适中 | W20: =VLOOKUP($V$1&V20,【1】定价因子!E:F,2,0) -> 1 | X20: 适中 | Y20: =VLOOKUP($X$1&X20,【1】定价因子!$E:$F,2,0) -> 1 | Z20: 适中 | AA20: =VLOOKUP($Z$1&Z20,【1】定价因子!$E:$F,2,0) -> 1 | AB20: =VLOOKUP(H20,'【3-1】大区填-采光基本要素'!A:H,8,0) -> 4 | AC20: =VLOOKUP($AB$1&AB20,【1】定价因子!$E:$F,2,0) -> 1.03 | AD20: =L20*PRODUCT(Y20,AC20,W20,U20,S20,Q20,O20) -> 1249.7309 | AE20: 1250 | AF20: =AE20/AD20-1 -> 0.00021534851 | AG20: 1338

Sheet 【4】价目表
A1: ="安居乐寓"&'【2】运营中心填-基本信息&审核标准'!C2&'【2】运营中心填-基本信息&审核标准'!E2&"公寓定价" -> 安居乐寓福围村福围广生1-41栋公寓定价
A3: 1层 | B3: 房号 | C3: 101 | D3: 102
B4: 户型 | C4: =VLOOKUP(C3,'【3-2】大区&运营中心填-房间模型价'!$H:$AE,2,0) -> 1-41A | D4: =VLOOKUP(D3,'【3-2】大区&运营中心填-房间模型价'!$H:$AE,2,0) -> 1-41B
B5: 价格 | C5: =VLOOKUP(C3,'【3-2】大区&运营中心填-房间模型价'!$H:$AE,24,0) -> 850 | D5: =VLOOKUP(D3,'【3-2】大区&运营中心填-房间模型价'!$H:$AE,24,0) -> 1407.8
A7: 2层 | B7: 房号 | C7: 201 | D7: 202 | E7: 203
B8: 户型 | C8: =VLOOKUP(C7,'【3-2】大区&运营中心填-房间模型价'!$H:$AE,2,0) -> 1-41C | D8: =VLOOKUP(D7,'【3-2】大区&运营中心填-房间模型价'!$H:$AE,2,0) -> 1-41D | E8: =VLOOKUP(E7,'【3-2】大区&运营中心填-房间模型价'!$H:$AE,2,0) -> 1-41E
B9: 价格 | C9: =VLOOKUP(C7,'【3-2】大区&运营中心填-房间模型价'!$H:$AE,24,0) -> 1137.8 | D9: =VLOOKUP(D7,'【3-2】大区&运营中心填-房间模型价'!$H:$AE,24,0) -> 1517.8 | E9: =VLOOKUP(E7,'【3-2】大区&运营中心填-房间模型价'!$H:$AE,24,0) -> 1878
A11: 3层 | B11: 房号 | C11: 301 | D11: 302 | E11: 303 | F11: 304
B12: 户型 | C12: =VLOOKUP(C11,'【3-2】大区&运营中心填-房间模型价'!$H:$AE,2,0) -> 1-41F | D12: =VLOOKUP(D11,'【3-2】大区&运营中心填-房间模型价'!$H:$AE,2,0) -> 1-41G | E12: =VLOOKUP(E11,'【3-2】大区&运营中心填-房间模型价'!$H:$AE,2,0) -> 1-41G | F12: =VLOOKUP(F11,'【3-2】大区&运营中心填-房间模型价'!$H:$AE,2,0) -> 1-41F
B13: 价格 | C13: 1433.8 | D13: =VLOOKUP(D11,'【3-2】大区&运营中心填-房间模型价'!$H:$AE,24,0) -> 1837.8 | E13: =VLOOKUP(E11,'【3-2】大区&运营中心填-房间模型价'!$H:$AE,24,0) -> 1868 | F13: =VLOOKUP(F11,'【3-2】大区&运营中心填-房间模型价'!$H:$AE,24,0) -> 1337.8
A15: 4层 | B15: 房号 | C15: 401 | D15: 402 | E15: 403 | F15: 404
B16: 户型 | C16: =VLOOKUP(C15,'【3-2】大区&运营中心填-房间模型价'!$H:$AE,2,0) -> 1-41F | D16: =VLOOKUP(D15,'【3-2】大区&运营中心填-房间模型价'!$H:$AE,2,0) -> 1-41G | E16: =VLOOKUP(E15,'【3-2】大区&运营中心填-房间模型价'!$H:$AE,2,0) -> 1-41G | F16: =VLOOKUP(F15,'【3-2】大区&运营中心填-房间模型价'!$H:$AE,2,0) -> 1-41F
B17: 价格 | C17: =VLOOKUP(C15,'【3-2】大区&运营中心填-房间模型价'!$H:$AE,24,0) -> 1150 | D17: =VLOOKUP(D15,'【3-2】大区&运营中心填-房间模型价'!$H:$AE,24,0) -> 1837.8 | E17: =VLOOKUP(E15,'【3-2】大区&运营中心填-房间模型价'!$H:$AE,24,0) -> 1868 | F17: =VLOOKUP(F15,'【3-2】大区&运营中心填-房间模型价'!$H:$AE,24,0) -> 1250
A19: 5层 | B19: 房号 | C19: 501 | D19: 502 | E19: 503 | F19: 504
B20: 户型 | C20: =VLOOKUP(C19,'【3-2】大区&运营中心填-房间模型价'!$H:$AE,2,0) -> 1-41F | D20: =VLOOKUP(D19,'【3-2】大区&运营中心填-房间模型价'!$H:$AE,2,0) -> 1-41G | E20: =VLOOKUP(E19,'【3-2】大区&运营中心填-房间模型价'!$H:$AE,2,0) -> 1-41G | F20: =VLOOKUP(F19,'【3-2】大区&运营中心填-房间模型价'!$H:$AE,2,0) -> 1-41F
B21: 价格 | C21: =VLOOKUP(C19,'【3-2】大区&运营中心填-房间模型价'!$H:$AE,24,0) -> 1150 | D21: =VLOOKUP(D19,'【3-2】大区&运营中心填-房间模型价'!$H:$AE,24,0) -> 1837.8 | E21: =VLOOKUP(E19,'【3-2】大区&运营中心填-房间模型价'!$H:$AE,24,0) -> 1838 | F21: =VLOOKUP(F19,'【3-2】大区&运营中心填-房间模型价'!$H:$AE,24,0) -> 1337.8
A23: 6层 | B23: 房号 | C23: 601 | D23: 602
B24: 户型 | C24: =VLOOKUP(C23,'【3-2】大区&运营中心填-房间模型价'!$H:$AE,2,0) -> 1-41F | D24: =VLOOKUP(D23,'【3-2】大区&运营中心填-房间模型价'!$H:$AE,2,0) -> 1-41F
B25: 价格 | C25: =VLOOKUP(C23,'【3-2】大区&运营中心填-房间模型价'!$H:$AE,24,0) -> 1150 | D25: =VLOOKUP(D23,'【3-2】大区&运营中心填-房间模型价'!$H:$AE,24,0) -> 1250

Sheet 【5】平面图

Sheet 【补充】采光验证因素
C1: 1 | D1: 2 | E1: 3 | F1: 4 | G1: 5
B3: 采光名词设定标准 | C3: 阴暗 | D3: 不足 | E3: 良好 | F3: 充足 | G3: 完美 | H3: 备注：阳台按两扇窗户计入
B4: 遮挡定义标准 | C4: 1-3楼楼间距＜4米
C5: 4楼以上楼间距＜2米
B7: 五个遮挡 | I7: 五个遮挡 | N7: 差 | P7: 五个遮挡 | U7: 差 | W7: 五个遮挡 | AB7: 差
B8: 四个遮挡 | F8: 差 | I8: 四个遮挡 | M8: 差 | N8: 差 | P8: 四个遮挡 | T8: 差 | U8: 差 | W8: 四个遮挡 | AA8: 差 | AB8: 差
B9: 三个遮挡 | E9: 差 | F9: 较差 | I9: 三个遮挡 | L9: 差 | M9: 差 | N9: 较差 | P9: 三个遮挡 | S9: 差 | T9: 差 | U9: 较差 | W9: 三个遮挡 | Z9: 差 | AA9: 差 | AB9: 较差
B10: 两个遮挡 | D10: 差 | E10: 较差 | F10: 适中 | I10: 两个遮挡 | K10: 差 | L10: 差 | M10: 较差 | N10: 适中 | P10: 两个遮挡 | R10: 差 | S10: 差 | T10: 较差 | U10: 适中 | W10: 两个遮挡 | Y10: 差 | Z10: 差 | AA10: 较差 | AB10: 适中
B11: 一个遮挡 | C11: 差 | D11: 较差 | E11: 适中 | F11: 较优 | I11: 一个遮挡 | J11: 差 | K11: 差 | L11: 较差 | M11: 适中 | N11: 较优 | P11: 一个遮挡 | Q11: 差 | R11: 差 | S11: 较差 | T11: 适中 | U11: 较优 | W11: 一个遮挡 | X11: 差 | Y11: 差 | Z11: 较差 | AA11: 适中 | AB11: 较优
B12: 无遮挡 | C12: 较差 | D12: 适中 | E12: 较优 | F12: 优 | I12: 无遮挡 | J12: 差 | K12: 较差 | L12: 适中 | M12: 较优 | N12: 优 | P12: 无遮挡 | Q12: 差 | R12: 较差 | S12: 适中 | T12: 较优 | U12: 优 | W12: 无遮挡 | X12: 差 | Y12: 较差 | Z12: 适中 | AA12: 较优 | AB12: 优
C13: 一扇窗户 | D13: 两扇窗户 | E13: 三扇窗户 | F13: 四扇窗户 | G13: 五扇窗户 | J13: 一扇窗户 | K13: 两扇窗户 | L13: 三扇窗户 | M13: 四扇窗户 | N13: 五扇窗户 | Q13: 一扇窗户 | R13: 两扇窗户 | S13: 三扇窗户 | T13: 四扇窗户 | U13: 五扇窗户 | X13: 一扇窗户 | Y13: 两扇窗户 | Z13: 三扇窗户 | AA13: 四扇窗户 | AB13: 五扇窗户
B15: 格局：单间 轻复式 二人宿舍 三人宿舍 | I15: 格局：一居室 四人宿舍 六人宿舍 | R15: 格局：二居室 | Y15: 格局：三居室
