Workbook
Name 采光: 【1】定价因子!$D$42:$D$46
Name 床型: 【1】定价因子!$D$48:$D$53
Name 地铁站步行时间: 【1】定价因子!#REF!
Name 电梯房楼层: 【1】定价因子!$D$26:$D$34
Name 公区步行距离: 【1】定价因子!$D$2:$D$6
Name 功能: 【1】定价因子!$D$36:$D$41
Name 户型格局: 【1】定价因子!#REF!
Name 楼栋外观: 【1】定价因子!#REF!
Name 楼梯房楼层: 【1】定价因子!$D$16:$D$25
Name 套内空间: 【1】定价因子!$D$9:$D$13
Name 梯户比: 【1】定价因子!#REF!
Name 阳台: 【1】定价因子!$D$14:$D$15
Name 有无电梯: 【1】定价因子!$D$7:$D$8

Sheet 更新日志
B2: 版本号 | C2: 更新日期 | D2: 主要更新内容 | E2: 决议方式 | F2: 启用时间
B3: v1.0 | C3: 44036 | D3: 1. 创建了xlsx格式的模型，便于过程数据留存 | F3: 44039
B4: v1.01 | C4: 44056 | D4: 1. 优化了【楼栋公区距离】因子下的调价系数，使公区距离的影响力扩大，更符合市场需求； 2. 新增了定价模型的【更新日志】 | E4: 公寓例会 | F4: 44056
B5: v1.10 | C5: 44131 | D5: 1. 对各个格局的【套内空间】分档明确面积范围； 2. 【地铁站距离】测量方式改为步行时长（百度地图）； 3. 深化完善【户型】【功能】【采光】等因子各分档的标准描述，减小主观误差； | E5: 定价小组会议 | F5: 44132
B6: v1.11 | C6: 44281 | D6: 1. 更新了两个项目的基准价：元芬上早1468.41元，创业花园1763元，以及各个格局的基准价； 2. 删除“高架床/窄床开间”格局，使格局类型与实际业务名词体系一致，新增【床型】因子，用于描述不同床型对定价的影响； 3. 调整了【采光】【地铁站距离】【有无电梯】【楼层】【功能】因子的分档和系数； 4. 删除了【公交站距离】【噪音】【污染】【视野】等极少使用或影响力极小的因子； 5. 深化完善各个因子各分档的标准描述； | F6: 44287
B7: v1.12 | C7: 44670 | D7: 1.更新采光因素量化标准，并增加采光因素填写sheet，需填写房间窗户数量，根据楼间距填写遮挡信息 2.增加审批条件，整体均价≥模型均价，实际定价在模型价格的-5%~15%之间 | F7: 44670
B8: v2.2 | C8: 45127 | D8: 1.将很狭小的折价从0.91修正为0.9； 2.将较宽敞的溢价由1.05提高到1.06，很宽敞溢价由1.09提高到1.10； 3.将楼梯一层的折价由0.9，提高到0.91；将电梯一层的折价由0.85，提高到0.87； | F8: 45127
B9: v2.3 | C9: 45468 | D9: 1.增加房间面积，增加自动取值逻辑 | F9: 45468
B10: v2.4 | C10: 45482 | D10: 1.更新了一下村成本算法，增加自动取值逻辑 | F10: 45482
B11: V2.5 | C11: 45483 | D11: 1.增加二居室相关配置信息 | F11: 45483

Sheet 【1】定价因子
B1: 序号 | C1: 定价因子 | D1: 分档 | E1: 数列 | F1: 调价倍数 | G1: 备注 | L1: 项目基准价 | M1: =VLOOKUP('【2】运营中心填-基本信息&审核标准'!C2,各村基准价!A:C,2,FALSE) -> 1634.8
A2: 基准格局定价因子 | B2: 1 | C2: 区位 | D2: 交通很便利 | E2: =$C$2&D2 -> 区位交通很便利 | F2: 1.04 | G2: 距离中心楼栋步行300米以上，且为方向交通更便利，如更靠近地铁，更靠近主干道 | I2: =J2*#REF!-J2 -> #REF! | J2: 1350 | L2: 基准格局 | M2: 套均价
D3: 交通较便利 | E3: =$C$2&D3 -> 区位交通较便利 | F3: 1.02 | G3: 距离中心楼栋步行150米以上，且为方向交通更便利，如更靠近地铁，更靠近主干道 | I3: =J3*#REF!-J3 -> #REF! | J3: 1350 | K3: 1 | L3: 开间 | M3: =$M$1*K3 -> 1634.8
D4: 中心位置 | E4: =$C$2&D4 -> 区位中心位置 | F4: 1 | G4: 在中心楼栋步行半径150米的位置范围内 | I4: =J4*F2-J4 -> 54 | J4: 1350 | K4: 1.5 | L4: 一居室 | M4: =VLOOKUP('【2】运营中心填-基本信息&审核标准'!C2,各村基准价!A:C,3,FALSE) -> 2426.1
D5: 交通较不便 | E5: =$C$2&D5 -> 区位交通较不便 | F5: 0.98 | G5: 距离中心楼栋步行150米以上，且为方向交通更不便，如更远离地铁，距离村口位置更远 | I5: =J5*F3-J5 -> 27 | J5: 1350 | K5: 2 | L5: 二居室 | M5: =$M$1*K5 -> 3269.6
D6: 交通很不便 | E6: =$C$2&D6 -> 区位交通很不便 | F6: 0.96 | G6: 距离中心楼栋步行300米以上，且为方向交通更不便，如更远离地铁，距离村口位置更远 | I6: 100 | J6: 1350 | K6: 1 | L6: 轻复式 | M6: =$M$1*K6 -> 1634.8
B7: 2 | C7: 有无电梯 | D7: 有 | E7: =$C$7&D7 -> 有无电梯有 | F7: 1.05 | G7: 只比较楼梯4F和电梯4F | I7: 80 | J7: 1350 | K7: 1 | L7: 二人宿舍 | M7: =$M$1*K7 -> 1634.8
D8: 无 | E8: =$C$7&D8 -> 有无电梯无 | F8: 1 | I8: =J8*F6-J8 -> -54 | J8: 1350 | K8: 1.5 | L8: 四人宿舍 | M8: =M4 -> 2426.1
A9: 房间定价因子 | B9: 1 | C9: 套内空间 | D9: 很宽敞 | E9: =$C$9&D9 -> 套内空间很宽敞 | F9: 1.1 | G9: 权重：客厅>卧室>＞卫生间/洗漱区； 空间为住户实际使用感知的空间，如：（1）裸露地板的面积（2）床周边通行宽度（3）高架床、LOFT利用了立体空间，套内面积狭小但可能套内空间适中 | I9: =J9*F7-J9 -> 0 | K9: 2 | L9: 六人宿舍 | M9: =$M$1*K9 -> 3269.6
D10: 较宽敞 | E10: =$C$9&D10 -> 套内空间较宽敞 | F10: 1.06 | I10: =J10*F8-J10 -> 0 | K10: 2 | L10: 八人宿舍 | M10: =$M$1*K10 -> 3269.6
D11: 适中 | E11: =$C$9&D11 -> 套内空间适中 | F11: 1 | I11: =J11*#REF!-J11 -> #REF! | K11: 2 | L11: 二居轻复式 | M11: =$M$1*K11 -> 3269.6
D12: 较狭小 | E12: =$C$9&D12 -> 套内空间较狭小 | F12: 0.95 | I12: =J12*#REF!-J12 -> #REF!
D13: 很狭小 | E13: =$C$9&D13 -> 套内空间很狭小 | F13: 0.9 | I13: =J13*#REF!-J13 -> #REF!
B14: 3 | C14: 阳台 | D14: 有 | E14: =$C$14&D14 -> 阳台有 | F14: 1.07 | I14: =J14*#REF!-J14 -> #REF!
D15: 无 | E15: =$C$14&D15 -> 阳台无 | F15: 1
B16: 4 | C16: 楼梯房楼层 | D16: 无 | E16: =$C$16&D16 -> 楼梯房楼层无 | F16: 1 | G16: 不考虑采光和视野的差异 | I16: =J16*F11-J16 -> 0 | J16: 1350 | K16: 套内空间类型 | L16: 高架床/窄床 | M16: 正常开间 | N16: 正常一居室 | O16: 两居室
D17: 1F | E17: =$C$16&D17 -> 楼梯房楼层1F | F17: 0.91 | I17: =J17*F12-J17 -> -67.5 | J17: 1350 | K17: 很宽敞 | L17: >18 | M17: >20㎡ | N17: >28㎡ | O17: >45㎡
D18: 2F | E18: =$C$16&D18 -> 楼梯房楼层2F | F18: 1.02 | I18: =J18*F13-J18 -> -135 | J18: 1350 | K18: 较宽敞 | L18: 15-18㎡ | M18: 17-20㎡ | N18: 26-28㎡ | O18: 40-45㎡
D19: 3F | E19: =$C$16&D19 -> 楼梯房楼层3F | F19: 1.01 | I19: =J19*#REF!-J19 -> #REF! | J19: 1350 | K19: 适中 | L19: 11-15㎡ | M19: 13-17㎡ | N19: 23-26㎡ | O19: 35-40㎡
D20: 4F | E20: =$C$16&D20 -> 楼梯房楼层4F | F20: 1 | I20: =J20*#REF!-J20 -> #REF! | J20: 1350 | K20: 较狭小 | L20: 9-11㎡ | M20: 10-13㎡ | N20: 20-23㎡ | O20: 30-35㎡
D21: 5F | E21: =$C$16&D21 -> 楼梯房楼层5F | F21: 0.99 | I21: =J21*#REF!-J21 -> #REF! | J21: 1350 | K21: 很狭小 | L21: <9㎡ | M21: <10㎡ | N21: <20㎡ | O21: <30㎡
D22: 6F | E22: =$C$16&D22 -> 楼梯房楼层6F | F22: 0.98 | I22: =J22*#REF!-J22 -> #REF! | J22: 1350
D23: 7F | E23: =$C$16&D23 -> 楼梯房楼层7F | F23: 0.96 | I23: =J23*#REF!-J23 -> #REF! | J23: 1350
D24: 8F | E24: =$C$16&D24 -> 楼梯房楼层8F | F24: 0.93 | I24: =J24*F14-J24 -> 94.5 | J24: 1350
D25: 9F | E25: =$C$16&D25 -> 楼梯房楼层9F | F25: 0.9 | I25: =J25*F15-J25 -> 0 | J25: 1350
B26: 5 | C26: 电梯房楼层 | D26: 无 | E26: =$C$26&D26 -> 电梯房楼层无 | F26: 1 | I26: =J26*#REF!-J26 -> #REF! | J26: 1350
D27: 1F | E27: =$C$26&D27 -> 电梯房楼层1F | F27: 0.87 | G27: 不考虑采光和视野的差异
D28: 2-3F | E28: =$C$26&D28 -> 电梯房楼层2-3F | F28: 0.99 | I28: =J28*#REF!-J28 -> #REF!
D29: 4F | E29: =$C$26&D29 -> 电梯房楼层4F | F29: 1 | I29: =1325*F16-1325 -> 0
D30: 5-6F | E30: =$C$26&D30 -> 电梯房楼层5-6F | F30: 1.01
D31: 7-8F | E31: =$C$26&D31 -> 电梯房楼层7-8F | F31: 1.02 | I31: =1325*F18-1325 -> 26.5
D32: 9-10F | E32: =$C$26&D32 -> 电梯房楼层9-10F | F32: 1.03 | I32: =1325*F19-1325 -> 13.25
D33: 11-12F | E33: =$C$26&D33 -> 电梯房楼层11-12F | F33: 1.04 | I33: =1325*F20-1325 -> 0
D34: 13以上F | E34: =$C$26&D34 -> 电梯房楼层13以上F | F34: 1.05 | I34: =1325*F21-1325 -> -13.25
B35: 6 | C35: 功能配置（开间） | D35: 缺失 | E35: =$C$35&D35 -> 功能配置（开间）缺失 | F35: 0.93
D36: 缺失（书桌） | E36: =$C$35&D36 -> 功能配置（开间）缺失（书桌） | F36: 0.98 | I36: =1325*F22-1325 -> -26.5
D37: 缺失（操作台） | E37: =$C$35&D37 -> 功能配置（开间）缺失（操作台） | F37: 0.96 | I37: =1325*F23-1325 -> -53
D38: 适中 | E38: =$C$35&D38 -> 功能配置（开间）适中 | F38: 1 | I38: =1325*F24-1325 -> -92.75
D39: 充足（油烟机/双人沙发） | E39: =$C$35&D39 -> 功能配置（开间）充足（油烟机/双人沙发） | F39: 1.04 | I39: =1325*F25-1325 -> -132.5
D40: 充足（单人沙发/餐桌） | E40: =$C$35&D40 -> 功能配置（开间）充足（单人沙发/餐桌） | F40: 1.03
D41: 非常充足 | E41: =$C$35&D41 -> 功能配置（开间）非常充足 | F41: 1.06 | I41: =1325*F27-1325 -> -172.25
C42: 采光 | D42: 5 | E42: =$C$42&D42 -> 采光5 | F42: 1.06 | G42: 根据采光模型
D43: 4 | E43: =$C$42&D43 -> 采光4 | F43: 1.03
D44: 3 | E44: =$C$42&D44 -> 采光3 | F44: 1 | I44: =1325*F31-1325 -> 26.5
D45: 2 | E45: =$C$42&D45 -> 采光2 | F45: 0.96 | I45: =1325*F32-1325 -> 39.75
D46: 1 | E46: =$C$42&D46 -> 采光1 | F46: 0.91 | I46: =1325*F33-1325 -> 53
B47: 8 | C47: 功能配置（一居） | D47: 缺失 | E47: =$C$47&D47 -> 功能配置（一居）缺失 | F47: 0.93
D48: 缺失（操作台/双人沙发） | E48: =$C$47&D48 -> 功能配置（一居）缺失（操作台/双人沙发） | F48: 0.96 | K48: 各格局功能分档说明 | L48: 开间（含窄床） | M48: 正常一居室 | N48: 两居室
D49: 缺失（餐桌） | E49: =$C$47&D49 -> 功能配置（一居）缺失（餐桌） | F49: 0.98 | I49: =J49*F36-J49 -> -27 | J49: 1350 | K49: 缺失 | L49: 无操作台或无书桌 | M49: 沙发/餐桌/操作台任意缺一 | N49: 缺失沙发、餐桌、操作台、电视柜
D50: 适中 | E50: =$C$47&D50 -> 功能配置（一居）适中 | F50: 1 | K50: 适中 | L50: 操作台+书桌 | M50: 沙发+餐桌+操作台 | N50: 沙发+餐桌+操作台+电视柜
D51: 充配（书桌） | E51: =$C$47&D51 -> 功能配置（一居）充配（书桌） | F51: 1.02 | I51: =J51*F38-J51 -> 0 | J51: 1350 | K51: 充足 | L51: 操作台+书桌+沙发/餐桌 | M51: 沙发+餐桌+操作台+电视柜/卧室书桌 | N51: 客厅（沙发、餐桌、茶几、电视柜、油烟机/冰箱）
D52: 充配（油烟机） | E52: =$C$47&D52 -> 功能配置（一居）充配（油烟机） | F52: 1.04 | I52: =J52*F39-J52 -> 54 | J52: 1350 | K52: 非常充足 | L52: 操作台+书桌+沙发+餐桌 | M52: 沙发+餐桌+操作台+厨房（含油烟机） | N52: 充足+油烟机+冰箱
D53: 非常充配 | E53: =$C$47&D53 -> 功能配置（一居）非常充配 | F53: 1.06
B54: 9 | C54: 功能配置（二居） | D54: 缺失 | E54: =$C$54&D54 -> 功能配置（二居）缺失 | F54: 0.93
D55: 缺失（沙发/餐桌） | E55: =$C$54&D55 -> 功能配置（二居）缺失（沙发/餐桌） | F55: 0.96
D56: 缺失（电视柜/操作台） | E56: =$C$54&D56 -> 功能配置（二居）缺失（电视柜/操作台） | F56: 0.98
D57: 适中 | E57: =$C$54&D57 -> 功能配置（二居）适中 | F57: 1
D58: 充配（油烟机/冰箱） | E58: =$C$54&D58 -> 功能配置（二居）充配（油烟机/冰箱） | F58: 1.04
D59: 非常充配 | E59: =$C$54&D59 -> 功能配置（二居）非常充配 | F59: 1.06
C60: 公交站步行距离 | D60: <0.5km | F60: 1 | H60: 从定价因子中剔除，正常收集标签
D61: 0.5~1km | F61: 0.975 | H61: 从定价因子中剔除，正常收集标签 | I61: =J61*#REF!-J61 -> #REF! | J61: 1350
D62: 1~1.5km | F62: 0.95 | H62: 从定价因子中剔除，正常收集标签 | I62: =J62*F42-J62 -> 81 | J62: 1350
D63: >1.5km | F63: 0.91 | H63: 从定价因子中剔除，正常收集标签 | I63: =J63*F43-J63 -> 40.5 | J63: 1350
C64: 视野 | D64: 很好 | F64: 1.045 | G64: 如：窗前有水景、山景、花园等 | H64: 从定价因子中剔除，正常收集标签 | I64: =J64*F44-J64 -> 0 | J64: 1350
D65: 较好 | F65: 1.02 | G65: 如：视野开阔，无遮挡 | H65: 从定价因子中剔除，正常收集标签 | I65: =J65*F45-J65 -> -54 | J65: 1350
D66: 适中 | F66: 1 | G66: 看的是邻栋楼 | H66: 从定价因子中剔除，正常收集标签
D67: 差 | F67: 0.95 | G67: 如：窗前有垃圾站、烂尾建筑等 | H67: 从定价因子中剔除，正常收集标签 | I67: =J67*F48-J67 -> -58 | J67: 1450
C68: 噪音影响度 | D68: 无 | F68: 1 | G68: 如：马路行车、商业喧嚣等（主要考虑噪音发生时间是否客户经常在家，如：早晨、夜间、周末；相邻马路车流量、隔音情况等） | H68: 从定价因子中剔除，正常收集标签 | I68: =J68*F49-J68 -> -29 | J68: 1450
D69: 小 | F69: 0.975 | H69: 从定价因子中剔除，正常收集标签 | I69: =J69*F50-J69 -> 0 | J69: 1450
D70: 中 | F70: 0.95 | H70: 从定价因子中剔除，正常收集标签
D71: 大 | F71: 0.91 | H71: 从定价因子中剔除，正常收集标签
C72: 污染 | D72: 无 | F72: 1 | G72: 如:臭气等 | H72: 从定价因子中剔除，正常收集标签 | I72: =J72*F53-J72 -> 180 | J72: 3000
D73: 小 | F73: 0.975 | H73: 从定价因子中剔除，正常收集标签
D74: 中 | F74: 0.945 | H74: 从定价因子中剔除，正常收集标签
D75: 大 | F75: 0.9 | H75: 从定价因子中剔除，正常收集标签
I81: =J81*F68-J81 -> 0
I82: =J82*F69-J82 -> 0
I83: =J83*F70-J83 -> 0
I84: =J84*F71-J84 -> 0
I85: =J85*F72-J85 -> 0
I86: =J86*F73-J86 -> 0
I87: =J87*F74-J87 -> 0
I88: =J88*F75-J88 -> 0

Sheet 各村基准价
A1: 村 | B1: 开间 | C1: 一居室
A2: 马蹄山村 | B2: 2075.1 | C2: 2847.2
A3: 禾坪岗村 | B3: 2080.7 | C3: 2851.9
A4: 中心围村 | B4: 2075.2 | C4: 2847.3
A5: 白石龙老村 | B5: 2200.7 | C5: 2945.6
A6: 东边新村 | B6: 1889.9 | C6: 2669.3
A7: 陶吓新村 | B7: 1585.3 | C7: 2353.9
A8: 元芬新村 | B8: 1707.9 | C8: 2486.2
A9: 塘水围二区 | B9: 1943.3 | C9: 2720.1
A10: 三合华侨新村 | B10: 1530.2 | C10: 2292.2
A11: 谭罗华侨新村 | B11: 1530.7 | C11: 2292.8
A12: 下早新村 | B12: 1624.6 | C12: 2397.1
A13: 赤岭头村 | B13: 1748.1 | C13: 2528
... A90: 74区布心二村 | B90: 2306.2 | C90: 3032.4

Sheet piovt_各村均价
C3: 成本 | E3: 实际
B4: 村 | C4: 收楼坪效 | D4: 标准成本坪效 | E4: 挂牌坪效 | F4: 签约坪效 | G4: 总面积
B5: 31区水口花园 | C5: 76.488565 | D5: 84.393728 | E5: 114.57053 | G5: 893.31 | H5: =C5*G5 -> 68328
B6: 坳下村 | C6: 62.262344 | D6: 104.98889 | E6: 95.122886 | G6: 4959.9 | H6: =C6*G6 -> 308815
B7: 白石龙二区 | C7: 59.762105 | D7: 79.955556 | E7: 102.00649 | G7: 832.3 | H7: =C7*G7 -> 49740
B8: 白石龙老村 | C8: 58.724033 | D8: 79.2 | E8: 91.136763 | G8: 10909.22 | H8: =C8*G8 -> 640633.4
B9: 白石龙一区 | C9: 60.200836 | E9: 109.89186 | G9: 1100.4 | H9: =C9*G9 -> 66245
B10: 宝安永丰八区 | C10: 86.996901 | E10: 118.2469 | G10: 968 | H10: =C10*G10 -> 84213
B11: 赤岭头新村 | C11: 47.829279 | E11: 82.290041 | G11: 1089.5 | H11: =C11*G11 -> 52110
B12: 东边坑 | C12: 31.947913 | E12: 60.09364 | G12: 1025.2 | H12: =C12*G12 -> 32753
B13: 东边新村 | C13: 59.711601 | E13: 91.020319 | G13: 915.4 | H13: =C13*G13 -> 54660
B14: 东方二街 | C14: 28.062348 | E14: 52.03701 | G14: 2487.96 | H14: =C14*G14 -> 69818
B15: 福围广生 | C15: 51.940645 | E15: 77.358156 | G15: 2540.65 | H15: =C15*G15 -> 131963
B16: 福永新村 | C16: 46.077623 | E16: 73.4127 | G16: 2825.71 | H16: =C16*G16 -> 130202
B17: 弓村 | C17: 44.838467 | E17: 79.876688 | G17: 3584.4 | H17: =C17*G17 -> 160719
B18: 和顺新村 | C18: 38.974508 | E18: 64.761258 | G18: 1545.6 | H18: =C18*G18 -> 60239
B19: 后瑞村 | C19: 53.272104 | E19: 83.713307 | G19: 338.62 | H19: =C19*G19 -> 18039
B20: 后亭村 | C20: 32.113961 | E20: 63.069143 | G20: 1512.8 | H20: =C20*G20 -> 48582
... B39: 元芬新村 | C39: 43.566971 | E39: 86.429829 | G39: 624.9 | H39: =C39*G39 -> 27225

Sheet 【2】运营中心填-基本信息&审核标准
B2: 小区（村） | C2: 兴围村 | D2: 楼栋号 | E2: 兴围西4-11栋
B3: 楼栋基本画像 | C3: 屋面晾晒区 | D3: 电梯 | E3: 格局 | F3: 公寓楼层 | G3: 总销售单元数 | H3: 标准层单元数 | I3: 开间均价 | J3: 一居均价 | K3: 单元均价 | L3: 开间均面积 | M3: 一居室均面积 | N3: 标准层面积 | O3: 公寓面积 | P3: 月租金 | Q3: 村公寓面积
C4: 是 | D4: 是 | E4: {=_xlfn.TEXTJOIN("&",TRUE,_xlfn._xlws.FILTER('【3-2】大区&运营中心填-房间模型价'!K2:K10,'【3-2】大区&运营中心填-房间模型价'!K2:K10<>""))} -> 开间&一居室 | F4: {=INT(LOOKUP(2,1/(NOT(ISBLANK('【3-2】大区&运营中心填-房间模型价'!H:H))),'【3-2】大区&运营中心填-房间模型价'!H:H)/100)} -> 9 | G4: =SUMPRODUCT(('【3-2】大区&运营中心填-房间模型价'!J:J="开间")*1+('【3-2】大区&运营中心填-房间模型价'!J:J="二人宿舍")*1+('【3-2】大区&运营中心填-房间模型价'!J:J="一居室")*1.5+('【3-2】大区&运营中心填-房间模型价'!J:J="四人宿舍")*1.5+('【3-2】大区&运营中心填-房间模型价'!J:J="二居室")*2+('【3-2】大区&运营中心填-房间模型价'!J:J="六人宿舍")*2) -> 83.5 | H4: ='【3-2】大区&运营中心填-房间模型价'!G2 -> 8 | I4: =AVERAGEIF('【3-2】大区&运营中心填-房间模型价'!J:J,"开间",'【3-2】大区&运营中心填-房间模型价'!AM:AM) -> 1493.2609 | J4: =AVERAGEIF('【3-2】大区&运营中心填-房间模型价'!J:J,"一居室",'【3-2】大区&运营中心填-房间模型价'!AM:AM) -> 2062 | K4: =SUMIF('【3-2】大区&运营中心填-房间模型价'!A:A,E2,'【3-2】大区&运营中心填-房间模型价'!AM:AM)/G4 -> 1440 | L4: =AVERAGEIF('【3-2】大区&运营中心填-房间模型价'!J:J,"开间",'【3-2】大区&运营中心填-房间模型价'!N:N) -> 14.306739 | M4: =AVERAGEIF('【3-2】大区&运营中心填-房间模型价'!J:J,"一居室",'【3-2】大区&运营中心填-房间模型价'!N:N) -> 16.808 | N4: 176.48 | O4: 1547.01 | P4: 86199 | Q4: =VLOOKUP(C2,piovt_各村均价!B:G,6,0) -> 1426.06
B7: 审批标准
B8: 成本线指标 | C8: 楼栋成本线 | D8: 收楼成本单价 | E8: 成本标准单价 | F8: 定价坪效 | G8: 收楼溢价率 | H8: 成本溢价率 | I8: check
D9: =P4/O4 -> 55.719743 | E9: =(D9+18)/0.9 -> 81.910826 | F9: =SUMIF('【3-2】大区&运营中心填-房间模型价'!A:A,E2,'【3-2】大区&运营中心填-房间模型价'!AM:AM)/O4 -> 77.724126 | G9: =F9/D9 -> 1.3949118 | H9: =F9/E9 -> 0.9488871 | I9: =IF(H9<1,"不通过","通过") -> 不通过
C11: 村成本线 | D11: 收楼成本均价 | E11: 成本标准均价 | F11: 项目整体定价坪效 | G11: 收楼溢价率 | H11: 成本溢价率 | I11: check
D12: =(VLOOKUP(C2,piovt_各村均价!B:H,7,0)+O4*D9)/(VLOOKUP(C2,piovt_各村均价!B:G,6,0)+O4) -> 53.251689 | E12: =(D12+18)/0.9 -> 79.168544 | F12: =(VLOOKUP(C2,piovt_各村均价!B:E,4,0)*Q4+F9*O4)/(O4+Q4) -> 79.642928 | G12: =F12/D12 -> 1.4955944 | H12: =F12/E12 -> 1.0059921 | I12: =IF(H12<1.05,"不通过","通过") -> 不通过
B15: 竞争线指标 | C15: 村竞争线 | D15: 项目 | E15: 标签属性 | J15: 挂牌均价 | K15: 签约均价 | L15: 本楼栋同标签定价均价 | M15: check
M17: =L17/J17 -> #DIV/0!
M18: =L18/J18 -> #DIV/0!
M19: =L19/J19 -> #DIV/0!
B21: 模型线指标 | C21: 房间模型线 | D21: 房间偏差最小值 | E21: 房间偏差最大值 | F21: check
D22: =MIN('【3-2】大区&运营中心填-房间模型价'!AN:AN) -> -0.098991549 | E22: =MAX('【3-2】大区&运营中心填-房间模型价'!AN:AN) -> 0.065036569 | F22: =IF(OR(D22<-10%,E22>10%),"不通过","通过") -> 通过
C25: 楼栋模型线 | D25: 模型均价 | E25: 定价均价 | F25: check
D26: =AVERAGE('【3-2】大区&运营中心填-房间模型价'!AL:AL) -> 1775.8373 | E26: =AVERAGE('【3-2】大区&运营中心填-房间模型价'!AM:AM) -> 1693.5211 | F26: =E26/D26 -> 0.95364658

Sheet 【1】楼栋基本信息
B2: 楼栋号： | C2: A28栋
B3: 房源基本画像 | C3: 电梯 | D3: 公区 | E3: 格局
C4: 无 | D4: 无 | E4: 开间&一居室
B6: 公寓楼层 | C6: 总销售单元数 | D6: 标准层单元数 | E6: 开间均价 | F6: 一居均价 | G6: 单元均价 | H6: 标准层面积 | I6: 公寓面积 | J6: 模型均价
B7: 5 | C7: 34 | D7: 7.5 | E7: =AVERAGEIF('【3-2】大区&运营中心填-房间模型价'!J:J,"开间",'【3-2】大区&运营中心填-房间模型价'!AM:AM) -> 1493.2609 | F7: =AVERAGEIF('【3-2】大区&运营中心填-房间模型价'!J:J,"一居室",'【3-2】大区&运营中心填-房间模型价'!AM:AM) -> 2062 | G7: 1681.0588 | H7: 135.73 | I7: 662 | J7: =SUMIF('【3-2】大区&运营中心填-房间模型价'!A:A,C2,'【3-2】大区&运营中心填-房间模型价'!AL:AL)/C7 -> 0
C9: 收楼-楼梯（元/㎡） | D9: 收楼-电梯(元/㎡） | E9: 成本坪效 （含建设按出租率96%） | F9: 定价坪效 | G9: 收楼溢价率 | H9: 成本溢价率
B10: 坪效 | C10: 45 | D10: 55 | E10: =(C10+21)/0.96 -> 68.75 | F10: =SUMIF('【3-2】大区&运营中心填-房间模型价'!A:A,C2,'【3-2】大区&运营中心填-房间模型价'!AM:AM)/I7 -> 0 | G10: =F10/C10 -> 0 | H10: =F10/E10 -> 0
B11: 备注 | C11: 成本坪效=（收入成本+建设成本）/ 96%
B12: 项目 | C12: 属性 | G12: 挂牌价 | H12: 同房型对比
B13: 元芬村 | C13: 10-15平 | D13: 标配 | E13: 无电梯 | F13: 无阳台 | G13: 1533 | H13: =E7/G13 -> 0.97407754
B14: 元芬村 | C14: 15-20平 | D14: 标配 | E14: 无电梯 | F14: 无阳台 | G14: 1619 | H14: =E7/G14 -> 0.92233531
B15: 元芬村 | C15: 20-25平 | D15: 标配 | E15: 无电梯 | F15: 无阳台 | G15: 2202 | H15: =F7/G15 -> 0.93642144
C21: 成本线 | D21: 单楼栋
D22: 全项目

Sheet 项目基准价
A1: 项目 | B1: 单位 | C1: 数值
A2: 租金成本坪效 | B2: 元/㎡/月 | C2: 46.3
A3: 单元平均面积 | B3: ㎡/单元 | C3: 18.9
A4: 单位面积装修成本 | B4: 元/㎡ | C4: 2500
A5: 装修线性折旧年限 | B5: 年 | C5: 10
A6: 稳定出租率 | B6: % | C6: 0.98
A7: 成本法基准价 | B7: 元/单元/月 | C7: =(C2*C3+C4*C3/C5/12)/C6 -> 1294.7143
A8: 成本法权重 | B8: % | C8: 1
A9: 市场法基准价 | B9: 元/单元/月
A10: 市场法权重 | B10: % | C10: =1-C8 -> 0
A11: 项目基准价 | B11: 元/单元/月 | C11: =C7*C8+C9*C10 -> 1294.7143
C12: 套均价 | D12: 单元均价 | F12: 基准价条件 | G12: 地铁站步行距离 | H12: 公交站步行距离 | I12: 公区步行距离 | J12: 噪音 | K12: 污染 | L12: 4楼有无电梯 | M12: 梯户比 | N12: 楼栋外观 | O12: 套内空间 | P12: 户型 | Q12: 阳台 | R12: 楼梯房楼层 | S12: 功能 | T12: 采光 | U12: 视野
A13: 普通开间基准价 | B13: 元/套 | C13: 1325 | D13: =C13/1 -> 1325 | F13: 分档 | G13: 1~1.5km | H13: <0.5km | I13: 0~0.2km | J13: 无 | K13: 无 | L13: 无 | M13: 5~8 | N13: 适中 | O13: 适中 | P13: 适中 | Q13: 无 | R13: 4楼 | S13: 适中 | T13: 适中 | U13: 适中
A14: 高架床/窄床开间基准价 | B14: 元/套 | C14: 1200 | D14: =C14/1 -> 1200
A15: 普通1居基准价 | B15: 元/套 | C15: 1850 | D15: =C15/1.5 -> 1233.3333
A16: 客厅功能性弱的1居基准价 | B16: 元/套 | C16: 1650 | D16: =C16/1.5 -> 1100
A17: LOFT基准价 | B17: 元/套 | D17: =C17/1.5 -> 0
A18: 2居基准价 | B18: 元/套 | D18: =C18/2 -> 0
A19: 2人间宿舍基准价 | B19: 元/套 | D19: =C19/1 -> 0

Sheet 赋权表
F1: 运营中心 | N1: 营销中心
E2: =MEDIAN(E8:E54) -> #REF! | F2: 地铁站步行距离 | G2: 公交站步行距离 | H2: 公区步行距离 | I2: 噪音 | J2: 污染 | K2: 4楼有无电梯 | L2: 梯户比 | M2: 楼栋外观 | N2: 套内空间 | O2: 户型 | P2: 阳台 | Q2: 楼梯房楼层 | R2: 功能 | S2: 采光 | T2: 视野
B3: 基准条件 | F3: 1~1.5km | G3: <0.5km | H3: 0~0.2km | I3: 无 | J3: 无 | K3: 无 | L3: 5~8 | M3: 适中 | N3: 适中 | O3: 适中 | P3: 无 | Q3: 4楼 | R3: 适中 | S3: 适中 | T3: 适中
B4: 相对优 | F4: 0.5~1km | G4: <0.5km | H4: 0~0.2km | I4: 无 | J4: 无 | K4: 无 | L4: 5~8 | M4: 优 | N4: 较宽敞 | O4: 适中 | P4: 小 | Q4: 4楼 | R4: 充足 | S4: 很好 | T4: 优
B5: 相对差 | E5: 差异率 | F5: 1~1.5km | G5: 0.5~1km | H5: 0.2~0.5km | I5: 中 | J5: 中 | K5: 有 | L5: >8 | M5: 适中 | N5: 适中 | O5: 差 | P5: 无 | Q5: 5楼 | R5: 适中 | S5: 适中 | T5: 适中
B7: V59-406 | C7: 定价租金 | D7: 1419 | F7: 1~1.5km | G7: <0.5km | H7: 0~0.2km | I7: 无 | J7: 无 | K7: 无 | L7: 5~8 | M7: 适中 | N7: 较宽敞 | O7: 适中 | P7: 无 | Q7: 4楼 | R7: 适中 | S7: 较差 | T7: 适中
C8: 模型租金 | D8: =项目基准价!C13*PRODUCT(赋权表!F8:T8) -> #REF! | E8: =D7/D8-1 -> #REF! | F8: =【1】定价因子!#REF! -> #REF! | G8: =【1】定价因子!F60 -> 1 | H8: =【1】定价因子!F6 -> 0.96 | I8: =【1】定价因子!F68 -> 1 | J8: =【1】定价因子!F72 -> 1 | K8: =【1】定价因子!F8 -> 1 | L8: =【1】定价因子!#REF! -> #REF! | M8: =【1】定价因子!#REF! -> #REF! | N8: =【1】定价因子!F10 -> 1.06 | O8: =【1】定价因子!#REF! -> #REF! | P8: =【1】定价因子!#REF! -> #REF! | Q8: =【1】定价因子!F20 -> 1 | R8: =【1】定价因子!F38 -> 1 | S8: =【1】定价因子!F44 -> 1 | T8: =【1】定价因子!F66 -> 1
B9: N258-305 | C9: 定价租金 | D9: 1469 | F9: >1.5km | G9: <0.5km | H9: 0.2~0.5km | I9: 无 | J9: 无 | K9: 无 | L9: 5~8 | M9: 适中 | N9: 较宽敞 | O9: 适中 | P9: 无 | Q9: 3楼 | R9: 充足 | S9: 好 | T9: 优
C10: 模型租金 | D10: =项目基准价!C13*PRODUCT(赋权表!F10:T10) -> #REF! | E10: =D9/D10-1 -> #REF! | F10: =【1】定价因子!#REF! -> #REF! | G10: =【1】定价因子!F60 -> 1 | H10: =【1】定价因子!#REF! -> #REF! | I10: =I8 -> 1 | J10: =J8 -> 1 | K10: =K8 -> 1 | L10: =L8 -> #REF! | M10: =M8 -> #REF! | N10: =N8 -> 1.06 | O10: =O8 -> #REF! | P10: =P8 -> #REF! | Q10: =【1】定价因子!F19 -> 1.01 | R10: =【1】定价因子!F39 -> 1.04 | S10: =【1】定价因子!F42 -> 1.06 | T10: =【1】定价因子!F64 -> 1.045
B11: T78-1404 | C11: 定价租金 | D11: 1470 | F11: 1~1.5km | G11: <0.5km | H11: 楼内 | I11: 无 | J11: 无 | K11: 有 | L11: >8 | M11: 适中 | N11: 适中 | O11: 适中 | P11: 小 | Q11: 14楼 | R11: 适中 | S11: 好 | T11: 适中
C12: 模型租金 | D12: =项目基准价!$C$13*PRODUCT(赋权表!F12:T12) -> #REF! | E12: =D11/D12-1 -> #REF! | F12: =F8 -> #REF! | G12: =G8 -> 1 | H12: =【1】定价因子!F2 -> 1.04 | I12: =I8 -> 1 | J12: =J8 -> 1 | K12: =【1】定价因子!F7 -> 1.05 | L12: =【1】定价因子!#REF! -> #REF! | M12: =M8 -> #REF! | N12: 1 | O12: =O8 -> #REF! | P12: =【1】定价因子!#REF! -> #REF! | Q12: =【1】定价因子!F32 -> 1.03 | R12: =R8 -> 1 | S12: =【1】定价因子!F42 -> 1.06 | T12: =T8 -> 1
B13: V20-410 | C13: 定价租金 | D13: 1509 | F13: 1~1.5km | G13: <0.5km | H13: 0~0.2km | I13: 无 | J13: 无 | K13: 无 | L13: >8 | M13: 适中 | N13: 很宽敞 | O13: 适中 | P13: 无 | Q13: 4楼 | R13: 充足 | S13: 好 | T13: 适中 | U13: =70/1300 -> 0.053846154
C14: 模型租金 | D14: =项目基准价!$C$13*PRODUCT(赋权表!F14:T14) -> #REF! | E14: =D13/D14-1 -> #REF! | F14: =F8 -> #REF! | G14: =G8 -> 1 | H14: =H8 -> 0.96 | I14: =I8 -> 1 | J14: =J8 -> 1 | K14: =K8 -> 1 | L14: =L12 -> #REF! | M14: =M8 -> #REF! | N14: =【1】定价因子!F9 -> 1.1 | O14: =O8 -> #REF! | P14: =P8 -> #REF! | Q14: =Q8 -> 1 | R14: =R10 -> 1.04 | S14: =S10 -> 1.06 | T14: =T8 -> 1
B15: V17-105 | C15: 定价租金 | D15: 1519 | F15: 1~1.5km | G15: <0.5km | H15: 0.2~0.5km | I15: 无 | J15: 无 | K15: 无 | L15: 5~8 | M15: 适中 | N15: 较宽敞 | O15: 适中 | P15: 无 | Q15: 1楼 | R15: 适中 | S15: 很差 | T15: 适中
C16: 模型租金 | D16: =项目基准价!$C$15*PRODUCT(赋权表!F16:T16) -> #REF! | E16: =D15/D16-1 -> #REF! | F16: =F14 -> #REF! | G16: =G14 -> 1 | H16: =H10 -> #REF! | I16: =I10 -> 1 | J16: =J10 -> 1 | K16: =K10 -> 1 | L16: =L10 -> #REF! | M16: =M10 -> #REF! | N16: =N10 -> 1.06 | O16: =O10 -> #REF! | P16: =P10 -> #REF! | Q16: =【1】定价因子!F27 -> 0.87 | R16: =R8 -> 1 | S16: =【1】定价因子!F45 -> 0.96 | T16: =T8 -> 1
B17: V17-104 | C17: 定价租金 | D17: 1099 | F17: 1~1.5km | G17: <0.5km | H17: 0.2~0.5km | I17: 无 | J17: 无 | K17: 无 | L17: 5~8 | M17: 适中 | N17: 较狭小 | O17: 适中 | P17: 无 | Q17: 1楼 | R17: 适中 | S17: 很差 | T17: 适中
C18: 模型租金 | D18: =项目基准价!$C$13*PRODUCT(赋权表!F18:T18) -> #REF! | E18: =D17/D18-1 -> #REF! | F18: =F16 -> #REF! | G18: =G16 -> 1 | H18: =H16 -> #REF! | I18: =I16 -> 1 | J18: =J16 -> 1 | K18: =K16 -> 1 | L18: =L16 -> #REF! | M18: =M16 -> #REF! | N18: =【1】定价因子!F12 -> 0.95 | O18: =O16 -> #REF! | P18: =P16 -> #REF! | Q18: =Q16 -> 0.87 | R18: =R16 -> 1 | S18: =S16 -> 0.96 | T18: =T16 -> 1
B19: X20-1020 | C19: 定价租金 | D19: 2199 | F19: 1~1.5km | G19: <0.5km | H19: >0.5km | I19: 无 | J19: 无 | K19: 有 | L19: >8 | M19: 适中 | N19: 很宽敞 | O19: 适中 | P19: 无 | Q19: 10楼 | R19: 适中 | S19: 好 | T19: 较好
C20: 模型租金 | D20: =项目基准价!$C$15*PRODUCT(赋权表!F20:T20) -> #REF! | E20: =D19/D20-1 -> #REF! | F20: =F18 -> #REF! | G20: =G18 -> 1 | H20: =【1】定价因子!#REF! -> #REF! | I20: =I12 -> 1 | J20: =J12 -> 1 | K20: =K12 -> 1.05 | L20: =L12 -> #REF! | M20: =M12 -> #REF! | N20: =N14 -> 1.1 | O20: =O14 -> #REF! | P20: =P14 -> #REF! | Q20: =Q12 -> 1.03 | R20: =R12 -> 1 | S20: =S14 -> 1.06 | T20: =【1】定价因子!F65 -> 1.02
B21: X20-1001 | C21: 定价租金 | D21: 839 | F21: 1~1.5km | G21: <0.5km | H21: >0.5km | I21: 无 | J21: 无 | K21: 有 | L21: >8 | M21: 适中 | N21: 非常狭小 | O21: 适中 | P21: 无 | Q21: 10楼 | R21: 非常缺失 | S21: 好 | T21: 较好
C22: 模型租金 | D22: =项目基准价!$C$14*PRODUCT(赋权表!F22:T22) -> #REF! | E22: =D21/D22-1 -> #REF! | F22: =F20 -> #REF! | G22: =G20 -> 1 | H22: =H20 -> #REF! | I22: =I20 -> 1 | J22: =J20 -> 1 | K22: =K20 -> 1.05 | L22: =L20 -> #REF! | M22: =M20 -> #REF! | N22: 0.86 | O22: =O20 -> #REF! | P22: =P20 -> #REF! | Q22: =Q20 -> 1.03 | R22: 0.9 | S22: =S20 -> 1.06 | T22: =T20 -> 1.02
B23: T78-815 | C23: 定价租金 | D23: 1379 | F23: 1~1.5km | G23: <0.5km | H23: 楼内 | I23: 无 | J23: 无 | K23: 有 | L23: >8 | M23: 适中 | N23: 适中 | O23: 适中 | P23: 小 | Q23: 8楼 | R23: 适中 | S23: 好 | T23: 适中
C24: 模型租金 | D24: =项目基准价!$C$14*PRODUCT(赋权表!F24:T24) -> #REF! | E24: =D23/D24-1 -> #REF! | F24: =F12 -> #REF! | G24: =G12 -> 1 | H24: =H12 -> 1.04 | I24: =I12 -> 1 | J24: =J12 -> 1 | K24: =K12 -> 1.05 | L24: =L12 -> #REF! | M24: =M12 -> #REF! | N24: =N12 -> 1 | O24: =O22 -> #REF! | P24: =P12 -> #REF! | Q24: =【1】定价因子!F31 -> 1.02 | R24: =R12 -> 1 | S24: =S12 -> 1.06 | T24: =T12 -> 1
A25: 高架 | B25: V21-301 | C25: 定价租金 | D25: 1439 | F25: 1~1.5km | G25: <0.5km | H25: 0~0.2km | I25: 无 | J25: 无 | K25: 无 | L25: 5~8 | M25: 适中 | N25: 较宽敞 | O25: 适中 | P25: 超大 | Q25: 3楼 | R25: 适中 | S25: 好 | T25: 适中
C26: 模型租金 | D26: =项目基准价!$C$14*PRODUCT(赋权表!F26:T26) -> #REF! | E26: =D25/D26-1 -> #REF! | F26: =F14 -> #REF! | G26: =G14 -> 1 | H26: =H14 -> 0.96 | I26: =I14 -> 1 | J26: =J14 -> 1 | K26: =K14 -> 1 | L26: =L18 -> #REF! | M26: =M14 -> #REF! | N26: =N16 -> 1.06 | O26: =O16 -> #REF! | P26: =【1】定价因子!F14 -> 1.07 | Q26: =【1】定价因子!F19 -> 1.01 | R26: =R24 -> 1 | S26: =S24 -> 1.06 | T26: =T24 -> 1
B27: V46-204 | C27: 定价租金 | D27: 1799 | F27: 1~1.5km | G27: <0.5km | H27: 0~0.2km | I27: 无 | J27: 无 | K27: 无 | L27: 5~8 | M27: 优 | N27: 适中 | O27: 适中 | P27: 无 | Q27: 2楼 | R27: 适中 | S27: 适中 | T27: 适中
C28: 模型租金 | D28: =项目基准价!$C$15*PRODUCT(赋权表!F28:T28) -> #REF! | E28: =D27/D28-1 -> #REF! | F28: =F26 -> #REF! | G28: =G26 -> 1 | H28: =H26 -> 0.96 | I28: =I26 -> 1 | J28: =J26 -> 1 | K28: =K26 -> 1 | L28: =L26 -> #REF! | M28: =【1】定价因子!#REF! -> #REF! | N28: =N24 -> 1 | O28: =O24 -> #REF! | P28: =P22 -> #REF! | Q28: =【1】定价因子!F18 -> 1.02 | R28: =R26 -> 1 | S28: =【1】定价因子!F43 -> 1.03 | T28: =T26 -> 1
B29: V46-304 | C29: 定价租金 | D29: 1999 | F29: 1~1.5km | G29: <0.5km | H29: 0~0.2km | I29: 无 | J29: 无 | K29: 无 | L29: 5~8 | M29: 优 | N29: 适中 | O29: 适中 | P29: 大 | Q29: 2楼 | R29: 适中 | S29: 适中 | T29: 很好
C30: 模型租金 | D30: =项目基准价!$C$15*PRODUCT(赋权表!F30:T30) -> #REF! | E30: =D29/D30-1 -> #REF! | F30: =F28 -> #REF! | G30: =G28 -> 1 | H30: =H28 -> 0.96 | I30: =I28 -> 1 | J30: =J28 -> 1 | K30: =K28 -> 1 | L30: =L28 -> #REF! | M30: =M28 -> #REF! | ... O30: =O28 -> #REF! | P30: =【1】定价因子!F15 -> 1 | Q30: =Q28 -> 1.02 | R30: =R28 -> 1 | S30: =S28 -> 1.03 | T30: =【1】定价因子!F64 -> 1.045
B31: V17-301 | C31: 定价租金 | D31: 1569 | F31: 1~1.5km | G31: <0.5km | H31: 0.2~0.5km | I31: 无 | J31: 无 | K31: 无 | L31: 5~8 | M31: 适中 | N31: 适中 | O31: 适中 | P31: 大 | Q31: 3楼 | R31: 缺失 | S31: 较差 | T31: 适中
A32: 弱1居 | C32: 模型租金 | D32: =项目基准价!$C$16*PRODUCT(赋权表!F32:T32) -> #REF! | E32: =D31/D32-1 -> #REF! | F32: =F18 -> #REF! | G32: =G18 -> 1 | H32: =H18 -> #REF! | I32: =I18 -> 1 | J32: =J18 -> 1 | K32: =K18 -> 1 | L32: =L18 -> #REF! | M32: =M18 -> #REF! | N32: =N30 -> 1 | O32: =O30 -> #REF! | P32: =P30 -> 1 | Q32: =Q30 -> 1.02 | S32: =S8 -> 1 | T32: =T28 -> 1
B33: T78-1401 | C33: 定价租金 | D33: 2299 | F33: 1~1.5km | G33: <0.5km | H33: 楼内 | I33: 无 | J33: 无 | K33: 有 | L33: >8 | M33: 适中 | N33: 较宽敞 | O33: 适中 | P33: 小 | Q33: 14楼 | R33: 适中 | S33: 好 | T33: 较好
C34: 模型租金 | D34: =项目基准价!$C$15*PRODUCT(赋权表!F34:T34) -> #REF! | E34: =D33/D34-1 -> #REF! | F34: =F24 -> #REF! | G34: =G24 -> 1 | H34: =H24 -> 1.04 | I34: =I24 -> 1 | J34: =J24 -> 1 | K34: =K24 -> 1.05 | L34: =L24 -> #REF! | M34: =M24 -> #REF! | N34: =N26 -> 1.06 | O34: =O26 -> #REF! | P34: =P24 -> #REF! | Q34: =【1】定价因子!F32 -> 1.03 | R34: =R30 -> 1 | S34: =S10 -> 1.06 | T34: =T20 -> 1.02
A35: 高架 | B35: V46-606 | C35: 定价租金 | D35: 1249 | F35: 1~1.5km | G35: <0.5km | H35: 0~0.2km | I35: 无 | J35: 无 | K35: 无 | L35: 5~8 | M35: 优 | N35: 适中 | O35: 适中 | P35: 无 | Q35: 6楼 | R35: 适中 | S35: 好 | T35: 适中
C36: 模型租金 | D36: =项目基准价!$C$14*PRODUCT(赋权表!F36:T36) -> #REF! | E36: =D35/D36-1 -> #REF! | F36: =F30 -> #REF! | G36: =G30 -> 1 | H36: =H30 -> 0.96 | I36: =I34 -> 1 | J36: =J30 -> 1 | K36: =K30 -> 1 | L36: =L32 -> #REF! | M36: =M30 -> #REF! | N36: =N30 -> 1 | O36: =O34 -> #REF! | P36: =P28 -> #REF! | Q36: =【1】定价因子!F22 -> 0.98 | R36: =R34 -> 1 | S36: =S34 -> 1.06 | T36: =T32 -> 1
A37: 高架 | B37: V60-504 | C37: 定价租金 | D37: 1299 | F37: 1~1.5km | G37: <0.5km | H37: 0~0.2km | I37: 无 | J37: 无 | K37: 无 | L37: 5~8 | M37: 适中 | N37: 适中 | O37: 适中 | P37: 无 | Q37: 5楼 | R37: 适中 | S37: 适中 | T37: 适中
C38: 模型租金 | D38: =项目基准价!$C$14*PRODUCT(赋权表!F38:T38) -> #REF! | E38: =D37/D38-1 -> #REF! | F38: =F8 -> #REF! | G38: =G8 -> 1 | H38: =H8 -> 0.96 | I38: =I36 -> 1 | J38: =J8 -> 1 | K38: =K8 -> 1 | L38: =L8 -> #REF! | M38: =M8 -> #REF! | N38: =N36 -> 1 | O38: =O36 -> #REF! | P38: =P36 -> #REF! | Q38: =【1】定价因子!F21 -> 0.99 | R38: =R36 -> 1 | S38: =S28 -> 1.03 | T38: =T28 -> 1
B39: V19-505 | C39: 定价租金 | D39: 1239 | F39: 1~1.5km | G39: <0.5km | H39: 0.2~0.5km | I39: 无 | J39: 无 | K39: 无 | L39: 5~8 | M39: 适中 | N39: 适中 | O39: 适中 | P39: 无 | Q39: 5楼 | R39: 充足 | S39: 较差 | T39: 适中
C40: 模型租金 | D40: =项目基准价!$C$13*PRODUCT(赋权表!F40:T40) -> #REF! | E40: =D39/D40-1 -> #REF! | F40: =F32 -> #REF! | G40: =G32 -> 1 | H40: =H32 -> #REF! | I40: =I38 -> 1 | J40: =J32 -> 1 | K40: =K32 -> 1 | L40: =L32 -> #REF! | M40: =M32 -> #REF! | N40: =N38 -> 1 | O40: =O38 -> #REF! | P40: =P38 -> #REF! | Q40: =Q38 -> 0.99 | R40: =R14 -> 1.04 | S40: =S32 -> 1 | T40: =T38 -> 1
A41: 弱1居 | B41: V60-303 | C41: 定价租金 | D41: 1699 | F41: 1~1.5km | G41: <0.5km | H41: 0~0.2km | I41: 无 | J41: 无 | K41: 无 | L41: 5~8 | M41: 适中 | N41: 适中 | O41: 适中 | P41: 无 | Q41: 3楼 | R41: 缺失 | S41: 适中 | T41: 适中
C42: 模型租金 | D42: =项目基准价!$C$16*PRODUCT(赋权表!F42:T42) -> #REF! | E42: =D41/D42-1 -> #REF! | F42: =F38 -> #REF! | G42: =G38 -> 1 | H42: =H38 -> 0.96 | I42: =I38 -> 1 | J42: =J38 -> 1 | K42: =K38 -> 1 | L42: =L38 -> #REF! | M42: =M38 -> #REF! | N42: =N38 -> 1 | O42: =O40 -> #REF! | P42: =P40 -> #REF! | Q42: =Q32 -> 1.02 | S42: =S38 -> 1.03 | T42: =T40 -> 1
B43: T133-505 | C43: 定价租金 | D43: 1239 | F43: 1~1.5km | G43: <0.5km | H43: 0.2~0.5km | I43: 小 | J43: 无 | K43: 无 | L43: 5~8 | M43: 适中 | N43: 较宽敞 | O43: 适中 | P43: 无 | Q43: 5楼 | R43: 充足 | S43: 较差 | T43: 适中
C44: 模型租金 | D44: =项目基准价!$C$13*PRODUCT(赋权表!F44:T44) -> #REF! | E44: =D43/D44-1 -> #REF! | F44: =F42 -> #REF! | G44: =G42 -> 1 | H44: =H40 -> #REF! | I44: =【1】定价因子!F69 -> 0.975 | J44: =J34 -> 1 | K44: =K38 -> 1 | L44: =L36 -> #REF! | M44: =M34 -> #REF! | N44: =N34 -> 1.06 | O44: =O40 -> #REF! | P44: =P40 -> #REF! | Q44: =Q40 -> 0.99 | R44: =R40 -> 1.04 | S44: =S32 -> 1 | T44: =T40 -> 1
B45: N248-306 | C45: 定价租金 | D45: 1239 | F45: >1.5km | G45: <0.5km | H45: 0.2~0.5km | I45: 无 | J45: 无 | K45: 无 | L45: 5~8 | M45: 适中 | N45: 较宽敞 | O45: 适中 | P45: 无 | Q45: 3楼 | R45: 充足 | S45: 适中 | T45: 适中
C46: 模型租金 | D46: =项目基准价!$C$13*PRODUCT(赋权表!F46:T46) -> #REF! | E46: =D45/D46-1 -> #REF! | F46: =F10 -> #REF! | G46: =G10 -> 1 | H46: =H10 -> #REF! | I46: =I10 -> 1 | J46: =J10 -> 1 | K46: =K10 -> 1 | L46: =L10 -> #REF! | M46: =M10 -> #REF! | N46: =N34 -> 1.06 | O46: =O44 -> #REF! | P46: =P44 -> #REF! | Q46: =Q42 -> 1.02 | R46: =R44 -> 1.04 | S46: =S42 -> 1.03 | T46: =T44 -> 1
B47: V43-1101 | C47: 定价租金 | D47: 1629 | F47: 1~1.5km | G47: <0.5km | H47: 0~0.2km | I47: 无 | J47: 无 | K47: 有 | L47: 5~8 | M47: 适中 | N47: 适中 | O47: 适中 | P47: 无 | Q47: 11楼 | R47: 适中 | S47: 适中 | T47: 较好
C48: 模型租金 | D48: =项目基准价!$C$13*PRODUCT(赋权表!F48:T48) -> #REF! | E48: =D47/D48-1 -> #REF! | F48: =F34 -> #REF! | G48: =G34 -> 1 | H48: =H42 -> 0.96 | I48: =I34 -> 1 | J48: =J34 -> 1 | K48: =K34 -> 1.05 | L48: =L46 -> #REF! | M48: =M34 -> #REF! | N48: =N40 -> 1 | O48: =O40 -> #REF! | P48: =P40 -> #REF! | Q48: =【1】定价因子!F32 -> 1.03 | R48: =R38 -> 1 | S48: =S38 -> 1.03 | T48: =T20 -> 1.02
A49: 对标T133-505 | B49: V21-304 | C49: 定价租金 | D49: 1449 | F49: 1~1.5km | G49: <0.5km | H49: 0~0.2km | I49: 无 | J49: 无 | K49: 有 | L49: 5~8 | M49: 适中 | N49: 适中 | O49: 适中 | P49: 无 | Q49: 3楼 | R49: 充足 | S49: 较差 | T49: 适中
C50: 模型租金 | D50: =项目基准价!$C$13*PRODUCT(赋权表!F50:T50) -> #REF! | E50: =D49/D50-1 -> #REF! | F50: =F26 -> #REF! | G50: =G26 -> 1 | H50: =H26 -> 0.96 | I50: =I26 -> 1 | J50: =J26 -> 1 | K50: =K26 -> 1 | L50: =L26 -> #REF! | M50: =M26 -> #REF! | N50: =N48 -> 1 | O50: =O48 -> #REF! | P50: =P48 -> #REF! | Q50: =Q46 -> 1.02 | R50: =R46 -> 1.04 | S50: =S44 -> 1 | T50: =T46 -> 1
B51: V20-404 | C51: 定价租金 | D51: 1449 | F51: 1~1.5km | G51: <0.5km | H51: 0~0.2km | I51: 无 | J51: 无 | K51: 无 | L51: >8 | M51: 适中 | N51: 适中 | O51: 适中 | P51: 无 | Q51: 4楼 | R51: 适中 | S51: 适中 | T51: 适中
C52: 模型租金 | D52: =项目基准价!$C$13*PRODUCT(赋权表!F52:T52) -> #REF! | E52: =D51/D52-1 -> #REF! | F52: =F14 -> #REF! | G52: =G14 -> 1 | H52: =H14 -> 0.96 | I52: =I14 -> 1 | J52: =J14 -> 1 | K52: =K14 -> 1 | L52: =L14 -> #REF! | M52: =M14 -> #REF! | N52: =N50 -> 1 | O52: =O50 -> #REF! | P52: =P50 -> #REF! | Q52: =Q8 -> 1 | R52: =R48 -> 1 | S52: =S48 -> 1.03 | T52: =T46 -> 1
B53: 合计 | F53: =SUM(F55:F71) -> 152 | G53: =SUM(G55:G71) -> 65 | H53: =SUM(H55:H71) -> 32 | I53: =SUM(I55:I71) -> 125 | J53: =SUM(J55:J71) -> 139 | K53: =SUM(K55:K71) -> 51 | L53: =SUM(L55:L71) -> 38 | M53: =SUM(M55:M71) -> 26 | ... T53: =SUM(T55:T71) -> 100
A54: =6%/150 -> 0.0004 | B54: 调价系数 | F54: 0.06 | G54: 0.025 | H54: 0.015 | I54: 0.05 | J54: 0.055 | K54: 0.02 | L54: 0.015 | M54: 0.01 | N54: 0.06 | O54: 0.05 | P54: 0.06 | Q54: 0.015 | R54: 0.035 | S54: 0.065 | T54: 0.04
A55: 李晓阳 | F55: 20 | G55: 2 | H55: 12 | I55: 20 | J55: 10 | K55: 8 | L55: 12 | M55: 0 | N55: 26 | O55: 18 | P55: 26 | Q55: 10 | R55: 4 | S55: 26 | T55: 16
A56: 姚欢 | F56: 13 | G56: 7 | H56: 1 | I56: 10 | J56: 14 | K56: 2 | L56: 3 | M56: 0 | N56: 9 | O56: 8 | P56: 11 | Q56: 4 | R56: 6 | S56: 11 | T56: 6
A57: 孙铭馗 | F57: 20 | G57: 4 | H57: 8 | I57: 12 | J57: 18 | K57: 6 | L57: 0 | M57: 2 | N57: 26 | O57: 12 | P57: 24 | Q57: 20 | R57: 16 | S57: 28 | T57: 14
A58: 王漫柔 | F58: 14 | G58: 13 | H58: 4 | I58: 5 | J58: 5 | K58: 8 | L58: 1 | M58: 2 | N58: 4 | O58: 10 | P58: 12 | Q58: 0 | R58: 7 | S58: 11 | T58: 9
A59: 邓彬彬 | F59: 13 | G59: 5 | H59: 3 | I59: 12 | J59: 14 | K59: 2 | L59: 0 | M59: 1 | N59: 7 | O59: 6 | P59: 9 | Q59: 4 | R59: 10 | S59: 10 | T59: 9
A60: 胡文竹 | F60: 24 | G60: 8 | H60: 0 | I60: 20 | J60: 26 | K60: 4 | L60: 8 | M60: 10 | N60: 18 | O60: 20 | P60: 16 | Q60: 8 | R60: 8 | S60: 24 | T60: 16
A61: 贾矿营 | F61: 22 | G61: 10 | H61: 2 | I61: 10 | J61: 10 | K61: 6 | L61: 4 | M61: 0 | N61: 26 | O61: 28 | P61: 22 | Q61: 14 | R61: 18 | S61: 22 | T61: 16
A62: 戚梓茵 | F62: 8 | G62: 2 | H62: 0 | I62: 10 | J62: 14 | K62: 1 | L62: 4 | M62: 9 | N62: 6 | O62: 11 | P62: 6 | Q62: 4 | R62: 5 | S62: 13 | T62: 12
A63: 庹凯 | F63: 18 | G63: 14 | H63: 2 | I63: 26 | J63: 28 | K63: 14 | L63: 6 | M63: 2 | N63: 32 | O63: 10 | P63: 18 | Q63: 10 | R63: 12 | S63: 16 | T63: 2

Sheet 目录
A1: 地铁站步行距离
A2: 公交站步行距离
A3: 公区步行距离
A4: 噪音影响度
A5: 污染
A6: 四楼有无电梯
A7: 梯户比
A8: 楼栋外观
A9: 套内空间
A10: 户型
A11: 阳台
A12: 楼梯房楼层
... A16: 视野

Sheet 【3】大区填-楼栋基准格局定价
A1: 楼栋 | B1: 基准格局 | C1: 基准格局基准价 | D1: 区位 | E1: 调价倍数1 | F1: 有无电梯 | G1: 调价倍数2 | H1: 基准格局定价
A2: ='【2】运营中心填-基本信息&审核标准'!$E$2 -> 兴围西4-11栋 | B2: ='【3-2】大区&运营中心填-房间模型价'!K2 -> 开间 | C2: =VLOOKUP(B2,【1】定价因子!L:M,2,0) -> 1634.8 | D2: 交通很不便 | E2: =VLOOKUP(D2,【1】定价因子!$D:$F,3,0) -> 0.96 | F2: =IF('【2】运营中心填-基本信息&审核标准'!$D$4="否","无",IF('【2】运营中心填-基本信息&审核标准'!$D$4="是","有")) -> 有 | G2: =VLOOKUP(F2,【1】定价因子!D:F,3,0) -> 1.05 | H2: =C2*PRODUCT(G2,,E2) -> 1647.8784
A3: ='【2】运营中心填-基本信息&审核标准'!$E$2 -> 兴围西4-11栋 | B3: ='【3-2】大区&运营中心填-房间模型价'!K3 -> 一居室 | C3: =VLOOKUP(B3,【1】定价因子!L:M,2,0) -> 2426.1 | D3: 交通很不便 | E3: =VLOOKUP(D3,【1】定价因子!$D:$F,3,0) -> 0.96 | F3: =IF('【2】运营中心填-基本信息&审核标准'!$D$4="否","无",IF('【2】运营中心填-基本信息&审核标准'!$D$4="是","有")) -> 有 | G3: =VLOOKUP(F3,【1】定价因子!D:F,3,0) -> 1.05 | H3: =C3*PRODUCT(G3,,E3) -> 2445.5088
A4: ='【2】运营中心填-基本信息&审核标准'!$E$2 -> 兴围西4-11栋 | B4: ='【3-2】大区&运营中心填-房间模型价'!K4 | C4: =VLOOKUP(B4,【1】定价因子!L:M,2,0) -> #N/A | D4: 交通很便利 | E4: =VLOOKUP(D4,【1】定价因子!$D:$F,3,0) -> 1.04 | F4: =IF('【2】运营中心填-基本信息&审核标准'!$D$4="否","无",IF('【2】运营中心填-基本信息&审核标准'!$D$4="是","有")) -> 有 | G4: =VLOOKUP(F4,【1】定价因子!D:F,3,0) -> 1.05 | H4: =C4*PRODUCT(G4,,E4) -> #N/A
A5: ='【2】运营中心填-基本信息&审核标准'!$E$2 -> 兴围西4-11栋 | B5: ='【3-2】大区&运营中心填-房间模型价'!K5 | C5: =VLOOKUP(B5,【1】定价因子!L:M,2,0) -> #N/A | D5: 交通很便利 | E5: =VLOOKUP(D5,【1】定价因子!$D:$F,3,0) -> 1.04 | F5: =IF('【2】运营中心填-基本信息&审核标准'!$D$4="否","无",IF('【2】运营中心填-基本信息&审核标准'!$D$4="是","有")) -> 有 | G5: =VLOOKUP(F5,【1】定价因子!D:F,3,0) -> 1.05 | H5: =C5*PRODUCT(G5,,E5) -> #N/A
A6: ='【2】运营中心填-基本信息&审核标准'!$E$2 -> 兴围西4-11栋 | B6: ='【3-2】大区&运营中心填-房间模型价'!K6 | C6: =VLOOKUP(B6,【1】定价因子!L:M,2,0) -> #N/A | D6: 交通很便利 | E6: =VLOOKUP(D6,【1】定价因子!$D:$F,3,0) -> 1.04 | F6: =IF('【2】运营中心填-基本信息&审核标准'!$D$4="否","无",IF('【2】运营中心填-基本信息&审核标准'!$D$4="是","有")) -> 有 | G6: =VLOOKUP(F6,【1】定价因子!D:F,3,0) -> 1.05 | H6: =C6*PRODUCT(G6,,E6) -> #N/A
A7: ='【2】运营中心填-基本信息&审核标准'!$E$2 -> 兴围西4-11栋 | B7: ='【3-2】大区&运营中心填-房间模型价'!K7 | C7: =VLOOKUP(B7,【1】定价因子!L:M,2,0) -> #N/A | D7: 交通很便利 | E7: =VLOOKUP(D7,【1】定价因子!$D:$F,3,0) -> 1.04 | F7: =IF('【2】运营中心填-基本信息&审核标准'!$D$4="否","无",IF('【2】运营中心填-基本信息&审核标准'!$D$4="是","有")) -> 有 | G7: =VLOOKUP(F7,【1】定价因子!D:F,3,0) -> 1.05 | H7: =C7*PRODUCT(G7,,E7) -> #N/A
A8: ='【2】运营中心填-基本信息&审核标准'!$E$2 -> 兴围西4-11栋 | B8: ='【3-2】大区&运营中心填-房间模型价'!K8 | C8: =VLOOKUP(B8,【1】定价因子!L:M,2,0) -> #N/A | D8: 交通很便利 | E8: =VLOOKUP(D8,【1】定价因子!$D:$F,3,0) -> 1.04 | F8: =IF('【2】运营中心填-基本信息&审核标准'!$D$4="否","无",IF('【2】运营中心填-基本信息&审核标准'!$D$4="是","有")) -> 有 | G8: =VLOOKUP(F8,【1】定价因子!D:F,3,0) -> 1.05 | H8: =C8*PRODUCT(G8,,E8) -> #N/A
A9: ='【2】运营中心填-基本信息&审核标准'!$E$2 -> 兴围西4-11栋 | B9: ='【3-2】大区&运营中心填-房间模型价'!K9 | C9: =VLOOKUP(B9,【1】定价因子!L:M,2,0) -> #N/A | D9: 交通很便利 | E9: =VLOOKUP(D9,【1】定价因子!$D:$F,3,0) -> 1.04 | F9: =IF('【2】运营中心填-基本信息&审核标准'!$D$4="否","无",IF('【2】运营中心填-基本信息&审核标准'!$D$4="是","有")) -> 有 | G9: =VLOOKUP(F9,【1】定价因子!D:F,3,0) -> 1.05 | H9: =C9*PRODUCT(G9,,E9) -> #N/A
A10: ='【2】运营中心填-基本信息&审核标准'!$E$2 -> 兴围西4-11栋 | B10: ='【3-2】大区&运营中心填-房间模型价'!K10 | C10: =VLOOKUP(B10,【1】定价因子!L:M,2,0) -> #N/A | D10: 交通很便利 | E10: =VLOOKUP(D10,【1】定价因子!$D:$F,3,0) -> 1.04 | F10: =IF('【2】运营中心填-基本信息&审核标准'!$D$4="否","无",IF('【2】运营中心填-基本信息&审核标准'!$D$4="是","有")) -> 有 | G10: =VLOOKUP(F10,【1】定价因子!D:F,3,0) -> 1.05 | H10: =C10*PRODUCT(G10,,E10) -> #N/A

Sheet 【3-1】大区填-采光基本要素
D1: 仅需填写绿色部分，其余部分自动带出
A2: 房间号 | B2: 户型 | C2: 格局 | D2: 房间窗户数量（不含卫生间窗户） | E2: 阳台数量 | F2: 阳台面积（有阳台填写） | G2: 窗户遮挡数量 | H2: 采光判断 | I2: 有无玄关 | L2: 窗户遮挡填写标准
A3: ='【3-2】大区&运营中心填-房间模型价'!H2 -> 101 | B3: ='【3-2】大区&运营中心填-房间模型价'!I2 -> A | C3: =VLOOKUP(A3,'【3-2】大区&运营中心填-房间模型价'!H:J,3,0) -> 开间 | D3: 1 | E3: 0 | G3: 1 | H3: =IF(C3="开间",IF(D3+E3*2-G3<=0,"1",IF(D3+E3*2-G3<=1,"2",IF(D3+E3*2-G3<=2,"3",IF(D3+E3*2-G3<=3,"4","5")))),IF(D3+E3*2-G3<1.1,"1",IF(D3+E3*2-G3<=2,"2",IF(D3+E3*2-G3<=3,"3",IF(D3+E3*2-G3<=4,"4","5"))))) -> 1 | L3: 情况 | O3: 填写值
A4: ='【3-2】大区&运营中心填-房间模型价'!H3 -> 102 | B4: ='【3-2】大区&运营中心填-房间模型价'!I3 -> B | C4: =VLOOKUP(A4,'【3-2】大区&运营中心填-房间模型价'!H:J,3,0) -> 开间 | D4: 1 | E4: 0 | G4: 1 | H4: =IF(C4="开间",IF(D4+E4*2-G4<=0,"1",IF(D4+E4*2-G4<=1,"2",IF(D4+E4*2-G4<=2,"3",IF(D4+E4*2-G4<=3,"4","5")))),IF(D4+E4*2-G4<1.1,"1",IF(D4+E4*2-G4<=2,"2",IF(D4+E4*2-G4<=3,"3",IF(D4+E4*2-G4<=4,"4","5"))))) -> 1 | L4: 窗户所面对的完全无楼栋或楼间距＞10米 | O4: -1
A5: ='【3-2】大区&运营中心填-房间模型价'!H4 -> 103 | B5: ='【3-2】大区&运营中心填-房间模型价'!I4 -> B | C5: =VLOOKUP(A5,'【3-2】大区&运营中心填-房间模型价'!H:J,3,0) -> 开间 | D5: 1 | E5: 0 | G5: 1 | H5: =IF(C5="开间",IF(D5+E5*2-G5<=0,"1",IF(D5+E5*2-G5<=1,"2",IF(D5+E5*2-G5<=2,"3",IF(D5+E5*2-G5<=3,"4","5")))),IF(D5+E5*2-G5<1.1,"1",IF(D5+E5*2-G5<=2,"2",IF(D5+E5*2-G5<=3,"3",IF(D5+E5*2-G5<=4,"4","5"))))) -> 1 | L5: 窗户对面有楼 | M5: 1-4楼窗户所对楼间距＞3米 | O5: 0
A6: ='【3-2】大区&运营中心填-房间模型价'!H5 -> 104 | B6: ='【3-2】大区&运营中心填-房间模型价'!I5 -> C | C6: =VLOOKUP(A6,'【3-2】大区&运营中心填-房间模型价'!H:J,3,0) -> 一居室 | D6: 2.5 | E6: 0 | G6: 2.5 | H6: =IF(C6="开间",IF(D6+E6*2-G6<=0,"1",IF(D6+E6*2-G6<=1,"2",IF(D6+E6*2-G6<=2,"3",IF(D6+E6*2-G6<=3,"4","5")))),IF(D6+E6*2-G6<1.1,"1",IF(D6+E6*2-G6<=2,"2",IF(D6+E6*2-G6<=3,"3",IF(D6+E6*2-G6<=4,"4","5"))))) -> 1 | M6: 4楼以上窗户所对楼间距＞2米 | O6: 0
A7: ='【3-2】大区&运营中心填-房间模型价'!H6 -> 105 | B7: ='【3-2】大区&运营中心填-房间模型价'!I6 -> D | C7: =VLOOKUP(A7,'【3-2】大区&运营中心填-房间模型价'!H:J,3,0) -> 开间 | D7: 2 | E7: 0 | G7: 2 | H7: =IF(C7="开间",IF(D7+E7*2-G7<=0,"1",IF(D7+E7*2-G7<=1,"2",IF(D7+E7*2-G7<=2,"3",IF(D7+E7*2-G7<=3,"4","5")))),IF(D7+E7*2-G7<1.1,"1",IF(D7+E7*2-G7<=2,"2",IF(D7+E7*2-G7<=3,"3",IF(D7+E7*2-G7<=4,"4","5"))))) -> 1 | M7: 1-4楼窗户所对楼间距＜3米 | O7: 1*窗户遮挡数量
A8: ='【3-2】大区&运营中心填-房间模型价'!H7 -> 106 | B8: ='【3-2】大区&运营中心填-房间模型价'!I7 -> E | C8: =VLOOKUP(A8,'【3-2】大区&运营中心填-房间模型价'!H:J,3,0) -> 开间 | D8: 1 | E8: 0 | G8: 0 | H8: =IF(C8="开间",IF(D8+E8*2-G8<=0,"1",IF(D8+E8*2-G8<=1,"2",IF(D8+E8*2-G8<=2,"3",IF(D8+E8*2-G8<=3,"4","5")))),IF(D8+E8*2-G8<1.1,"1",IF(D8+E8*2-G8<=2,"2",IF(D8+E8*2-G8<=3,"3",IF(D8+E8*2-G8<=4,"4","5"))))) -> 2 | M8: 4楼以上窗户所对楼间距＜2米 | O8: 1*窗户遮挡数量
A9: ='【3-2】大区&运营中心填-房间模型价'!H8 -> 107 | B9: ='【3-2】大区&运营中心填-房间模型价'!I8 -> F | C9: =VLOOKUP(A9,'【3-2】大区&运营中心填-房间模型价'!H:J,3,0) -> 开间 | D9: 2 | E9: 0 | G9: 2 | H9: =IF(C9="开间",IF(D9+E9*2-G9<=0,"1",IF(D9+E9*2-G9<=1,"2",IF(D9+E9*2-G9<=2,"3",IF(D9+E9*2-G9<=3,"4","5")))),IF(D9+E9*2-G9<1.1,"1",IF(D9+E9*2-G9<=2,"2",IF(D9+E9*2-G9<=3,"3",IF(D9+E9*2-G9<=4,"4","5"))))) -> 1
A10: ='【3-2】大区&运营中心填-房间模型价'!H9 -> 201 | B10: ='【3-2】大区&运营中心填-房间模型价'!I9 -> G | C10: =VLOOKUP(A10,'【3-2】大区&运营中心填-房间模型价'!H:J,3,0) -> 开间 | D10: 2 | E10: 0 | G10: -2 | H10: =IF(C10="开间",IF(D10+E10*2-G10<=0,"1",IF(D10+E10*2-G10<=1,"2",IF(D10+E10*2-G10<=2,"3",IF(D10+E10*2-G10<=3,"4","5")))),IF(D10+E10*2-G10<1.1,"1",IF(D10+E10*2-G10<=2,"2",IF(D10+E10*2-G10<=3,"3",IF(D10+E10*2-G10<=4,"4","5"))))) -> 5
A11: ='【3-2】大区&运营中心填-房间模型价'!H10 -> 202 | B11: ='【3-2】大区&运营中心填-房间模型价'!I10 -> H | C11: =VLOOKUP(A11,'【3-2】大区&运营中心填-房间模型价'!H:J,3,0) -> 一居室 | D11: 0.5 | E11: 0 | G11: 0 | H11: =IF(C11="开间",IF(D11+E11*2-G11<=0,"1",IF(D11+E11*2-G11<=1,"2",IF(D11+E11*2-G11<=2,"3",IF(D11+E11*2-G11<=3,"4","5")))),IF(D11+E11*2-G11<1.1,"1",IF(D11+E11*2-G11<=2,"2",IF(D11+E11*2-G11<=3,"3",IF(D11+E11*2-G11<=4,"4","5"))))) -> 1
A12: ='【3-2】大区&运营中心填-房间模型价'!H11 -> 203 | B12: ='【3-2】大区&运营中心填-房间模型价'!I11 -> I | C12: =VLOOKUP(A12,'【3-2】大区&运营中心填-房间模型价'!H:J,3,0) -> 开间 | D12: 1 | E12: 0 | G12: 1 | H12: =IF(C12="开间",IF(D12+E12*2-G12<=0,"1",IF(D12+E12*2-G12<=1,"2",IF(D12+E12*2-G12<=2,"3",IF(D12+E12*2-G12<=3,"4","5")))),IF(D12+E12*2-G12<1.1,"1",IF(D12+E12*2-G12<=2,"2",IF(D12+E12*2-G12<=3,"3",IF(D12+E12*2-G12<=4,"4","5"))))) -> 1
A13: ='【3-2】大区&运营中心填-房间模型价'!H12 -> 204 | B13: ='【3-2】大区&运营中心填-房间模型价'!I12 -> J | C13: =VLOOKUP(A13,'【3-2】大区&运营中心填-房间模型价'!H:J,3,0) -> 开间 | D13: 0.5 | E13: 0 | G13: 0.5 | H13: =IF(C13="开间",IF(D13+E13*2-G13<=0,"1",IF(D13+E13*2-G13<=1,"2",IF(D13+E13*2-G13<=2,"3",IF(D13+E13*2-G13<=3,"4","5")))),IF(D13+E13*2-G13<1.1,"1",IF(D13+E13*2-G13<=2,"2",IF(D13+E13*2-G13<=3,"3",IF(D13+E13*2-G13<=4,"4","5"))))) -> 1
A14: ='【3-2】大区&运营中心填-房间模型价'!H13 -> 205 | B14: ='【3-2】大区&运营中心填-房间模型价'!I13 -> K | C14: =VLOOKUP(A14,'【3-2】大区&运营中心填-房间模型价'!H:J,3,0) -> 开间 | D14: 2 | E14: 0 | G14: 1 | H14: =IF(C14="开间",IF(D14+E14*2-G14<=0,"1",IF(D14+E14*2-G14<=1,"2",IF(D14+E14*2-G14<=2,"3",IF(D14+E14*2-G14<=3,"4","5")))),IF(D14+E14*2-G14<1.1,"1",IF(D14+E14*2-G14<=2,"2",IF(D14+E14*2-G14<=3,"3",IF(D14+E14*2-G14<=4,"4","5"))))) -> 2
A15: ='【3-2】大区&运营中心填-房间模型价'!H14 -> 206 | B15: ='【3-2】大区&运营中心填-房间模型价'!I14 -> L | C15: =VLOOKUP(A15,'【3-2】大区&运营中心填-房间模型价'!H:J,3,0) -> 一居室 | D15: 2 | E15: 0 | G15: 1 | H15: =IF(C15="开间",IF(D15+E15*2-G15<=0,"1",IF(D15+E15*2-G15<=1,"2",IF(D15+E15*2-G15<=2,"3",IF(D15+E15*2-G15<=3,"4","5")))),IF(D15+E15*2-G15<1.1,"1",IF(D15+E15*2-G15<=2,"2",IF(D15+E15*2-G15<=3,"3",IF(D15+E15*2-G15<=4,"4","5"))))) -> 1
A16: ='【3-2】大区&运营中心填-房间模型价'!H15 -> 207 | B16: ='【3-2】大区&运营中心填-房间模型价'!I15 -> J | C16: =VLOOKUP(A16,'【3-2】大区&运营中心填-房间模型价'!H:J,3,0) -> 开间 | D16: 1 | E16: 0 | G16: 1 | H16: =IF(C16="开间",IF(D16+E16*2-G16<=0,"1",IF(D16+E16*2-G16<=1,"2",IF(D16+E16*2-G16<=2,"3",IF(D16+E16*2-G16<=3,"4","5")))),IF(D16+E16*2-G16<1.1,"1",IF(D16+E16*2-G16<=2,"2",IF(D16+E16*2-G16<=3,"3",IF(D16+E16*2-G16<=4,"4","5"))))) -> 1 | L16: 以下规格，窗户数按0.5算 | R16: 以下规格，窗户数按1算 | AB16: 以下规格，按窗户数2计算
A17: ='【3-2】大区&运营中心填-房间模型价'!H16 -> 208 | B17: ='【3-2】大区&运营中心填-房间模型价'!I16 -> M | C17: =VLOOKUP(A17,'【3-2】大区&运营中心填-房间模型价'!H:J,3,0) -> 一居室 | D17: 2 | E17: 0 | G17: 0 | H17: =IF(C17="开间",IF(D17+E17*2-G17<=0,"1",IF(D17+E17*2-G17<=1,"2",IF(D17+E17*2-G17<=2,"3",IF(D17+E17*2-G17<=3,"4","5")))),IF(D17+E17*2-G17<1.1,"1",IF(D17+E17*2-G17<=2,"2",IF(D17+E17*2-G17<=3,"3",IF(D17+E17*2-G17<=4,"4","5"))))) -> 2
A18: ='【3-2】大区&运营中心填-房间模型价'!H17 -> 301 | B18: ='【3-2】大区&运营中心填-房间模型价'!I17 -> N | C18: =VLOOKUP(A18,'【3-2】大区&运营中心填-房间模型价'!H:J,3,0) -> 开间 | D18: 2 | E18: 0 | G18: -2 | H18: =IF(C18="开间",IF(D18+E18*2-G18<=0,"1",IF(D18+E18*2-G18<=1,"2",IF(D18+E18*2-G18<=2,"3",IF(D18+E18*2-G18<=3,"4","5")))),IF(D18+E18*2-G18<1.1,"1",IF(D18+E18*2-G18<=2,"2",IF(D18+E18*2-G18<=3,"3",IF(D18+E18*2-G18<=4,"4","5"))))) -> 5
A19: ='【3-2】大区&运营中心填-房间模型价'!H18 -> 302 | B19: ='【3-2】大区&运营中心填-房间模型价'!I18 -> H | C19: =VLOOKUP(A19,'【3-2】大区&运营中心填-房间模型价'!H:J,3,0) -> 一居室 | D19: 1 | E19: 0 | G19: -1 | H19: =IF(C19="开间",IF(D19+E19*2-G19<=0,"1",IF(D19+E19*2-G19<=1,"2",IF(D19+E19*2-G19<=2,"3",IF(D19+E19*2-G19<=3,"4","5")))),IF(D19+E19*2-G19<1.1,"1",IF(D19+E19*2-G19<=2,"2",IF(D19+E19*2-G19<=3,"3",IF(D19+E19*2-G19<=4,"4","5"))))) -> 2
A20: ='【3-2】大区&运营中心填-房间模型价'!H19 -> 303 | B20: ='【3-2】大区&运营中心填-房间模型价'!I19 -> O | C20: =VLOOKUP(A20,'【3-2】大区&运营中心填-房间模型价'!H:J,3,0) -> 开间 | D20: 1 | E20: 1 | F20: 0.7 | G20: 2 | H20: =IF(C20="开间",IF(D20+E20*2-G20<=0,"1",IF(D20+E20*2-G20<=1,"2",IF(D20+E20*2-G20<=2,"3",IF(D20+E20*2-G20<=3,"4","5")))),IF(D20+E20*2-G20<1.1,"1",IF(D20+E20*2-G20<=2,"2",IF(D20+E20*2-G20<=3,"3",IF(D20+E20*2-G20<=4,"4","5"))))) -> 2
A21: ='【3-2】大区&运营中心填-房间模型价'!H20 -> 304 | B21: ='【3-2】大区&运营中心填-房间模型价'!I20 -> P | C21: =VLOOKUP(A21,'【3-2】大区&运营中心填-房间模型价'!H:J,3,0) -> 开间 | D21: 1 | E21: 0 | G21: 1 | H21: =IF(C21="开间",IF(D21+E21*2-G21<=0,"1",IF(D21+E21*2-G21<=1,"2",IF(D21+E21*2-G21<=2,"3",IF(D21+E21*2-G21<=3,"4","5")))),IF(D21+E21*2-G21<1.1,"1",IF(D21+E21*2-G21<=2,"2",IF(D21+E21*2-G21<=3,"3",IF(D21+E21*2-G21<=4,"4","5"))))) -> 1
A22: ='【3-2】大区&运营中心填-房间模型价'!H21 -> 305 | B22: ='【3-2】大区&运营中心填-房间模型价'!I21 -> K | C22: =VLOOKUP(A22,'【3-2】大区&运营中心填-房间模型价'!H:J,3,0) -> 开间 | D22: 2 | E22: 0 | G22: 1 | H22: =IF(C22="开间",IF(D22+E22*2-G22<=0,"1",IF(D22+E22*2-G22<=1,"2",IF(D22+E22*2-G22<=2,"3",IF(D22+E22*2-G22<=3,"4","5")))),IF(D22+E22*2-G22<1.1,"1",IF(D22+E22*2-G22<=2,"2",IF(D22+E22*2-G22<=3,"3",IF(D22+E22*2-G22<=4,"4","5"))))) -> 2
A23: ='【3-2】大区&运营中心填-房间模型价'!H22 -> 306 | B23: ='【3-2】大区&运营中心填-房间模型价'!I22 -> L | C23: =VLOOKUP(A23,'【3-2】大区&运营中心填-房间模型价'!H:J,3,0) -> 一居室 | D23: 2 | E23: 0 | G23: 1 | H23: =IF(C23="开间",IF(D23+E23*2-G23<=0,"1",IF(D23+E23*2-G23<=1,"2",IF(D23+E23*2-G23<=2,"3",IF(D23+E23*2-G23<=3,"4","5")))),IF(D23+E23*2-G23<1.1,"1",IF(D23+E23*2-G23<=2,"2",IF(D23+E23*2-G23<=3,"3",IF(D23+E23*2-G23<=4,"4","5"))))) -> 1
A24: ='【3-2】大区&运营中心填-房间模型价'!H23 -> 307 | B24: ='【3-2】大区&运营中心填-房间模型价'!I23 -> J | C24: =VLOOKUP(A24,'【3-2】大区&运营中心填-房间模型价'!H:J,3,0) -> 开间 | D24: 1 | E24: 0 | G24: 1 | H24: =IF(C24="开间",IF(D24+E24*2-G24<=0,"1",IF(D24+E24*2-G24<=1,"2",IF(D24+E24*2-G24<=2,"3",IF(D24+E24*2-G24<=3,"4","5")))),IF(D24+E24*2-G24<1.1,"1",IF(D24+E24*2-G24<=2,"2",IF(D24+E24*2-G24<=3,"3",IF(D24+E24*2-G24<=4,"4","5"))))) -> 1
A25: ='【3-2】大区&运营中心填-房间模型价'!H24 -> 308 | B25: ='【3-2】大区&运营中心填-房间模型价'!I24 -> Q | C25: =VLOOKUP(A25,'【3-2】大区&运营中心填-房间模型价'!H:J,3,0) -> 一居室 | D25: 2 | E25: 0 | G25: 0 | H25: =IF(C25="开间",IF(D25+E25*2-G25<=0,"1",IF(D25+E25*2-G25<=1,"2",IF(D25+E25*2-G25<=2,"3",IF(D25+E25*2-G25<=3,"4","5")))),IF(D25+E25*2-G25<1.1,"1",IF(D25+E25*2-G25<=2,"2",IF(D25+E25*2-G25<=3,"3",IF(D25+E25*2-G25<=4,"4","5"))))) -> 2
A26: ='【3-2】大区&运营中心填-房间模型价'!H25 -> 401 | B26: ='【3-2】大区&运营中心填-房间模型价'!I25 -> N | C26: =VLOOKUP(A26,'【3-2】大区&运营中心填-房间模型价'!H:J,3,0) -> 开间 | D26: 2 | E26: 0 | G26: -2 | H26: =IF(C26="开间",IF(D26+E26*2-G26<=0,"1",IF(D26+E26*2-G26<=1,"2",IF(D26+E26*2-G26<=2,"3",IF(D26+E26*2-G26<=3,"4","5")))),IF(D26+E26*2-G26<1.1,"1",IF(D26+E26*2-G26<=2,"2",IF(D26+E26*2-G26<=3,"3",IF(D26+E26*2-G26<=4,"4","5"))))) -> 5
A27: ='【3-2】大区&运营中心填-房间模型价'!H26 -> 402 | B27: ='【3-2】大区&运营中心填-房间模型价'!I26 -> H | C27: =VLOOKUP(A27,'【3-2】大区&运营中心填-房间模型价'!H:J,3,0) -> 一居室 | D27: 1 | E27: 0 | G27: -1 | H27: =IF(C27="开间",IF(D27+E27*2-G27<=0,"1",IF(D27+E27*2-G27<=1,"2",IF(D27+E27*2-G27<=2,"3",IF(D27+E27*2-G27<=3,"4","5")))),IF(D27+E27*2-G27<1.1,"1",IF(D27+E27*2-G27<=2,"2",IF(D27+E27*2-G27<=3,"3",IF(D27+E27*2-G27<=4,"4","5"))))) -> 2
A28: ='【3-2】大区&运营中心填-房间模型价'!H27 -> 403 | B28: ='【3-2】大区&运营中心填-房间模型价'!I27 -> O | C28: =VLOOKUP(A28,'【3-2】大区&运营中心填-房间模型价'!H:J,3,0) -> 开间 | D28: 1 | E28: 1 | F28: 0.7 | G28: 0 | H28: =IF(C28="开间",IF(D28+E28*2-G28<=0,"1",IF(D28+E28*2-G28<=1,"2",IF(D28+E28*2-G28<=2,"3",IF(D28+E28*2-G28<=3,"4","5")))),IF(D28+E28*2-G28<1.1,"1",IF(D28+E28*2-G28<=2,"2",IF(D28+E28*2-G28<=3,"3",IF(D28+E28*2-G28<=4,"4","5"))))) -> 4
A29: ='【3-2】大区&运营中心填-房间模型价'!H28 -> 404 | B29: ='【3-2】大区&运营中心填-房间模型价'!I28 -> P | C29: =VLOOKUP(A29,'【3-2】大区&运营中心填-房间模型价'!H:J,3,0) -> 开间 | D29: 0.5 | E29: 0 | G29: 0.5 | H29: =IF(C29="开间",IF(D29+E29*2-G29<=0,"1",IF(D29+E29*2-G29<=1,"2",IF(D29+E29*2-G29<=2,"3",IF(D29+E29*2-G29<=3,"4","5")))),IF(D29+E29*2-G29<1.1,"1",IF(D29+E29*2-G29<=2,"2",IF(D29+E29*2-G29<=3,"3",IF(D29+E29*2-G29<=4,"4","5"))))) -> 1
A30: ='【3-2】大区&运营中心填-房间模型价'!H29 -> 405 | B30: ='【3-2】大区&运营中心填-房间模型价'!I29 -> K | C30: =VLOOKUP(A30,'【3-2】大区&运营中心填-房间模型价'!H:J,3,0) -> 开间 | D30: 2 | E30: 0 | G30: 0 | H30: =IF(C30="开间",IF(D30+E30*2-G30<=0,"1",IF(D30+E30*2-G30<=1,"2",IF(D30+E30*2-G30<=2,"3",IF(D30+E30*2-G30<=3,"4","5")))),IF(D30+E30*2-G30<1.1,"1",IF(D30+E30*2-G30<=2,"2",IF(D30+E30*2-G30<=3,"3",IF(D30+E30*2-G30<=4,"4","5"))))) -> 3
A31: ='【3-2】大区&运营中心填-房间模型价'!H30 -> 406 | B31: ='【3-2】大区&运营中心填-房间模型价'!I30 -> L | C31: =VLOOKUP(A31,'【3-2】大区&运营中心填-房间模型价'!H:J,3,0) -> 一居室 | D31: 2 | E31: 0 | G31: 1 | H31: =IF(C31="开间",IF(D31+E31*2-G31<=0,"1",IF(D31+E31*2-G31<=1,"2",IF(D31+E31*2-G31<=2,"3",IF(D31+E31*2-G31<=3,"4","5")))),IF(D31+E31*2-G31<1.1,"1",IF(D31+E31*2-G31<=2,"2",IF(D31+E31*2-G31<=3,"3",IF(D31+E31*2-G31<=4,"4","5"))))) -> 1
A32: ='【3-2】大区&运营中心填-房间模型价'!H31 -> 407 | B32: ='【3-2】大区&运营中心填-房间模型价'!I31 -> J | C32: =VLOOKUP(A32,'【3-2】大区&运营中心填-房间模型价'!H:J,3,0) -> 开间 | D32: 1 | E32: 0 | G32: 1 | H32: =IF(C32="开间",IF(D32+E32*2-G32<=0,"1",IF(D32+E32*2-G32<=1,"2",IF(D32+E32*2-G32<=2,"3",IF(D32+E32*2-G32<=3,"4","5")))),IF(D32+E32*2-G32<1.1,"1",IF(D32+E32*2-G32<=2,"2",IF(D32+E32*2-G32<=3,"3",IF(D32+E32*2-G32<=4,"4","5"))))) -> 1
A33: ='【3-2】大区&运营中心填-房间模型价'!H32 -> 408 | B33: ='【3-2】大区&运营中心填-房间模型价'!I32 -> Q | C33: =VLOOKUP(A33,'【3-2】大区&运营中心填-房间模型价'!H:J,3,0) -> 一居室 | D33: 2 | E33: 0 | G33: 0 | H33: =IF(C33="开间",IF(D33+E33*2-G33<=0,"1",IF(D33+E33*2-G33<=1,"2",IF(D33+E33*2-G33<=2,"3",IF(D33+E33*2-G33<=3,"4","5")))),IF(D33+E33*2-G33<1.1,"1",IF(D33+E33*2-G33<=2,"2",IF(D33+E33*2-G33<=3,"3",IF(D33+E33*2-G33<=4,"4","5"))))) -> 2
A34: ='【3-2】大区&运营中心填-房间模型价'!H33 -> 501 | B34: ='【3-2】大区&运营中心填-房间模型价'!I33 -> N | C34: =VLOOKUP(A34,'【3-2】大区&运营中心填-房间模型价'!H:J,3,0) -> 开间 | D34: 2 | E34: 0 | G34: -2 | H34: =IF(C34="开间",IF(D34+E34*2-G34<=0,"1",IF(D34+E34*2-G34<=1,"2",IF(D34+E34*2-G34<=2,"3",IF(D34+E34*2-G34<=3,"4","5")))),IF(D34+E34*2-G34<1.1,"1",IF(D34+E34*2-G34<=2,"2",IF(D34+E34*2-G34<=3,"3",IF(D34+E34*2-G34<=4,"4","5"))))) -> 5
A35: ='【3-2】大区&运营中心填-房间模型价'!H34 -> 502 | B35: ='【3-2】大区&运营中心填-房间模型价'!I34 -> H | C35: =VLOOKUP(A35,'【3-2】大区&运营中心填-房间模型价'!H:J,3,0) -> 一居室 | D35: 1 | E35: 0 | G35: -1 | H35: =IF(C35="开间",IF(D35+E35*2-G35<=0,"1",IF(D35+E35*2-G35<=1,"2",IF(D35+E35*2-G35<=2,"3",IF(D35+E35*2-G35<=3,"4","5")))),IF(D35+E35*2-G35<1.1,"1",IF(D35+E35*2-G35<=2,"2",IF(D35+E35*2-G35<=3,"3",IF(D35+E35*2-G35<=4,"4","5"))))) -> 2
A36: ='【3-2】大区&运营中心填-房间模型价'!H35 -> 503 | B36: ='【3-2】大区&运营中心填-房间模型价'!I35 -> O | C36: =VLOOKUP(A36,'【3-2】大区&运营中心填-房间模型价'!H:J,3,0) -> 开间 | D36: 1 | E36: 1 | F36: 0.7 | G36: 0 | H36: =IF(C36="开间",IF(D36+E36*2-G36<=0,"1",IF(D36+E36*2-G36<=1,"2",IF(D36+E36*2-G36<=2,"3",IF(D36+E36*2-G36<=3,"4","5")))),IF(D36+E36*2-G36<1.1,"1",IF(D36+E36*2-G36<=2,"2",IF(D36+E36*2-G36<=3,"3",IF(D36+E36*2-G36<=4,"4","5"))))) -> 4
A37: ='【3-2】大区&运营中心填-房间模型价'!H36 -> 504 | B37: ='【3-2】大区&运营中心填-房间模型价'!I36 -> P | C37: =VLOOKUP(A37,'【3-2】大区&运营中心填-房间模型价'!H:J,3,0) -> 开间 | D37: 0.5 | E37: 0 | G37: -0.5 | H37: =IF(C37="开间",IF(D37+E37*2-G37<=0,"1",IF(D37+E37*2-G37<=1,"2",IF(D37+E37*2-G37<=2,"3",IF(D37+E37*2-G37<=3,"4","5")))),IF(D37+E37*2-G37<1.1,"1",IF(D37+E37*2-G37<=2,"2",IF(D37+E37*2-G37<=3,"3",IF(D37+E37*2-G37<=4,"4","5"))))) -> 2
A38: ='【3-2】大区&运营中心填-房间模型价'!H37 -> 505 | B38: ='【3-2】大区&运营中心填-房间模型价'!I37 -> K | C38: =VLOOKUP(A38,'【3-2】大区&运营中心填-房间模型价'!H:J,3,0) -> 开间 | D38: 2 | E38: 0 | G38: -1 | H38: =IF(C38="开间",IF(D38+E38*2-G38<=0,"1",IF(D38+E38*2-G38<=1,"2",IF(D38+E38*2-G38<=2,"3",IF(D38+E38*2-G38<=3,"4","5")))),IF(D38+E38*2-G38<1.1,"1",IF(D38+E38*2-G38<=2,"2",IF(D38+E38*2-G38<=3,"3",IF(D38+E38*2-G38<=4,"4","5"))))) -> 4
A39: ='【3-2】大区&运营中心填-房间模型价'!H38 -> 506 | B39: ='【3-2】大区&运营中心填-房间模型价'!I38 -> L | C39: =VLOOKUP(A39,'【3-2】大区&运营中心填-房间模型价'!H:J,3,0) -> 一居室 | D39: 2 | E39: 0 | G39: 1 | H39: =IF(C39="开间",IF(D39+E39*2-G39<=0,"1",IF(D39+E39*2-G39<=1,"2",IF(D39+E39*2-G39<=2,"3",IF(D39+E39*2-G39<=3,"4","5")))),IF(D39+E39*2-G39<1.1,"1",IF(D39+E39*2-G39<=2,"2",IF(D39+E39*2-G39<=3,"3",IF(D39+E39*2-G39<=4,"4","5"))))) -> 1
A40: ='【3-2】大区&运营中心填-房间模型价'!H39 -> 507 | B40: ='【3-2】大区&运营中心填-房间模型价'!I39 -> J | C40: =VLOOKUP(A40,'【3-2】大区&运营中心填-房间模型价'!H:J,3,0) -> 开间 | D40: 1 | E40: 0 | G40: 1 | H40: =IF(C40="开间",IF(D40+E40*2-G40<=0,"1",IF(D40+E40*2-G40<=1,"2",IF(D40+E40*2-G40<=2,"3",IF(D40+E40*2-G40<=3,"4","5")))),IF(D40+E40*2-G40<1.1,"1",IF(D40+E40*2-G40<=2,"2",IF(D40+E40*2-G40<=3,"3",IF(D40+E40*2-G40<=4,"4","5"))))) -> 1
A41: ='【3-2】大区&运营中心填-房间模型价'!H40 -> 508 | B41: ='【3-2】大区&运营中心填-房间模型价'!I40 -> Q | C41: =VLOOKUP(A41,'【3-2】大区&运营中心填-房间模型价'!H:J,3,0) -> 一居室 | D41: 2 | E41: 0 | G41: 0 | H41: =IF(C41="开间",IF(D41+E41*2-G41<=0,"1",IF(D41+E41*2-G41<=1,"2",IF(D41+E41*2-G41<=2,"3",IF(D41+E41*2-G41<=3,"4","5")))),IF(D41+E41*2-G41<1.1,"1",IF(D41+E41*2-G41<=2,"2",IF(D41+E41*2-G41<=3,"3",IF(D41+E41*2-G41<=4,"4","5"))))) -> 2
A42: ='【3-2】大区&运营中心填-房间模型价'!H41 -> 601 | B42: ='【3-2】大区&运营中心填-房间模型价'!I41 -> N | C42: =VLOOKUP(A42,'【3-2】大区&运营中心填-房间模型价'!H:J,3,0) -> 开间 | D42: 2 | E42: 0 | G42: -2 | H42: =IF(C42="开间",IF(D42+E42*2-G42<=0,"1",IF(D42+E42*2-G42<=1,"2",IF(D42+E42*2-G42<=2,"3",IF(D42+E42*2-G42<=3,"4","5")))),IF(D42+E42*2-G42<1.1,"1",IF(D42+E42*2-G42<=2,"2",IF(D42+E42*2-G42<=3,"3",IF(D42+E42*2-G42<=4,"4","5"))))) -> 5
A43: ='【3-2】大区&运营中心填-房间模型价'!H42 -> 602 | B43: ='【3-2】大区&运营中心填-房间模型价'!I42 -> H | C43: =VLOOKUP(A43,'【3-2】大区&运营中心填-房间模型价'!H:J,3,0) -> 一居室 | D43: 1 | E43: 0 | G43: -1 | H43: =IF(C43="开间",IF(D43+E43*2-G43<=0,"1",IF(D43+E43*2-G43<=1,"2",IF(D43+E43*2-G43<=2,"3",IF(D43+E43*2-G43<=3,"4","5")))),IF(D43+E43*2-G43<1.1,"1",IF(D43+E43*2-G43<=2,"2",IF(D43+E43*2-G43<=3,"3",IF(D43+E43*2-G43<=4,"4","5"))))) -> 2
A44: ='【3-2】大区&运营中心填-房间模型价'!H43 -> 603 | B44: ='【3-2】大区&运营中心填-房间模型价'!I43 -> O | C44: =VLOOKUP(A44,'【3-2】大区&运营中心填-房间模型价'!H:J,3,0) -> 开间 | D44: 1 | E44: 1 | F44: 0.7 | G44: 0 | H44: =IF(C44="开间",IF(D44+E44*2-G44<=0,"1",IF(D44+E44*2-G44<=1,"2",IF(D44+E44*2-G44<=2,"3",IF(D44+E44*2-G44<=3,"4","5")))),IF(D44+E44*2-G44<1.1,"1",IF(D44+E44*2-G44<=2,"2",IF(D44+E44*2-G44<=3,"3",IF(D44+E44*2-G44<=4,"4","5"))))) -> 4
A45: ='【3-2】大区&运营中心填-房间模型价'!H44 -> 604 | B45: ='【3-2】大区&运营中心填-房间模型价'!I44 -> P | C45: =VLOOKUP(A45,'【3-2】大区&运营中心填-房间模型价'!H:J,3,0) -> 开间 | D45: 0.5 | E45: 0 | G45: -0.5 | H45: =IF(C45="开间",IF(D45+E45*2-G45<=0,"1",IF(D45+E45*2-G45<=1,"2",IF(D45+E45*2-G45<=2,"3",IF(D45+E45*2-G45<=3,"4","5")))),IF(D45+E45*2-G45<1.1,"1",IF(D45+E45*2-G45<=2,"2",IF(D45+E45*2-G45<=3,"3",IF(D45+E45*2-G45<=4,"4","5"))))) -> 2
A46: ='【3-2】大区&运营中心填-房间模型价'!H45 -> 605 | B46: ='【3-2】大区&运营中心填-房间模型价'!I45 -> K | C46: =VLOOKUP(A46,'【3-2】大区&运营中心填-房间模型价'!H:J,3,0) -> 开间 | D46: 2 | E46: 0 | G46: -1 | H46: =IF(C46="开间",IF(D46+E46*2-G46<=0,"1",IF(D46+E46*2-G46<=1,"2",IF(D46+E46*2-G46<=2,"3",IF(D46+E46*2-G46<=3,"4","5")))),IF(D46+E46*2-G46<1.1,"1",IF(D46+E46*2-G46<=2,"2",IF(D46+E46*2-G46<=3,"3",IF(D46+E46*2-G46<=4,"4","5"))))) -> 4
A47: ='【3-2】大区&运营中心填-房间模型价'!H46 -> 606 | B47: ='【3-2】大区&运营中心填-房间模型价'!I46 -> L | C47: =VLOOKUP(A47,'【3-2】大区&运营中心填-房间模型价'!H:J,3,0) -> 一居室 | D47: 2 | E47: 0 | G47: 1 | H47: =IF(C47="开间",IF(D47+E47*2-G47<=0,"1",IF(D47+E47*2-G47<=1,"2",IF(D47+E47*2-G47<=2,"3",IF(D47+E47*2-G47<=3,"4","5")))),IF(D47+E47*2-G47<1.1,"1",IF(D47+E47*2-G47<=2,"2",IF(D47+E47*2-G47<=3,"3",IF(D47+E47*2-G47<=4,"4","5"))))) -> 1
A48: ='【3-2】大区&运营中心填-房间模型价'!H47 -> 607 | B48: ='【3-2】大区&运营中心填-房间模型价'!I47 -> J | C48: =VLOOKUP(A48,'【3-2】大区&运营中心填-房间模型价'!H:J,3,0) -> 开间 | D48: 1 | E48: 0 | G48: 1 | H48: =IF(C48="开间",IF(D48+E48*2-G48<=0,"1",IF(D48+E48*2-G48<=1,"2",IF(D48+E48*2-G48<=2,"3",IF(D48+E48*2-G48<=3,"4","5")))),IF(D48+E48*2-G48<1.1,"1",IF(D48+E48*2-G48<=2,"2",IF(D48+E48*2-G48<=3,"3",IF(D48+E48*2-G48<=4,"4","5"))))) -> 1
A49: ='【3-2】大区&运营中心填-房间模型价'!H48 -> 608 | B49: ='【3-2】大区&运营中心填-房间模型价'!I48 -> Q | C49: =VLOOKUP(A49,'【3-2】大区&运营中心填-房间模型价'!H:J,3,0) -> 一居室 | D49: 2 | E49: 0 | G49: 0 | H49: =IF(C49="开间",IF(D49+E49*2-G49<=0,"1",IF(D49+E49*2-G49<=1,"2",IF(D49+E49*2-G49<=2,"3",IF(D49+E49*2-G49<=3,"4","5")))),IF(D49+E49*2-G49<1.1,"1",IF(D49+E49*2-G49<=2,"2",IF(D49+E49*2-G49<=3,"3",IF(D49+E49*2-G49<=4,"4","5"))))) -> 2
A50: ='【3-2】大区&运营中心填-房间模型价'!H49 -> 701 | B50: ='【3-2】大区&运营中心填-房间模型价'!I49 -> N | C50: =VLOOKUP(A50,'【3-2】大区&运营中心填-房间模型价'!H:J,3,0) -> 开间 | D50: 2 | E50: 0 | G50: -2 | H50: =IF(C50="开间",IF(D50+E50*2-G50<=0,"1",IF(D50+E50*2-G50<=1,"2",IF(D50+E50*2-G50<=2,"3",IF(D50+E50*2-G50<=3,"4","5")))),IF(D50+E50*2-G50<1.1,"1",IF(D50+E50*2-G50<=2,"2",IF(D50+E50*2-G50<=3,"3",IF(D50+E50*2-G50<=4,"4","5"))))) -> 5
A51: ='【3-2】大区&运营中心填-房间模型价'!H50 -> 702 | B51: ='【3-2】大区&运营中心填-房间模型价'!I50 -> H | C51: =VLOOKUP(A51,'【3-2】大区&运营中心填-房间模型价'!H:J,3,0) -> 一居室 | D51: 1 | E51: 0 | G51: -1 | H51: =IF(C51="开间",IF(D51+E51*2-G51<=0,"1",IF(D51+E51*2-G51<=1,"2",IF(D51+E51*2-G51<=2,"3",IF(D51+E51*2-G51<=3,"4","5")))),IF(D51+E51*2-G51<1.1,"1",IF(D51+E51*2-G51<=2,"2",IF(D51+E51*2-G51<=3,"3",IF(D51+E51*2-G51<=4,"4","5"))))) -> 2
A52: ='【3-2】大区&运营中心填-房间模型价'!H51 -> 703 | B52: ='【3-2】大区&运营中心填-房间模型价'!I51 -> O | C52: =VLOOKUP(A52,'【3-2】大区&运营中心填-房间模型价'!H:J,3,0) -> 开间 | D52: 1 | E52: 1 | F52: 0.7 | G52: 0 | H52: =IF(C52="开间",IF(D52+E52*2-G52<=0,"1",IF(D52+E52*2-G52<=1,"2",IF(D52+E52*2-G52<=2,"3",IF(D52+E52*2-G52<=3,"4","5")))),IF(D52+E52*2-G52<1.1,"1",IF(D52+E52*2-G52<=2,"2",IF(D52+E52*2-G52<=3,"3",IF(D52+E52*2-G52<=4,"4","5"))))) -> 4
A53: ='【3-2】大区&运营中心填-房间模型价'!H52 -> 704 | B53: ='【3-2】大区&运营中心填-房间模型价'!I52 -> P | C53: =VLOOKUP(A53,'【3-2】大区&运营中心填-房间模型价'!H:J,3,0) -> 开间 | D53: 0.5 | E53: 0 | G53: -0.5 | H53: =IF(C53="开间",IF(D53+E53*2-G53<=0,"1",IF(D53+E53*2-G53<=1,"2",IF(D53+E53*2-G53<=2,"3",IF(D53+E53*2-G53<=3,"4","5")))),IF(D53+E53*2-G53<1.1,"1",IF(D53+E53*2-G53<=2,"2",IF(D53+E53*2-G53<=3,"3",IF(D53+E53*2-G53<=4,"4","5"))))) -> 2
A54: ='【3-2】大区&运营中心填-房间模型价'!H53 -> 705 | B54: ='【3-2】大区&运营中心填-房间模型价'!I53 -> K | C54: =VLOOKUP(A54,'【3-2】大区&运营中心填-房间模型价'!H:J,3,0) -> 开间 | D54: 2 | E54: 0 | G54: -1 | H54: =IF(C54="开间",IF(D54+E54*2-G54<=0,"1",IF(D54+E54*2-G54<=1,"2",IF(D54+E54*2-G54<=2,"3",IF(D54+E54*2-G54<=3,"4","5")))),IF(D54+E54*2-G54<1.1,"1",IF(D54+E54*2-G54<=2,"2",IF(D54+E54*2-G54<=3,"3",IF(D54+E54*2-G54<=4,"4","5"))))) -> 4
A55: ='【3-2】大区&运营中心填-房间模型价'!H54 -> 706 | B55: ='【3-2】大区&运营中心填-房间模型价'!I54 -> L | C55: =VLOOKUP(A55,'【3-2】大区&运营中心填-房间模型价'!H:J,3,0) -> 一居室 | D55: 2 | E55: 0 | G55: 1 | H55: =IF(C55="开间",IF(D55+E55*2-G55<=0,"1",IF(D55+E55*2-G55<=1,"2",IF(D55+E55*2-G55<=2,"3",IF(D55+E55*2-G55<=3,"4","5")))),IF(D55+E55*2-G55<1.1,"1",IF(D55+E55*2-G55<=2,"2",IF(D55+E55*2-G55<=3,"3",IF(D55+E55*2-G55<=4,"4","5"))))) -> 1
A56: ='【3-2】大区&运营中心填-房间模型价'!H55 -> 707 | B56: ='【3-2】大区&运营中心填-房间模型价'!I55 -> J | C56: =VLOOKUP(A56,'【3-2】大区&运营中心填-房间模型价'!H:J,3,0) -> 开间 | D56: 1 | E56: 0 | G56: 1 | H56: =IF(C56="开间",IF(D56+E56*2-G56<=0,"1",IF(D56+E56*2-G56<=1,"2",IF(D56+E56*2-G56<=2,"3",IF(D56+E56*2-G56<=3,"4","5")))),IF(D56+E56*2-G56<1.1,"1",IF(D56+E56*2-G56<=2,"2",IF(D56+E56*2-G56<=3,"3",IF(D56+E56*2-G56<=4,"4","5"))))) -> 1
A57: ='【3-2】大区&运营中心填-房间模型价'!H56 -> 708 | B57: ='【3-2】大区&运营中心填-房间模型价'!I56 -> Q | C57: =VLOOKUP(A57,'【3-2】大区&运营中心填-房间模型价'!H:J,3,0) -> 一居室 | D57: 2 | E57: 0 | G57: 0 | H57: =IF(C57="开间",IF(D57+E57*2-G57<=0,"1",IF(D57+E57*2-G57<=1,"2",IF(D57+E57*2-G57<=2,"3",IF(D57+E57*2-G57<=3,"4","5")))),IF(D57+E57*2-G57<1.1,"1",IF(D57+E57*2-G57<=2,"2",IF(D57+E57*2-G57<=3,"3",IF(D57+E57*2-G57<=4,"4","5"))))) -> 2
A58: ='【3-2】大区&运营中心填-房间模型价'!H57 -> 801 | B58: ='【3-2】大区&运营中心填-房间模型价'!I57 -> N | C58: =VLOOKUP(A58,'【3-2】大区&运营中心填-房间模型价'!H:J,3,0) -> 开间 | D58: 2 | E58: 0 | G58: -2 | H58: =IF(C58="开间",IF(D58+E58*2-G58<=0,"1",IF(D58+E58*2-G58<=1,"2",IF(D58+E58*2-G58<=2,"3",IF(D58+E58*2-G58<=3,"4","5")))),IF(D58+E58*2-G58<1.1,"1",IF(D58+E58*2-G58<=2,"2",IF(D58+E58*2-G58<=3,"3",IF(D58+E58*2-G58<=4,"4","5"))))) -> 5
A59: ='【3-2】大区&运营中心填-房间模型价'!H58 -> 802 | B59: ='【3-2】大区&运营中心填-房间模型价'!I58 -> H | C59: =VLOOKUP(A59,'【3-2】大区&运营中心填-房间模型价'!H:J,3,0) -> 一居室 | D59: 1 | E59: 0 | G59: -1 | H59: =IF(C59="开间",IF(D59+E59*2-G59<=0,"1",IF(D59+E59*2-G59<=1,"2",IF(D59+E59*2-G59<=2,"3",IF(D59+E59*2-G59<=3,"4","5")))),IF(D59+E59*2-G59<1.1,"1",IF(D59+E59*2-G59<=2,"2",IF(D59+E59*2-G59<=3,"3",IF(D59+E59*2-G59<=4,"4","5"))))) -> 2
A60: ='【3-2】大区&运营中心填-房间模型价'!H59 -> 803 | B60: ='【3-2】大区&运营中心填-房间模型价'!I59 -> O | C60: =VLOOKUP(A60,'【3-2】大区&运营中心填-房间模型价'!H:J,3,0) -> 开间 | D60: 1 | E60: 1 | F60: 0.7 | G60: 0 | H60: =IF(C60="开间",IF(D60+E60*2-G60<=0,"1",IF(D60+E60*2-G60<=1,"2",IF(D60+E60*2-G60<=2,"3",IF(D60+E60*2-G60<=3,"4","5")))),IF(D60+E60*2-G60<1.1,"1",IF(D60+E60*2-G60<=2,"2",IF(D60+E60*2-G60<=3,"3",IF(D60+E60*2-G60<=4,"4","5"))))) -> 4
A61: ='【3-2】大区&运营中心填-房间模型价'!H60 -> 804 | B61: ='【3-2】大区&运营中心填-房间模型价'!I60 -> P | C61: =VLOOKUP(A61,'【3-2】大区&运营中心填-房间模型价'!H:J,3,0) -> 开间 | D61: 0.5 | E61: 0 | G61: -0.5 | H61: =IF(C61="开间",IF(D61+E61*2-G61<=0,"1",IF(D61+E61*2-G61<=1,"2",IF(D61+E61*2-G61<=2,"3",IF(D61+E61*2-G61<=3,"4","5")))),IF(D61+E61*2-G61<1.1,"1",IF(D61+E61*2-G61<=2,"2",IF(D61+E61*2-G61<=3,"3",IF(D61+E61*2-G61<=4,"4","5"))))) -> 2
A62: ='【3-2】大区&运营中心填-房间模型价'!H61 -> 805 | B62: ='【3-2】大区&运营中心填-房间模型价'!I61 -> K | C62: =VLOOKUP(A62,'【3-2】大区&运营中心填-房间模型价'!H:J,3,0) -> 开间 | D62: 2 | E62: 0 | G62: -1 | H62: =IF(C62="开间",IF(D62+E62*2-G62<=0,"1",IF(D62+E62*2-G62<=1,"2",IF(D62+E62*2-G62<=2,"3",IF(D62+E62*2-G62<=3,"4","5")))),IF(D62+E62*2-G62<1.1,"1",IF(D62+E62*2-G62<=2,"2",IF(D62+E62*2-G62<=3,"3",IF(D62+E62*2-G62<=4,"4","5"))))) -> 4
A63: ='【3-2】大区&运营中心填-房间模型价'!H62 -> 806 | B63: ='【3-2】大区&运营中心填-房间模型价'!I62 -> L | C63: =VLOOKUP(A63,'【3-2】大区&运营中心填-房间模型价'!H:J,3,0) -> 一居室 | D63: 2 | E63: 0 | G63: 1 | H63: =IF(C63="开间",IF(D63+E63*2-G63<=0,"1",IF(D63+E63*2-G63<=1,"2",IF(D63+E63*2-G63<=2,"3",IF(D63+E63*2-G63<=3,"4","5")))),IF(D63+E63*2-G63<1.1,"1",IF(D63+E63*2-G63<=2,"2",IF(D63+E63*2-G63<=3,"3",IF(D63+E63*2-G63<=4,"4","5"))))) -> 1
A64: ='【3-2】大区&运营中心填-房间模型价'!H63 -> 807 | B64: ='【3-2】大区&运营中心填-房间模型价'!I63 -> J | C64: =VLOOKUP(A64,'【3-2】大区&运营中心填-房间模型价'!H:J,3,0) -> 开间 | D64: 1 | E64: 0 | G64: 1 | H64: =IF(C64="开间",IF(D64+E64*2-G64<=0,"1",IF(D64+E64*2-G64<=1,"2",IF(D64+E64*2-G64<=2,"3",IF(D64+E64*2-G64<=3,"4","5")))),IF(D64+E64*2-G64<1.1,"1",IF(D64+E64*2-G64<=2,"2",IF(D64+E64*2-G64<=3,"3",IF(D64+E64*2-G64<=4,"4","5"))))) -> 1
A65: ='【3-2】大区&运营中心填-房间模型价'!H64 -> 808 | B65: ='【3-2】大区&运营中心填-房间模型价'!I64 -> Q | C65: =VLOOKUP(A65,'【3-2】大区&运营中心填-房间模型价'!H:J,3,0) -> 一居室 | D65: 2 | E65: 0 | G65: 0 | H65: =IF(C65="开间",IF(D65+E65*2-G65<=0,"1",IF(D65+E65*2-G65<=1,"2",IF(D65+E65*2-G65<=2,"3",IF(D65+E65*2-G65<=3,"4","5")))),IF(D65+E65*2-G65<1.1,"1",IF(D65+E65*2-G65<=2,"2",IF(D65+E65*2-G65<=3,"3",IF(D65+E65*2-G65<=4,"4","5"))))) -> 2
A66: ='【3-2】大区&运营中心填-房间模型价'!H65 -> 901 | B66: ='【3-2】大区&运营中心填-房间模型价'!I65 -> N | C66: =VLOOKUP(A66,'【3-2】大区&运营中心填-房间模型价'!H:J,3,0) -> 开间 | D66: 2 | E66: 0 | G66: -2 | H66: =IF(C66="开间",IF(D66+E66*2-G66<=0,"1",IF(D66+E66*2-G66<=1,"2",IF(D66+E66*2-G66<=2,"3",IF(D66+E66*2-G66<=3,"4","5")))),IF(D66+E66*2-G66<1.1,"1",IF(D66+E66*2-G66<=2,"2",IF(D66+E66*2-G66<=3,"3",IF(D66+E66*2-G66<=4,"4","5"))))) -> 5
A67: ='【3-2】大区&运营中心填-房间模型价'!H66 -> 902 | B67: ='【3-2】大区&运营中心填-房间模型价'!I66 -> H | C67: =VLOOKUP(A67,'【3-2】大区&运营中心填-房间模型价'!H:J,3,0) -> 一居室 | D67: 1 | E67: 0 | G67: -1 | H67: =IF(C67="开间",IF(D67+E67*2-G67<=0,"1",IF(D67+E67*2-G67<=1,"2",IF(D67+E67*2-G67<=2,"3",IF(D67+E67*2-G67<=3,"4","5")))),IF(D67+E67*2-G67<1.1,"1",IF(D67+E67*2-G67<=2,"2",IF(D67+E67*2-G67<=3,"3",IF(D67+E67*2-G67<=4,"4","5"))))) -> 2
A68: ='【3-2】大区&运营中心填-房间模型价'!H67 -> 903 | B68: ='【3-2】大区&运营中心填-房间模型价'!I67 -> O | C68: =VLOOKUP(A68,'【3-2】大区&运营中心填-房间模型价'!H:J,3,0) -> 开间 | D68: 1 | E68: 1 | F68: 0.7 | G68: 0 | H68: =IF(C68="开间",IF(D68+E68*2-G68<=0,"1",IF(D68+E68*2-G68<=1,"2",IF(D68+E68*2-G68<=2,"3",IF(D68+E68*2-G68<=3,"4","5")))),IF(D68+E68*2-G68<1.1,"1",IF(D68+E68*2-G68<=2,"2",IF(D68+E68*2-G68<=3,"3",IF(D68+E68*2-G68<=4,"4","5"))))) -> 4
A69: ='【3-2】大区&运营中心填-房间模型价'!H68 -> 904 | B69: ='【3-2】大区&运营中心填-房间模型价'!I68 -> P | C69: =VLOOKUP(A69,'【3-2】大区&运营中心填-房间模型价'!H:J,3,0) -> 开间 | D69: 0.5 | E69: 0 | G69: -0.5 | H69: =IF(C69="开间",IF(D69+E69*2-G69<=0,"1",IF(D69+E69*2-G69<=1,"2",IF(D69+E69*2-G69<=2,"3",IF(D69+E69*2-G69<=3,"4","5")))),IF(D69+E69*2-G69<1.1,"1",IF(D69+E69*2-G69<=2,"2",IF(D69+E69*2-G69<=3,"3",IF(D69+E69*2-G69<=4,"4","5"))))) -> 2
A70: ='【3-2】大区&运营中心填-房间模型价'!H69 -> 905 | B70: ='【3-2】大区&运营中心填-房间模型价'!I69 -> K | C70: =VLOOKUP(A70,'【3-2】大区&运营中心填-房间模型价'!H:J,3,0) -> 开间 | D70: 2 | E70: 0 | G70: -1 | H70: =IF(C70="开间",IF(D70+E70*2-G70<=0,"1",IF(D70+E70*2-G70<=1,"2",IF(D70+E70*2-G70<=2,"3",IF(D70+E70*2-G70<=3,"4","5")))),IF(D70+E70*2-G70<1.1,"1",IF(D70+E70*2-G70<=2,"2",IF(D70+E70*2-G70<=3,"3",IF(D70+E70*2-G70<=4,"4","5"))))) -> 4
A71: ='【3-2】大区&运营中心填-房间模型价'!H70 -> 906 | B71: ='【3-2】大区&运营中心填-房间模型价'!I70 -> L | C71: =VLOOKUP(A71,'【3-2】大区&运营中心填-房间模型价'!H:J,3,0) -> 一居室 | D71: 2 | E71: 0 | G71: 1 | H71: =IF(C71="开间",IF(D71+E71*2-G71<=0,"1",IF(D71+E71*2-G71<=1,"2",IF(D71+E71*2-G71<=2,"3",IF(D71+E71*2-G71<=3,"4","5")))),IF(D71+E71*2-G71<1.1,"1",IF(D71+E71*2-G71<=2,"2",IF(D71+E71*2-G71<=3,"3",IF(D71+E71*2-G71<=4,"4","5"))))) -> 1
A72: ='【3-2】大区&运营中心填-房间模型价'!H71 -> 907 | B72: ='【3-2】大区&运营中心填-房间模型价'!I71 -> J | C72: =VLOOKUP(A72,'【3-2】大区&运营中心填-房间模型价'!H:J,3,0) -> 开间 | D72: 1 | E72: 0 | G72: 1 | H72: =IF(C72="开间",IF(D72+E72*2-G72<=0,"1",IF(D72+E72*2-G72<=1,"2",IF(D72+E72*2-G72<=2,"3",IF(D72+E72*2-G72<=3,"4","5")))),IF(D72+E72*2-G72<1.1,"1",IF(D72+E72*2-G72<=2,"2",IF(D72+E72*2-G72<=3,"3",IF(D72+E72*2-G72<=4,"4","5"))))) -> 1
A73: ='【3-2】大区&运营中心填-房间模型价'!H72 -> 908 | B73: ='【3-2】大区&运营中心填-房间模型价'!I72 -> Q | C73: =VLOOKUP(A73,'【3-2】大区&运营中心填-房间模型价'!H:J,3,0) -> 一居室 | D73: 2 | E73: 0 | G73: 0 | H73: =IF(C73="开间",IF(D73+E73*2-G73<=0,"1",IF(D73+E73*2-G73<=1,"2",IF(D73+E73*2-G73<=2,"3",IF(D73+E73*2-G73<=3,"4","5")))),IF(D73+E73*2-G73<1.1,"1",IF(D73+E73*2-G73<=2,"2",IF(D73+E73*2-G73<=3,"3",IF(D73+E73*2-G73<=4,"4","5"))))) -> 2
A74: ='【3-2】大区&运营中心填-房间模型价'!#REF! -> #REF! | B74: ='【3-2】大区&运营中心填-房间模型价'!#REF! -> #REF! | C74: =VLOOKUP(A74,'【3-2】大区&运营中心填-房间模型价'!H:J,3,0) -> #REF! | H74: =IF(C74="开间",IF(D74+E74*2-G74<=0,"1",IF(D74+E74*2-G74<=1,"2",IF(D74+E74*2-G74<=2,"3",IF(D74+E74*2-G74<=3,"4","5")))),IF(D74+E74*2-G74<1.1,"1",IF(D74+E74*2-G74<=2,"2",IF(D74+E74*2-G74<=3,"3",IF(D74+E74*2-G74<=4,"4","5"))))) -> #REF!
A75: ='【3-2】大区&运营中心填-房间模型价'!#REF! -> #REF! | B75: ='【3-2】大区&运营中心填-房间模型价'!#REF! -> #REF! | C75: =VLOOKUP(A75,'【3-2】大区&运营中心填-房间模型价'!H:J,3,0) -> #REF! | H75: =IF(C75="开间",IF(D75+E75*2-G75<=0,"1",IF(D75+E75*2-G75<=1,"2",IF(D75+E75*2-G75<=2,"3",IF(D75+E75*2-G75<=3,"4","5")))),IF(D75+E75*2-G75<1.1,"1",IF(D75+E75*2-G75<=2,"2",IF(D75+E75*2-G75<=3,"3",IF(D75+E75*2-G75<=4,"4","5"))))) -> #REF!
A76: ='【3-2】大区&运营中心填-房间模型价'!#REF! -> #REF! | B76: ='【3-2】大区&运营中心填-房间模型价'!#REF! -> #REF! | C76: =VLOOKUP(A76,'【3-2】大区&运营中心填-房间模型价'!H:J,3,0) -> #REF! | H76: =IF(C76="开间",IF(D76+E76*2-G76<=0,"1",IF(D76+E76*2-G76<=1,"2",IF(D76+E76*2-G76<=2,"3",IF(D76+E76*2-G76<=3,"4","5")))),IF(D76+E76*2-G76<1.1,"1",IF(D76+E76*2-G76<=2,"2",IF(D76+E76*2-G76<=3,"3",IF(D76+E76*2-G76<=4,"4","5"))))) -> #REF!
A77: ='【3-2】大区&运营中心填-房间模型价'!#REF! -> #REF! | B77: ='【3-2】大区&运营中心填-房间模型价'!#REF! -> #REF! | C77: =VLOOKUP(A77,'【3-2】大区&运营中心填-房间模型价'!H:J,3,0) -> #REF! | H77: =IF(C77="开间",IF(D77+E77*2-G77<=0,"1",IF(D77+E77*2-G77<=1,"2",IF(D77+E77*2-G77<=2,"3",IF(D77+E77*2-G77<=3,"4","5")))),IF(D77+E77*2-G77<1.1,"1",IF(D77+E77*2-G77<=2,"2",IF(D77+E77*2-G77<=3,"3",IF(D77+E77*2-G77<=4,"4","5"))))) -> #REF!
A78: ='【3-2】大区&运营中心填-房间模型价'!#REF! -> #REF! | B78: ='【3-2】大区&运营中心填-房间模型价'!#REF! -> #REF! | C78: =VLOOKUP(A78,'【3-2】大区&运营中心填-房间模型价'!H:J,3,0) -> #REF! | H78: =IF(C78="开间",IF(D78+E78*2-G78<=0,"1",IF(D78+E78*2-G78<=1,"2",IF(D78+E78*2-G78<=2,"3",IF(D78+E78*2-G78<=3,"4","5")))),IF(D78+E78*2-G78<1.1,"1",IF(D78+E78*2-G78<=2,"2",IF(D78+E78*2-G78<=3,"3",IF(D78+E78*2-G78<=4,"4","5"))))) -> #REF!
A79: ='【3-2】大区&运营中心填-房间模型价'!#REF! -> #REF! | B79: ='【3-2】大区&运营中心填-房间模型价'!#REF! -> #REF! | C79: =VLOOKUP(A79,'【3-2】大区&运营中心填-房间模型价'!H:J,3,0) -> #REF! | H79: =IF(C79="开间",IF(D79+E79*2-G79<=0,"1",IF(D79+E79*2-G79<=1,"2",IF(D79+E79*2-G79<=2,"3",IF(D79+E79*2-G79<=3,"4","5")))),IF(D79+E79*2-G79<1.1,"1",IF(D79+E79*2-G79<=2,"2",IF(D79+E79*2-G79<=3,"3",IF(D79+E79*2-G79<=4,"4","5"))))) -> #REF!
A80: ='【3-2】大区&运营中心填-房间模型价'!#REF! -> #REF! | B80: ='【3-2】大区&运营中心填-房间模型价'!#REF! -> #REF! | C80: =VLOOKUP(A80,'【3-2】大区&运营中心填-房间模型价'!H:J,3,0) -> #REF! | H80: =IF(C80="开间",IF(D80+E80*2-G80<=0,"1",IF(D80+E80*2-G80<=1,"2",IF(D80+E80*2-G80<=2,"3",IF(D80+E80*2-G80<=3,"4","5")))),IF(D80+E80*2-G80<1.1,"1",IF(D80+E80*2-G80<=2,"2",IF(D80+E80*2-G80<=3,"3",IF(D80+E80*2-G80<=4,"4","5"))))) -> #REF!
A81: ='【3-2】大区&运营中心填-房间模型价'!#REF! -> #REF! | B81: ='【3-2】大区&运营中心填-房间模型价'!#REF! -> #REF! | C81: =VLOOKUP(A81,'【3-2】大区&运营中心填-房间模型价'!H:J,3,0) -> #REF! | H81: =IF(C81="开间",IF(D81+E81*2-G81<=0,"1",IF(D81+E81*2-G81<=1,"2",IF(D81+E81*2-G81<=2,"3",IF(D81+E81*2-G81<=3,"4","5")))),IF(D81+E81*2-G81<1.1,"1",IF(D81+E81*2-G81<=2,"2",IF(D81+E81*2-G81<=3,"3",IF(D81+E81*2-G81<=4,"4","5"))))) -> #REF!
A82: ='【3-2】大区&运营中心填-房间模型价'!#REF! -> #REF! | B82: ='【3-2】大区&运营中心填-房间模型价'!#REF! -> #REF! | C82: =VLOOKUP(A82,'【3-2】大区&运营中心填-房间模型价'!H:J,3,0) -> #REF! | H82: =IF(C82="开间",IF(D82+E82*2-G82<=0,"1",IF(D82+E82*2-G82<=1,"2",IF(D82+E82*2-G82<=2,"3",IF(D82+E82*2-G82<=3,"4","5")))),IF(D82+E82*2-G82<1.1,"1",IF(D82+E82*2-G82<=2,"2",IF(D82+E82*2-G82<=3,"3",IF(D82+E82*2-G82<=4,"4","5"))))) -> #REF!
A83: ='【3-2】大区&运营中心填-房间模型价'!#REF! -> #REF! | B83: ='【3-2】大区&运营中心填-房间模型价'!#REF! -> #REF! | C83: =VLOOKUP(A83,'【3-2】大区&运营中心填-房间模型价'!H:J,3,0) -> #REF! | H83: =IF(C83="开间",IF(D83+E83*2-G83<=0,"1",IF(D83+E83*2-G83<=1,"2",IF(D83+E83*2-G83<=2,"3",IF(D83+E83*2-G83<=3,"4","5")))),IF(D83+E83*2-G83<1.1,"1",IF(D83+E83*2-G83<=2,"2",IF(D83+E83*2-G83<=3,"3",IF(D83+E83*2-G83<=4,"4","5"))))) -> #REF!
A84: ='【3-2】大区&运营中心填-房间模型价'!#REF! -> #REF! | B84: ='【3-2】大区&运营中心填-房间模型价'!#REF! -> #REF! | C84: =VLOOKUP(A84,'【3-2】大区&运营中心填-房间模型价'!H:J,3,0) -> #REF! | H84: =IF(C84="开间",IF(D84+E84*2-G84<=0,"1",IF(D84+E84*2-G84<=1,"2",IF(D84+E84*2-G84<=2,"3",IF(D84+E84*2-G84<=3,"4","5")))),IF(D84+E84*2-G84<1.1,"1",IF(D84+E84*2-G84<=2,"2",IF(D84+E84*2-G84<=3,"3",IF(D84+E84*2-G84<=4,"4","5"))))) -> #REF!
A85: ='【3-2】大区&运营中心填-房间模型价'!#REF! -> #REF! | B85: ='【3-2】大区&运营中心填-房间模型价'!#REF! -> #REF! | C85: =VLOOKUP(A85,'【3-2】大区&运营中心填-房间模型价'!H:J,3,0) -> #REF! | H85: =IF(C85="开间",IF(D85+E85*2-G85<=0,"1",IF(D85+E85*2-G85<=1,"2",IF(D85+E85*2-G85<=2,"3",IF(D85+E85*2-G85<=3,"4","5")))),IF(D85+E85*2-G85<1.1,"1",IF(D85+E85*2-G85<=2,"2",IF(D85+E85*2-G85<=3,"3",IF(D85+E85*2-G85<=4,"4","5"))))) -> #REF!
... A200: ='【3-2】大区&运营中心填-房间模型价'!#REF! -> #REF! | B200: ='【3-2】大区&运营中心填-房间模型价'!#REF! -> #REF! | C200: =VLOOKUP(A200,'【3-2】大区&运营中心填-房间模型价'!H:J,3,0) -> #REF! | H200: =IF(C200="开间",IF(D200+E200*2-G200<=0,"1",IF(D200+E200*2-G200<=1,"2",IF(D200+E200*2-G200<=2,"3",IF(D200+E200*2-G200<=3,"4","5")))),IF(D200+E200*2-G200<1.1,"1",IF(D200+E200*2-G200<=2,"2",IF(D200+E200*2-G200<=3,"3",IF(D200+E200*2-G200<=4,"4","5"))))) -> #REF!

Sheet 【3-2】大区&运营中心填-房间模型价
A1: 楼栋 | B1: 标准层1 | C1: 标准层2 | D1: 标准层3 | E1: 标准层4 | F1: 标准层5 | G1: 标准层6 | H1: 房间号 | I1: 户型 | J1: 基准格局 | K1: 格局 | L1: 基准格局定价 | M1: 套内空间 | N1: 套内面积 | O1: 调价倍数1 | P1: 阳台 | Q1: 调价倍数2 | R1: 楼梯房楼层 | S1: 调价倍数3 | T1: 电梯房楼层 | U1: 调价倍数4 | V1: 操作台 | W1: 书桌 | X1: 单人沙发 | Y1: 双人沙发 | Z1: 餐桌 | AA1: 吸油烟机 | AB1: 冰箱 | AC1: 电视柜 | AD1: =【1】定价因子!$C$35 -> 功能配置（开间） | AE1: 调价倍数5 | AF1: =【1】定价因子!$C$47 -> 功能配置（一居） | AG1: 调价倍数6 | AH1: =【1】定价因子!$C$54 -> 功能配置（二居） | AI1: 调价倍数7 | AJ1: 采光 | AK1: 调价倍数8 | AL1: 房间模型价 | AM1: 实际定价 | AN1: 差距
A2: ='【2】运营中心填-基本信息&审核标准'!$E$2 -> 兴围西4-11栋 | B2: =INT(H2/100) -> 1 | C2: =COUNTIF($B$2:$B$72,B2) -> 7 | D2: =COUNTIF(C$2:C$72,C2) -> 7 | E2: =MAX(D2:D72) -> 64 | F2: =IF(D2=$E$2,C2,"") | G2: =MAX(F2:F72) -> 8 | H2: 101 | I2: A | J2: 开间 | K2: {=IFERROR(INDEX($J$2:$J$72,MATCH(0,IF(ISBLANK($J$2:$J$72),1,COUNTIF($K$1:K1,$J$2:$J$72)),0)),"")} -> 开间 | L2: =VLOOKUP(J2,'【3】大区填-楼栋基准格局定价'!B:H,7,0) -> 1647.8784 | M2: =IF(OR(J2="开间",J2="二人宿舍"),IF(N2<10,"很狭小",IF(N2<13,"较狭小",IF(N2<17,"适中",IF(N2<20,"较宽敞","很宽敞")))),IF(OR(J2="一居室",J2="四人宿舍"),IF(N2<20,"很狭小",IF(N2<23,"较狭小",IF(N2<26,"适中",IF(N2<28,"较宽敞","很宽敞")))),IF(OR(J2="二居室",J2="六人宿舍"),IF(N2<30,"很狭小",IF(N2<35,"较狭小",IF(N2<40,"适中",IF(N2<45,"较宽敞","很宽敞")))),""))) -> 较狭小 | N2: 12.77 | O2: =VLOOKUP($M$1&M2,【1】定价因子!E:F,2,0) -> 0.95 | P2: =IF(COUNTIFS(户型资产表!E:E,I2,户型资产表!H:H,"阳台门")>0,"有","无") -> 无 | Q2: =VLOOKUP($P$1&P2,【1】定价因子!E:F,2,0) -> 1 | R2: =IF('【2】运营中心填-基本信息&审核标准'!$D$4="是","无",IF(INT(H2/100)>9,"9F",INT(H2/100)&"F")) -> 无 | S2: =VLOOKUP(R2,【1】定价因子!D:F,3,0) -> 1 | T2: =IF('【2】运营中心填-基本信息&审核标准'!$D$4="否","无",IF(INT(H2/100)=1,"1F",IF(AND(INT(H2/100)>=2,INT(H2/100)<=3),"2-3F",IF(INT(H2/100)=4,"4F",IF(AND(INT(H2/100)>=5,INT(H2/100)<=6),"5-6F",IF(AND(INT(H2/100)>=7,INT(H2/100)<=8),"7-8F",IF(AND(INT(H2/100)>=9,INT(H2/100)<=10),"9-10F",IF(AND(INT(H2/100)>=11,INT(H2/100)<=12),"11-12F",IF(INT(H2/100)>=13,"13以上F",""))))))))) -> 1F | U2: =VLOOKUP($T$1&T2,【1】定价因子!E:F,2,0) -> 0.87 | V2: =IF(COUNTIFS(户型资产表!E:E,I2,户型资产表!H:H,"操作台")>0,"有","无") -> 有 | W2: =IF(COUNTIFS(户型资产表!E:E,I2,户型资产表!H:H,"书桌")>0,"有","无") -> 有 | X2: {=IF(SUMPRODUCT((户型资产表!E:E=I2)*((户型资产表!I:I="沙发01单人")+(户型资产表!I:I="单人沙发02")))>0,"有","无")} -> 无 | Y2: {=IF(SUMPRODUCT((户型资产表!E:E=I2)*((户型资产表!I:I="沙发02两人")+(户型资产表!I:I="双人沙发01")))>0,"有","无")} -> 无 | Z2: =IF(COUNTIFS(户型资产表!E:E,I2,户型资产表!H:H,"餐桌")>0,"有","无") -> 无 | AA2: =IF(COUNTIFS(户型资产表!E:E,I2,户型资产表!H:H,"吸油烟机")>0,"有","无") -> 无 | AB2: =IF(COUNTIFS(户型资产表!E:E,I2,户型资产表!H:H,"冰箱")>0,"有","无") -> 无 | AC2: =IF(COUNTIFS(户型资产表!E:E,I2,户型资产表!H:H,"电视柜")>0,"有","无") -> 无 | AD2: =IF(J2="开间",IF(AND(V2="无",W2="无"),"缺失",IF(AND(V2="无",W2="有"),"缺失（操作台）",IF(AND(V2="有",W2="无"),"缺失（书桌）",IF(AND(V2="有",W2="有"),IF(OR(AA2="有",Y2="有"),"充足（油烟机/双人沙发）",IF(OR(X2="有",Z2="有"),"充足（单人沙发/餐桌）",IF(AND(OR(X2="有",Y2="有"),Z2="有"),"非常充足","适中"))),"")))),"适中") -> 适中 | AE2: =VLOOKUP($AD$1&AD2,【1】定价因子!E:F,2,0) -> 1 | AF2: =IF(J2="一居室",IF(AND(V2="无",Y2="无",Z2="无"),"缺失",IF(OR(AND(Z2="有",V2="无",Y2="无"),AND(Z2="有",V2="无",Y2="有"),AND(Z2="有",V2="有",Y2="无"),AND(Z2="无",V2="有",Y2="无"),AND(Z2="无",V2="无",Y2="有")),"缺失（操作台/双人沙发）",IF(AND(V2="有",Y2="有",Z2="无"),"缺失（餐桌）",IF(AND(V2="有",Y2="有",Z2="有"),IF(AND(W2="无",AA2="有"),"充配（油烟机）",IF(AND(W2="有",AA2="无"),"充配（书桌）",IF(AND(W2="有",AA2="有"),"非常充配","适中"))),"")))),"适中") -> 适中 | AG2: =VLOOKUP($AF$1&AF2,【1】定价因子!E:F,2,0) -> 1 | AH2: =IF(J2="二居室",IF(AND(Y2="无",Z2="无",AC2="无",V2="无"),"缺失",IF(OR(AND(Y2="无",Z2="无",AC2="有"),AND(Y2="无",Z2="无",V2="有"),AND(Y2="无",Z2="无",AC2="有",V2="有"),AND(Y2="无",Z2="有",AC2="无"),AND(Y2="无",Z2="有",V2="无"),AND(Y2="无",Z2="有",AC2="有"),AND(Y2="无",Z2="有",V2="有"),AND(Y2="有",Z2="无",AC2="无"),AND(Y2="有",Z2="无",V2="无"),AND(Y2="有",Z2="无",AC2="有"),AND(Y2="有",Z2="无",V2="有")),"缺失（沙发/餐桌）",IF(AND(Y2="有",Z2="有",OR(AC2="无",V2="无")),"缺失（电视柜/操作台）",IF(AND(Y2="有",Z2="有",AC2="有",V2="有"),IF(OR(AA2="有",AB2="有"),"充配（油烟机/冰箱）",IF(AND(AA2="无",AB2="无"),"适中","")),"")))),"适中") -> 适中 | AI2: =VLOOKUP($AH$1&AH2,【1】定价因子!E:F,2,0) -> 1 | AJ2: =VLOOKUP(H2,'【3-1】大区填-采光基本要素'!A:H,8,0) -> 1 | AK2: =VLOOKUP($AJ$1&AJ2,【1】定价因子!E:F,2,0) -> 0.91 | AL2: =L2*PRODUCT(AG2,AK2,AE2,U2,S2,Q2,O2) -> 1239.3941 | AM2: 1320 | AN2: =AM2/AL2-1 -> 0.065036569
A3: ='【2】运营中心填-基本信息&审核标准'!$E$2 -> 兴围西4-11栋 | B3: =INT(H3/100) -> 1 | C3: =COUNTIF($B$2:$B$72,B3) -> 7 | D3: =COUNTIF(C$2:C$72,C3) -> 7 | F3: =IF(D3=$E$2,C3,"") | H3: 102 | I3: B | J3: 开间 | K3: {=IFERROR(INDEX($J$2:$J$72,MATCH(0,IF(ISBLANK($J$2:$J$72),1,COUNTIF($K$1:K2,$J$2:$J$72)),0)),"")} -> 一居室 | L3: =VLOOKUP(J3,'【3】大区填-楼栋基准格局定价'!B:H,7,0) -> 1647.8784 | M3: =IF(OR(J3="开间",J3="二人宿舍"),IF(N3<10,"很狭小",IF(N3<13,"较狭小",IF(N3<17,"适中",IF(N3<20,"较宽敞","很宽敞")))),IF(OR(J3="一居室",J3="四人宿舍"),IF(N3<20,"很狭小",IF(N3<23,"较狭小",IF(N3<26,"适中",IF(N3<28,"较宽敞","很宽敞")))),IF(OR(J3="二居室",J3="六人宿舍"),IF(N3<30,"很狭小",IF(N3<35,"较狭小",IF(N3<40,"适中",IF(N3<45,"较宽敞","很宽敞")))),""))) -> 较狭小 | N3: 11.15 | O3: =VLOOKUP($M$1&M3,【1】定价因子!E:F,2,0) -> 0.95 | P3: =IF(COUNTIFS(户型资产表!E:E,I3,户型资产表!H:H,"阳台门")>0,"有","无") -> 无 | Q3: =VLOOKUP($P$1&P3,【1】定价因子!E:F,2,0) -> 1 | R3: =IF('【2】运营中心填-基本信息&审核标准'!$D$4="是","无",IF(INT(H3/100)>9,"9F",INT(H3/100)&"F")) -> 无 | S3: =VLOOKUP(R3,【1】定价因子!D:F,3,0) -> 1 | T3: =IF('【2】运营中心填-基本信息&审核标准'!$D$4="否","无",IF(INT(H3/100)=1,"1F",IF(AND(INT(H3/100)>=2,INT(H3/100)<=3),"2-3F",IF(INT(H3/100)=4,"4F",IF(AND(INT(H3/100)>=5,INT(H3/100)<=6),"5-6F",IF(AND(INT(H3/100)>=7,INT(H3/100)<=8),"7-8F",IF(AND(INT(H3/100)>=9,INT(H3/100)<=10),"9-10F",IF(AND(INT(H3/100)>=11,INT(H3/100)<=12),"11-12F",IF(INT(H3/100)>=13,"13以上F",""))))))))) -> 1F | U3: =VLOOKUP($T$1&T3,【1】定价因子!E:F,2,0) -> 0.87 | V3: =IF(COUNTIFS(户型资产表!E:E,I3,户型资产表!H:H,"操作台")>0,"有","无") -> 有 | W3: =IF(COUNTIFS(户型资产表!E:E,I3,户型资产表!H:H,"书桌")>0,"有","无") -> 有 | X3: {=IF(SUMPRODUCT((户型资产表!E:E=I3)*((户型资产表!I:I="沙发01单人")+(户型资产表!I:I="单人沙发02")))>0,"有","无")} -> 无 | Y3: {=IF(SUMPRODUCT((户型资产表!E:E=I3)*((户型资产表!I:I="沙发02两人")+(户型资产表!I:I="双人沙发01")))>0,"有","无")} -> 无 | Z3: =IF(COUNTIFS(户型资产表!E:E,I3,户型资产表!H:H,"餐桌")>0,"有","无") -> 无 | AA3: =IF(COUNTIFS(户型资产表!E:E,I3,户型资产表!H:H,"吸油烟机")>0,"有","无") -> 无 | AB3: =IF(COUNTIFS(户型资产表!E:E,I3,户型资产表!H:H,"冰箱")>0,"有","无") -> 无 | AC3: =IF(COUNTIFS(户型资产表!E:E,I3,户型资产表!H:H,"电视柜")>0,"有","无") -> 无 | AD3: =IF(J3="开间",IF(AND(V3="无",W3="无"),"缺失",IF(AND(V3="无",W3="有"),"缺失（操作台）",IF(AND(V3="有",W3="无"),"缺失（书桌）",IF(AND(V3="有",W3="有"),IF(OR(AA3="有",Y3="有"),"充足（油烟机/双人沙发）",IF(OR(X3="有",Z3="有"),"充足（单人沙发/餐桌）",IF(AND(OR(X3="有",Y3="有"),Z3="有"),"非常充足","适中"))),"")))),"适中") -> 适中 | AE3: =VLOOKUP($AD$1&AD3,【1】定价因子!E:F,2,0) -> 1 | AF3: =IF(J3="一居室",IF(AND(V3="无",Y3="无",Z3="无"),"缺失",IF(OR(AND(Z3="有",V3="无",Y3="无"),AND(Z3="有",V3="无",Y3="有"),AND(Z3="有",V3="有",Y3="无"),AND(Z3="无",V3="有",Y3="无"),AND(Z3="无",V3="无",Y3="有")),"缺失（操作台/双人沙发）",IF(AND(V3="有",Y3="有",Z3="无"),"缺失（餐桌）",IF(AND(V3="有",Y3="有",Z3="有"),IF(AND(W3="无",AA3="有"),"充配（油烟机）",IF(AND(W3="有",AA3="无"),"充配（书桌）",IF(AND(W3="有",AA3="有"),"非常充配","适中"))),"")))),"适中") -> 适中 | AG3: =VLOOKUP($AF$1&AF3,【1】定价因子!E:F,2,0) -> 1 | AH3: =IF(J3="二居室",IF(AND(Y3="无",Z3="无",AC3="无",V3="无"),"缺失",IF(OR(AND(Y3="无",Z3="无",AC3="有"),AND(Y3="无",Z3="无",V3="有"),AND(Y3="无",Z3="无",AC3="有",V3="有"),AND(Y3="无",Z3="有",AC3="无"),AND(Y3="无",Z3="有",V3="无"),AND(Y3="无",Z3="有",AC3="有"),AND(Y3="无",Z3="有",V3="有"),AND(Y3="有",Z3="无",AC3="无"),AND(Y3="有",Z3="无",V3="无"),AND(Y3="有",Z3="无",AC3="有"),AND(Y3="有",Z3="无",V3="有")),"缺失（沙发/餐桌）",IF(AND(Y3="有",Z3="有",OR(AC3="无",V3="无")),"缺失（电视柜/操作台）",IF(AND(Y3="有",Z3="有",AC3="有",V3="有"),IF(OR(AA3="有",AB3="有"),"充配（油烟机/冰箱）",IF(AND(AA3="无",AB3="无"),"适中","")),"")))),"适中") -> 适中 | AI3: =VLOOKUP($AH$1&AH3,【1】定价因子!E:F,2,0) -> 1 | AJ3: =VLOOKUP(H3,'【3-1】大区填-采光基本要素'!A:H,8,0) -> 1 | AK3: =VLOOKUP($AJ$1&AJ3,【1】定价因子!E:F,2,0) -> 0.91 | AL3: =L3*PRODUCT(AG3,AK3,AE3,U3,S3,Q3,O3) -> 1239.3941 | AM3: 1320 | AN3: =AM3/AL3-1 -> 0.065036569
A4: ='【2】运营中心填-基本信息&审核标准'!$E$2 -> 兴围西4-11栋 | B4: =INT(H4/100) -> 1 | C4: =COUNTIF($B$2:$B$72,B4) -> 7 | D4: =COUNTIF(C$2:C$72,C4) -> 7 | F4: =IF(D4=$E$2,C4,"") | H4: 103 | I4: B | J4: 开间 | K4: {=IFERROR(INDEX($J$2:$J$72,MATCH(0,IF(ISBLANK($J$2:$J$72),1,COUNTIF($K$1:K3,$J$2:$J$72)),0)),"")} | L4: =VLOOKUP(J4,'【3】大区填-楼栋基准格局定价'!B:H,7,0) -> 1647.8784 | M4: =IF(OR(J4="开间",J4="二人宿舍"),IF(N4<10,"很狭小",IF(N4<13,"较狭小",IF(N4<17,"适中",IF(N4<20,"较宽敞","很宽敞")))),IF(OR(J4="一居室",J4="四人宿舍"),IF(N4<20,"很狭小",IF(N4<23,"较狭小",IF(N4<26,"适中",IF(N4<28,"较宽敞","很宽敞")))),IF(OR(J4="二居室",J4="六人宿舍"),IF(N4<30,"很狭小",IF(N4<35,"较狭小",IF(N4<40,"适中",IF(N4<45,"较宽敞","很宽敞")))),""))) -> 适中 | N4: 15.69 | O4: =VLOOKUP($M$1&M4,【1】定价因子!E:F,2,0) -> 1 | P4: =IF(COUNTIFS(户型资产表!E:E,I4,户型资产表!H:H,"阳台门")>0,"有","无") -> 无 | Q4: =VLOOKUP($P$1&P4,【1】定价因子!E:F,2,0) -> 1 | R4: =IF('【2】运营中心填-基本信息&审核标准'!$D$4="是","无",IF(INT(H4/100)>9,"9F",INT(H4/100)&"F")) -> 无 | S4: =VLOOKUP(R4,【1】定价因子!D:F,3,0) -> 1 | T4: =IF('【2】运营中心填-基本信息&审核标准'!$D$4="否","无",IF(INT(H4/100)=1,"1F",IF(AND(INT(H4/100)>=2,INT(H4/100)<=3),"2-3F",IF(INT(H4/100)=4,"4F",IF(AND(INT(H4/100)>=5,INT(H4/100)<=6),"5-6F",IF(AND(INT(H4/100)>=7,INT(H4/100)<=8),"7-8F",IF(AND(INT(H4/100)>=9,INT(H4/100)<=10),"9-10F",IF(AND(INT(H4/100)>=11,INT(H4/100)<=12),"11-12F",IF(INT(H4/100)>=13,"13以上F",""))))))))) -> 1F | U4: =VLOOKUP($T$1&T4,【1】定价因子!E:F,2,0) -> 0.87 | V4: =IF(COUNTIFS(户型资产表!E:E,I4,户型资产表!H:H,"操作台")>0,"有","无") -> 有 | W4: =IF(COUNTIFS(户型资产表!E:E,I4,户型资产表!H:H,"书桌")>0,"有","无") -> 有 | X4: {=IF(SUMPRODUCT((户型资产表!E:E=I4)*((户型资产表!I:I="沙发01单人")+(户型资产表!I:I="单人沙发02")))>0,"有","无")} -> 无 | Y4: {=IF(SUMPRODUCT((户型资产表!E:E=I4)*((户型资产表!I:I="沙发02两人")+(户型资产表!I:I="双人沙发01")))>0,"有","无")} -> 无 | Z4: =IF(COUNTIFS(户型资产表!E:E,I4,户型资产表!H:H,"餐桌")>0,"有","无") -> 无 | AA4: =IF(COUNTIFS(户型资产表!E:E,I4,户型资产表!H:H,"吸油烟机")>0,"有","无") -> 无 | AB4: =IF(COUNTIFS(户型资产表!E:E,I4,户型资产表!H:H,"冰箱")>0,"有","无") -> 无 | AC4: =IF(COUNTIFS(户型资产表!E:E,I4,户型资产表!H:H,"电视柜")>0,"有","无") -> 无 | AD4: =IF(J4="开间",IF(AND(V4="无",W4="无"),"缺失",IF(AND(V4="无",W4="有"),"缺失（操作台）",IF(AND(V4="有",W4="无"),"缺失（书桌）",IF(AND(V4="有",W4="有"),IF(OR(AA4="有",Y4="有"),"充足（油烟机/双人沙发）",IF(OR(X4="有",Z4="有"),"充足（单人沙发/餐桌）",IF(AND(OR(X4="有",Y4="有"),Z4="有"),"非常充足","适中"))),"")))),"适中") -> 适中 | AE4: =VLOOKUP($AD$1&AD4,【1】定价因子!E:F,2,0) -> 1 | AF4: =IF(J4="一居室",IF(AND(V4="无",Y4="无",Z4="无"),"缺失",IF(OR(AND(Z4="有",V4="无",Y4="无"),AND(Z4="有",V4="无",Y4="有"),AND(Z4="有",V4="有",Y4="无"),AND(Z4="无",V4="有",Y4="无"),AND(Z4="无",V4="无",Y4="有")),"缺失（操作台/双人沙发）",IF(AND(V4="有",Y4="有",Z4="无"),"缺失（餐桌）",IF(AND(V4="有",Y4="有",Z4="有"),IF(AND(W4="无",AA4="有"),"充配（油烟机）",IF(AND(W4="有",AA4="无"),"充配（书桌）",IF(AND(W4="有",AA4="有"),"非常充配","适中"))),"")))),"适中") -> 适中 | AG4: =VLOOKUP($AF$1&AF4,【1】定价因子!E:F,2,0) -> 1 | AH4: =IF(J4="二居室",IF(AND(Y4="无",Z4="无",AC4="无",V4="无"),"缺失",IF(OR(AND(Y4="无",Z4="无",AC4="有"),AND(Y4="无",Z4="无",V4="有"),AND(Y4="无",Z4="无",AC4="有",V4="有"),AND(Y4="无",Z4="有",AC4="无"),AND(Y4="无",Z4="有",V4="无"),AND(Y4="无",Z4="有",AC4="有"),AND(Y4="无",Z4="有",V4="有"),AND(Y4="有",Z4="无",AC4="无"),AND(Y4="有",Z4="无",V4="无"),AND(Y4="有",Z4="无",AC4="有"),AND(Y4="有",Z4="无",V4="有")),"缺失（沙发/餐桌）",IF(AND(Y4="有",Z4="有",OR(AC4="无",V4="无")),"缺失（电视柜/操作台）",IF(AND(Y4="有",Z4="有",AC4="有",V4="有"),IF(OR(AA4="有",AB4="有"),"充配（油烟机/冰箱）",IF(AND(AA4="无",AB4="无"),"适中","")),"")))),"适中") -> 适中 | AI4: =VLOOKUP($AH$1&AH4,【1】定价因子!E:F,2,0) -> 1 | AJ4: =VLOOKUP(H4,'【3-1】大区填-采光基本要素'!A:H,8,0) -> 1 | AK4: =VLOOKUP($AJ$1&AJ4,【1】定价因子!E:F,2,0) -> 0.91 | AL4: =L4*PRODUCT(AG4,AK4,AE4,U4,S4,Q4,O4) -> 1304.6253 | AM4: 1380 | AN4: =AM4/AL4-1 -> 0.057774956
A5: ='【2】运营中心填-基本信息&审核标准'!$E$2 -> 兴围西4-11栋 | B5: =INT(H5/100) -> 1 | C5: =COUNTIF($B$2:$B$72,B5) -> 7 | D5: =COUNTIF(C$2:C$72,C5) -> 7 | F5: =IF(D5=$E$2,C5,"") | H5: 104 | I5: C | J5: 一居室 | K5: {=IFERROR(INDEX($J$2:$J$72,MATCH(0,IF(ISBLANK($J$2:$J$72),1,COUNTIF($K$1:K4,$J$2:$J$72)),0)),"")} | L5: =VLOOKUP(J5,'【3】大区填-楼栋基准格局定价'!B:H,7,0) -> 2445.5088 | M5: =IF(OR(J5="开间",J5="二人宿舍"),IF(N5<10,"很狭小",IF(N5<13,"较狭小",IF(N5<17,"适中",IF(N5<20,"较宽敞","很宽敞")))),IF(OR(J5="一居室",J5="四人宿舍"),IF(N5<20,"很狭小",IF(N5<23,"较狭小",IF(N5<26,"适中",IF(N5<28,"较宽敞","很宽敞")))),IF(OR(J5="二居室",J5="六人宿舍"),IF(N5<30,"很狭小",IF(N5<35,"较狭小",IF(N5<40,"适中",IF(N5<45,"较宽敞","很宽敞")))),""))) -> 很狭小 | N5: 18.95 | O5: =VLOOKUP($M$1&M5,【1】定价因子!E:F,2,0) -> 0.9 | P5: =IF(COUNTIFS(户型资产表!E:E,I5,户型资产表!H:H,"阳台门")>0,"有","无") -> 无 | Q5: =VLOOKUP($P$1&P5,【1】定价因子!E:F,2,0) -> 1 | R5: =IF('【2】运营中心填-基本信息&审核标准'!$D$4="是","无",IF(INT(H5/100)>9,"9F",INT(H5/100)&"F")) -> 无 | S5: =VLOOKUP(R5,【1】定价因子!D:F,3,0) -> 1 | T5: =IF('【2】运营中心填-基本信息&审核标准'!$D$4="否","无",IF(INT(H5/100)=1,"1F",IF(AND(INT(H5/100)>=2,INT(H5/100)<=3),"2-3F",IF(INT(H5/100)=4,"4F",IF(AND(INT(H5/100)>=5,INT(H5/100)<=6),"5-6F",IF(AND(INT(H5/100)>=7,INT(H5/100)<=8),"7-8F",IF(AND(INT(H5/100)>=9,INT(H5/100)<=10),"9-10F",IF(AND(INT(H5/100)>=11,INT(H5/100)<=12),"11-12F",IF(INT(H5/100)>=13,"13以上F",""))))))))) -> 1F | U5: =VLOOKUP($T$1&T5,【1】定价因子!E:F,2,0) -> 0.87 | V5: =IF(COUNTIFS(户型资产表!E:E,I5,户型资产表!H:H,"操作台")>0,"有","无") -> 有 | W5: =IF(COUNTIFS(户型资产表!E:E,I5,户型资产表!H:H,"书桌")>0,"有","无") -> 无 | X5: {=IF(SUMPRODUCT((户型资产表!E:E=I5)*((户型资产表!I:I="沙发01单人")+(户型资产表!I:I="单人沙发02")))>0,"有","无")} -> 无 | Y5: {=IF(SUMPRODUCT((户型资产表!E:E=I5)*((户型资产表!I:I="沙发02两人")+(户型资产表!I:I="双人沙发01")))>0,"有","无")} -> 无 | Z5: =IF(COUNTIFS(户型资产表!E:E,I5,户型资产表!H:H,"餐桌")>0,"有","无") -> 无 | AA5: =IF(COUNTIFS(户型资产表!E:E,I5,户型资产表!H:H,"吸油烟机")>0,"有","无") -> 无 | AB5: =IF(COUNTIFS(户型资产表!E:E,I5,户型资产表!H:H,"冰箱")>0,"有","无") -> 无 | AC5: =IF(COUNTIFS(户型资产表!E:E,I5,户型资产表!H:H,"电视柜")>0,"有","无") -> 无 | AD5: =IF(J5="开间",IF(AND(V5="无",W5="无"),"缺失",IF(AND(V5="无",W5="有"),"缺失（操作台）",IF(AND(V5="有",W5="无"),"缺失（书桌）",IF(AND(V5="有",W5="有"),IF(OR(AA5="有",Y5="有"),"充足（油烟机/双人沙发）",IF(OR(X5="有",Z5="有"),"充足（单人沙发/餐桌）",IF(AND(OR(X5="有",Y5="有"),Z5="有"),"非常充足","适中"))),"")))),"适中") -> 适中 | AE5: =VLOOKUP($AD$1&AD5,【1】定价因子!E:F,2,0) -> 1 | AF5: 适中 | AG5: =VLOOKUP($AF$1&AF5,【1】定价因子!E:F,2,0) -> 1 | AH5: =IF(J5="二居室",IF(AND(Y5="无",Z5="无",AC5="无",V5="无"),"缺失",IF(OR(AND(Y5="无",Z5="无",AC5="有"),AND(Y5="无",Z5="无",V5="有"),AND(Y5="无",Z5="无",AC5="有",V5="有"),AND(Y5="无",Z5="有",AC5="无"),AND(Y5="无",Z5="有",V5="无"),AND(Y5="无",Z5="有",AC5="有"),AND(Y5="无",Z5="有",V5="有"),AND(Y5="有",Z5="无",AC5="无"),AND(Y5="有",Z5="无",V5="无"),AND(Y5="有",Z5="无",AC5="有"),AND(Y5="有",Z5="无",V5="有")),"缺失（沙发/餐桌）",IF(AND(Y5="有",Z5="有",OR(AC5="无",V5="无")),"缺失（电视柜/操作台）",IF(AND(Y5="有",Z5="有",AC5="有",V5="有"),IF(OR(AA5="有",AB5="有"),"充配（油烟机/冰箱）",IF(AND(AA5="无",AB5="无"),"适中","")),"")))),"适中") -> 适中 | AI5: =VLOOKUP($AH$1&AH5,【1】定价因子!E:F,2,0) -> 1 | AJ5: =VLOOKUP(H5,'【3-1】大区填-采光基本要素'!A:H,8,0) -> 1 | AK5: =VLOOKUP($AJ$1&AJ5,【1】定价因子!E:F,2,0) -> 0.91 | AL5: =L5*PRODUCT(AG5,AK5,AE5,U5,S5,Q5,O5) -> 1742.4984 | AM5: 1700 | AN5: =AM5/AL5-1 -> -0.02438934
A6: ='【2】运营中心填-基本信息&审核标准'!$E$2 -> 兴围西4-11栋 | B6: =INT(H6/100) -> 1 | C6: =COUNTIF($B$2:$B$72,B6) -> 7 | D6: =COUNTIF(C$2:C$72,C6) -> 7 | F6: =IF(D6=$E$2,C6,"") | H6: 105 | I6: D | J6: 开间 | K6: {=IFERROR(INDEX($J$2:$J$72,MATCH(0,IF(ISBLANK($J$2:$J$72),1,COUNTIF($K$1:K5,$J$2:$J$72)),0)),"")} | L6: =VLOOKUP(J6,'【3】大区填-楼栋基准格局定价'!B:H,7,0) -> 1647.8784 | M6: =IF(OR(J6="开间",J6="二人宿舍"),IF(N6<10,"很狭小",IF(N6<13,"较狭小",IF(N6<17,"适中",IF(N6<20,"较宽敞","很宽敞")))),IF(OR(J6="一居室",J6="四人宿舍"),IF(N6<20,"很狭小",IF(N6<23,"较狭小",IF(N6<26,"适中",IF(N6<28,"较宽敞","很宽敞")))),IF(OR(J6="二居室",J6="六人宿舍"),IF(N6<30,"很狭小",IF(N6<35,"较狭小",IF(N6<40,"适中",IF(N6<45,"较宽敞","很宽敞")))),""))) -> 适中 | N6: 15.52 | O6: =VLOOKUP($M$1&M6,【1】定价因子!E:F,2,0) -> 1 | P6: =IF(COUNTIFS(户型资产表!E:E,I6,户型资产表!H:H,"阳台门")>0,"有","无") -> 无 | Q6: =VLOOKUP($P$1&P6,【1】定价因子!E:F,2,0) -> 1 | R6: =IF('【2】运营中心填-基本信息&审核标准'!$D$4="是","无",IF(INT(H6/100)>9,"9F",INT(H6/100)&"F")) -> 无 | S6: =VLOOKUP(R6,【1】定价因子!D:F,3,0) -> 1 | T6: =IF('【2】运营中心填-基本信息&审核标准'!$D$4="否","无",IF(INT(H6/100)=1,"1F",IF(AND(INT(H6/100)>=2,INT(H6/100)<=3),"2-3F",IF(INT(H6/100)=4,"4F",IF(AND(INT(H6/100)>=5,INT(H6/100)<=6),"5-6F",IF(AND(INT(H6/100)>=7,INT(H6/100)<=8),"7-8F",IF(AND(INT(H6/100)>=9,INT(H6/100)<=10),"9-10F",IF(AND(INT(H6/100)>=11,INT(H6/100)<=12),"11-12F",IF(INT(H6/100)>=13,"13以上F",""))))))))) -> 1F | U6: =VLOOKUP($T$1&T6,【1】定价因子!E:F,2,0) -> 0.87 | V6: =IF(COUNTIFS(户型资产表!E:E,I6,户型资产表!H:H,"操作台")>0,"有","无") -> 有 | W6: =IF(COUNTIFS(户型资产表!E:E,I6,户型资产表!H:H,"书桌")>0,"有","无") -> 有 | X6: {=IF(SUMPRODUCT((户型资产表!E:E=I6)*((户型资产表!I:I="沙发01单人")+(户型资产表!I:I="单人沙发02")))>0,"有","无")} -> 无 | Y6: {=IF(SUMPRODUCT((户型资产表!E:E=I6)*((户型资产表!I:I="沙发02两人")+(户型资产表!I:I="双人沙发01")))>0,"有","无")} -> 无 | Z6: =IF(COUNTIFS(户型资产表!E:E,I6,户型资产表!H:H,"餐桌")>0,"有","无") -> 无 | AA6: =IF(COUNTIFS(户型资产表!E:E,I6,户型资产表!H:H,"吸油烟机")>0,"有","无") -> 无 | AB6: =IF(COUNTIFS(户型资产表!E:E,I6,户型资产表!H:H,"冰箱")>0,"有","无") -> 无 | AC6: =IF(COUNTIFS(户型资产表!E:E,I6,户型资产表!H:H,"电视柜")>0,"有","无") -> 无 | AD6: =IF(J6="开间",IF(AND(V6="无",W6="无"),"缺失",IF(AND(V6="无",W6="有"),"缺失（操作台）",IF(AND(V6="有",W6="无"),"缺失（书桌）",IF(AND(V6="有",W6="有"),IF(OR(AA6="有",Y6="有"),"充足（油烟机/双人沙发）",IF(OR(X6="有",Z6="有"),"充足（单人沙发/餐桌）",IF(AND(OR(X6="有",Y6="有"),Z6="有"),"非常充足","适中"))),"")))),"适中") -> 适中 | AE6: =VLOOKUP($AD$1&AD6,【1】定价因子!E:F,2,0) -> 1 | AF6: =IF(J6="一居室",IF(AND(V6="无",Y6="无",Z6="无"),"缺失",IF(OR(AND(Z6="有",V6="无",Y6="无"),AND(Z6="有",V6="无",Y6="有"),AND(Z6="有",V6="有",Y6="无"),AND(Z6="无",V6="有",Y6="无"),AND(Z6="无",V6="无",Y6="有")),"缺失（操作台/双人沙发）",IF(AND(V6="有",Y6="有",Z6="无"),"缺失（餐桌）",IF(AND(V6="有",Y6="有",Z6="有"),IF(AND(W6="无",AA6="有"),"充配（油烟机）",IF(AND(W6="有",AA6="无"),"充配（书桌）",IF(AND(W6="有",AA6="有"),"非常充配","适中"))),"")))),"适中") -> 适中 | AG6: =VLOOKUP($AF$1&AF6,【1】定价因子!E:F,2,0) -> 1 | AH6: =IF(J6="二居室",IF(AND(Y6="无",Z6="无",AC6="无",V6="无"),"缺失",IF(OR(AND(Y6="无",Z6="无",AC6="有"),AND(Y6="无",Z6="无",V6="有"),AND(Y6="无",Z6="无",AC6="有",V6="有"),AND(Y6="无",Z6="有",AC6="无"),AND(Y6="无",Z6="有",V6="无"),AND(Y6="无",Z6="有",AC6="有"),AND(Y6="无",Z6="有",V6="有"),AND(Y6="有",Z6="无",AC6="无"),AND(Y6="有",Z6="无",V6="无"),AND(Y6="有",Z6="无",AC6="有"),AND(Y6="有",Z6="无",V6="有")),"缺失（沙发/餐桌）",IF(AND(Y6="有",Z6="有",OR(AC6="无",V6="无")),"缺失（电视柜/操作台）",IF(AND(Y6="有",Z6="有",AC6="有",V6="有"),IF(OR(AA6="有",AB6="有"),"充配（油烟机/冰箱）",IF(AND(AA6="无",AB6="无"),"适中","")),"")))),"适中") -> 适中 | AI6: =VLOOKUP($AH$1&AH6,【1】定价因子!E:F,2,0) -> 1 | AJ6: =VLOOKUP(H6,'【3-1】大区填-采光基本要素'!A:H,8,0) -> 1 | AK6: =VLOOKUP($AJ$1&AJ6,【1】定价因子!E:F,2,0) -> 0.91 | AL6: =L6*PRODUCT(AG6,AK6,AE6,U6,S6,Q6,O6) -> 1304.6253 | AM6: 1280 | AN6: =AM6/AL6-1 -> -0.018875403
A7: ='【2】运营中心填-基本信息&审核标准'!$E$2 -> 兴围西4-11栋 | B7: =INT(H7/100) -> 1 | C7: =COUNTIF($B$2:$B$72,B7) -> 7 | D7: =COUNTIF(C$2:C$72,C7) -> 7 | F7: =IF(D7=$E$2,C7,"") | H7: 106 | I7: E | J7: 开间 | K7: {=IFERROR(INDEX($J$2:$J$72,MATCH(0,IF(ISBLANK($J$2:$J$72),1,COUNTIF($K$1:K6,$J$2:$J$72)),0)),"")} | L7: =VLOOKUP(J7,'【3】大区填-楼栋基准格局定价'!B:H,7,0) -> 1647.8784 | M7: =IF(OR(J7="开间",J7="二人宿舍"),IF(N7<10,"很狭小",IF(N7<13,"较狭小",IF(N7<17,"适中",IF(N7<20,"较宽敞","很宽敞")))),IF(OR(J7="一居室",J7="四人宿舍"),IF(N7<20,"很狭小",IF(N7<23,"较狭小",IF(N7<26,"适中",IF(N7<28,"较宽敞","很宽敞")))),IF(OR(J7="二居室",J7="六人宿舍"),IF(N7<30,"很狭小",IF(N7<35,"较狭小",IF(N7<40,"适中",IF(N7<45,"较宽敞","很宽敞")))),""))) -> 较狭小 | N7: 12.03 | O7: =VLOOKUP($M$1&M7,【1】定价因子!E:F,2,0) -> 0.95 | P7: =IF(COUNTIFS(户型资产表!E:E,I7,户型资产表!H:H,"阳台门")>0,"有","无") -> 无 | Q7: =VLOOKUP($P$1&P7,【1】定价因子!E:F,2,0) -> 1 | R7: =IF('【2】运营中心填-基本信息&审核标准'!$D$4="是","无",IF(INT(H7/100)>9,"9F",INT(H7/100)&"F")) -> 无 | S7: =VLOOKUP(R7,【1】定价因子!D:F,3,0) -> 1 | T7: =IF('【2】运营中心填-基本信息&审核标准'!$D$4="否","无",IF(INT(H7/100)=1,"1F",IF(AND(INT(H7/100)>=2,INT(H7/100)<=3),"2-3F",IF(INT(H7/100)=4,"4F",IF(AND(INT(H7/100)>=5,INT(H7/100)<=6),"5-6F",IF(AND(INT(H7/100)>=7,INT(H7/100)<=8),"7-8F",IF(AND(INT(H7/100)>=9,INT(H7/100)<=10),"9-10F",IF(AND(INT(H7/100)>=11,INT(H7/100)<=12),"11-12F",IF(INT(H7/100)>=13,"13以上F",""))))))))) -> 1F | U7: =VLOOKUP($T$1&T7,【1】定价因子!E:F,2,0) -> 0.87 | V7: =IF(COUNTIFS(户型资产表!E:E,I7,户型资产表!H:H,"操作台")>0,"有","无") -> 有 | W7: =IF(COUNTIFS(户型资产表!E:E,I7,户型资产表!H:H,"书桌")>0,"有","无") -> 有 | X7: {=IF(SUMPRODUCT((户型资产表!E:E=I7)*((户型资产表!I:I="沙发01单人")+(户型资产表!I:I="单人沙发02")))>0,"有","无")} -> 无 | Y7: {=IF(SUMPRODUCT((户型资产表!E:E=I7)*((户型资产表!I:I="沙发02两人")+(户型资产表!I:I="双人沙发01")))>0,"有","无")} -> 无 | Z7: =IF(COUNTIFS(户型资产表!E:E,I7,户型资产表!H:H,"餐桌")>0,"有","无") -> 无 | AA7: =IF(COUNTIFS(户型资产表!E:E,I7,户型资产表!H:H,"吸油烟机")>0,"有","无") -> 无 | AB7: =IF(COUNTIFS(户型资产表!E:E,I7,户型资产表!H:H,"冰箱")>0,"有","无") -> 无 | AC7: =IF(COUNTIFS(户型资产表!E:E,I7,户型资产表!H:H,"电视柜")>0,"有","无") -> 无 | AD7: =IF(J7="开间",IF(AND(V7="无",W7="无"),"缺失",IF(AND(V7="无",W7="有"),"缺失（操作台）",IF(AND(V7="有",W7="无"),"缺失（书桌）",IF(AND(V7="有",W7="有"),IF(OR(AA7="有",Y7="有"),"充足（油烟机/双人沙发）",IF(OR(X7="有",Z7="有"),"充足（单人沙发/餐桌）",IF(AND(OR(X7="有",Y7="有"),Z7="有"),"非常充足","适中"))),"")))),"适中") -> 适中 | AE7: =VLOOKUP($AD$1&AD7,【1】定价因子!E:F,2,0) -> 1 | AF7: =IF(J7="一居室",IF(AND(V7="无",Y7="无",Z7="无"),"缺失",IF(OR(AND(Z7="有",V7="无",Y7="无"),AND(Z7="有",V7="无",Y7="有"),AND(Z7="有",V7="有",Y7="无"),AND(Z7="无",V7="有",Y7="无"),AND(Z7="无",V7="无",Y7="有")),"缺失（操作台/双人沙发）",IF(AND(V7="有",Y7="有",Z7="无"),"缺失（餐桌）",IF(AND(V7="有",Y7="有",Z7="有"),IF(AND(W7="无",AA7="有"),"充配（油烟机）",IF(AND(W7="有",AA7="无"),"充配（书桌）",IF(AND(W7="有",AA7="有"),"非常充配","适中"))),"")))),"适中") -> 适中 | AG7: =VLOOKUP($AF$1&AF7,【1】定价因子!E:F,2,0) -> 1 | AH7: =IF(J7="二居室",IF(AND(Y7="无",Z7="无",AC7="无",V7="无"),"缺失",IF(OR(AND(Y7="无",Z7="无",AC7="有"),AND(Y7="无",Z7="无",V7="有"),AND(Y7="无",Z7="无",AC7="有",V7="有"),AND(Y7="无",Z7="有",AC7="无"),AND(Y7="无",Z7="有",V7="无"),AND(Y7="无",Z7="有",AC7="有"),AND(Y7="无",Z7="有",V7="有"),AND(Y7="有",Z7="无",AC7="无"),AND(Y7="有",Z7="无",V7="无"),AND(Y7="有",Z7="无",AC7="有"),AND(Y7="有",Z7="无",V7="有")),"缺失（沙发/餐桌）",IF(AND(Y7="有",Z7="有",OR(AC7="无",V7="无")),"缺失（电视柜/操作台）",IF(AND(Y7="有",Z7="有",AC7="有",V7="有"),IF(OR(AA7="有",AB7="有"),"充配（油烟机/冰箱）",IF(AND(AA7="无",AB7="无"),"适中","")),"")))),"适中") -> 适中 | AI7: =VLOOKUP($AH$1&AH7,【1】定价因子!E:F,2,0) -> 1 | AJ7: =VLOOKUP(H7,'【3-1】大区填-采光基本要素'!A:H,8,0) -> 2 | AK7: =VLOOKUP($AJ$1&AJ7,【1】定价因子!E:F,2,0) -> 0.96 | AL7: =L7*PRODUCT(AG7,AK7,AE7,U7,S7,Q7,O7) -> 1307.4926 | AM7: 1380 | AN7: =AM7/AL7-1 -> 0.055455274
A8: ='【2】运营中心填-基本信息&审核标准'!$E$2 -> 兴围西4-11栋 | B8: =INT(H8/100) -> 1 | C8: =COUNTIF($B$2:$B$72,B8) -> 7 | D8: =COUNTIF(C$2:C$72,C8) -> 7 | F8: =IF(D8=$E$2,C8,"") | H8: 107 | I8: F | J8: 开间 | K8: {=IFERROR(INDEX($J$2:$J$72,MATCH(0,IF(ISBLANK($J$2:$J$72),1,COUNTIF($K$1:K7,$J$2:$J$72)),0)),"")} | L8: =VLOOKUP(J8,'【3】大区填-楼栋基准格局定价'!B:H,7,0) -> 1647.8784 | M8: =IF(OR(J8="开间",J8="二人宿舍"),IF(N8<10,"很狭小",IF(N8<13,"较狭小",IF(N8<17,"适中",IF(N8<20,"较宽敞","很宽敞")))),IF(OR(J8="一居室",J8="四人宿舍"),IF(N8<20,"很狭小",IF(N8<23,"较狭小",IF(N8<26,"适中",IF(N8<28,"较宽敞","很宽敞")))),IF(OR(J8="二居室",J8="六人宿舍"),IF(N8<30,"很狭小",IF(N8<35,"较狭小",IF(N8<40,"适中",IF(N8<45,"较宽敞","很宽敞")))),""))) -> 适中 | N8: 14.29 | O8: =VLOOKUP($M$1&M8,【1】定价因子!E:F,2,0) -> 1 | P8: =IF(COUNTIFS(户型资产表!E:E,I8,户型资产表!H:H,"阳台门")>0,"有","无") -> 无 | Q8: =VLOOKUP($P$1&P8,【1】定价因子!E:F,2,0) -> 1 | R8: =IF('【2】运营中心填-基本信息&审核标准'!$D$4="是","无",IF(INT(H8/100)>9,"9F",INT(H8/100)&"F")) -> 无 | S8: =VLOOKUP(R8,【1】定价因子!D:F,3,0) -> 1 | T8: =IF('【2】运营中心填-基本信息&审核标准'!$D$4="否","无",IF(INT(H8/100)=1,"1F",IF(AND(INT(H8/100)>=2,INT(H8/100)<=3),"2-3F",IF(INT(H8/100)=4,"4F",IF(AND(INT(H8/100)>=5,INT(H8/100)<=6),"5-6F",IF(AND(INT(H8/100)>=7,INT(H8/100)<=8),"7-8F",IF(AND(INT(H8/100)>=9,INT(H8/100)<=10),"9-10F",IF(AND(INT(H8/100)>=11,INT(H8/100)<=12),"11-12F",IF(INT(H8/100)>=13,"13以上F",""))))))))) -> 1F | U8: =VLOOKUP($T$1&T8,【1】定价因子!E:F,2,0) -> 0.87 | V8: =IF(COUNTIFS(户型资产表!E:E,I8,户型资产表!H:H,"操作台")>0,"有","无") -> 有 | W8: =IF(COUNTIFS(户型资产表!E:E,I8,户型资产表!H:H,"书桌")>0,"有","无") -> 有 | X8: {=IF(SUMPRODUCT((户型资产表!E:E=I8)*((户型资产表!I:I="沙发01单人")+(户型资产表!I:I="单人沙发02")))>0,"有","无")} -> 无 | Y8: {=IF(SUMPRODUCT((户型资产表!E:E=I8)*((户型资产表!I:I="沙发02两人")+(户型资产表!I:I="双人沙发01")))>0,"有","无")} -> 无 | Z8: =IF(COUNTIFS(户型资产表!E:E,I8,户型资产表!H:H,"餐桌")>0,"有","无") -> 无 | AA8: =IF(COUNTIFS(户型资产表!E:E,I8,户型资产表!H:H,"吸油烟机")>0,"有","无") -> 无 | AB8: =IF(COUNTIFS(户型资产表!E:E,I8,户型资产表!H:H,"冰箱")>0,"有","无") -> 无 | AC8: =IF(COUNTIFS(户型资产表!E:E,I8,户型资产表!H:H,"电视柜")>0,"有","无") -> 无 | AD8: =IF(J8="开间",IF(AND(V8="无",W8="无"),"缺失",IF(AND(V8="无",W8="有"),"缺失（操作台）",IF(AND(V8="有",W8="无"),"缺失（书桌）",IF(AND(V8="有",W8="有"),IF(OR(AA8="有",Y8="有"),"充足（油烟机/双人沙发）",IF(OR(X8="有",Z8="有"),"充足（单人沙发/餐桌）",IF(AND(OR(X8="有",Y8="有"),Z8="有"),"非常充足","适中"))),"")))),"适中") -> 适中 | AE8: =VLOOKUP($AD$1&AD8,【1】定价因子!E:F,2,0) -> 1 | AF8: =IF(J8="一居室",IF(AND(V8="无",Y8="无",Z8="无"),"缺失",IF(OR(AND(Z8="有",V8="无",Y8="无"),AND(Z8="有",V8="无",Y8="有"),AND(Z8="有",V8="有",Y8="无"),AND(Z8="无",V8="有",Y8="无"),AND(Z8="无",V8="无",Y8="有")),"缺失（操作台/双人沙发）",IF(AND(V8="有",Y8="有",Z8="无"),"缺失（餐桌）",IF(AND(V8="有",Y8="有",Z8="有"),IF(AND(W8="无",AA8="有"),"充配（油烟机）",IF(AND(W8="有",AA8="无"),"充配（书桌）",IF(AND(W8="有",AA8="有"),"非常充配","适中"))),"")))),"适中") -> 适中 | AG8: =VLOOKUP($AF$1&AF8,【1】定价因子!E:F,2,0) -> 1 | AH8: =IF(J8="二居室",IF(AND(Y8="无",Z8="无",AC8="无",V8="无"),"缺失",IF(OR(AND(Y8="无",Z8="无",AC8="有"),AND(Y8="无",Z8="无",V8="有"),AND(Y8="无",Z8="无",AC8="有",V8="有"),AND(Y8="无",Z8="有",AC8="无"),AND(Y8="无",Z8="有",V8="无"),AND(Y8="无",Z8="有",AC8="有"),AND(Y8="无",Z8="有",V8="有"),AND(Y8="有",Z8="无",AC8="无"),AND(Y8="有",Z8="无",V8="无"),AND(Y8="有",Z8="无",AC8="有"),AND(Y8="有",Z8="无",V8="有")),"缺失（沙发/餐桌）",IF(AND(Y8="有",Z8="有",OR(AC8="无",V8="无")),"缺失（电视柜/操作台）",IF(AND(Y8="有",Z8="有",AC8="有",V8="有"),IF(OR(AA8="有",AB8="有"),"充配（油烟机/冰箱）",IF(AND(AA8="无",AB8="无"),"适中","")),"")))),"适中") -> 适中 | AI8: =VLOOKUP($AH$1&AH8,【1】定价因子!E:F,2,0) -> 1 | AJ8: =VLOOKUP(H8,'【3-1】大区填-采光基本要素'!A:H,8,0) -> 1 | AK8: =VLOOKUP($AJ$1&AJ8,【1】定价因子!E:F,2,0) -> 0.91 | AL8: =L8*PRODUCT(AG8,AK8,AE8,U8,S8,Q8,O8) -> 1304.6253 | AM8: 1380 | AN8: =AM8/AL8-1 -> 0.057774956
A9: ='【2】运营中心填-基本信息&审核标准'!$E$2 -> 兴围西4-11栋 | B9: =INT(H9/100) -> 2 | C9: =COUNTIF($B$2:$B$72,B9) -> 8 | D9: =COUNTIF(C$2:C$72,C9) -> 64 | F9: =IF(D9=$E$2,C9,"") -> 8 | H9: 201 | I9: G | J9: 开间 | K9: {=IFERROR(INDEX($J$2:$J$72,MATCH(0,IF(ISBLANK($J$2:$J$72),1,COUNTIF($K$1:K8,$J$2:$J$72)),0)),"")} | L9: =VLOOKUP(J9,'【3】大区填-楼栋基准格局定价'!B:H,7,0) -> 1647.8784 | M9: =IF(OR(J9="开间",J9="二人宿舍"),IF(N9<10,"很狭小",IF(N9<13,"较狭小",IF(N9<17,"适中",IF(N9<20,"较宽敞","很宽敞")))),IF(OR(J9="一居室",J9="四人宿舍"),IF(N9<20,"很狭小",IF(N9<23,"较狭小",IF(N9<26,"适中",IF(N9<28,"较宽敞","很宽敞")))),IF(OR(J9="二居室",J9="六人宿舍"),IF(N9<30,"很狭小",IF(N9<35,"较狭小",IF(N9<40,"适中",IF(N9<45,"较宽敞","很宽敞")))),""))) -> 较狭小 | N9: 10.46 | O9: =VLOOKUP($M$1&M9,【1】定价因子!E:F,2,0) -> 0.95 | P9: =IF(COUNTIFS(户型资产表!E:E,I9,户型资产表!H:H,"阳台门")>0,"有","无") -> 无 | Q9: =VLOOKUP($P$1&P9,【1】定价因子!E:F,2,0) -> 1 | R9: =IF('【2】运营中心填-基本信息&审核标准'!$D$4="是","无",IF(INT(H9/100)>9,"9F",INT(H9/100)&"F")) -> 无 | S9: =VLOOKUP(R9,【1】定价因子!D:F,3,0) -> 1 | T9: =IF('【2】运营中心填-基本信息&审核标准'!$D$4="否","无",IF(INT(H9/100)=1,"1F",IF(AND(INT(H9/100)>=2,INT(H9/100)<=3),"2-3F",IF(INT(H9/100)=4,"4F",IF(AND(INT(H9/100)>=5,INT(H9/100)<=6),"5-6F",IF(AND(INT(H9/100)>=7,INT(H9/100)<=8),"7-8F",IF(AND(INT(H9/100)>=9,INT(H9/100)<=10),"9-10F",IF(AND(INT(H9/100)>=11,INT(H9/100)<=12),"11-12F",IF(INT(H9/100)>=13,"13以上F",""))))))))) -> 2-3F | U9: =VLOOKUP($T$1&T9,【1】定价因子!E:F,2,0) -> 0.99 | V9: =IF(COUNTIFS(户型资产表!E:E,I9,户型资产表!H:H,"操作台")>0,"有","无") -> 有 | W9: =IF(COUNTIFS(户型资产表!E:E,I9,户型资产表!H:H,"书桌")>0,"有","无") -> 有 | X9: {=IF(SUMPRODUCT((户型资产表!E:E=I9)*((户型资产表!I:I="沙发01单人")+(户型资产表!I:I="单人沙发02")))>0,"有","无")} -> 无 | Y9: {=IF(SUMPRODUCT((户型资产表!E:E=I9)*((户型资产表!I:I="沙发02两人")+(户型资产表!I:I="双人沙发01")))>0,"有","无")} -> 无 | Z9: =IF(COUNTIFS(户型资产表!E:E,I9,户型资产表!H:H,"餐桌")>0,"有","无") -> 无 | AA9: =IF(COUNTIFS(户型资产表!E:E,I9,户型资产表!H:H,"吸油烟机")>0,"有","无") -> 无 | AB9: =IF(COUNTIFS(户型资产表!E:E,I9,户型资产表!H:H,"冰箱")>0,"有","无") -> 无 | AC9: =IF(COUNTIFS(户型资产表!E:E,I9,户型资产表!H:H,"电视柜")>0,"有","无") -> 无 | AD9: =IF(J9="开间",IF(AND(V9="无",W9="无"),"缺失",IF(AND(V9="无",W9="有"),"缺失（操作台）",IF(AND(V9="有",W9="无"),"缺失（书桌）",IF(AND(V9="有",W9="有"),IF(OR(AA9="有",Y9="有"),"充足（油烟机/双人沙发）",IF(OR(X9="有",Z9="有"),"充足（单人沙发/餐桌）",IF(AND(OR(X9="有",Y9="有"),Z9="有"),"非常充足","适中"))),"")))),"适中") -> 适中 | AE9: =VLOOKUP($AD$1&AD9,【1】定价因子!E:F,2,0) -> 1 | AF9: =IF(J9="一居室",IF(AND(V9="无",Y9="无",Z9="无"),"缺失",IF(OR(AND(Z9="有",V9="无",Y9="无"),AND(Z9="有",V9="无",Y9="有"),AND(Z9="有",V9="有",Y9="无"),AND(Z9="无",V9="有",Y9="无"),AND(Z9="无",V9="无",Y9="有")),"缺失（操作台/双人沙发）",IF(AND(V9="有",Y9="有",Z9="无"),"缺失（餐桌）",IF(AND(V9="有",Y9="有",Z9="有"),IF(AND(W9="无",AA9="有"),"充配（油烟机）",IF(AND(W9="有",AA9="无"),"充配（书桌）",IF(AND(W9="有",AA9="有"),"非常充配","适中"))),"")))),"适中") -> 适中 | AG9: =VLOOKUP($AF$1&AF9,【1】定价因子!E:F,2,0) -> 1 | AH9: =IF(J9="二居室",IF(AND(Y9="无",Z9="无",AC9="无",V9="无"),"缺失",IF(OR(AND(Y9="无",Z9="无",AC9="有"),AND(Y9="无",Z9="无",V9="有"),AND(Y9="无",Z9="无",AC9="有",V9="有"),AND(Y9="无",Z9="有",AC9="无"),AND(Y9="无",Z9="有",V9="无"),AND(Y9="无",Z9="有",AC9="有"),AND(Y9="无",Z9="有",V9="有"),AND(Y9="有",Z9="无",AC9="无"),AND(Y9="有",Z9="无",V9="无"),AND(Y9="有",Z9="无",AC9="有"),AND(Y9="有",Z9="无",V9="有")),"缺失（沙发/餐桌）",IF(AND(Y9="有",Z9="有",OR(AC9="无",V9="无")),"缺失（电视柜/操作台）",IF(AND(Y9="有",Z9="有",AC9="有",V9="有"),IF(OR(AA9="有",AB9="有"),"充配（油烟机/冰箱）",IF(AND(AA9="无",AB9="无"),"适中","")),"")))),"适中") -> 适中 | AI9: =VLOOKUP($AH$1&AH9,【1】定价因子!E:F,2,0) -> 1 | AJ9: =VLOOKUP(H9,'【3-1】大区填-采光基本要素'!A:H,8,0) -> 5 | AK9: =VLOOKUP($AJ$1&AJ9,【1】定价因子!E:F,2,0) -> 1.06 | AL9: =L9*PRODUCT(AG9,AK9,AE9,U9,S9,Q9,O9) -> 1642.8194 | AM9: 1500 | AN9: =AM9/AL9-1 -> -0.086935552
A10: ='【2】运营中心填-基本信息&审核标准'!$E$2 -> 兴围西4-11栋 | B10: =INT(H10/100) -> 2 | C10: =COUNTIF($B$2:$B$72,B10) -> 8 | D10: =COUNTIF(C$2:C$72,C10) -> 64 | F10: =IF(D10=$E$2,C10,"") -> 8 | H10: 202 | I10: H | J10: 一居室 | K10: {=IFERROR(INDEX($J$2:$J$72,MATCH(0,IF(ISBLANK($J$2:$J$72),1,COUNTIF($K$1:K9,$J$2:$J$72)),0)),"")} | L10: =VLOOKUP(J10,'【3】大区填-楼栋基准格局定价'!B:H,7,0) -> 2445.5088 | M10: =IF(OR(J10="开间",J10="二人宿舍"),IF(N10<10,"很狭小",IF(N10<13,"较狭小",IF(N10<17,"适中",IF(N10<20,"较宽敞","很宽敞")))),IF(OR(J10="一居室",J10="四人宿舍"),IF(N10<20,"很狭小",IF(N10<23,"较狭小",IF(N10<26,"适中",IF(N10<28,"较宽敞","很宽敞")))),IF(OR(J10="二居室",J10="六人宿舍"),IF(N10<30,"很狭小",IF(N10<35,"较狭小",IF(N10<40,"适中",IF(N10<45,"较宽敞","很宽敞")))),""))) -> 很狭小 | N10: 18.44 | O10: =VLOOKUP($M$1&M10,【1】定价因子!E:F,2,0) -> 0.9 | P10: =IF(COUNTIFS(户型资产表!E:E,I10,户型资产表!H:H,"阳台门")>0,"有","无") -> 无 | Q10: =VLOOKUP($P$1&P10,【1】定价因子!E:F,2,0) -> 1 | R10: =IF('【2】运营中心填-基本信息&审核标准'!$D$4="是","无",IF(INT(H10/100)>9,"9F",INT(H10/100)&"F")) -> 无 | S10: =VLOOKUP(R10,【1】定价因子!D:F,3,0) -> 1 | T10: =IF('【2】运营中心填-基本信息&审核标准'!$D$4="否","无",IF(INT(H10/100)=1,"1F",IF(AND(INT(H10/100)>=2,INT(H10/100)<=3),"2-3F",IF(INT(H10/100)=4,"4F",IF(AND(INT(H10/100)>=5,INT(H10/100)<=6),"5-6F",IF(AND(INT(H10/100)>=7,INT(H10/100)<=8),"7-8F",IF(AND(INT(H10/100)>=9,INT(H10/100)<=10),"9-10F",IF(AND(INT(H10/100)>=11,INT(H10/100)<=12),"11-12F",IF(INT(H10/100)>=13,"13以上F",""))))))))) -> 2-3F | U10: =VLOOKUP($T$1&T10,【1】定价因子!E:F,2,0) -> 0.99 | V10: =IF(COUNTIFS(户型资产表!E:E,I10,户型资产表!H:H,"操作台")>0,"有","无") -> 有 | W10: =IF(COUNTIFS(户型资产表!E:E,I10,户型资产表!H:H,"书桌")>0,"有","无") -> 有 | X10: {=IF(SUMPRODUCT((户型资产表!E:E=I10)*((户型资产表!I:I="沙发01单人")+(户型资产表!I:I="单人沙发02")))>0,"有","无")} -> 无 | Y10: {=IF(SUMPRODUCT((户型资产表!E:E=I10)*((户型资产表!I:I="沙发02两人")+(户型资产表!I:I="双人沙发01")))>0,"有","无")} -> 有 | Z10: =IF(COUNTIFS(户型资产表!E:E,I10,户型资产表!H:H,"餐桌")>0,"有","无") -> 有 | AA10: =IF(COUNTIFS(户型资产表!E:E,I10,户型资产表!H:H,"吸油烟机")>0,"有","无") -> 无 | AB10: =IF(COUNTIFS(户型资产表!E:E,I10,户型资产表!H:H,"冰箱")>0,"有","无") -> 无 | AC10: =IF(COUNTIFS(户型资产表!E:E,I10,户型资产表!H:H,"电视柜")>0,"有","无") -> 无 | AD10: =IF(J10="开间",IF(AND(V10="无",W10="无"),"缺失",IF(AND(V10="无",W10="有"),"缺失（操作台）",IF(AND(V10="有",W10="无"),"缺失（书桌）",IF(AND(V10="有",W10="有"),IF(OR(AA10="有",Y10="有"),"充足（油烟机/双人沙发）",IF(OR(X10="有",Z10="有"),"充足（单人沙发/餐桌）",IF(AND(OR(X10="有",Y10="有"),Z10="有"),"非常充足","适中"))),"")))),"适中") -> 适中 | AE10: =VLOOKUP($AD$1&AD10,【1】定价因子!E:F,2,0) -> 1 | AF10: 适中 | AG10: =VLOOKUP($AF$1&AF10,【1】定价因子!E:F,2,0) -> 1 | AH10: =IF(J10="二居室",IF(AND(Y10="无",Z10="无",AC10="无",V10="无"),"缺失",IF(OR(AND(Y10="无",Z10="无",AC10="有"),AND(Y10="无",Z10="无",V10="有"),AND(Y10="无",Z10="无",AC10="有",V10="有"),AND(Y10="无",Z10="有",AC10="无"),AND(Y10="无",Z10="有",V10="无"),AND(Y10="无",Z10="有",AC10="有"),AND(Y10="无",Z10="有",V10="有"),AND(Y10="有",Z10="无",AC10="无"),AND(Y10="有",Z10="无",V10="无"),AND(Y10="有",Z10="无",AC10="有"),AND(Y10="有",Z10="无",V10="有")),"缺失（沙发/餐桌）",IF(AND(Y10="有",Z10="有",OR(AC10="无",V10="无")),"缺失（电视柜/操作台）",IF(AND(Y10="有",Z10="有",AC10="有",V10="有"),IF(OR(AA10="有",AB10="有"),"充配（油烟机/冰箱）",IF(AND(AA10="无",AB10="无"),"适中","")),"")))),"适中") -> 适中 | AI10: =VLOOKUP($AH$1&AH10,【1】定价因子!E:F,2,0) -> 1 | AJ10: =VLOOKUP(H10,'【3-1】大区填-采光基本要素'!A:H,8,0) -> 1 | AK10: =VLOOKUP($AJ$1&AJ10,【1】定价因子!E:F,2,0) -> 0.91 | AL10: =L10*PRODUCT(AG10,AK10,AE10,U10,S10,Q10,O10) -> 1982.843 | AM10: 1980 | AN10: =AM10/AL10-1 -> -0.0014337949
A11: ='【2】运营中心填-基本信息&审核标准'!$E$2 -> 兴围西4-11栋 | B11: =INT(H11/100) -> 2 | C11: =COUNTIF($B$2:$B$72,B11) -> 8 | D11: =COUNTIF(C$2:C$72,C11) -> 64 | F11: =IF(D11=$E$2,C11,"") -> 8 | H11: 203 | I11: I | J11: 开间 | L11: =VLOOKUP(J11,'【3】大区填-楼栋基准格局定价'!B:H,7,0) -> 1647.8784 | M11: =IF(OR(J11="开间",J11="二人宿舍"),IF(N11<10,"很狭小",IF(N11<13,"较狭小",IF(N11<17,"适中",IF(N11<20,"较宽敞","很宽敞")))),IF(OR(J11="一居室",J11="四人宿舍"),IF(N11<20,"很狭小",IF(N11<23,"较狭小",IF(N11<26,"适中",IF(N11<28,"较宽敞","很宽敞")))),IF(OR(J11="二居室",J11="六人宿舍"),IF(N11<30,"很狭小",IF(N11<35,"较狭小",IF(N11<40,"适中",IF(N11<45,"较宽敞","很宽敞")))),""))) -> 适中 | N11: 13.87 | O11: =VLOOKUP($M$1&M11,【1】定价因子!E:F,2,0) -> 1 | P11: =IF(COUNTIFS(户型资产表!E:E,I11,户型资产表!H:H,"阳台门")>0,"有","无") -> 无 | Q11: =VLOOKUP($P$1&P11,【1】定价因子!E:F,2,0) -> 1 | R11: =IF('【2】运营中心填-基本信息&审核标准'!$D$4="是","无",IF(INT(H11/100)>9,"9F",INT(H11/100)&"F")) -> 无 | S11: =VLOOKUP(R11,【1】定价因子!D:F,3,0) -> 1 | T11: =IF('【2】运营中心填-基本信息&审核标准'!$D$4="否","无",IF(INT(H11/100)=1,"1F",IF(AND(INT(H11/100)>=2,INT(H11/100)<=3),"2-3F",IF(INT(H11/100)=4,"4F",IF(AND(INT(H11/100)>=5,INT(H11/100)<=6),"5-6F",IF(AND(INT(H11/100)>=7,INT(H11/100)<=8),"7-8F",IF(AND(INT(H11/100)>=9,INT(H11/100)<=10),"9-10F",IF(AND(INT(H11/100)>=11,INT(H11/100)<=12),"11-12F",IF(INT(H11/100)>=13,"13以上F",""))))))))) -> 2-3F | U11: =VLOOKUP($T$1&T11,【1】定价因子!E:F,2,0) -> 0.99 | V11: =IF(COUNTIFS(户型资产表!E:E,I11,户型资产表!H:H,"操作台")>0,"有","无") -> 有 | W11: =IF(COUNTIFS(户型资产表!E:E,I11,户型资产表!H:H,"书桌")>0,"有","无") -> 有 | X11: {=IF(SUMPRODUCT((户型资产表!E:E=I11)*((户型资产表!I:I="沙发01单人")+(户型资产表!I:I="单人沙发02")))>0,"有","无")} -> 无 | Y11: {=IF(SUMPRODUCT((户型资产表!E:E=I11)*((户型资产表!I:I="沙发02两人")+(户型资产表!I:I="双人沙发01")))>0,"有","无")} -> 无 | Z11: =IF(COUNTIFS(户型资产表!E:E,I11,户型资产表!H:H,"餐桌")>0,"有","无") -> 无 | AA11: =IF(COUNTIFS(户型资产表!E:E,I11,户型资产表!H:H,"吸油烟机")>0,"有","无") -> 无 | AB11: =IF(COUNTIFS(户型资产表!E:E,I11,户型资产表!H:H,"冰箱")>0,"有","无") -> 无 | AC11: =IF(COUNTIFS(户型资产表!E:E,I11,户型资产表!H:H,"电视柜")>0,"有","无") -> 无 | AD11: =IF(J11="开间",IF(AND(V11="无",W11="无"),"缺失",IF(AND(V11="无",W11="有"),"缺失（操作台）",IF(AND(V11="有",W11="无"),"缺失（书桌）",IF(AND(V11="有",W11="有"),IF(OR(AA11="有",Y11="有"),"充足（油烟机/双人沙发）",IF(OR(X11="有",Z11="有"),"充足（单人沙发/餐桌）",IF(AND(OR(X11="有",Y11="有"),Z11="有"),"非常充足","适中"))),"")))),"适中") -> 适中 | AE11: =VLOOKUP($AD$1&AD11,【1】定价因子!E:F,2,0) -> 1 | AF11: =IF(J11="一居室",IF(AND(V11="无",Y11="无",Z11="无"),"缺失",IF(OR(AND(Z11="有",V11="无",Y11="无"),AND(Z11="有",V11="无",Y11="有"),AND(Z11="有",V11="有",Y11="无"),AND(Z11="无",V11="有",Y11="无"),AND(Z11="无",V11="无",Y11="有")),"缺失（操作台/双人沙发）",IF(AND(V11="有",Y11="有",Z11="无"),"缺失（餐桌）",IF(AND(V11="有",Y11="有",Z11="有"),IF(AND(W11="无",AA11="有"),"充配（油烟机）",IF(AND(W11="有",AA11="无"),"充配（书桌）",IF(AND(W11="有",AA11="有"),"非常充配","适中"))),"")))),"适中") -> 适中 | AG11: =VLOOKUP($AF$1&AF11,【1】定价因子!E:F,2,0) -> 1 | AH11: =IF(J11="二居室",IF(AND(Y11="无",Z11="无",AC11="无",V11="无"),"缺失",IF(OR(AND(Y11="无",Z11="无",AC11="有"),AND(Y11="无",Z11="无",V11="有"),AND(Y11="无",Z11="无",AC11="有",V11="有"),AND(Y11="无",Z11="有",AC11="无"),AND(Y11="无",Z11="有",V11="无"),AND(Y11="无",Z11="有",AC11="有"),AND(Y11="无",Z11="有",V11="有"),AND(Y11="有",Z11="无",AC11="无"),AND(Y11="有",Z11="无",V11="无"),AND(Y11="有",Z11="无",AC11="有"),AND(Y11="有",Z11="无",V11="有")),"缺失（沙发/餐桌）",IF(AND(Y11="有",Z11="有",OR(AC11="无",V11="无")),"缺失（电视柜/操作台）",IF(AND(Y11="有",Z11="有",AC11="有",V11="有"),IF(OR(AA11="有",AB11="有"),"充配（油烟机/冰箱）",IF(AND(AA11="无",AB11="无"),"适中","")),"")))),"适中") -> 适中 | AI11: =VLOOKUP($AH$1&AH11,【1】定价因子!E:F,2,0) -> 1 | AJ11: =VLOOKUP(H11,'【3-1】大区填-采光基本要素'!A:H,8,0) -> 1 | AK11: =VLOOKUP($AJ$1&AJ11,【1】定价因子!E:F,2,0) -> 0.91 | AL11: =L11*PRODUCT(AG11,AK11,AE11,U11,S11,Q11,O11) -> 1484.5737 | AM11: 1430 | AN11: =AM11/AL11-1 -> -0.036760487
A12: ='【2】运营中心填-基本信息&审核标准'!$E$2 -> 兴围西4-11栋 | B12: =INT(H12/100) -> 2 | C12: =COUNTIF($B$2:$B$72,B12) -> 8 | D12: =COUNTIF(C$2:C$72,C12) -> 64 | F12: =IF(D12=$E$2,C12,"") -> 8 | H12: 204 | I12: J | J12: 开间 | L12: =VLOOKUP(J12,'【3】大区填-楼栋基准格局定价'!B:H,7,0) -> 1647.8784 | M12: 适中 | N12: 19.76 | O12: =VLOOKUP($M$1&M12,【1】定价因子!E:F,2,0) -> 1 | P12: =IF(COUNTIFS(户型资产表!E:E,I12,户型资产表!H:H,"阳台门")>0,"有","无") -> 无 | Q12: =VLOOKUP($P$1&P12,【1】定价因子!E:F,2,0) -> 1 | R12: =IF('【2】运营中心填-基本信息&审核标准'!$D$4="是","无",IF(INT(H12/100)>9,"9F",INT(H12/100)&"F")) -> 无 | S12: =VLOOKUP(R12,【1】定价因子!D:F,3,0) -> 1 | T12: =IF('【2】运营中心填-基本信息&审核标准'!$D$4="否","无",IF(INT(H12/100)=1,"1F",IF(AND(INT(H12/100)>=2,INT(H12/100)<=3),"2-3F",IF(INT(H12/100)=4,"4F",IF(AND(INT(H12/100)>=5,INT(H12/100)<=6),"5-6F",IF(AND(INT(H12/100)>=7,INT(H12/100)<=8),"7-8F",IF(AND(INT(H12/100)>=9,INT(H12/100)<=10),"9-10F",IF(AND(INT(H12/100)>=11,INT(H12/100)<=12),"11-12F",IF(INT(H12/100)>=13,"13以上F",""))))))))) -> 2-3F | U12: =VLOOKUP($T$1&T12,【1】定价因子!E:F,2,0) -> 0.99 | V12: =IF(COUNTIFS(户型资产表!E:E,I12,户型资产表!H:H,"操作台")>0,"有","无") -> 有 | W12: =IF(COUNTIFS(户型资产表!E:E,I12,户型资产表!H:H,"书桌")>0,"有","无") -> 有 | X12: {=IF(SUMPRODUCT((户型资产表!E:E=I12)*((户型资产表!I:I="沙发01单人")+(户型资产表!I:I="单人沙发02")))>0,"有","无")} -> 无 | Y12: {=IF(SUMPRODUCT((户型资产表!E:E=I12)*((户型资产表!I:I="沙发02两人")+(户型资产表!I:I="双人沙发01")))>0,"有","无")} -> 无 | Z12: =IF(COUNTIFS(户型资产表!E:E,I12,户型资产表!H:H,"餐桌")>0,"有","无") -> 无 | AA12: =IF(COUNTIFS(户型资产表!E:E,I12,户型资产表!H:H,"吸油烟机")>0,"有","无") -> 无 | AB12: =IF(COUNTIFS(户型资产表!E:E,I12,户型资产表!H:H,"冰箱")>0,"有","无") -> 无 | AC12: =IF(COUNTIFS(户型资产表!E:E,I12,户型资产表!H:H,"电视柜")>0,"有","无") -> 无 | AD12: =IF(J12="开间",IF(AND(V12="无",W12="无"),"缺失",IF(AND(V12="无",W12="有"),"缺失（操作台）",IF(AND(V12="有",W12="无"),"缺失（书桌）",IF(AND(V12="有",W12="有"),IF(OR(AA12="有",Y12="有"),"充足（油烟机/双人沙发）",IF(OR(X12="有",Z12="有"),"充足（单人沙发/餐桌）",IF(AND(OR(X12="有",Y12="有"),Z12="有"),"非常充足","适中"))),"")))),"适中") -> 适中 | AE12: =VLOOKUP($AD$1&AD12,【1】定价因子!E:F,2,0) -> 1 | AF12: =IF(J12="一居室",IF(AND(V12="无",Y12="无",Z12="无"),"缺失",IF(OR(AND(Z12="有",V12="无",Y12="无"),AND(Z12="有",V12="无",Y12="有"),AND(Z12="有",V12="有",Y12="无"),AND(Z12="无",V12="有",Y12="无"),AND(Z12="无",V12="无",Y12="有")),"缺失（操作台/双人沙发）",IF(AND(V12="有",Y12="有",Z12="无"),"缺失（餐桌）",IF(AND(V12="有",Y12="有",Z12="有"),IF(AND(W12="无",AA12="有"),"充配（油烟机）",IF(AND(W12="有",AA12="无"),"充配（书桌）",IF(AND(W12="有",AA12="有"),"非常充配","适中"))),"")))),"适中") -> 适中 | AG12: =VLOOKUP($AF$1&AF12,【1】定价因子!E:F,2,0) -> 1 | AH12: =IF(J12="二居室",IF(AND(Y12="无",Z12="无",AC12="无",V12="无"),"缺失",IF(OR(AND(Y12="无",Z12="无",AC12="有"),AND(Y12="无",Z12="无",V12="有"),AND(Y12="无",Z12="无",AC12="有",V12="有"),AND(Y12="无",Z12="有",AC12="无"),AND(Y12="无",Z12="有",V12="无"),AND(Y12="无",Z12="有",AC12="有"),AND(Y12="无",Z12="有",V12="有"),AND(Y12="有",Z12="无",AC12="无"),AND(Y12="有",Z12="无",V12="无"),AND(Y12="有",Z12="无",AC12="有"),AND(Y12="有",Z12="无",V12="有")),"缺失（沙发/餐桌）",IF(AND(Y12="有",Z12="有",OR(AC12="无",V12="无")),"缺失（电视柜/操作台）",IF(AND(Y12="有",Z12="有",AC12="有",V12="有"),IF(OR(AA12="有",AB12="有"),"充配（油烟机/冰箱）",IF(AND(AA12="无",AB12="无"),"适中","")),"")))),"适中") -> 适中 | AI12: =VLOOKUP($AH$1&AH12,【1】定价因子!E:F,2,0) -> 1 | AJ12: =VLOOKUP(H12,'【3-1】大区填-采光基本要素'!A:H,8,0) -> 1 | AK12: =VLOOKUP($AJ$1&AJ12,【1】定价因子!E:F,2,0) -> 0.91 | AL12: =L12*PRODUCT(AG12,AK12,AE12,U12,S12,Q12,O12) -> 1484.5737 | AM12: 1340 | AN12: =AM12/AL12-1 -> -0.097383953
A13: ='【2】运营中心填-基本信息&审核标准'!$E$2 -> 兴围西4-11栋 | B13: =INT(H13/100) -> 2 | C13: =COUNTIF($B$2:$B$72,B13) -> 8 | D13: =COUNTIF(C$2:C$72,C13) -> 64 | F13: =IF(D13=$E$2,C13,"") -> 8 | H13: 205 | I13: K | J13: 开间 | L13: =VLOOKUP(J13,'【3】大区填-楼栋基准格局定价'!B:H,7,0) -> 1647.8784 | M13: =IF(OR(J13="开间",J13="二人宿舍"),IF(N13<10,"很狭小",IF(N13<13,"较狭小",IF(N13<17,"适中",IF(N13<20,"较宽敞","很宽敞")))),IF(OR(J13="一居室",J13="四人宿舍"),IF(N13<20,"很狭小",IF(N13<23,"较狭小",IF(N13<26,"适中",IF(N13<28,"较宽敞","很宽敞")))),IF(OR(J13="二居室",J13="六人宿舍"),IF(N13<30,"很狭小",IF(N13<35,"较狭小",IF(N13<40,"适中",IF(N13<45,"较宽敞","很宽敞")))),""))) -> 适中 | N13: 13.43 | O13: =VLOOKUP($M$1&M13,【1】定价因子!E:F,2,0) -> 1 | P13: =IF(COUNTIFS(户型资产表!E:E,I13,户型资产表!H:H,"阳台门")>0,"有","无") -> 无 | Q13: =VLOOKUP($P$1&P13,【1】定价因子!E:F,2,0) -> 1 | R13: =IF('【2】运营中心填-基本信息&审核标准'!$D$4="是","无",IF(INT(H13/100)>9,"9F",INT(H13/100)&"F")) -> 无 | S13: =VLOOKUP(R13,【1】定价因子!D:F,3,0) -> 1 | T13: =IF('【2】运营中心填-基本信息&审核标准'!$D$4="否","无",IF(INT(H13/100)=1,"1F",IF(AND(INT(H13/100)>=2,INT(H13/100)<=3),"2-3F",IF(INT(H13/100)=4,"4F",IF(AND(INT(H13/100)>=5,INT(H13/100)<=6),"5-6F",IF(AND(INT(H13/100)>=7,INT(H13/100)<=8),"7-8F",IF(AND(INT(H13/100)>=9,INT(H13/100)<=10),"9-10F",IF(AND(INT(H13/100)>=11,INT(H13/100)<=12),"11-12F",IF(INT(H13/100)>=13,"13以上F",""))))))))) -> 2-3F | U13: =VLOOKUP($T$1&T13,【1】定价因子!E:F,2,0) -> 0.99 | V13: =IF(COUNTIFS(户型资产表!E:E,I13,户型资产表!H:H,"操作台")>0,"有","无") -> 有 | W13: =IF(COUNTIFS(户型资产表!E:E,I13,户型资产表!H:H,"书桌")>0,"有","无") -> 有 | X13: {=IF(SUMPRODUCT((户型资产表!E:E=I13)*((户型资产表!I:I="沙发01单人")+(户型资产表!I:I="单人沙发02")))>0,"有","无")} -> 无 | Y13: {=IF(SUMPRODUCT((户型资产表!E:E=I13)*((户型资产表!I:I="沙发02两人")+(户型资产表!I:I="双人沙发01")))>0,"有","无")} -> 无 | Z13: =IF(COUNTIFS(户型资产表!E:E,I13,户型资产表!H:H,"餐桌")>0,"有","无") -> 无 | AA13: =IF(COUNTIFS(户型资产表!E:E,I13,户型资产表!H:H,"吸油烟机")>0,"有","无") -> 无 | AB13: =IF(COUNTIFS(户型资产表!E:E,I13,户型资产表!H:H,"冰箱")>0,"有","无") -> 无 | AC13: =IF(COUNTIFS(户型资产表!E:E,I13,户型资产表!H:H,"电视柜")>0,"有","无") -> 无 | AD13: =IF(J13="开间",IF(AND(V13="无",W13="无"),"缺失",IF(AND(V13="无",W13="有"),"缺失（操作台）",IF(AND(V13="有",W13="无"),"缺失（书桌）",IF(AND(V13="有",W13="有"),IF(OR(AA13="有",Y13="有"),"充足（油烟机/双人沙发）",IF(OR(X13="有",Z13="有"),"充足（单人沙发/餐桌）",IF(AND(OR(X13="有",Y13="有"),Z13="有"),"非常充足","适中"))),"")))),"适中") -> 适中 | AE13: =VLOOKUP($AD$1&AD13,【1】定价因子!E:F,2,0) -> 1 | AF13: =IF(J13="一居室",IF(AND(V13="无",Y13="无",Z13="无"),"缺失",IF(OR(AND(Z13="有",V13="无",Y13="无"),AND(Z13="有",V13="无",Y13="有"),AND(Z13="有",V13="有",Y13="无"),AND(Z13="无",V13="有",Y13="无"),AND(Z13="无",V13="无",Y13="有")),"缺失（操作台/双人沙发）",IF(AND(V13="有",Y13="有",Z13="无"),"缺失（餐桌）",IF(AND(V13="有",Y13="有",Z13="有"),IF(AND(W13="无",AA13="有"),"充配（油烟机）",IF(AND(W13="有",AA13="无"),"充配（书桌）",IF(AND(W13="有",AA13="有"),"非常充配","适中"))),"")))),"适中") -> 适中 | AG13: =VLOOKUP($AF$1&AF13,【1】定价因子!E:F,2,0) -> 1 | AH13: =IF(J13="二居室",IF(AND(Y13="无",Z13="无",AC13="无",V13="无"),"缺失",IF(OR(AND(Y13="无",Z13="无",AC13="有"),AND(Y13="无",Z13="无",V13="有"),AND(Y13="无",Z13="无",AC13="有",V13="有"),AND(Y13="无",Z13="有",AC13="无"),AND(Y13="无",Z13="有",V13="无"),AND(Y13="无",Z13="有",AC13="有"),AND(Y13="无",Z13="有",V13="有"),AND(Y13="有",Z13="无",AC13="无"),AND(Y13="有",Z13="无",V13="无"),AND(Y13="有",Z13="无",AC13="有"),AND(Y13="有",Z13="无",V13="有")),"缺失（沙发/餐桌）",IF(AND(Y13="有",Z13="有",OR(AC13="无",V13="无")),"缺失（电视柜/操作台）",IF(AND(Y13="有",Z13="有",AC13="有",V13="有"),IF(OR(AA13="有",AB13="有"),"充配（油烟机/冰箱）",IF(AND(AA13="无",AB13="无"),"适中","")),"")))),"适中") -> 适中 | AI13: =VLOOKUP($AH$1&AH13,【1】定价因子!E:F,2,0) -> 1 | AJ13: =VLOOKUP(H13,'【3-1】大区填-采光基本要素'!A:H,8,0) -> 2 | AK13: =VLOOKUP($AJ$1&AJ13,【1】定价因子!E:F,2,0) -> 0.96 | AL13: =L13*PRODUCT(AG13,AK13,AE13,U13,S13,Q13,O13) -> 1566.1436 | AM13: 1430 | AN13: =AM13/AL13-1 -> -0.086929212
A14: ='【2】运营中心填-基本信息&审核标准'!$E$2 -> 兴围西4-11栋 | B14: =INT(H14/100) -> 2 | C14: =COUNTIF($B$2:$B$72,B14) -> 8 | D14: =COUNTIF(C$2:C$72,C14) -> 64 | F14: =IF(D14=$E$2,C14,"") -> 8 | H14: 206 | I14: L | J14: 一居室 | L14: =VLOOKUP(J14,'【3】大区填-楼栋基准格局定价'!B:H,7,0) -> 2445.5088 | M14: =IF(OR(J14="开间",J14="二人宿舍"),IF(N14<10,"很狭小",IF(N14<13,"较狭小",IF(N14<17,"适中",IF(N14<20,"较宽敞","很宽敞")))),IF(OR(J14="一居室",J14="四人宿舍"),IF(N14<20,"很狭小",IF(N14<23,"较狭小",IF(N14<26,"适中",IF(N14<28,"较宽敞","很宽敞")))),IF(OR(J14="二居室",J14="六人宿舍"),IF(N14<30,"很狭小",IF(N14<35,"较狭小",IF(N14<40,"适中",IF(N14<45,"较宽敞","很宽敞")))),""))) -> 很狭小 | N14: 11.18 | O14: =VLOOKUP($M$1&M14,【1】定价因子!E:F,2,0) -> 0.9 | P14: =IF(COUNTIFS(户型资产表!E:E,I14,户型资产表!H:H,"阳台门")>0,"有","无") -> 无 | Q14: =VLOOKUP($P$1&P14,【1】定价因子!E:F,2,0) -> 1 | R14: =IF('【2】运营中心填-基本信息&审核标准'!$D$4="是","无",IF(INT(H14/100)>9,"9F",INT(H14/100)&"F")) -> 无 | S14: =VLOOKUP(R14,【1】定价因子!D:F,3,0) -> 1 | T14: =IF('【2】运营中心填-基本信息&审核标准'!$D$4="否","无",IF(INT(H14/100)=1,"1F",IF(AND(INT(H14/100)>=2,INT(H14/100)<=3),"2-3F",IF(INT(H14/100)=4,"4F",IF(AND(INT(H14/100)>=5,INT(H14/100)<=6),"5-6F",IF(AND(INT(H14/100)>=7,INT(H14/100)<=8),"7-8F",IF(AND(INT(H14/100)>=9,INT(H14/100)<=10),"9-10F",IF(AND(INT(H14/100)>=11,INT(H14/100)<=12),"11-12F",IF(INT(H14/100)>=13,"13以上F",""))))))))) -> 2-3F | U14: =VLOOKUP($T$1&T14,【1】定价因子!E:F,2,0) -> 0.99 | V14: =IF(COUNTIFS(户型资产表!E:E,I14,户型资产表!H:H,"操作台")>0,"有","无") -> 有 | W14: =IF(COUNTIFS(户型资产表!E:E,I14,户型资产表!H:H,"书桌")>0,"有","无") -> 无 | X14: {=IF(SUMPRODUCT((户型资产表!E:E=I14)*((户型资产表!I:I="沙发01单人")+(户型资产表!I:I="单人沙发02")))>0,"有","无")} -> 无 | Y14: {=IF(SUMPRODUCT((户型资产表!E:E=I14)*((户型资产表!I:I="沙发02两人")+(户型资产表!I:I="双人沙发01")))>0,"有","无")} -> 有 | Z14: =IF(COUNTIFS(户型资产表!E:E,I14,户型资产表!H:H,"餐桌")>0,"有","无") -> 有 | AA14: =IF(COUNTIFS(户型资产表!E:E,I14,户型资产表!H:H,"吸油烟机")>0,"有","无") -> 无 | AB14: =IF(COUNTIFS(户型资产表!E:E,I14,户型资产表!H:H,"冰箱")>0,"有","无") -> 无 | AC14: =IF(COUNTIFS(户型资产表!E:E,I14,户型资产表!H:H,"电视柜")>0,"有","无") -> 无 | AD14: =IF(J14="开间",IF(AND(V14="无",W14="无"),"缺失",IF(AND(V14="无",W14="有"),"缺失（操作台）",IF(AND(V14="有",W14="无"),"缺失（书桌）",IF(AND(V14="有",W14="有"),IF(OR(AA14="有",Y14="有"),"充足（油烟机/双人沙发）",IF(OR(X14="有",Z14="有"),"充足（单人沙发/餐桌）",IF(AND(OR(X14="有",Y14="有"),Z14="有"),"非常充足","适中"))),"")))),"适中") -> 适中 | AE14: =VLOOKUP($AD$1&AD14,【1】定价因子!E:F,2,0) -> 1 | AF14: =IF(J14="一居室",IF(AND(V14="无",Y14="无",Z14="无"),"缺失",IF(OR(AND(Z14="有",V14="无",Y14="无"),AND(Z14="有",V14="无",Y14="有"),AND(Z14="有",V14="有",Y14="无"),AND(Z14="无",V14="有",Y14="无"),AND(Z14="无",V14="无",Y14="有")),"缺失（操作台/双人沙发）",IF(AND(V14="有",Y14="有",Z14="无"),"缺失（餐桌）",IF(AND(V14="有",Y14="有",Z14="有"),IF(AND(W14="无",AA14="有"),"充配（油烟机）",IF(AND(W14="有",AA14="无"),"充配（书桌）",IF(AND(W14="有",AA14="有"),"非常充配","适中"))),"")))),"适中") -> 适中 | AG14: =VLOOKUP($AF$1&AF14,【1】定价因子!E:F,2,0) -> 1 | AH14: =IF(J14="二居室",IF(AND(Y14="无",Z14="无",AC14="无",V14="无"),"缺失",IF(OR(AND(Y14="无",Z14="无",AC14="有"),AND(Y14="无",Z14="无",V14="有"),AND(Y14="无",Z14="无",AC14="有",V14="有"),AND(Y14="无",Z14="有",AC14="无"),AND(Y14="无",Z14="有",V14="无"),AND(Y14="无",Z14="有",AC14="有"),AND(Y14="无",Z14="有",V14="有"),AND(Y14="有",Z14="无",AC14="无"),AND(Y14="有",Z14="无",V14="无"),AND(Y14="有",Z14="无",AC14="有"),AND(Y14="有",Z14="无",V14="有")),"缺失（沙发/餐桌）",IF(AND(Y14="有",Z14="有",OR(AC14="无",V14="无")),"缺失（电视柜/操作台）",IF(AND(Y14="有",Z14="有",AC14="有",V14="有"),IF(OR(AA14="有",AB14="有"),"充配（油烟机/冰箱）",IF(AND(AA14="无",AB14="无"),"适中","")),"")))),"适中") -> 适中 | AI14: =VLOOKUP($AH$1&AH14,【1】定价因子!E:F,2,0) -> 1 | AJ14: =VLOOKUP(H14,'【3-1】大区填-采光基本要素'!A:H,8,0) -> 1 | AK14: =VLOOKUP($AJ$1&AJ14,【1】定价因子!E:F,2,0) -> 0.91 | AL14: =L14*PRODUCT(AG14,AK14,AE14,U14,S14,Q14,O14) -> 1982.843 | AM14: 1980 | AN14: =AM14/AL14-1 -> -0.0014337949
A15: ='【2】运营中心填-基本信息&审核标准'!$E$2 -> 兴围西4-11栋 | B15: =INT(H15/100) -> 2 | C15: =COUNTIF($B$2:$B$72,B15) -> 8 | D15: =COUNTIF(C$2:C$72,C15) -> 64 | F15: =IF(D15=$E$2,C15,"") -> 8 | H15: 207 | I15: J | J15: 开间 | L15: =VLOOKUP(J15,'【3】大区填-楼栋基准格局定价'!B:H,7,0) -> 1647.8784 | M15: =IF(OR(J15="开间",J15="二人宿舍"),IF(N15<10,"很狭小",IF(N15<13,"较狭小",IF(N15<17,"适中",IF(N15<20,"较宽敞","很宽敞")))),IF(OR(J15="一居室",J15="四人宿舍"),IF(N15<20,"很狭小",IF(N15<23,"较狭小",IF(N15<26,"适中",IF(N15<28,"较宽敞","很宽敞")))),IF(OR(J15="二居室",J15="六人宿舍"),IF(N15<30,"很狭小",IF(N15<35,"较狭小",IF(N15<40,"适中",IF(N15<45,"较宽敞","很宽敞")))),""))) -> 适中 | N15: 13.81 | O15: =VLOOKUP($M$1&M15,【1】定价因子!E:F,2,0) -> 1 | P15: =IF(COUNTIFS(户型资产表!E:E,I15,户型资产表!H:H,"阳台门")>0,"有","无") -> 无 | Q15: =VLOOKUP($P$1&P15,【1】定价因子!E:F,2,0) -> 1 | R15: =IF('【2】运营中心填-基本信息&审核标准'!$D$4="是","无",IF(INT(H15/100)>9,"9F",INT(H15/100)&"F")) -> 无 | S15: =VLOOKUP(R15,【1】定价因子!D:F,3,0) -> 1 | T15: =IF('【2】运营中心填-基本信息&审核标准'!$D$4="否","无",IF(INT(H15/100)=1,"1F",IF(AND(INT(H15/100)>=2,INT(H15/100)<=3),"2-3F",IF(INT(H15/100)=4,"4F",IF(AND(INT(H15/100)>=5,INT(H15/100)<=6),"5-6F",IF(AND(INT(H15/100)>=7,INT(H15/100)<=8),"7-8F",IF(AND(INT(H15/100)>=9,INT(H15/100)<=10),"9-10F",IF(AND(INT(H15/100)>=11,INT(H15/100)<=12),"11-12F",IF(INT(H15/100)>=13,"13以上F",""))))))))) -> 2-3F | U15: =VLOOKUP($T$1&T15,【1】定价因子!E:F,2,0) -> 0.99 | V15: =IF(COUNTIFS(户型资产表!E:E,I15,户型资产表!H:H,"操作台")>0,"有","无") -> 有 | W15: =IF(COUNTIFS(户型资产表!E:E,I15,户型资产表!H:H,"书桌")>0,"有","无") -> 有 | X15: {=IF(SUMPRODUCT((户型资产表!E:E=I15)*((户型资产表!I:I="沙发01单人")+(户型资产表!I:I="单人沙发02")))>0,"有","无")} -> 无 | Y15: {=IF(SUMPRODUCT((户型资产表!E:E=I15)*((户型资产表!I:I="沙发02两人")+(户型资产表!I:I="双人沙发01")))>0,"有","无")} -> 无 | Z15: =IF(COUNTIFS(户型资产表!E:E,I15,户型资产表!H:H,"餐桌")>0,"有","无") -> 无 | AA15: =IF(COUNTIFS(户型资产表!E:E,I15,户型资产表!H:H,"吸油烟机")>0,"有","无") -> 无 | AB15: =IF(COUNTIFS(户型资产表!E:E,I15,户型资产表!H:H,"冰箱")>0,"有","无") -> 无 | AC15: =IF(COUNTIFS(户型资产表!E:E,I15,户型资产表!H:H,"电视柜")>0,"有","无") -> 无 | AD15: =IF(J15="开间",IF(AND(V15="无",W15="无"),"缺失",IF(AND(V15="无",W15="有"),"缺失（操作台）",IF(AND(V15="有",W15="无"),"缺失（书桌）",IF(AND(V15="有",W15="有"),IF(OR(AA15="有",Y15="有"),"充足（油烟机/双人沙发）",IF(OR(X15="有",Z15="有"),"充足（单人沙发/餐桌）",IF(AND(OR(X15="有",Y15="有"),Z15="有"),"非常充足","适中"))),"")))),"适中") -> 适中 | AE15: =VLOOKUP($AD$1&AD15,【1】定价因子!E:F,2,0) -> 1 | AF15: =IF(J15="一居室",IF(AND(V15="无",Y15="无",Z15="无"),"缺失",IF(OR(AND(Z15="有",V15="无",Y15="无"),AND(Z15="有",V15="无",Y15="有"),AND(Z15="有",V15="有",Y15="无"),AND(Z15="无",V15="有",Y15="无"),AND(Z15="无",V15="无",Y15="有")),"缺失（操作台/双人沙发）",IF(AND(V15="有",Y15="有",Z15="无"),"缺失（餐桌）",IF(AND(V15="有",Y15="有",Z15="有"),IF(AND(W15="无",AA15="有"),"充配（油烟机）",IF(AND(W15="有",AA15="无"),"充配（书桌）",IF(AND(W15="有",AA15="有"),"非常充配","适中"))),"")))),"适中") -> 适中 | AG15: =VLOOKUP($AF$1&AF15,【1】定价因子!E:F,2,0) -> 1 | AH15: =IF(J15="二居室",IF(AND(Y15="无",Z15="无",AC15="无",V15="无"),"缺失",IF(OR(AND(Y15="无",Z15="无",AC15="有"),AND(Y15="无",Z15="无",V15="有"),AND(Y15="无",Z15="无",AC15="有",V15="有"),AND(Y15="无",Z15="有",AC15="无"),AND(Y15="无",Z15="有",V15="无"),AND(Y15="无",Z15="有",AC15="有"),AND(Y15="无",Z15="有",V15="有"),AND(Y15="有",Z15="无",AC15="无"),AND(Y15="有",Z15="无",V15="无"),AND(Y15="有",Z15="无",AC15="有"),AND(Y15="有",Z15="无",V15="有")),"缺失（沙发/餐桌）",IF(AND(Y15="有",Z15="有",OR(AC15="无",V15="无")),"缺失（电视柜/操作台）",IF(AND(Y15="有",Z15="有",AC15="有",V15="有"),IF(OR(AA15="有",AB15="有"),"充配（油烟机/冰箱）",IF(AND(AA15="无",AB15="无"),"适中","")),"")))),"适中") -> 适中 | AI15: =VLOOKUP($AH$1&AH15,【1】定价因子!E:F,2,0) -> 1 | AJ15: =VLOOKUP(H15,'【3-1】大区填-采光基本要素'!A:H,8,0) -> 1 | AK15: =VLOOKUP($AJ$1&AJ15,【1】定价因子!E:F,2,0) -> 0.91 | AL15: =L15*PRODUCT(AG15,AK15,AE15,U15,S15,Q15,O15) -> 1484.5737 | AM15: 1430 | AN15: =AM15/AL15-1 -> -0.036760487
A16: ='【2】运营中心填-基本信息&审核标准'!$E$2 -> 兴围西4-11栋 | B16: =INT(H16/100) -> 2 | C16: =COUNTIF($B$2:$B$72,B16) -> 8 | D16: =COUNTIF(C$2:C$72,C16) -> 64 | F16: =IF(D16=$E$2,C16,"") -> 8 | H16: 208 | I16: M | J16: 一居室 | L16: =VLOOKUP(J16,'【3】大区填-楼栋基准格局定价'!B:H,7,0) -> 2445.5088 | M16: =IF(OR(J16="开间",J16="二人宿舍"),IF(N16<10,"很狭小",IF(N16<13,"较狭小",IF(N16<17,"适中",IF(N16<20,"较宽敞","很宽敞")))),IF(OR(J16="一居室",J16="四人宿舍"),IF(N16<20,"很狭小",IF(N16<23,"较狭小",IF(N16<26,"适中",IF(N16<28,"较宽敞","很宽敞")))),IF(OR(J16="二居室",J16="六人宿舍"),IF(N16<30,"很狭小",IF(N16<35,"较狭小",IF(N16<40,"适中",IF(N16<45,"较宽敞","很宽敞")))),""))) -> 很狭小 | N16: 19.88 | O16: =VLOOKUP($M$1&M16,【1】定价因子!E:F,2,0) -> 0.9 | P16: =IF(COUNTIFS(户型资产表!E:E,I16,户型资产表!H:H,"阳台门")>0,"有","无") -> 无 | Q16: =VLOOKUP($P$1&P16,【1】定价因子!E:F,2,0) -> 1 | R16: =IF('【2】运营中心填-基本信息&审核标准'!$D$4="是","无",IF(INT(H16/100)>9,"9F",INT(H16/100)&"F")) -> 无 | S16: =VLOOKUP(R16,【1】定价因子!D:F,3,0) -> 1 | T16: =IF('【2】运营中心填-基本信息&审核标准'!$D$4="否","无",IF(INT(H16/100)=1,"1F",IF(AND(INT(H16/100)>=2,INT(H16/100)<=3),"2-3F",IF(INT(H16/100)=4,"4F",IF(AND(INT(H16/100)>=5,INT(H16/100)<=6),"5-6F",IF(AND(INT(H16/100)>=7,INT(H16/100)<=8),"7-8F",IF(AND(INT(H16/100)>=9,INT(H16/100)<=10),"9-10F",IF(AND(INT(H16/100)>=11,INT(H16/100)<=12),"11-12F",IF(INT(H16/100)>=13,"13以上F",""))))))))) -> 2-3F | U16: =VLOOKUP($T$1&T16,【1】定价因子!E:F,2,0) -> 0.99 | V16: =IF(COUNTIFS(户型资产表!E:E,I16,户型资产表!H:H,"操作台")>0,"有","无") -> 有 | W16: =IF(COUNTIFS(户型资产表!E:E,I16,户型资产表!H:H,"书桌")>0,"有","无") -> 无 | X16: {=IF(SUMPRODUCT((户型资产表!E:E=I16)*((户型资产表!I:I="沙发01单人")+(户型资产表!I:I="单人沙发02")))>0,"有","无")} -> 无 | Y16: {=IF(SUMPRODUCT((户型资产表!E:E=I16)*((户型资产表!I:I="沙发02两人")+(户型资产表!I:I="双人沙发01")))>0,"有","无")} -> 有 | Z16: =IF(COUNTIFS(户型资产表!E:E,I16,户型资产表!H:H,"餐桌")>0,"有","无") -> 有 | AA16: =IF(COUNTIFS(户型资产表!E:E,I16,户型资产表!H:H,"吸油烟机")>0,"有","无") -> 有 | AB16: =IF(COUNTIFS(户型资产表!E:E,I16,户型资产表!H:H,"冰箱")>0,"有","无") -> 无 | AC16: =IF(COUNTIFS(户型资产表!E:E,I16,户型资产表!H:H,"电视柜")>0,"有","无") -> 无 | AD16: =IF(J16="开间",IF(AND(V16="无",W16="无"),"缺失",IF(AND(V16="无",W16="有"),"缺失（操作台）",IF(AND(V16="有",W16="无"),"缺失（书桌）",IF(AND(V16="有",W16="有"),IF(OR(AA16="有",Y16="有"),"充足（油烟机/双人沙发）",IF(OR(X16="有",Z16="有"),"充足（单人沙发/餐桌）",IF(AND(OR(X16="有",Y16="有"),Z16="有"),"非常充足","适中"))),"")))),"适中") -> 适中 | AE16: =VLOOKUP($AD$1&AD16,【1】定价因子!E:F,2,0) -> 1 | AF16: 适中 | AG16: =VLOOKUP($AF$1&AF16,【1】定价因子!E:F,2,0) -> 1 | AH16: =IF(J16="二居室",IF(AND(Y16="无",Z16="无",AC16="无",V16="无"),"缺失",IF(OR(AND(Y16="无",Z16="无",AC16="有"),AND(Y16="无",Z16="无",V16="有"),AND(Y16="无",Z16="无",AC16="有",V16="有"),AND(Y16="无",Z16="有",AC16="无"),AND(Y16="无",Z16="有",V16="无"),AND(Y16="无",Z16="有",AC16="有"),AND(Y16="无",Z16="有",V16="有"),AND(Y16="有",Z16="无",AC16="无"),AND(Y16="有",Z16="无",V16="无"),AND(Y16="有",Z16="无",AC16="有"),AND(Y16="有",Z16="无",V16="有")),"缺失（沙发/餐桌）",IF(AND(Y16="有",Z16="有",OR(AC16="无",V16="无")),"缺失（电视柜/操作台）",IF(AND(Y16="有",Z16="有",AC16="有",V16="有"),IF(OR(AA16="有",AB16="有"),"充配（油烟机/冰箱）",IF(AND(AA16="无",AB16="无"),"适中","")),"")))),"适中") -> 适中 | AI16: =VLOOKUP($AH$1&AH16,【1】定价因子!E:F,2,0) -> 1 | AJ16: =VLOOKUP(H16,'【3-1】大区填-采光基本要素'!A:H,8,0) -> 2 | AK16: =VLOOKUP($AJ$1&AJ16,【1】定价因子!E:F,2,0) -> 0.96 | AL16: =L16*PRODUCT(AG16,AK16,AE16,U16,S16,Q16,O16) -> 2091.7904 | AM16: 2080 | AN16: =AM16/AL16-1 -> -0.0056365146
A17: ='【2】运营中心填-基本信息&审核标准'!$E$2 -> 兴围西4-11栋 | B17: =INT(H17/100) -> 3 | C17: =COUNTIF($B$2:$B$72,B17) -> 8 | D17: =COUNTIF(C$2:C$72,C17) -> 64 | F17: =IF(D17=$E$2,C17,"") -> 8 | H17: 301 | I17: N | J17: 开间 | L17: =VLOOKUP(J17,'【3】大区填-楼栋基准格局定价'!B:H,7,0) -> 1647.8784 | M17: =IF(OR(J17="开间",J17="二人宿舍"),IF(N17<10,"很狭小",IF(N17<13,"较狭小",IF(N17<17,"适中",IF(N17<20,"较宽敞","很宽敞")))),IF(OR(J17="一居室",J17="四人宿舍"),IF(N17<20,"很狭小",IF(N17<23,"较狭小",IF(N17<26,"适中",IF(N17<28,"较宽敞","很宽敞")))),IF(OR(J17="二居室",J17="六人宿舍"),IF(N17<30,"很狭小",IF(N17<35,"较狭小",IF(N17<40,"适中",IF(N17<45,"较宽敞","很宽敞")))),""))) -> 较狭小 | N17: 10.96 | O17: =VLOOKUP($M$1&M17,【1】定价因子!E:F,2,0) -> 0.95 | P17: =IF(COUNTIFS(户型资产表!E:E,I17,户型资产表!H:H,"阳台门")>0,"有","无") -> 无 | Q17: =VLOOKUP($P$1&P17,【1】定价因子!E:F,2,0) -> 1 | R17: =IF('【2】运营中心填-基本信息&审核标准'!$D$4="是","无",IF(INT(H17/100)>9,"9F",INT(H17/100)&"F")) -> 无 | S17: =VLOOKUP(R17,【1】定价因子!D:F,3,0) -> 1 | T17: =IF('【2】运营中心填-基本信息&审核标准'!$D$4="否","无",IF(INT(H17/100)=1,"1F",IF(AND(INT(H17/100)>=2,INT(H17/100)<=3),"2-3F",IF(INT(H17/100)=4,"4F",IF(AND(INT(H17/100)>=5,INT(H17/100)<=6),"5-6F",IF(AND(INT(H17/100)>=7,INT(H17/100)<=8),"7-8F",IF(AND(INT(H17/100)>=9,INT(H17/100)<=10),"9-10F",IF(AND(INT(H17/100)>=11,INT(H17/100)<=12),"11-12F",IF(INT(H17/100)>=13,"13以上F",""))))))))) -> 2-3F | U17: =VLOOKUP($T$1&T17,【1】定价因子!E:F,2,0) -> 0.99 | V17: =IF(COUNTIFS(户型资产表!E:E,I17,户型资产表!H:H,"操作台")>0,"有","无") -> 有 | W17: =IF(COUNTIFS(户型资产表!E:E,I17,户型资产表!H:H,"书桌")>0,"有","无") -> 有 | X17: {=IF(SUMPRODUCT((户型资产表!E:E=I17)*((户型资产表!I:I="沙发01单人")+(户型资产表!I:I="单人沙发02")))>0,"有","无")} -> 无 | Y17: {=IF(SUMPRODUCT((户型资产表!E:E=I17)*((户型资产表!I:I="沙发02两人")+(户型资产表!I:I="双人沙发01")))>0,"有","无")} -> 无 | Z17: =IF(COUNTIFS(户型资产表!E:E,I17,户型资产表!H:H,"餐桌")>0,"有","无") -> 无 | AA17: =IF(COUNTIFS(户型资产表!E:E,I17,户型资产表!H:H,"吸油烟机")>0,"有","无") -> 无 | AB17: =IF(COUNTIFS(户型资产表!E:E,I17,户型资产表!H:H,"冰箱")>0,"有","无") -> 无 | AC17: =IF(COUNTIFS(户型资产表!E:E,I17,户型资产表!H:H,"电视柜")>0,"有","无") -> 无 | AD17: =IF(J17="开间",IF(AND(V17="无",W17="无"),"缺失",IF(AND(V17="无",W17="有"),"缺失（操作台）",IF(AND(V17="有",W17="无"),"缺失（书桌）",IF(AND(V17="有",W17="有"),IF(OR(AA17="有",Y17="有"),"充足（油烟机/双人沙发）",IF(OR(X17="有",Z17="有"),"充足（单人沙发/餐桌）",IF(AND(OR(X17="有",Y17="有"),Z17="有"),"非常充足","适中"))),"")))),"适中") -> 适中 | AE17: =VLOOKUP($AD$1&AD17,【1】定价因子!E:F,2,0) -> 1 | AF17: =IF(J17="一居室",IF(AND(V17="无",Y17="无",Z17="无"),"缺失",IF(OR(AND(Z17="有",V17="无",Y17="无"),AND(Z17="有",V17="无",Y17="有"),AND(Z17="有",V17="有",Y17="无"),AND(Z17="无",V17="有",Y17="无"),AND(Z17="无",V17="无",Y17="有")),"缺失（操作台/双人沙发）",IF(AND(V17="有",Y17="有",Z17="无"),"缺失（餐桌）",IF(AND(V17="有",Y17="有",Z17="有"),IF(AND(W17="无",AA17="有"),"充配（油烟机）",IF(AND(W17="有",AA17="无"),"充配（书桌）",IF(AND(W17="有",AA17="有"),"非常充配","适中"))),"")))),"适中") -> 适中 | AG17: =VLOOKUP($AF$1&AF17,【1】定价因子!E:F,2,0) -> 1 | AH17: =IF(J17="二居室",IF(AND(Y17="无",Z17="无",AC17="无",V17="无"),"缺失",IF(OR(AND(Y17="无",Z17="无",AC17="有"),AND(Y17="无",Z17="无",V17="有"),AND(Y17="无",Z17="无",AC17="有",V17="有"),AND(Y17="无",Z17="有",AC17="无"),AND(Y17="无",Z17="有",V17="无"),AND(Y17="无",Z17="有",AC17="有"),AND(Y17="无",Z17="有",V17="有"),AND(Y17="有",Z17="无",AC17="无"),AND(Y17="有",Z17="无",V17="无"),AND(Y17="有",Z17="无",AC17="有"),AND(Y17="有",Z17="无",V17="有")),"缺失（沙发/餐桌）",IF(AND(Y17="有",Z17="有",OR(AC17="无",V17="无")),"缺失（电视柜/操作台）",IF(AND(Y17="有",Z17="有",AC17="有",V17="有"),IF(OR(AA17="有",AB17="有"),"充配（油烟机/冰箱）",IF(AND(AA17="无",AB17="无"),"适中","")),"")))),"适中") -> 适中 | AI17: =VLOOKUP($AH$1&AH17,【1】定价因子!E:F,2,0) -> 1 | AJ17: =VLOOKUP(H17,'【3-1】大区填-采光基本要素'!A:H,8,0) -> 5 | AK17: =VLOOKUP($AJ$1&AJ17,【1】定价因子!E:F,2,0) -> 1.06 | AL17: =L17*PRODUCT(AG17,AK17,AE17,U17,S17,Q17,O17) -> 1642.8194 | AM17: 1500 | AN17: =AM17/AL17-1 -> -0.086935552
A18: ='【2】运营中心填-基本信息&审核标准'!$E$2 -> 兴围西4-11栋 | B18: =INT(H18/100) -> 3 | C18: =COUNTIF($B$2:$B$72,B18) -> 8 | D18: =COUNTIF(C$2:C$72,C18) -> 64 | F18: =IF(D18=$E$2,C18,"") -> 8 | H18: 302 | I18: H | J18: 一居室 | L18: =VLOOKUP(J18,'【3】大区填-楼栋基准格局定价'!B:H,7,0) -> 2445.5088 | M18: =IF(OR(J18="开间",J18="二人宿舍"),IF(N18<10,"很狭小",IF(N18<13,"较狭小",IF(N18<17,"适中",IF(N18<20,"较宽敞","很宽敞")))),IF(OR(J18="一居室",J18="四人宿舍"),IF(N18<20,"很狭小",IF(N18<23,"较狭小",IF(N18<26,"适中",IF(N18<28,"较宽敞","很宽敞")))),IF(OR(J18="二居室",J18="六人宿舍"),IF(N18<30,"很狭小",IF(N18<35,"较狭小",IF(N18<40,"适中",IF(N18<45,"较宽敞","很宽敞")))),""))) -> 很狭小 | N18: 18.86 | O18: =VLOOKUP($M$1&M18,【1】定价因子!E:F,2,0) -> 0.9 | P18: =IF(COUNTIFS(户型资产表!E:E,I18,户型资产表!H:H,"阳台门")>0,"有","无") -> 无 | Q18: =VLOOKUP($P$1&P18,【1】定价因子!E:F,2,0) -> 1 | R18: =IF('【2】运营中心填-基本信息&审核标准'!$D$4="是","无",IF(INT(H18/100)>9,"9F",INT(H18/100)&"F")) -> 无 | S18: =VLOOKUP(R18,【1】定价因子!D:F,3,0) -> 1 | T18: =IF('【2】运营中心填-基本信息&审核标准'!$D$4="否","无",IF(INT(H18/100)=1,"1F",IF(AND(INT(H18/100)>=2,INT(H18/100)<=3),"2-3F",IF(INT(H18/100)=4,"4F",IF(AND(INT(H18/100)>=5,INT(H18/100)<=6),"5-6F",IF(AND(INT(H18/100)>=7,INT(H18/100)<=8),"7-8F",IF(AND(INT(H18/100)>=9,INT(H18/100)<=10),"9-10F",IF(AND(INT(H18/100)>=11,INT(H18/100)<=12),"11-12F",IF(INT(H18/100)>=13,"13以上F",""))))))))) -> 2-3F | U18: =VLOOKUP($T$1&T18,【1】定价因子!E:F,2,0) -> 0.99 | V18: =IF(COUNTIFS(户型资产表!E:E,I18,户型资产表!H:H,"操作台")>0,"有","无") -> 有 | W18: =IF(COUNTIFS(户型资产表!E:E,I18,户型资产表!H:H,"书桌")>0,"有","无") -> 有 | X18: {=IF(SUMPRODUCT((户型资产表!E:E=I18)*((户型资产表!I:I="沙发01单人")+(户型资产表!I:I="单人沙发02")))>0,"有","无")} -> 无 | Y18: {=IF(SUMPRODUCT((户型资产表!E:E=I18)*((户型资产表!I:I="沙发02两人")+(户型资产表!I:I="双人沙发01")))>0,"有","无")} -> 有 | Z18: =IF(COUNTIFS(户型资产表!E:E,I18,户型资产表!H:H,"餐桌")>0,"有","无") -> 有 | AA18: =IF(COUNTIFS(户型资产表!E:E,I18,户型资产表!H:H,"吸油烟机")>0,"有","无") -> 无 | AB18: =IF(COUNTIFS(户型资产表!E:E,I18,户型资产表!H:H,"冰箱")>0,"有","无") -> 无 | AC18: =IF(COUNTIFS(户型资产表!E:E,I18,户型资产表!H:H,"电视柜")>0,"有","无") -> 无 | AD18: =IF(J18="开间",IF(AND(V18="无",W18="无"),"缺失",IF(AND(V18="无",W18="有"),"缺失（操作台）",IF(AND(V18="有",W18="无"),"缺失（书桌）",IF(AND(V18="有",W18="有"),IF(OR(AA18="有",Y18="有"),"充足（油烟机/双人沙发）",IF(OR(X18="有",Z18="有"),"充足（单人沙发/餐桌）",IF(AND(OR(X18="有",Y18="有"),Z18="有"),"非常充足","适中"))),"")))),"适中") -> 适中 | AE18: =VLOOKUP($AD$1&AD18,【1】定价因子!E:F,2,0) -> 1 | AF18: 适中 | AG18: =VLOOKUP($AF$1&AF18,【1】定价因子!E:F,2,0) -> 1 | AH18: =IF(J18="二居室",IF(AND(Y18="无",Z18="无",AC18="无",V18="无"),"缺失",IF(OR(AND(Y18="无",Z18="无",AC18="有"),AND(Y18="无",Z18="无",V18="有"),AND(Y18="无",Z18="无",AC18="有",V18="有"),AND(Y18="无",Z18="有",AC18="无"),AND(Y18="无",Z18="有",V18="无"),AND(Y18="无",Z18="有",AC18="有"),AND(Y18="无",Z18="有",V18="有"),AND(Y18="有",Z18="无",AC18="无"),AND(Y18="有",Z18="无",V18="无"),AND(Y18="有",Z18="无",AC18="有"),AND(Y18="有",Z18="无",V18="有")),"缺失（沙发/餐桌）",IF(AND(Y18="有",Z18="有",OR(AC18="无",V18="无")),"缺失（电视柜/操作台）",IF(AND(Y18="有",Z18="有",AC18="有",V18="有"),IF(OR(AA18="有",AB18="有"),"充配（油烟机/冰箱）",IF(AND(AA18="无",AB18="无"),"适中","")),"")))),"适中") -> 适中 | AI18: =VLOOKUP($AH$1&AH18,【1】定价因子!E:F,2,0) -> 1 | AJ18: =VLOOKUP(H18,'【3-1】大区填-采光基本要素'!A:H,8,0) -> 2 | AK18: =VLOOKUP($AJ$1&AJ18,【1】定价因子!E:F,2,0) -> 0.96 | AL18: =L18*PRODUCT(AG18,AK18,AE18,U18,S18,Q18,O18) -> 2091.7904 | AM18: 1980 | AN18: =AM18/AL18-1 -> -0.053442451
A19: ='【2】运营中心填-基本信息&审核标准'!$E$2 -> 兴围西4-11栋 | B19: =INT(H19/100) -> 3 | C19: =COUNTIF($B$2:$B$72,B19) -> 8 | D19: =COUNTIF(C$2:C$72,C19) -> 64 | F19: =IF(D19=$E$2,C19,"") -> 8 | H19: 303 | I19: O | J19: 开间 | L19: =VLOOKUP(J19,'【3】大区填-楼栋基准格局定价'!B:H,7,0) -> 1647.8784 | M19: =IF(OR(J19="开间",J19="二人宿舍"),IF(N19<10,"很狭小",IF(N19<13,"较狭小",IF(N19<17,"适中",IF(N19<20,"较宽敞","很宽敞")))),IF(OR(J19="一居室",J19="四人宿舍"),IF(N19<20,"很狭小",IF(N19<23,"较狭小",IF(N19<26,"适中",IF(N19<28,"较宽敞","很宽敞")))),IF(OR(J19="二居室",J19="六人宿舍"),IF(N19<30,"很狭小",IF(N19<35,"较狭小",IF(N19<40,"适中",IF(N19<45,"较宽敞","很宽敞")))),""))) -> 适中 | N19: 13.87 | O19: =VLOOKUP($M$1&M19,【1】定价因子!E:F,2,0) -> 1 | P19: =IF(COUNTIFS(户型资产表!E:E,I19,户型资产表!H:H,"阳台门")>0,"有","无") -> 有 | Q19: =VLOOKUP($P$1&P19,【1】定价因子!E:F,2,0) -> 1.07 | R19: =IF('【2】运营中心填-基本信息&审核标准'!$D$4="是","无",IF(INT(H19/100)>9,"9F",INT(H19/100)&"F")) -> 无 | S19: =VLOOKUP(R19,【1】定价因子!D:F,3,0) -> 1 | T19: =IF('【2】运营中心填-基本信息&审核标准'!$D$4="否","无",IF(INT(H19/100)=1,"1F",IF(AND(INT(H19/100)>=2,INT(H19/100)<=3),"2-3F",IF(INT(H19/100)=4,"4F",IF(AND(INT(H19/100)>=5,INT(H19/100)<=6),"5-6F",IF(AND(INT(H19/100)>=7,INT(H19/100)<=8),"7-8F",IF(AND(INT(H19/100)>=9,INT(H19/100)<=10),"9-10F",IF(AND(INT(H19/100)>=11,INT(H19/100)<=12),"11-12F",IF(INT(H19/100)>=13,"13以上F",""))))))))) -> 2-3F | U19: =VLOOKUP($T$1&T19,【1】定价因子!E:F,2,0) -> 0.99 | V19: =IF(COUNTIFS(户型资产表!E:E,I19,户型资产表!H:H,"操作台")>0,"有","无") -> 有 | W19: =IF(COUNTIFS(户型资产表!E:E,I19,户型资产表!H:H,"书桌")>0,"有","无") -> 有 | X19: {=IF(SUMPRODUCT((户型资产表!E:E=I19)*((户型资产表!I:I="沙发01单人")+(户型资产表!I:I="单人沙发02")))>0,"有","无")} -> 无 | Y19: {=IF(SUMPRODUCT((户型资产表!E:E=I19)*((户型资产表!I:I="沙发02两人")+(户型资产表!I:I="双人沙发01")))>0,"有","无")} -> 无 | Z19: =IF(COUNTIFS(户型资产表!E:E,I19,户型资产表!H:H,"餐桌")>0,"有","无") -> 无 | AA19: =IF(COUNTIFS(户型资产表!E:E,I19,户型资产表!H:H,"吸油烟机")>0,"有","无") -> 无 | AB19: =IF(COUNTIFS(户型资产表!E:E,I19,户型资产表!H:H,"冰箱")>0,"有","无") -> 无 | AC19: =IF(COUNTIFS(户型资产表!E:E,I19,户型资产表!H:H,"电视柜")>0,"有","无") -> 无 | AD19: =IF(J19="开间",IF(AND(V19="无",W19="无"),"缺失",IF(AND(V19="无",W19="有"),"缺失（操作台）",IF(AND(V19="有",W19="无"),"缺失（书桌）",IF(AND(V19="有",W19="有"),IF(OR(AA19="有",Y19="有"),"充足（油烟机/双人沙发）",IF(OR(X19="有",Z19="有"),"充足（单人沙发/餐桌）",IF(AND(OR(X19="有",Y19="有"),Z19="有"),"非常充足","适中"))),"")))),"适中") -> 适中 | AE19: =VLOOKUP($AD$1&AD19,【1】定价因子!E:F,2,0) -> 1 | AF19: =IF(J19="一居室",IF(AND(V19="无",Y19="无",Z19="无"),"缺失",IF(OR(AND(Z19="有",V19="无",Y19="无"),AND(Z19="有",V19="无",Y19="有"),AND(Z19="有",V19="有",Y19="无"),AND(Z19="无",V19="有",Y19="无"),AND(Z19="无",V19="无",Y19="有")),"缺失（操作台/双人沙发）",IF(AND(V19="有",Y19="有",Z19="无"),"缺失（餐桌）",IF(AND(V19="有",Y19="有",Z19="有"),IF(AND(W19="无",AA19="有"),"充配（油烟机）",IF(AND(W19="有",AA19="无"),"充配（书桌）",IF(AND(W19="有",AA19="有"),"非常充配","适中"))),"")))),"适中") -> 适中 | AG19: =VLOOKUP($AF$1&AF19,【1】定价因子!E:F,2,0) -> 1 | AH19: =IF(J19="二居室",IF(AND(Y19="无",Z19="无",AC19="无",V19="无"),"缺失",IF(OR(AND(Y19="无",Z19="无",AC19="有"),AND(Y19="无",Z19="无",V19="有"),AND(Y19="无",Z19="无",AC19="有",V19="有"),AND(Y19="无",Z19="有",AC19="无"),AND(Y19="无",Z19="有",V19="无"),AND(Y19="无",Z19="有",AC19="有"),AND(Y19="无",Z19="有",V19="有"),AND(Y19="有",Z19="无",AC19="无"),AND(Y19="有",Z19="无",V19="无"),AND(Y19="有",Z19="无",AC19="有"),AND(Y19="有",Z19="无",V19="有")),"缺失（沙发/餐桌）",IF(AND(Y19="有",Z19="有",OR(AC19="无",V19="无")),"缺失（电视柜/操作台）",IF(AND(Y19="有",Z19="有",AC19="有",V19="有"),IF(OR(AA19="有",AB19="有"),"充配（油烟机/冰箱）",IF(AND(AA19="无",AB19="无"),"适中","")),"")))),"适中") -> 适中 | AI19: =VLOOKUP($AH$1&AH19,【1】定价因子!E:F,2,0) -> 1 | AJ19: =VLOOKUP(H19,'【3-1】大区填-采光基本要素'!A:H,8,0) -> 2 | AK19: =VLOOKUP($AJ$1&AJ19,【1】定价因子!E:F,2,0) -> 0.96 | AL19: =L19*PRODUCT(AG19,AK19,AE19,U19,S19,Q19,O19) -> 1675.7737 | AM19: 1520 | AN19: =AM19/AL19-1 -> -0.092956279
A20: ='【2】运营中心填-基本信息&审核标准'!$E$2 -> 兴围西4-11栋 | B20: =INT(H20/100) -> 3 | C20: =COUNTIF($B$2:$B$72,B20) -> 8 | D20: =COUNTIF(C$2:C$72,C20) -> 64 | F20: =IF(D20=$E$2,C20,"") -> 8 | H20: 304 | I20: P | J20: 开间 | L20: =VLOOKUP(J20,'【3】大区填-楼栋基准格局定价'!B:H,7,0) -> 1647.8784 | M20: 适中 | N20: 19.76 | O20: =VLOOKUP($M$1&M20,【1】定价因子!E:F,2,0) -> 1 | P20: =IF(COUNTIFS(户型资产表!E:E,I20,户型资产表!H:H,"阳台门")>0,"有","无") -> 无 | Q20: =VLOOKUP($P$1&P20,【1】定价因子!E:F,2,0) -> 1 | R20: =IF('【2】运营中心填-基本信息&审核标准'!$D$4="是","无",IF(INT(H20/100)>9,"9F",INT(H20/100)&"F")) -> 无 | S20: =VLOOKUP(R20,【1】定价因子!D:F,3,0) -> 1 | T20: =IF('【2】运营中心填-基本信息&审核标准'!$D$4="否","无",IF(INT(H20/100)=1,"1F",IF(AND(INT(H20/100)>=2,INT(H20/100)<=3),"2-3F",IF(INT(H20/100)=4,"4F",IF(AND(INT(H20/100)>=5,INT(H20/100)<=6),"5-6F",IF(AND(INT(H20/100)>=7,INT(H20/100)<=8),"7-8F",IF(AND(INT(H20/100)>=9,INT(H20/100)<=10),"9-10F",IF(AND(INT(H20/100)>=11,INT(H20/100)<=12),"11-12F",IF(INT(H20/100)>=13,"13以上F",""))))))))) -> 2-3F | U20: =VLOOKUP($T$1&T20,【1】定价因子!E:F,2,0) -> 0.99 | V20: =IF(COUNTIFS(户型资产表!E:E,I20,户型资产表!H:H,"操作台")>0,"有","无") -> 有 | W20: =IF(COUNTIFS(户型资产表!E:E,I20,户型资产表!H:H,"书桌")>0,"有","无") -> 有 | X20: {=IF(SUMPRODUCT((户型资产表!E:E=I20)*((户型资产表!I:I="沙发01单人")+(户型资产表!I:I="单人沙发02")))>0,"有","无")} -> 无 | Y20: {=IF(SUMPRODUCT((户型资产表!E:E=I20)*((户型资产表!I:I="沙发02两人")+(户型资产表!I:I="双人沙发01")))>0,"有","无")} -> 无 | Z20: =IF(COUNTIFS(户型资产表!E:E,I20,户型资产表!H:H,"餐桌")>0,"有","无") -> 无 | AA20: =IF(COUNTIFS(户型资产表!E:E,I20,户型资产表!H:H,"吸油烟机")>0,"有","无") -> 无 | AB20: =IF(COUNTIFS(户型资产表!E:E,I20,户型资产表!H:H,"冰箱")>0,"有","无") -> 无 | AC20: =IF(COUNTIFS(户型资产表!E:E,I20,户型资产表!H:H,"电视柜")>0,"有","无") -> 无 | AD20: =IF(J20="开间",IF(AND(V20="无",W20="无"),"缺失",IF(AND(V20="无",W20="有"),"缺失（操作台）",IF(AND(V20="有",W20="无"),"缺失（书桌）",IF(AND(V20="有",W20="有"),IF(OR(AA20="有",Y20="有"),"充足（油烟机/双人沙发）",IF(OR(X20="有",Z20="有"),"充足（单人沙发/餐桌）",IF(AND(OR(X20="有",Y20="有"),Z20="有"),"非常充足","适中"))),"")))),"适中") -> 适中 | AE20: =VLOOKUP($AD$1&AD20,【1】定价因子!E:F,2,0) -> 1 | AF20: =IF(J20="一居室",IF(AND(V20="无",Y20="无",Z20="无"),"缺失",IF(OR(AND(Z20="有",V20="无",Y20="无"),AND(Z20="有",V20="无",Y20="有"),AND(Z20="有",V20="有",Y20="无"),AND(Z20="无",V20="有",Y20="无"),AND(Z20="无",V20="无",Y20="有")),"缺失（操作台/双人沙发）",IF(AND(V20="有",Y20="有",Z20="无"),"缺失（餐桌）",IF(AND(V20="有",Y20="有",Z20="有"),IF(AND(W20="无",AA20="有"),"充配（油烟机）",IF(AND(W20="有",AA20="无"),"充配（书桌）",IF(AND(W20="有",AA20="有"),"非常充配","适中"))),"")))),"适中") -> 适中 | AG20: =VLOOKUP($AF$1&AF20,【1】定价因子!E:F,2,0) -> 1 | AH20: =IF(J20="二居室",IF(AND(Y20="无",Z20="无",AC20="无",V20="无"),"缺失",IF(OR(AND(Y20="无",Z20="无",AC20="有"),AND(Y20="无",Z20="无",V20="有"),AND(Y20="无",Z20="无",AC20="有",V20="有"),AND(Y20="无",Z20="有",AC20="无"),AND(Y20="无",Z20="有",V20="无"),AND(Y20="无",Z20="有",AC20="有"),AND(Y20="无",Z20="有",V20="有"),AND(Y20="有",Z20="无",AC20="无"),AND(Y20="有",Z20="无",V20="无"),AND(Y20="有",Z20="无",AC20="有"),AND(Y20="有",Z20="无",V20="有")),"缺失（沙发/餐桌）",IF(AND(Y20="有",Z20="有",OR(AC20="无",V20="无")),"缺失（电视柜/操作台）",IF(AND(Y20="有",Z20="有",AC20="有",V20="有"),IF(OR(AA20="有",AB20="有"),"充配（油烟机/冰箱）",IF(AND(AA20="无",AB20="无"),"适中","")),"")))),"适中") -> 适中 | AI20: =VLOOKUP($AH$1&AH20,【1】定价因子!E:F,2,0) -> 1 | AJ20: =VLOOKUP(H20,'【3-1】大区填-采光基本要素'!A:H,8,0) -> 1 | AK20: =VLOOKUP($AJ$1&AJ20,【1】定价因子!E:F,2,0) -> 0.91 | AL20: =L20*PRODUCT(AG20,AK20,AE20,U20,S20,Q20,O20) -> 1484.5737 | AM20: 1430 | AN20: =AM20/AL20-1 -> -0.036760487
A21: ='【2】运营中心填-基本信息&审核标准'!$E$2 -> 兴围西4-11栋 | B21: =INT(H21/100) -> 3 | C21: =COUNTIF($B$2:$B$72,B21) -> 8 | D21: =COUNTIF(C$2:C$72,C21) -> 64 | F21: =IF(D21=$E$2,C21,"") -> 8 | H21: 305 | I21: K | J21: 开间 | L21: =VLOOKUP(J21,'【3】大区填-楼栋基准格局定价'!B:H,7,0) -> 1647.8784 | M21: =IF(OR(J21="开间",J21="二人宿舍"),IF(N21<10,"很狭小",IF(N21<13,"较狭小",IF(N21<17,"适中",IF(N21<20,"较宽敞","很宽敞")))),IF(OR(J21="一居室",J21="四人宿舍"),IF(N21<20,"很狭小",IF(N21<23,"较狭小",IF(N21<26,"适中",IF(N21<28,"较宽敞","很宽敞")))),IF(OR(J21="二居室",J21="六人宿舍"),IF(N21<30,"很狭小",IF(N21<35,"较狭小",IF(N21<40,"适中",IF(N21<45,"较宽敞","很宽敞")))),""))) -> 适中 | N21: 13.79 | O21: =VLOOKUP($M$1&M21,【1】定价因子!E:F,2,0) -> 1 | P21: =IF(COUNTIFS(户型资产表!E:E,I21,户型资产表!H:H,"阳台门")>0,"有","无") -> 无 | Q21: =VLOOKUP($P$1&P21,【1】定价因子!E:F,2,0) -> 1 | R21: =IF('【2】运营中心填-基本信息&审核标准'!$D$4="是","无",IF(INT(H21/100)>9,"9F",INT(H21/100)&"F")) -> 无 | S21: =VLOOKUP(R21,【1】定价因子!D:F,3,0) -> 1 | T21: =IF('【2】运营中心填-基本信息&审核标准'!$D$4="否","无",IF(INT(H21/100)=1,"1F",IF(AND(INT(H21/100)>=2,INT(H21/100)<=3),"2-3F",IF(INT(H21/100)=4,"4F",IF(AND(INT(H21/100)>=5,INT(H21/100)<=6),"5-6F",IF(AND(INT(H21/100)>=7,INT(H21/100)<=8),"7-8F",IF(AND(INT(H21/100)>=9,INT(H21/100)<=10),"9-10F",IF(AND(INT(H21/100)>=11,INT(H21/100)<=12),"11-12F",IF(INT(H21/100)>=13,"13以上F",""))))))))) -> 2-3F | U21: =VLOOKUP($T$1&T21,【1】定价因子!E:F,2,0) -> 0.99 | V21: =IF(COUNTIFS(户型资产表!E:E,I21,户型资产表!H:H,"操作台")>0,"有","无") -> 有 | W21: =IF(COUNTIFS(户型资产表!E:E,I21,户型资产表!H:H,"书桌")>0,"有","无") -> 有 | X21: {=IF(SUMPRODUCT((户型资产表!E:E=I21)*((户型资产表!I:I="沙发01单人")+(户型资产表!I:I="单人沙发02")))>0,"有","无")} -> 无 | Y21: {=IF(SUMPRODUCT((户型资产表!E:E=I21)*((户型资产表!I:I="沙发02两人")+(户型资产表!I:I="双人沙发01")))>0,"有","无")} -> 无 | Z21: =IF(COUNTIFS(户型资产表!E:E,I21,户型资产表!H:H,"餐桌")>0,"有","无") -> 无 | AA21: =IF(COUNTIFS(户型资产表!E:E,I21,户型资产表!H:H,"吸油烟机")>0,"有","无") -> 无 | AB21: =IF(COUNTIFS(户型资产表!E:E,I21,户型资产表!H:H,"冰箱")>0,"有","无") -> 无 | AC21: =IF(COUNTIFS(户型资产表!E:E,I21,户型资产表!H:H,"电视柜")>0,"有","无") -> 无 | AD21: =IF(J21="开间",IF(AND(V21="无",W21="无"),"缺失",IF(AND(V21="无",W21="有"),"缺失（操作台）",IF(AND(V21="有",W21="无"),"缺失（书桌）",IF(AND(V21="有",W21="有"),IF(OR(AA21="有",Y21="有"),"充足（油烟机/双人沙发）",IF(OR(X21="有",Z21="有"),"充足（单人沙发/餐桌）",IF(AND(OR(X21="有",Y21="有"),Z21="有"),"非常充足","适中"))),"")))),"适中") -> 适中 | AE21: =VLOOKUP($AD$1&AD21,【1】定价因子!E:F,2,0) -> 1 | AF21: =IF(J21="一居室",IF(AND(V21="无",Y21="无",Z21="无"),"缺失",IF(OR(AND(Z21="有",V21="无",Y21="无"),AND(Z21="有",V21="无",Y21="有"),AND(Z21="有",V21="有",Y21="无"),AND(Z21="无",V21="有",Y21="无"),AND(Z21="无",V21="无",Y21="有")),"缺失（操作台/双人沙发）",IF(AND(V21="有",Y21="有",Z21="无"),"缺失（餐桌）",IF(AND(V21="有",Y21="有",Z21="有"),IF(AND(W21="无",AA21="有"),"充配（油烟机）",IF(AND(W21="有",AA21="无"),"充配（书桌）",IF(AND(W21="有",AA21="有"),"非常充配","适中"))),"")))),"适中") -> 适中 | AG21: =VLOOKUP($AF$1&AF21,【1】定价因子!E:F,2,0) -> 1 | AH21: =IF(J21="二居室",IF(AND(Y21="无",Z21="无",AC21="无",V21="无"),"缺失",IF(OR(AND(Y21="无",Z21="无",AC21="有"),AND(Y21="无",Z21="无",V21="有"),AND(Y21="无",Z21="无",AC21="有",V21="有"),AND(Y21="无",Z21="有",AC21="无"),AND(Y21="无",Z21="有",V21="无"),AND(Y21="无",Z21="有",AC21="有"),AND(Y21="无",Z21="有",V21="有"),AND(Y21="有",Z21="无",AC21="无"),AND(Y21="有",Z21="无",V21="无"),AND(Y21="有",Z21="无",AC21="有"),AND(Y21="有",Z21="无",V21="有")),"缺失（沙发/餐桌）",IF(AND(Y21="有",Z21="有",OR(AC21="无",V21="无")),"缺失（电视柜/操作台）",IF(AND(Y21="有",Z21="有",AC21="有",V21="有"),IF(OR(AA21="有",AB21="有"),"充配（油烟机/冰箱）",IF(AND(AA21="无",AB21="无"),"适中","")),"")))),"适中") -> 适中 | AI21: =VLOOKUP($AH$1&AH21,【1】定价因子!E:F,2,0) -> 1 | AJ21: =VLOOKUP(H21,'【3-1】大区填-采光基本要素'!A:H,8,0) -> 2 | AK21: =VLOOKUP($AJ$1&AJ21,【1】定价因子!E:F,2,0) -> 0.96 | AL21: =L21*PRODUCT(AG21,AK21,AE21,U21,S21,Q21,O21) -> 1566.1436 | AM21: 1430 | AN21: =AM21/AL21-1 -> -0.086929212
A22: ='【2】运营中心填-基本信息&审核标准'!$E$2 -> 兴围西4-11栋 | B22: =INT(H22/100) -> 3 | C22: =COUNTIF($B$2:$B$72,B22) -> 8 | D22: =COUNTIF(C$2:C$72,C22) -> 64 | F22: =IF(D22=$E$2,C22,"") -> 8 | H22: 306 | I22: L | J22: 一居室 | L22: =VLOOKUP(J22,'【3】大区填-楼栋基准格局定价'!B:H,7,0) -> 2445.5088 | M22: =IF(OR(J22="开间",J22="二人宿舍"),IF(N22<10,"很狭小",IF(N22<13,"较狭小",IF(N22<17,"适中",IF(N22<20,"较宽敞","很宽敞")))),IF(OR(J22="一居室",J22="四人宿舍"),IF(N22<20,"很狭小",IF(N22<23,"较狭小",IF(N22<26,"适中",IF(N22<28,"较宽敞","很宽敞")))),IF(OR(J22="二居室",J22="六人宿舍"),IF(N22<30,"很狭小",IF(N22<35,"较狭小",IF(N22<40,"适中",IF(N22<45,"较宽敞","很宽敞")))),""))) -> 很狭小 | N22: 11.35 | O22: =VLOOKUP($M$1&M22,【1】定价因子!E:F,2,0) -> 0.9 | P22: =IF(COUNTIFS(户型资产表!E:E,I22,户型资产表!H:H,"阳台门")>0,"有","无") -> 无 | Q22: =VLOOKUP($P$1&P22,【1】定价因子!E:F,2,0) -> 1 | R22: =IF('【2】运营中心填-基本信息&审核标准'!$D$4="是","无",IF(INT(H22/100)>9,"9F",INT(H22/100)&"F")) -> 无 | S22: =VLOOKUP(R22,【1】定价因子!D:F,3,0) -> 1 | T22: =IF('【2】运营中心填-基本信息&审核标准'!$D$4="否","无",IF(INT(H22/100)=1,"1F",IF(AND(INT(H22/100)>=2,INT(H22/100)<=3),"2-3F",IF(INT(H22/100)=4,"4F",IF(AND(INT(H22/100)>=5,INT(H22/100)<=6),"5-6F",IF(AND(INT(H22/100)>=7,INT(H22/100)<=8),"7-8F",IF(AND(INT(H22/100)>=9,INT(H22/100)<=10),"9-10F",IF(AND(INT(H22/100)>=11,INT(H22/100)<=12),"11-12F",IF(INT(H22/100)>=13,"13以上F",""))))))))) -> 2-3F | U22: =VLOOKUP($T$1&T22,【1】定价因子!E:F,2,0) -> 0.99 | V22: =IF(COUNTIFS(户型资产表!E:E,I22,户型资产表!H:H,"操作台")>0,"有","无") -> 有 | W22: =IF(COUNTIFS(户型资产表!E:E,I22,户型资产表!H:H,"书桌")>0,"有","无") -> 无 | X22: {=IF(SUMPRODUCT((户型资产表!E:E=I22)*((户型资产表!I:I="沙发01单人")+(户型资产表!I:I="单人沙发02")))>0,"有","无")} -> 无 | Y22: {=IF(SUMPRODUCT((户型资产表!E:E=I22)*((户型资产表!I:I="沙发02两人")+(户型资产表!I:I="双人沙发01")))>0,"有","无")} -> 有 | Z22: =IF(COUNTIFS(户型资产表!E:E,I22,户型资产表!H:H,"餐桌")>0,"有","无") -> 有 | AA22: =IF(COUNTIFS(户型资产表!E:E,I22,户型资产表!H:H,"吸油烟机")>0,"有","无") -> 无 | AB22: =IF(COUNTIFS(户型资产表!E:E,I22,户型资产表!H:H,"冰箱")>0,"有","无") -> 无 | AC22: =IF(COUNTIFS(户型资产表!E:E,I22,户型资产表!H:H,"电视柜")>0,"有","无") -> 无 | AD22: =IF(J22="开间",IF(AND(V22="无",W22="无"),"缺失",IF(AND(V22="无",W22="有"),"缺失（操作台）",IF(AND(V22="有",W22="无"),"缺失（书桌）",IF(AND(V22="有",W22="有"),IF(OR(AA22="有",Y22="有"),"充足（油烟机/双人沙发）",IF(OR(X22="有",Z22="有"),"充足（单人沙发/餐桌）",IF(AND(OR(X22="有",Y22="有"),Z22="有"),"非常充足","适中"))),"")))),"适中") -> 适中 | AE22: =VLOOKUP($AD$1&AD22,【1】定价因子!E:F,2,0) -> 1 | AF22: =IF(J22="一居室",IF(AND(V22="无",Y22="无",Z22="无"),"缺失",IF(OR(AND(Z22="有",V22="无",Y22="无"),AND(Z22="有",V22="无",Y22="有"),AND(Z22="有",V22="有",Y22="无"),AND(Z22="无",V22="有",Y22="无"),AND(Z22="无",V22="无",Y22="有")),"缺失（操作台/双人沙发）",IF(AND(V22="有",Y22="有",Z22="无"),"缺失（餐桌）",IF(AND(V22="有",Y22="有",Z22="有"),IF(AND(W22="无",AA22="有"),"充配（油烟机）",IF(AND(W22="有",AA22="无"),"充配（书桌）",IF(AND(W22="有",AA22="有"),"非常充配","适中"))),"")))),"适中") -> 适中 | AG22: =VLOOKUP($AF$1&AF22,【1】定价因子!E:F,2,0) -> 1 | AH22: =IF(J22="二居室",IF(AND(Y22="无",Z22="无",AC22="无",V22="无"),"缺失",IF(OR(AND(Y22="无",Z22="无",AC22="有"),AND(Y22="无",Z22="无",V22="有"),AND(Y22="无",Z22="无",AC22="有",V22="有"),AND(Y22="无",Z22="有",AC22="无"),AND(Y22="无",Z22="有",V22="无"),AND(Y22="无",Z22="有",AC22="有"),AND(Y22="无",Z22="有",V22="有"),AND(Y22="有",Z22="无",AC22="无"),AND(Y22="有",Z22="无",V22="无"),AND(Y22="有",Z22="无",AC22="有"),AND(Y22="有",Z22="无",V22="有")),"缺失（沙发/餐桌）",IF(AND(Y22="有",Z22="有",OR(AC22="无",V22="无")),"缺失（电视柜/操作台）",IF(AND(Y22="有",Z22="有",AC22="有",V22="有"),IF(OR(AA22="有",AB22="有"),"充配（油烟机/冰箱）",IF(AND(AA22="无",AB22="无"),"适中","")),"")))),"适中") -> 适中 | AI22: =VLOOKUP($AH$1&AH22,【1】定价因子!E:F,2,0) -> 1 | AJ22: =VLOOKUP(H22,'【3-1】大区填-采光基本要素'!A:H,8,0) -> 1 | AK22: =VLOOKUP($AJ$1&AJ22,【1】定价因子!E:F,2,0) -> 0.91 | AL22: =L22*PRODUCT(AG22,AK22,AE22,U22,S22,Q22,O22) -> 1982.843 | AM22: 1980 | AN22: =AM22/AL22-1 -> -0.0014337949
A23: ='【2】运营中心填-基本信息&审核标准'!$E$2 -> 兴围西4-11栋 | B23: =INT(H23/100) -> 3 | C23: =COUNTIF($B$2:$B$72,B23) -> 8 | D23: =COUNTIF(C$2:C$72,C23) -> 64 | F23: =IF(D23=$E$2,C23,"") -> 8 | H23: 307 | I23: J | J23: 开间 | L23: =VLOOKUP(J23,'【3】大区填-楼栋基准格局定价'!B:H,7,0) -> 1647.8784 | M23: =IF(OR(J23="开间",J23="二人宿舍"),IF(N23<10,"很狭小",IF(N23<13,"较狭小",IF(N23<17,"适中",IF(N23<20,"较宽敞","很宽敞")))),IF(OR(J23="一居室",J23="四人宿舍"),IF(N23<20,"很狭小",IF(N23<23,"较狭小",IF(N23<26,"适中",IF(N23<28,"较宽敞","很宽敞")))),IF(OR(J23="二居室",J23="六人宿舍"),IF(N23<30,"很狭小",IF(N23<35,"较狭小",IF(N23<40,"适中",IF(N23<45,"较宽敞","很宽敞")))),""))) -> 适中 | N23: 13.81 | O23: =VLOOKUP($M$1&M23,【1】定价因子!E:F,2,0) -> 1 | P23: =IF(COUNTIFS(户型资产表!E:E,I23,户型资产表!H:H,"阳台门")>0,"有","无") -> 无 | Q23: =VLOOKUP($P$1&P23,【1】定价因子!E:F,2,0) -> 1 | R23: =IF('【2】运营中心填-基本信息&审核标准'!$D$4="是","无",IF(INT(H23/100)>9,"9F",INT(H23/100)&"F")) -> 无 | S23: =VLOOKUP(R23,【1】定价因子!D:F,3,0) -> 1 | T23: =IF('【2】运营中心填-基本信息&审核标准'!$D$4="否","无",IF(INT(H23/100)=1,"1F",IF(AND(INT(H23/100)>=2,INT(H23/100)<=3),"2-3F",IF(INT(H23/100)=4,"4F",IF(AND(INT(H23/100)>=5,INT(H23/100)<=6),"5-6F",IF(AND(INT(H23/100)>=7,INT(H23/100)<=8),"7-8F",IF(AND(INT(H23/100)>=9,INT(H23/100)<=10),"9-10F",IF(AND(INT(H23/100)>=11,INT(H23/100)<=12),"11-12F",IF(INT(H23/100)>=13,"13以上F",""))))))))) -> 2-3F | U23: =VLOOKUP($T$1&T23,【1】定价因子!E:F,2,0) -> 0.99 | V23: =IF(COUNTIFS(户型资产表!E:E,I23,户型资产表!H:H,"操作台")>0,"有","无") -> 有 | W23: =IF(COUNTIFS(户型资产表!E:E,I23,户型资产表!H:H,"书桌")>0,"有","无") -> 有 | X23: {=IF(SUMPRODUCT((户型资产表!E:E=I23)*((户型资产表!I:I="沙发01单人")+(户型资产表!I:I="单人沙发02")))>0,"有","无")} -> 无 | Y23: {=IF(SUMPRODUCT((户型资产表!E:E=I23)*((户型资产表!I:I="沙发02两人")+(户型资产表!I:I="双人沙发01")))>0,"有","无")} -> 无 | Z23: =IF(COUNTIFS(户型资产表!E:E,I23,户型资产表!H:H,"餐桌")>0,"有","无") -> 无 | AA23: =IF(COUNTIFS(户型资产表!E:E,I23,户型资产表!H:H,"吸油烟机")>0,"有","无") -> 无 | AB23: =IF(COUNTIFS(户型资产表!E:E,I23,户型资产表!H:H,"冰箱")>0,"有","无") -> 无 | AC23: =IF(COUNTIFS(户型资产表!E:E,I23,户型资产表!H:H,"电视柜")>0,"有","无") -> 无 | AD23: =IF(J23="开间",IF(AND(V23="无",W23="无"),"缺失",IF(AND(V23="无",W23="有"),"缺失（操作台）",IF(AND(V23="有",W23="无"),"缺失（书桌）",IF(AND(V23="有",W23="有"),IF(OR(AA23="有",Y23="有"),"充足（油烟机/双人沙发）",IF(OR(X23="有",Z23="有"),"充足（单人沙发/餐桌）",IF(AND(OR(X23="有",Y23="有"),Z23="有"),"非常充足","适中"))),"")))),"适中") -> 适中 | AE23: =VLOOKUP($AD$1&AD23,【1】定价因子!E:F,2,0) -> 1 | AF23: =IF(J23="一居室",IF(AND(V23="无",Y23="无",Z23="无"),"缺失",IF(OR(AND(Z23="有",V23="无",Y23="无"),AND(Z23="有",V23="无",Y23="有"),AND(Z23="有",V23="有",Y23="无"),AND(Z23="无",V23="有",Y23="无"),AND(Z23="无",V23="无",Y23="有")),"缺失（操作台/双人沙发）",IF(AND(V23="有",Y23="有",Z23="无"),"缺失（餐桌）",IF(AND(V23="有",Y23="有",Z23="有"),IF(AND(W23="无",AA23="有"),"充配（油烟机）",IF(AND(W23="有",AA23="无"),"充配（书桌）",IF(AND(W23="有",AA23="有"),"非常充配","适中"))),"")))),"适中") -> 适中 | AG23: =VLOOKUP($AF$1&AF23,【1】定价因子!E:F,2,0) -> 1 | AH23: =IF(J23="二居室",IF(AND(Y23="无",Z23="无",AC23="无",V23="无"),"缺失",IF(OR(AND(Y23="无",Z23="无",AC23="有"),AND(Y23="无",Z23="无",V23="有"),AND(Y23="无",Z23="无",AC23="有",V23="有"),AND(Y23="无",Z23="有",AC23="无"),AND(Y23="无",Z23="有",V23="无"),AND(Y23="无",Z23="有",AC23="有"),AND(Y23="无",Z23="有",V23="有"),AND(Y23="有",Z23="无",AC23="无"),AND(Y23="有",Z23="无",V23="无"),AND(Y23="有",Z23="无",AC23="有"),AND(Y23="有",Z23="无",V23="有")),"缺失（沙发/餐桌）",IF(AND(Y23="有",Z23="有",OR(AC23="无",V23="无")),"缺失（电视柜/操作台）",IF(AND(Y23="有",Z23="有",AC23="有",V23="有"),IF(OR(AA23="有",AB23="有"),"充配（油烟机/冰箱）",IF(AND(AA23="无",AB23="无"),"适中","")),"")))),"适中") -> 适中 | AI23: =VLOOKUP($AH$1&AH23,【1】定价因子!E:F,2,0) -> 1 | AJ23: =VLOOKUP(H23,'【3-1】大区填-采光基本要素'!A:H,8,0) -> 1 | AK23: =VLOOKUP($AJ$1&AJ23,【1】定价因子!E:F,2,0) -> 0.91 | AL23: =L23*PRODUCT(AG23,AK23,AE23,U23,S23,Q23,O23) -> 1484.5737 | AM23: 1430 | AN23: =AM23/AL23-1 -> -0.036760487
A24: ='【2】运营中心填-基本信息&审核标准'!$E$2 -> 兴围西4-11栋 | B24: =INT(H24/100) -> 3 | C24: =COUNTIF($B$2:$B$72,B24) -> 8 | D24: =COUNTIF(C$2:C$72,C24) -> 64 | F24: =IF(D24=$E$2,C24,"") -> 8 | H24: 308 | I24: Q | J24: 一居室 | L24: =VLOOKUP(J24,'【3】大区填-楼栋基准格局定价'!B:H,7,0) -> 2445.5088 | M24: =IF(OR(J24="开间",J24="二人宿舍"),IF(N24<10,"很狭小",IF(N24<13,"较狭小",IF(N24<17,"适中",IF(N24<20,"较宽敞","很宽敞")))),IF(OR(J24="一居室",J24="四人宿舍"),IF(N24<20,"很狭小",IF(N24<23,"较狭小",IF(N24<26,"适中",IF(N24<28,"较宽敞","很宽敞")))),IF(OR(J24="二居室",J24="六人宿舍"),IF(N24<30,"很狭小",IF(N24<35,"较狭小",IF(N24<40,"适中",IF(N24<45,"较宽敞","很宽敞")))),""))) -> 较狭小 | N24: 20.04 | O24: =VLOOKUP($M$1&M24,【1】定价因子!E:F,2,0) -> 0.95 | P24: =IF(COUNTIFS(户型资产表!E:E,I24,户型资产表!H:H,"阳台门")>0,"有","无") -> 无 | Q24: =VLOOKUP($P$1&P24,【1】定价因子!E:F,2,0) -> 1 | R24: =IF('【2】运营中心填-基本信息&审核标准'!$D$4="是","无",IF(INT(H24/100)>9,"9F",INT(H24/100)&"F")) -> 无 | S24: =VLOOKUP(R24,【1】定价因子!D:F,3,0) -> 1 | T24: =IF('【2】运营中心填-基本信息&审核标准'!$D$4="否","无",IF(INT(H24/100)=1,"1F",IF(AND(INT(H24/100)>=2,INT(H24/100)<=3),"2-3F",IF(INT(H24/100)=4,"4F",IF(AND(INT(H24/100)>=5,INT(H24/100)<=6),"5-6F",IF(AND(INT(H24/100)>=7,INT(H24/100)<=8),"7-8F",IF(AND(INT(H24/100)>=9,INT(H24/100)<=10),"9-10F",IF(AND(INT(H24/100)>=11,INT(H24/100)<=12),"11-12F",IF(INT(H24/100)>=13,"13以上F",""))))))))) -> 2-3F | U24: =VLOOKUP($T$1&T24,【1】定价因子!E:F,2,0) -> 0.99 | V24: =IF(COUNTIFS(户型资产表!E:E,I24,户型资产表!H:H,"操作台")>0,"有","无") -> 有 | W24: =IF(COUNTIFS(户型资产表!E:E,I24,户型资产表!H:H,"书桌")>0,"有","无") -> 无 | X24: {=IF(SUMPRODUCT((户型资产表!E:E=I24)*((户型资产表!I:I="沙发01单人")+(户型资产表!I:I="单人沙发02")))>0,"有","无")} -> 无 | Y24: {=IF(SUMPRODUCT((户型资产表!E:E=I24)*((户型资产表!I:I="沙发02两人")+(户型资产表!I:I="双人沙发01")))>0,"有","无")} -> 有 | Z24: =IF(COUNTIFS(户型资产表!E:E,I24,户型资产表!H:H,"餐桌")>0,"有","无") -> 有 | AA24: =IF(COUNTIFS(户型资产表!E:E,I24,户型资产表!H:H,"吸油烟机")>0,"有","无") -> 有 | AB24: =IF(COUNTIFS(户型资产表!E:E,I24,户型资产表!H:H,"冰箱")>0,"有","无") -> 无 | AC24: =IF(COUNTIFS(户型资产表!E:E,I24,户型资产表!H:H,"电视柜")>0,"有","无") -> 无 | AD24: =IF(J24="开间",IF(AND(V24="无",W24="无"),"缺失",IF(AND(V24="无",W24="有"),"缺失（操作台）",IF(AND(V24="有",W24="无"),"缺失（书桌）",IF(AND(V24="有",W24="有"),IF(OR(AA24="有",Y24="有"),"充足（油烟机/双人沙发）",IF(OR(X24="有",Z24="有"),"充足（单人沙发/餐桌）",IF(AND(OR(X24="有",Y24="有"),Z24="有"),"非常充足","适中"))),"")))),"适中") -> 适中 | AE24: =VLOOKUP($AD$1&AD24,【1】定价因子!E:F,2,0) -> 1 | AF24: 适中 | AG24: =VLOOKUP($AF$1&AF24,【1】定价因子!E:F,2,0) -> 1 | AH24: =IF(J24="二居室",IF(AND(Y24="无",Z24="无",AC24="无",V24="无"),"缺失",IF(OR(AND(Y24="无",Z24="无",AC24="有"),AND(Y24="无",Z24="无",V24="有"),AND(Y24="无",Z24="无",AC24="有",V24="有"),AND(Y24="无",Z24="有",AC24="无"),AND(Y24="无",Z24="有",V24="无"),AND(Y24="无",Z24="有",AC24="有"),AND(Y24="无",Z24="有",V24="有"),AND(Y24="有",Z24="无",AC24="无"),AND(Y24="有",Z24="无",V24="无"),AND(Y24="有",Z24="无",AC24="有"),AND(Y24="有",Z24="无",V24="有")),"缺失（沙发/餐桌）",IF(AND(Y24="有",Z24="有",OR(AC24="无",V24="无")),"缺失（电视柜/操作台）",IF(AND(Y24="有",Z24="有",AC24="有",V24="有"),IF(OR(AA24="有",AB24="有"),"充配（油烟机/冰箱）",IF(AND(AA24="无",AB24="无"),"适中","")),"")))),"适中") -> 适中 | AI24: =VLOOKUP($AH$1&AH24,【1】定价因子!E:F,2,0) -> 1 | AJ24: =VLOOKUP(H24,'【3-1】大区填-采光基本要素'!A:H,8,0) -> 2 | AK24: =VLOOKUP($AJ$1&AJ24,【1】定价因子!E:F,2,0) -> 0.96 | AL24: =L24*PRODUCT(AG24,AK24,AE24,U24,S24,Q24,O24) -> 2208.001 | AM24: 2080 | AN24: =AM24/AL24-1 -> -0.057971435
A25: ='【2】运营中心填-基本信息&审核标准'!$E$2 -> 兴围西4-11栋 | B25: =INT(H25/100) -> 4 | C25: =COUNTIF($B$2:$B$72,B25) -> 8 | D25: =COUNTIF(C$2:C$72,C25) -> 64 | F25: =IF(D25=$E$2,C25,"") -> 8 | H25: 401 | I25: N | J25: 开间 | L25: =VLOOKUP(J25,'【3】大区填-楼栋基准格局定价'!B:H,7,0) -> 1647.8784 | M25: =IF(OR(J25="开间",J25="二人宿舍"),IF(N25<10,"很狭小",IF(N25<13,"较狭小",IF(N25<17,"适中",IF(N25<20,"较宽敞","很宽敞")))),IF(OR(J25="一居室",J25="四人宿舍"),IF(N25<20,"很狭小",IF(N25<23,"较狭小",IF(N25<26,"适中",IF(N25<28,"较宽敞","很宽敞")))),IF(OR(J25="二居室",J25="六人宿舍"),IF(N25<30,"很狭小",IF(N25<35,"较狭小",IF(N25<40,"适中",IF(N25<45,"较宽敞","很宽敞")))),""))) -> 较狭小 | N25: 10.96 | O25: =VLOOKUP($M$1&M25,【1】定价因子!E:F,2,0) -> 0.95 | P25: =IF(COUNTIFS(户型资产表!E:E,I25,户型资产表!H:H,"阳台门")>0,"有","无") -> 无 | Q25: =VLOOKUP($P$1&P25,【1】定价因子!E:F,2,0) -> 1 | R25: =IF('【2】运营中心填-基本信息&审核标准'!$D$4="是","无",IF(INT(H25/100)>9,"9F",INT(H25/100)&"F")) -> 无 | S25: =VLOOKUP(R25,【1】定价因子!D:F,3,0) -> 1 | T25: =IF('【2】运营中心填-基本信息&审核标准'!$D$4="否","无",IF(INT(H25/100)=1,"1F",IF(AND(INT(H25/100)>=2,INT(H25/100)<=3),"2-3F",IF(INT(H25/100)=4,"4F",IF(AND(INT(H25/100)>=5,INT(H25/100)<=6),"5-6F",IF(AND(INT(H25/100)>=7,INT(H25/100)<=8),"7-8F",IF(AND(INT(H25/100)>=9,INT(H25/100)<=10),"9-10F",IF(AND(INT(H25/100)>=11,INT(H25/100)<=12),"11-12F",IF(INT(H25/100)>=13,"13以上F",""))))))))) -> 4F | U25: =VLOOKUP($T$1&T25,【1】定价因子!E:F,2,0) -> 1 | V25: =IF(COUNTIFS(户型资产表!E:E,I25,户型资产表!H:H,"操作台")>0,"有","无") -> 有 | W25: =IF(COUNTIFS(户型资产表!E:E,I25,户型资产表!H:H,"书桌")>0,"有","无") -> 有 | X25: {=IF(SUMPRODUCT((户型资产表!E:E=I25)*((户型资产表!I:I="沙发01单人")+(户型资产表!I:I="单人沙发02")))>0,"有","无")} -> 无 | Y25: {=IF(SUMPRODUCT((户型资产表!E:E=I25)*((户型资产表!I:I="沙发02两人")+(户型资产表!I:I="双人沙发01")))>0,"有","无")} -> 无 | Z25: =IF(COUNTIFS(户型资产表!E:E,I25,户型资产表!H:H,"餐桌")>0,"有","无") -> 无 | AA25: =IF(COUNTIFS(户型资产表!E:E,I25,户型资产表!H:H,"吸油烟机")>0,"有","无") -> 无 | AB25: =IF(COUNTIFS(户型资产表!E:E,I25,户型资产表!H:H,"冰箱")>0,"有","无") -> 无 | AC25: =IF(COUNTIFS(户型资产表!E:E,I25,户型资产表!H:H,"电视柜")>0,"有","无") -> 无 | AD25: =IF(J25="开间",IF(AND(V25="无",W25="无"),"缺失",IF(AND(V25="无",W25="有"),"缺失（操作台）",IF(AND(V25="有",W25="无"),"缺失（书桌）",IF(AND(V25="有",W25="有"),IF(OR(AA25="有",Y25="有"),"充足（油烟机/双人沙发）",IF(OR(X25="有",Z25="有"),"充足（单人沙发/餐桌）",IF(AND(OR(X25="有",Y25="有"),Z25="有"),"非常充足","适中"))),"")))),"适中") -> 适中 | AE25: =VLOOKUP($AD$1&AD25,【1】定价因子!E:F,2,0) -> 1 | AF25: =IF(J25="一居室",IF(AND(V25="无",Y25="无",Z25="无"),"缺失",IF(OR(AND(Z25="有",V25="无",Y25="无"),AND(Z25="有",V25="无",Y25="有"),AND(Z25="有",V25="有",Y25="无"),AND(Z25="无",V25="有",Y25="无"),AND(Z25="无",V25="无",Y25="有")),"缺失（操作台/双人沙发）",IF(AND(V25="有",Y25="有",Z25="无"),"缺失（餐桌）",IF(AND(V25="有",Y25="有",Z25="有"),IF(AND(W25="无",AA25="有"),"充配（油烟机）",IF(AND(W25="有",AA25="无"),"充配（书桌）",IF(AND(W25="有",AA25="有"),"非常充配","适中"))),"")))),"适中") -> 适中 | AG25: =VLOOKUP($AF$1&AF25,【1】定价因子!E:F,2,0) -> 1 | AH25: =IF(J25="二居室",IF(AND(Y25="无",Z25="无",AC25="无",V25="无"),"缺失",IF(OR(AND(Y25="无",Z25="无",AC25="有"),AND(Y25="无",Z25="无",V25="有"),AND(Y25="无",Z25="无",AC25="有",V25="有"),AND(Y25="无",Z25="有",AC25="无"),AND(Y25="无",Z25="有",V25="无"),AND(Y25="无",Z25="有",AC25="有"),AND(Y25="无",Z25="有",V25="有"),AND(Y25="有",Z25="无",AC25="无"),AND(Y25="有",Z25="无",V25="无"),AND(Y25="有",Z25="无",AC25="有"),AND(Y25="有",Z25="无",V25="有")),"缺失（沙发/餐桌）",IF(AND(Y25="有",Z25="有",OR(AC25="无",V25="无")),"缺失（电视柜/操作台）",IF(AND(Y25="有",Z25="有",AC25="有",V25="有"),IF(OR(AA25="有",AB25="有"),"充配（油烟机/冰箱）",IF(AND(AA25="无",AB25="无"),"适中","")),"")))),"适中") -> 适中 | AI25: =VLOOKUP($AH$1&AH25,【1】定价因子!E:F,2,0) -> 1 | AJ25: =VLOOKUP(H25,'【3-1】大区填-采光基本要素'!A:H,8,0) -> 5 | AK25: =VLOOKUP($AJ$1&AJ25,【1】定价因子!E:F,2,0) -> 1.06 | AL25: =L25*PRODUCT(AG25,AK25,AE25,U25,S25,Q25,O25) -> 1659.4135 | AM25: 1530 | AN25: =AM25/AL25-1 -> -0.077987521
A26: ='【2】运营中心填-基本信息&审核标准'!$E$2 -> 兴围西4-11栋 | B26: =INT(H26/100) -> 4 | C26: =COUNTIF($B$2:$B$72,B26) -> 8 | D26: =COUNTIF(C$2:C$72,C26) -> 64 | F26: =IF(D26=$E$2,C26,"") -> 8 | H26: 402 | I26: H | J26: 一居室 | L26: =VLOOKUP(J26,'【3】大区填-楼栋基准格局定价'!B:H,7,0) -> 2445.5088 | M26: =IF(OR(J26="开间",J26="二人宿舍"),IF(N26<10,"很狭小",IF(N26<13,"较狭小",IF(N26<17,"适中",IF(N26<20,"较宽敞","很宽敞")))),IF(OR(J26="一居室",J26="四人宿舍"),IF(N26<20,"很狭小",IF(N26<23,"较狭小",IF(N26<26,"适中",IF(N26<28,"较宽敞","很宽敞")))),IF(OR(J26="二居室",J26="六人宿舍"),IF(N26<30,"很狭小",IF(N26<35,"较狭小",IF(N26<40,"适中",IF(N26<45,"较宽敞","很宽敞")))),""))) -> 很狭小 | N26: 18.86 | O26: =VLOOKUP($M$1&M26,【1】定价因子!E:F,2,0) -> 0.9 | P26: =IF(COUNTIFS(户型资产表!E:E,I26,户型资产表!H:H,"阳台门")>0,"有","无") -> 无 | Q26: =VLOOKUP($P$1&P26,【1】定价因子!E:F,2,0) -> 1 | R26: =IF('【2】运营中心填-基本信息&审核标准'!$D$4="是","无",IF(INT(H26/100)>9,"9F",INT(H26/100)&"F")) -> 无 | S26: =VLOOKUP(R26,【1】定价因子!D:F,3,0) -> 1 | T26: =IF('【2】运营中心填-基本信息&审核标准'!$D$4="否","无",IF(INT(H26/100)=1,"1F",IF(AND(INT(H26/100)>=2,INT(H26/100)<=3),"2-3F",IF(INT(H26/100)=4,"4F",IF(AND(INT(H26/100)>=5,INT(H26/100)<=6),"5-6F",IF(AND(INT(H26/100)>=7,INT(H26/100)<=8),"7-8F",IF(AND(INT(H26/100)>=9,INT(H26/100)<=10),"9-10F",IF(AND(INT(H26/100)>=11,INT(H26/100)<=12),"11-12F",IF(INT(H26/100)>=13,"13以上F",""))))))))) -> 4F | U26: =VLOOKUP($T$1&T26,【1】定价因子!E:F,2,0) -> 1 | V26: =IF(COUNTIFS(户型资产表!E:E,I26,户型资产表!H:H,"操作台")>0,"有","无") -> 有 | W26: =IF(COUNTIFS(户型资产表!E:E,I26,户型资产表!H:H,"书桌")>0,"有","无") -> 有 | X26: {=IF(SUMPRODUCT((户型资产表!E:E=I26)*((户型资产表!I:I="沙发01单人")+(户型资产表!I:I="单人沙发02")))>0,"有","无")} -> 无 | Y26: {=IF(SUMPRODUCT((户型资产表!E:E=I26)*((户型资产表!I:I="沙发02两人")+(户型资产表!I:I="双人沙发01")))>0,"有","无")} -> 有 | Z26: =IF(COUNTIFS(户型资产表!E:E,I26,户型资产表!H:H,"餐桌")>0,"有","无") -> 有 | AA26: =IF(COUNTIFS(户型资产表!E:E,I26,户型资产表!H:H,"吸油烟机")>0,"有","无") -> 无 | AB26: =IF(COUNTIFS(户型资产表!E:E,I26,户型资产表!H:H,"冰箱")>0,"有","无") -> 无 | AC26: =IF(COUNTIFS(户型资产表!E:E,I26,户型资产表!H:H,"电视柜")>0,"有","无") -> 无 | AD26: =IF(J26="开间",IF(AND(V26="无",W26="无"),"缺失",IF(AND(V26="无",W26="有"),"缺失（操作台）",IF(AND(V26="有",W26="无"),"缺失（书桌）",IF(AND(V26="有",W26="有"),IF(OR(AA26="有",Y26="有"),"充足（油烟机/双人沙发）",IF(OR(X26="有",Z26="有"),"充足（单人沙发/餐桌）",IF(AND(OR(X26="有",Y26="有"),Z26="有"),"非常充足","适中"))),"")))),"适中") -> 适中 | AE26: =VLOOKUP($AD$1&AD26,【1】定价因子!E:F,2,0) -> 1 | AF26: 适中 | AG26: =VLOOKUP($AF$1&AF26,【1】定价因子!E:F,2,0) -> 1 | AH26: =IF(J26="二居室",IF(AND(Y26="无",Z26="无",AC26="无",V26="无"),"缺失",IF(OR(AND(Y26="无",Z26="无",AC26="有"),AND(Y26="无",Z26="无",V26="有"),AND(Y26="无",Z26="无",AC26="有",V26="有"),AND(Y26="无",Z26="有",AC26="无"),AND(Y26="无",Z26="有",V26="无"),AND(Y26="无",Z26="有",AC26="有"),AND(Y26="无",Z26="有",V26="有"),AND(Y26="有",Z26="无",AC26="无"),AND(Y26="有",Z26="无",V26="无"),AND(Y26="有",Z26="无",AC26="有"),AND(Y26="有",Z26="无",V26="有")),"缺失（沙发/餐桌）",IF(AND(Y26="有",Z26="有",OR(AC26="无",V26="无")),"缺失（电视柜/操作台）",IF(AND(Y26="有",Z26="有",AC26="有",V26="有"),IF(OR(AA26="有",AB26="有"),"充配（油烟机/冰箱）",IF(AND(AA26="无",AB26="无"),"适中","")),"")))),"适中") -> 适中 | AI26: =VLOOKUP($AH$1&AH26,【1】定价因子!E:F,2,0) -> 1 | AJ26: =VLOOKUP(H26,'【3-1】大区填-采光基本要素'!A:H,8,0) -> 2 | AK26: =VLOOKUP($AJ$1&AJ26,【1】定价因子!E:F,2,0) -> 0.96 | AL26: =L26*PRODUCT(AG26,AK26,AE26,U26,S26,Q26,O26) -> 2112.9196 | AM26: 2080 | AN26: =AM26/AL26-1 -> -0.015580149
A27: ='【2】运营中心填-基本信息&审核标准'!$E$2 -> 兴围西4-11栋 | B27: =INT(H27/100) -> 4 | C27: =COUNTIF($B$2:$B$72,B27) -> 8 | D27: =COUNTIF(C$2:C$72,C27) -> 64 | F27: =IF(D27=$E$2,C27,"") -> 8 | H27: 403 | I27: O | J27: 开间 | L27: =VLOOKUP(J27,'【3】大区填-楼栋基准格局定价'!B:H,7,0) -> 1647.8784 | M27: =IF(OR(J27="开间",J27="二人宿舍"),IF(N27<10,"很狭小",IF(N27<13,"较狭小",IF(N27<17,"适中",IF(N27<20,"较宽敞","很宽敞")))),IF(OR(J27="一居室",J27="四人宿舍"),IF(N27<20,"很狭小",IF(N27<23,"较狭小",IF(N27<26,"适中",IF(N27<28,"较宽敞","很宽敞")))),IF(OR(J27="二居室",J27="六人宿舍"),IF(N27<30,"很狭小",IF(N27<35,"较狭小",IF(N27<40,"适中",IF(N27<45,"较宽敞","很宽敞")))),""))) -> 适中 | N27: 13.87 | O27: =VLOOKUP($M$1&M27,【1】定价因子!E:F,2,0) -> 1 | P27: =IF(COUNTIFS(户型资产表!E:E,I27,户型资产表!H:H,"阳台门")>0,"有","无") -> 有 | Q27: =VLOOKUP($P$1&P27,【1】定价因子!E:F,2,0) -> 1.07 | R27: =IF('【2】运营中心填-基本信息&审核标准'!$D$4="是","无",IF(INT(H27/100)>9,"9F",INT(H27/100)&"F")) -> 无 | S27: =VLOOKUP(R27,【1】定价因子!D:F,3,0) -> 1 | T27: =IF('【2】运营中心填-基本信息&审核标准'!$D$4="否","无",IF(INT(H27/100)=1,"1F",IF(AND(INT(H27/100)>=2,INT(H27/100)<=3),"2-3F",IF(INT(H27/100)=4,"4F",IF(AND(INT(H27/100)>=5,INT(H27/100)<=6),"5-6F",IF(AND(INT(H27/100)>=7,INT(H27/100)<=8),"7-8F",IF(AND(INT(H27/100)>=9,INT(H27/100)<=10),"9-10F",IF(AND(INT(H27/100)>=11,INT(H27/100)<=12),"11-12F",IF(INT(H27/100)>=13,"13以上F",""))))))))) -> 4F | U27: =VLOOKUP($T$1&T27,【1】定价因子!E:F,2,0) -> 1 | V27: =IF(COUNTIFS(户型资产表!E:E,I27,户型资产表!H:H,"操作台")>0,"有","无") -> 有 | W27: =IF(COUNTIFS(户型资产表!E:E,I27,户型资产表!H:H,"书桌")>0,"有","无") -> 有 | X27: {=IF(SUMPRODUCT((户型资产表!E:E=I27)*((户型资产表!I:I="沙发01单人")+(户型资产表!I:I="单人沙发02")))>0,"有","无")} -> 无 | Y27: {=IF(SUMPRODUCT((户型资产表!E:E=I27)*((户型资产表!I:I="沙发02两人")+(户型资产表!I:I="双人沙发01")))>0,"有","无")} -> 无 | Z27: =IF(COUNTIFS(户型资产表!E:E,I27,户型资产表!H:H,"餐桌")>0,"有","无") -> 无 | AA27: =IF(COUNTIFS(户型资产表!E:E,I27,户型资产表!H:H,"吸油烟机")>0,"有","无") -> 无 | AB27: =IF(COUNTIFS(户型资产表!E:E,I27,户型资产表!H:H,"冰箱")>0,"有","无") -> 无 | AC27: =IF(COUNTIFS(户型资产表!E:E,I27,户型资产表!H:H,"电视柜")>0,"有","无") -> 无 | AD27: =IF(J27="开间",IF(AND(V27="无",W27="无"),"缺失",IF(AND(V27="无",W27="有"),"缺失（操作台）",IF(AND(V27="有",W27="无"),"缺失（书桌）",IF(AND(V27="有",W27="有"),IF(OR(AA27="有",Y27="有"),"充足（油烟机/双人沙发）",IF(OR(X27="有",Z27="有"),"充足（单人沙发/餐桌）",IF(AND(OR(X27="有",Y27="有"),Z27="有"),"非常充足","适中"))),"")))),"适中") -> 适中 | AE27: =VLOOKUP($AD$1&AD27,【1】定价因子!E:F,2,0) -> 1 | AF27: =IF(J27="一居室",IF(AND(V27="无",Y27="无",Z27="无"),"缺失",IF(OR(AND(Z27="有",V27="无",Y27="无"),AND(Z27="有",V27="无",Y27="有"),AND(Z27="有",V27="有",Y27="无"),AND(Z27="无",V27="有",Y27="无"),AND(Z27="无",V27="无",Y27="有")),"缺失（操作台/双人沙发）",IF(AND(V27="有",Y27="有",Z27="无"),"缺失（餐桌）",IF(AND(V27="有",Y27="有",Z27="有"),IF(AND(W27="无",AA27="有"),"充配（油烟机）",IF(AND(W27="有",AA27="无"),"充配（书桌）",IF(AND(W27="有",AA27="有"),"非常充配","适中"))),"")))),"适中") -> 适中 | AG27: =VLOOKUP($AF$1&AF27,【1】定价因子!E:F,2,0) -> 1 | AH27: =IF(J27="二居室",IF(AND(Y27="无",Z27="无",AC27="无",V27="无"),"缺失",IF(OR(AND(Y27="无",Z27="无",AC27="有"),AND(Y27="无",Z27="无",V27="有"),AND(Y27="无",Z27="无",AC27="有",V27="有"),AND(Y27="无",Z27="有",AC27="无"),AND(Y27="无",Z27="有",V27="无"),AND(Y27="无",Z27="有",AC27="有"),AND(Y27="无",Z27="有",V27="有"),AND(Y27="有",Z27="无",AC27="无"),AND(Y27="有",Z27="无",V27="无"),AND(Y27="有",Z27="无",AC27="有"),AND(Y27="有",Z27="无",V27="有")),"缺失（沙发/餐桌）",IF(AND(Y27="有",Z27="有",OR(AC27="无",V27="无")),"缺失（电视柜/操作台）",IF(AND(Y27="有",Z27="有",AC27="有",V27="有"),IF(OR(AA27="有",AB27="有"),"充配（油烟机/冰箱）",IF(AND(AA27="无",AB27="无"),"适中","")),"")))),"适中") -> 适中 | AI27: =VLOOKUP($AH$1&AH27,【1】定价因子!E:F,2,0) -> 1 | AJ27: =VLOOKUP(H27,'【3-1】大区填-采光基本要素'!A:H,8,0) -> 4 | AK27: =VLOOKUP($AJ$1&AJ27,【1】定价因子!E:F,2,0) -> 1.03 | AL27: =L27*PRODUCT(AG27,AK27,AE27,U27,S27,Q27,O27) -> 1816.1268 | AM27: 1640 | AN27: =AM27/AL27-1 -> -0.096979344
A28: ='【2】运营中心填-基本信息&审核标准'!$E$2 -> 兴围西4-11栋 | B28: =INT(H28/100) -> 4 | C28: =COUNTIF($B$2:$B$72,B28) -> 8 | D28: =COUNTIF(C$2:C$72,C28) -> 64 | F28: =IF(D28=$E$2,C28,"") -> 8 | H28: 404 | I28: P | J28: 开间 | L28: =VLOOKUP(J28,'【3】大区填-楼栋基准格局定价'!B:H,7,0) -> 1647.8784 | M28: 适中 | N28: 19.76 | O28: =VLOOKUP($M$1&M28,【1】定价因子!E:F,2,0) -> 1 | P28: =IF(COUNTIFS(户型资产表!E:E,I28,户型资产表!H:H,"阳台门")>0,"有","无") -> 无 | Q28: =VLOOKUP($P$1&P28,【1】定价因子!E:F,2,0) -> 1 | R28: =IF('【2】运营中心填-基本信息&审核标准'!$D$4="是","无",IF(INT(H28/100)>9,"9F",INT(H28/100)&"F")) -> 无 | S28: =VLOOKUP(R28,【1】定价因子!D:F,3,0) -> 1 | T28: =IF('【2】运营中心填-基本信息&审核标准'!$D$4="否","无",IF(INT(H28/100)=1,"1F",IF(AND(INT(H28/100)>=2,INT(H28/100)<=3),"2-3F",IF(INT(H28/100)=4,"4F",IF(AND(INT(H28/100)>=5,INT(H28/100)<=6),"5-6F",IF(AND(INT(H28/100)>=7,INT(H28/100)<=8),"7-8F",IF(AND(INT(H28/100)>=9,INT(H28/100)<=10),"9-10F",IF(AND(INT(H28/100)>=11,INT(H28/100)<=12),"11-12F",IF(INT(H28/100)>=13,"13以上F",""))))))))) -> 4F | U28: =VLOOKUP($T$1&T28,【1】定价因子!E:F,2,0) -> 1 | V28: =IF(COUNTIFS(户型资产表!E:E,I28,户型资产表!H:H,"操作台")>0,"有","无") -> 有 | W28: =IF(COUNTIFS(户型资产表!E:E,I28,户型资产表!H:H,"书桌")>0,"有","无") -> 有 | X28: {=IF(SUMPRODUCT((户型资产表!E:E=I28)*((户型资产表!I:I="沙发01单人")+(户型资产表!I:I="单人沙发02")))>0,"有","无")} -> 无 | Y28: {=IF(SUMPRODUCT((户型资产表!E:E=I28)*((户型资产表!I:I="沙发02两人")+(户型资产表!I:I="双人沙发01")))>0,"有","无")} -> 无 | Z28: =IF(COUNTIFS(户型资产表!E:E,I28,户型资产表!H:H,"餐桌")>0,"有","无") -> 无 | AA28: =IF(COUNTIFS(户型资产表!E:E,I28,户型资产表!H:H,"吸油烟机")>0,"有","无") -> 无 | AB28: =IF(COUNTIFS(户型资产表!E:E,I28,户型资产表!H:H,"冰箱")>0,"有","无") -> 无 | AC28: =IF(COUNTIFS(户型资产表!E:E,I28,户型资产表!H:H,"电视柜")>0,"有","无") -> 无 | AD28: =IF(J28="开间",IF(AND(V28="无",W28="无"),"缺失",IF(AND(V28="无",W28="有"),"缺失（操作台）",IF(AND(V28="有",W28="无"),"缺失（书桌）",IF(AND(V28="有",W28="有"),IF(OR(AA28="有",Y28="有"),"充足（油烟机/双人沙发）",IF(OR(X28="有",Z28="有"),"充足（单人沙发/餐桌）",IF(AND(OR(X28="有",Y28="有"),Z28="有"),"非常充足","适中"))),"")))),"适中") -> 适中 | AE28: =VLOOKUP($AD$1&AD28,【1】定价因子!E:F,2,0) -> 1 | AF28: =IF(J28="一居室",IF(AND(V28="无",Y28="无",Z28="无"),"缺失",IF(OR(AND(Z28="有",V28="无",Y28="无"),AND(Z28="有",V28="无",Y28="有"),AND(Z28="有",V28="有",Y28="无"),AND(Z28="无",V28="有",Y28="无"),AND(Z28="无",V28="无",Y28="有")),"缺失（操作台/双人沙发）",IF(AND(V28="有",Y28="有",Z28="无"),"缺失（餐桌）",IF(AND(V28="有",Y28="有",Z28="有"),IF(AND(W28="无",AA28="有"),"充配（油烟机）",IF(AND(W28="有",AA28="无"),"充配（书桌）",IF(AND(W28="有",AA28="有"),"非常充配","适中"))),"")))),"适中") -> 适中 | AG28: =VLOOKUP($AF$1&AF28,【1】定价因子!E:F,2,0) -> 1 | AH28: =IF(J28="二居室",IF(AND(Y28="无",Z28="无",AC28="无",V28="无"),"缺失",IF(OR(AND(Y28="无",Z28="无",AC28="有"),AND(Y28="无",Z28="无",V28="有"),AND(Y28="无",Z28="无",AC28="有",V28="有"),AND(Y28="无",Z28="有",AC28="无"),AND(Y28="无",Z28="有",V28="无"),AND(Y28="无",Z28="有",AC28="有"),AND(Y28="无",Z28="有",V28="有"),AND(Y28="有",Z28="无",AC28="无"),AND(Y28="有",Z28="无",V28="无"),AND(Y28="有",Z28="无",AC28="有"),AND(Y28="有",Z28="无",V28="有")),"缺失（沙发/餐桌）",IF(AND(Y28="有",Z28="有",OR(AC28="无",V28="无")),"缺失（电视柜/操作台）",IF(AND(Y28="有",Z28="有",AC28="有",V28="有"),IF(OR(AA28="有",AB28="有"),"充配（油烟机/冰箱）",IF(AND(AA28="无",AB28="无"),"适中","")),"")))),"适中") -> 适中 | AI28: =VLOOKUP($AH$1&AH28,【1】定价因子!E:F,2,0) -> 1 | AJ28: =VLOOKUP(H28,'【3-1】大区填-采光基本要素'!A:H,8,0) -> 1 | AK28: =VLOOKUP($AJ$1&AJ28,【1】定价因子!E:F,2,0) -> 0.91 | AL28: =L28*PRODUCT(AG28,AK28,AE28,U28,S28,Q28,O28) -> 1499.5693 | AM28: 1450 | AN28: =AM28/AL28-1 -> -0.03305572
A29: ='【2】运营中心填-基本信息&审核标准'!$E$2 -> 兴围西4-11栋 | B29: =INT(H29/100) -> 4 | C29: =COUNTIF($B$2:$B$72,B29) -> 8 | D29: =COUNTIF(C$2:C$72,C29) -> 64 | F29: =IF(D29=$E$2,C29,"") -> 8 | H29: 405 | I29: K | J29: 开间 | L29: =VLOOKUP(J29,'【3】大区填-楼栋基准格局定价'!B:H,7,0) -> 1647.8784 | M29: =IF(OR(J29="开间",J29="二人宿舍"),IF(N29<10,"很狭小",IF(N29<13,"较狭小",IF(N29<17,"适中",IF(N29<20,"较宽敞","很宽敞")))),IF(OR(J29="一居室",J29="四人宿舍"),IF(N29<20,"很狭小",IF(N29<23,"较狭小",IF(N29<26,"适中",IF(N29<28,"较宽敞","很宽敞")))),IF(OR(J29="二居室",J29="六人宿舍"),IF(N29<30,"很狭小",IF(N29<35,"较狭小",IF(N29<40,"适中",IF(N29<45,"较宽敞","很宽敞")))),""))) -> 适中 | N29: 13.79 | O29: =VLOOKUP($M$1&M29,【1】定价因子!E:F,2,0) -> 1 | P29: =IF(COUNTIFS(户型资产表!E:E,I29,户型资产表!H:H,"阳台门")>0,"有","无") -> 无 | Q29: =VLOOKUP($P$1&P29,【1】定价因子!E:F,2,0) -> 1 | R29: =IF('【2】运营中心填-基本信息&审核标准'!$D$4="是","无",IF(INT(H29/100)>9,"9F",INT(H29/100)&"F")) -> 无 | S29: =VLOOKUP(R29,【1】定价因子!D:F,3,0) -> 1 | T29: =IF('【2】运营中心填-基本信息&审核标准'!$D$4="否","无",IF(INT(H29/100)=1,"1F",IF(AND(INT(H29/100)>=2,INT(H29/100)<=3),"2-3F",IF(INT(H29/100)=4,"4F",IF(AND(INT(H29/100)>=5,INT(H29/100)<=6),"5-6F",IF(AND(INT(H29/100)>=7,INT(H29/100)<=8),"7-8F",IF(AND(INT(H29/100)>=9,INT(H29/100)<=10),"9-10F",IF(AND(INT(H29/100)>=11,INT(H29/100)<=12),"11-12F",IF(INT(H29/100)>=13,"13以上F",""))))))))) -> 4F | U29: =VLOOKUP($T$1&T29,【1】定价因子!E:F,2,0) -> 1 | V29: =IF(COUNTIFS(户型资产表!E:E,I29,户型资产表!H:H,"操作台")>0,"有","无") -> 有 | W29: =IF(COUNTIFS(户型资产表!E:E,I29,户型资产表!H:H,"书桌")>0,"有","无") -> 有 | X29: {=IF(SUMPRODUCT((户型资产表!E:E=I29)*((户型资产表!I:I="沙发01单人")+(户型资产表!I:I="单人沙发02")))>0,"有","无")} -> 无 | Y29: {=IF(SUMPRODUCT((户型资产表!E:E=I29)*((户型资产表!I:I="沙发02两人")+(户型资产表!I:I="双人沙发01")))>0,"有","无")} -> 无 | Z29: =IF(COUNTIFS(户型资产表!E:E,I29,户型资产表!H:H,"餐桌")>0,"有","无") -> 无 | AA29: =IF(COUNTIFS(户型资产表!E:E,I29,户型资产表!H:H,"吸油烟机")>0,"有","无") -> 无 | AB29: =IF(COUNTIFS(户型资产表!E:E,I29,户型资产表!H:H,"冰箱")>0,"有","无") -> 无 | AC29: =IF(COUNTIFS(户型资产表!E:E,I29,户型资产表!H:H,"电视柜")>0,"有","无") -> 无 | AD29: =IF(J29="开间",IF(AND(V29="无",W29="无"),"缺失",IF(AND(V29="无",W29="有"),"缺失（操作台）",IF(AND(V29="有",W29="无"),"缺失（书桌）",IF(AND(V29="有",W29="有"),IF(OR(AA29="有",Y29="有"),"充足（油烟机/双人沙发）",IF(OR(X29="有",Z29="有"),"充足（单人沙发/餐桌）",IF(AND(OR(X29="有",Y29="有"),Z29="有"),"非常充足","适中"))),"")))),"适中") -> 适中 | AE29: =VLOOKUP($AD$1&AD29,【1】定价因子!E:F,2,0) -> 1 | AF29: =IF(J29="一居室",IF(AND(V29="无",Y29="无",Z29="无"),"缺失",IF(OR(AND(Z29="有",V29="无",Y29="无"),AND(Z29="有",V29="无",Y29="有"),AND(Z29="有",V29="有",Y29="无"),AND(Z29="无",V29="有",Y29="无"),AND(Z29="无",V29="无",Y29="有")),"缺失（操作台/双人沙发）",IF(AND(V29="有",Y29="有",Z29="无"),"缺失（餐桌）",IF(AND(V29="有",Y29="有",Z29="有"),IF(AND(W29="无",AA29="有"),"充配（油烟机）",IF(AND(W29="有",AA29="无"),"充配（书桌）",IF(AND(W29="有",AA29="有"),"非常充配","适中"))),"")))),"适中") -> 适中 | AG29: =VLOOKUP($AF$1&AF29,【1】定价因子!E:F,2,0) -> 1 | AH29: =IF(J29="二居室",IF(AND(Y29="无",Z29="无",AC29="无",V29="无"),"缺失",IF(OR(AND(Y29="无",Z29="无",AC29="有"),AND(Y29="无",Z29="无",V29="有"),AND(Y29="无",Z29="无",AC29="有",V29="有"),AND(Y29="无",Z29="有",AC29="无"),AND(Y29="无",Z29="有",V29="无"),AND(Y29="无",Z29="有",AC29="有"),AND(Y29="无",Z29="有",V29="有"),AND(Y29="有",Z29="无",AC29="无"),AND(Y29="有",Z29="无",V29="无"),AND(Y29="有",Z29="无",AC29="有"),AND(Y29="有",Z29="无",V29="有")),"缺失（沙发/餐桌）",IF(AND(Y29="有",Z29="有",OR(AC29="无",V29="无")),"缺失（电视柜/操作台）",IF(AND(Y29="有",Z29="有",AC29="有",V29="有"),IF(OR(AA29="有",AB29="有"),"充配（油烟机/冰箱）",IF(AND(AA29="无",AB29="无"),"适中","")),"")))),"适中") -> 适中 | AI29: =VLOOKUP($AH$1&AH29,【1】定价因子!E:F,2,0) -> 1 | AJ29: =VLOOKUP(H29,'【3-1】大区填-采光基本要素'!A:H,8,0) -> 3 | AK29: =VLOOKUP($AJ$1&AJ29,【1】定价因子!E:F,2,0) -> 1 | AL29: =L29*PRODUCT(AG29,AK29,AE29,U29,S29,Q29,O29) -> 1647.8784 | AM29: 1560 | AN29: =AM29/AL29-1 -> -0.053328207
A30: ='【2】运营中心填-基本信息&审核标准'!$E$2 -> 兴围西4-11栋 | B30: =INT(H30/100) -> 4 | C30: =COUNTIF($B$2:$B$72,B30) -> 8 | D30: =COUNTIF(C$2:C$72,C30) -> 64 | F30: =IF(D30=$E$2,C30,"") -> 8 | H30: 406 | I30: L | J30: 一居室 | L30: =VLOOKUP(J30,'【3】大区填-楼栋基准格局定价'!B:H,7,0) -> 2445.5088 | M30: =IF(OR(J30="开间",J30="二人宿舍"),IF(N30<10,"很狭小",IF(N30<13,"较狭小",IF(N30<17,"适中",IF(N30<20,"较宽敞","很宽敞")))),IF(OR(J30="一居室",J30="四人宿舍"),IF(N30<20,"很狭小",IF(N30<23,"较狭小",IF(N30<26,"适中",IF(N30<28,"较宽敞","很宽敞")))),IF(OR(J30="二居室",J30="六人宿舍"),IF(N30<30,"很狭小",IF(N30<35,"较狭小",IF(N30<40,"适中",IF(N30<45,"较宽敞","很宽敞")))),""))) -> 很狭小 | N30: 11.35 | O30: =VLOOKUP($M$1&M30,【1】定价因子!E:F,2,0) -> 0.9 | P30: =IF(COUNTIFS(户型资产表!E:E,I30,户型资产表!H:H,"阳台门")>0,"有","无") -> 无 | Q30: =VLOOKUP($P$1&P30,【1】定价因子!E:F,2,0) -> 1 | R30: =IF('【2】运营中心填-基本信息&审核标准'!$D$4="是","无",IF(INT(H30/100)>9,"9F",INT(H30/100)&"F")) -> 无 | S30: =VLOOKUP(R30,【1】定价因子!D:F,3,0) -> 1 | T30: =IF('【2】运营中心填-基本信息&审核标准'!$D$4="否","无",IF(INT(H30/100)=1,"1F",IF(AND(INT(H30/100)>=2,INT(H30/100)<=3),"2-3F",IF(INT(H30/100)=4,"4F",IF(AND(INT(H30/100)>=5,INT(H30/100)<=6),"5-6F",IF(AND(INT(H30/100)>=7,INT(H30/100)<=8),"7-8F",IF(AND(INT(H30/100)>=9,INT(H30/100)<=10),"9-10F",IF(AND(INT(H30/100)>=11,INT(H30/100)<=12),"11-12F",IF(INT(H30/100)>=13,"13以上F",""))))))))) -> 4F | U30: =VLOOKUP($T$1&T30,【1】定价因子!E:F,2,0) -> 1 | V30: =IF(COUNTIFS(户型资产表!E:E,I30,户型资产表!H:H,"操作台")>0,"有","无") -> 有 | W30: =IF(COUNTIFS(户型资产表!E:E,I30,户型资产表!H:H,"书桌")>0,"有","无") -> 无 | X30: {=IF(SUMPRODUCT((户型资产表!E:E=I30)*((户型资产表!I:I="沙发01单人")+(户型资产表!I:I="单人沙发02")))>0,"有","无")} -> 无 | Y30: {=IF(SUMPRODUCT((户型资产表!E:E=I30)*((户型资产表!I:I="沙发02两人")+(户型资产表!I:I="双人沙发01")))>0,"有","无")} -> 有 | Z30: =IF(COUNTIFS(户型资产表!E:E,I30,户型资产表!H:H,"餐桌")>0,"有","无") -> 有 | AA30: =IF(COUNTIFS(户型资产表!E:E,I30,户型资产表!H:H,"吸油烟机")>0,"有","无") -> 无 | AB30: =IF(COUNTIFS(户型资产表!E:E,I30,户型资产表!H:H,"冰箱")>0,"有","无") -> 无 | AC30: =IF(COUNTIFS(户型资产表!E:E,I30,户型资产表!H:H,"电视柜")>0,"有","无") -> 无 | AD30: =IF(J30="开间",IF(AND(V30="无",W30="无"),"缺失",IF(AND(V30="无",W30="有"),"缺失（操作台）",IF(AND(V30="有",W30="无"),"缺失（书桌）",IF(AND(V30="有",W30="有"),IF(OR(AA30="有",Y30="有"),"充足（油烟机/双人沙发）",IF(OR(X30="有",Z30="有"),"充足（单人沙发/餐桌）",IF(AND(OR(X30="有",Y30="有"),Z30="有"),"非常充足","适中"))),"")))),"适中") -> 适中 | AE30: =VLOOKUP($AD$1&AD30,【1】定价因子!E:F,2,0) -> 1 | AF30: =IF(J30="一居室",IF(AND(V30="无",Y30="无",Z30="无"),"缺失",IF(OR(AND(Z30="有",V30="无",Y30="无"),AND(Z30="有",V30="无",Y30="有"),AND(Z30="有",V30="有",Y30="无"),AND(Z30="无",V30="有",Y30="无"),AND(Z30="无",V30="无",Y30="有")),"缺失（操作台/双人沙发）",IF(AND(V30="有",Y30="有",Z30="无"),"缺失（餐桌）",IF(AND(V30="有",Y30="有",Z30="有"),IF(AND(W30="无",AA30="有"),"充配（油烟机）",IF(AND(W30="有",AA30="无"),"充配（书桌）",IF(AND(W30="有",AA30="有"),"非常充配","适中"))),"")))),"适中") -> 适中 | AG30: =VLOOKUP($AF$1&AF30,【1】定价因子!E:F,2,0) -> 1 | AH30: =IF(J30="二居室",IF(AND(Y30="无",Z30="无",AC30="无",V30="无"),"缺失",IF(OR(AND(Y30="无",Z30="无",AC30="有"),AND(Y30="无",Z30="无",V30="有"),AND(Y30="无",Z30="无",AC30="有",V30="有"),AND(Y30="无",Z30="有",AC30="无"),AND(Y30="无",Z30="有",V30="无"),AND(Y30="无",Z30="有",AC30="有"),AND(Y30="无",Z30="有",V30="有"),AND(Y30="有",Z30="无",AC30="无"),AND(Y30="有",Z30="无",V30="无"),AND(Y30="有",Z30="无",AC30="有"),AND(Y30="有",Z30="无",V30="有")),"缺失（沙发/餐桌）",IF(AND(Y30="有",Z30="有",OR(AC30="无",V30="无")),"缺失（电视柜/操作台）",IF(AND(Y30="有",Z30="有",AC30="有",V30="有"),IF(OR(AA30="有",AB30="有"),"充配（油烟机/冰箱）",IF(AND(AA30="无",AB30="无"),"适中","")),"")))),"适中") -> 适中 | AI30: =VLOOKUP($AH$1&AH30,【1】定价因子!E:F,2,0) -> 1 | AJ30: =VLOOKUP(H30,'【3-1】大区填-采光基本要素'!A:H,8,0) -> 1 | AK30: =VLOOKUP($AJ$1&AJ30,【1】定价因子!E:F,2,0) -> 0.91 | AL30: =L30*PRODUCT(AG30,AK30,AE30,U30,S30,Q30,O30) -> 2002.8717 | AM30: 2000 | AN30: =AM30/AL30-1 -> -0.0014337949
A31: ='【2】运营中心填-基本信息&审核标准'!$E$2 -> 兴围西4-11栋 | B31: =INT(H31/100) -> 4 | C31: =COUNTIF($B$2:$B$72,B31) -> 8 | D31: =COUNTIF(C$2:C$72,C31) -> 64 | F31: =IF(D31=$E$2,C31,"") -> 8 | H31: 407 | I31: J | J31: 开间 | L31: =VLOOKUP(J31,'【3】大区填-楼栋基准格局定价'!B:H,7,0) -> 1647.8784 | M31: =IF(OR(J31="开间",J31="二人宿舍"),IF(N31<10,"很狭小",IF(N31<13,"较狭小",IF(N31<17,"适中",IF(N31<20,"较宽敞","很宽敞")))),IF(OR(J31="一居室",J31="四人宿舍"),IF(N31<20,"很狭小",IF(N31<23,"较狭小",IF(N31<26,"适中",IF(N31<28,"较宽敞","很宽敞")))),IF(OR(J31="二居室",J31="六人宿舍"),IF(N31<30,"很狭小",IF(N31<35,"较狭小",IF(N31<40,"适中",IF(N31<45,"较宽敞","很宽敞")))),""))) -> 适中 | N31: 13.81 | O31: =VLOOKUP($M$1&M31,【1】定价因子!E:F,2,0) -> 1 | P31: =IF(COUNTIFS(户型资产表!E:E,I31,户型资产表!H:H,"阳台门")>0,"有","无") -> 无 | Q31: =VLOOKUP($P$1&P31,【1】定价因子!E:F,2,0) -> 1 | R31: =IF('【2】运营中心填-基本信息&审核标准'!$D$4="是","无",IF(INT(H31/100)>9,"9F",INT(H31/100)&"F")) -> 无 | S31: =VLOOKUP(R31,【1】定价因子!D:F,3,0) -> 1 | T31: =IF('【2】运营中心填-基本信息&审核标准'!$D$4="否","无",IF(INT(H31/100)=1,"1F",IF(AND(INT(H31/100)>=2,INT(H31/100)<=3),"2-3F",IF(INT(H31/100)=4,"4F",IF(AND(INT(H31/100)>=5,INT(H31/100)<=6),"5-6F",IF(AND(INT(H31/100)>=7,INT(H31/100)<=8),"7-8F",IF(AND(INT(H31/100)>=9,INT(H31/100)<=10),"9-10F",IF(AND(INT(H31/100)>=11,INT(H31/100)<=12),"11-12F",IF(INT(H31/100)>=13,"13以上F",""))))))))) -> 4F | U31: =VLOOKUP($T$1&T31,【1】定价因子!E:F,2,0) -> 1 | V31: =IF(COUNTIFS(户型资产表!E:E,I31,户型资产表!H:H,"操作台")>0,"有","无") -> 有 | W31: =IF(COUNTIFS(户型资产表!E:E,I31,户型资产表!H:H,"书桌")>0,"有","无") -> 有 | X31: {=IF(SUMPRODUCT((户型资产表!E:E=I31)*((户型资产表!I:I="沙发01单人")+(户型资产表!I:I="单人沙发02")))>0,"有","无")} -> 无 | Y31: {=IF(SUMPRODUCT((户型资产表!E:E=I31)*((户型资产表!I:I="沙发02两人")+(户型资产表!I:I="双人沙发01")))>0,"有","无")} -> 无 | Z31: =IF(COUNTIFS(户型资产表!E:E,I31,户型资产表!H:H,"餐桌")>0,"有","无") -> 无 | AA31: =IF(COUNTIFS(户型资产表!E:E,I31,户型资产表!H:H,"吸油烟机")>0,"有","无") -> 无 | AB31: =IF(COUNTIFS(户型资产表!E:E,I31,户型资产表!H:H,"冰箱")>0,"有","无") -> 无 | AC31: =IF(COUNTIFS(户型资产表!E:E,I31,户型资产表!H:H,"电视柜")>0,"有","无") -> 无 | AD31: =IF(J31="开间",IF(AND(V31="无",W31="无"),"缺失",IF(AND(V31="无",W31="有"),"缺失（操作台）",IF(AND(V31="有",W31="无"),"缺失（书桌）",IF(AND(V31="有",W31="有"),IF(OR(AA31="有",Y31="有"),"充足（油烟机/双人沙发）",IF(OR(X31="有",Z31="有"),"充足（单人沙发/餐桌）",IF(AND(OR(X31="有",Y31="有"),Z31="有"),"非常充足","适中"))),"")))),"适中") -> 适中 | AE31: =VLOOKUP($AD$1&AD31,【1】定价因子!E:F,2,0) -> 1 | AF31: =IF(J31="一居室",IF(AND(V31="无",Y31="无",Z31="无"),"缺失",IF(OR(AND(Z31="有",V31="无",Y31="无"),AND(Z31="有",V31="无",Y31="有"),AND(Z31="有",V31="有",Y31="无"),AND(Z31="无",V31="有",Y31="无"),AND(Z31="无",V31="无",Y31="有")),"缺失（操作台/双人沙发）",IF(AND(V31="有",Y31="有",Z31="无"),"缺失（餐桌）",IF(AND(V31="有",Y31="有",Z31="有"),IF(AND(W31="无",AA31="有"),"充配（油烟机）",IF(AND(W31="有",AA31="无"),"充配（书桌）",IF(AND(W31="有",AA31="有"),"非常充配","适中"))),"")))),"适中") -> 适中 | AG31: =VLOOKUP($AF$1&AF31,【1】定价因子!E:F,2,0) -> 1 | AH31: =IF(J31="二居室",IF(AND(Y31="无",Z31="无",AC31="无",V31="无"),"缺失",IF(OR(AND(Y31="无",Z31="无",AC31="有"),AND(Y31="无",Z31="无",V31="有"),AND(Y31="无",Z31="无",AC31="有",V31="有"),AND(Y31="无",Z31="有",AC31="无"),AND(Y31="无",Z31="有",V31="无"),AND(Y31="无",Z31="有",AC31="有"),AND(Y31="无",Z31="有",V31="有"),AND(Y31="有",Z31="无",AC31="无"),AND(Y31="有",Z31="无",V31="无"),AND(Y31="有",Z31="无",AC31="有"),AND(Y31="有",Z31="无",V31="有")),"缺失（沙发/餐桌）",IF(AND(Y31="有",Z31="有",OR(AC31="无",V31="无")),"缺失（电视柜/操作台）",IF(AND(Y31="有",Z31="有",AC31="有",V31="有"),IF(OR(AA31="有",AB31="有"),"充配（油烟机/冰箱）",IF(AND(AA31="无",AB31="无"),"适中","")),"")))),"适中") -> 适中 | AI31: =VLOOKUP($AH$1&AH31,【1】定价因子!E:F,2,0) -> 1 | AJ31: =VLOOKUP(H31,'【3-1】大区填-采光基本要素'!A:H,8,0) -> 1 | AK31: =VLOOKUP($AJ$1&AJ31,【1】定价因子!E:F,2,0) -> 0.91 | AL31: =L31*PRODUCT(AG31,AK31,AE31,U31,S31,Q31,O31) -> 1499.5693 | AM31: 1460 | AN31: =AM31/AL31-1 -> -0.026387139
A32: ='【2】运营中心填-基本信息&审核标准'!$E$2 -> 兴围西4-11栋 | B32: =INT(H32/100) -> 4 | C32: =COUNTIF($B$2:$B$72,B32) -> 8 | D32: =COUNTIF(C$2:C$72,C32) -> 64 | F32: =IF(D32=$E$2,C32,"") -> 8 | H32: 408 | I32: Q | J32: 一居室 | L32: =VLOOKUP(J32,'【3】大区填-楼栋基准格局定价'!B:H,7,0) -> 2445.5088 | M32: =IF(OR(J32="开间",J32="二人宿舍"),IF(N32<10,"很狭小",IF(N32<13,"较狭小",IF(N32<17,"适中",IF(N32<20,"较宽敞","很宽敞")))),IF(OR(J32="一居室",J32="四人宿舍"),IF(N32<20,"很狭小",IF(N32<23,"较狭小",IF(N32<26,"适中",IF(N32<28,"较宽敞","很宽敞")))),IF(OR(J32="二居室",J32="六人宿舍"),IF(N32<30,"很狭小",IF(N32<35,"较狭小",IF(N32<40,"适中",IF(N32<45,"较宽敞","很宽敞")))),""))) -> 较狭小 | N32: 20.04 | O32: =VLOOKUP($M$1&M32,【1】定价因子!E:F,2,0) -> 0.95 | P32: =IF(COUNTIFS(户型资产表!E:E,I32,户型资产表!H:H,"阳台门")>0,"有","无") -> 无 | Q32: =VLOOKUP($P$1&P32,【1】定价因子!E:F,2,0) -> 1 | R32: =IF('【2】运营中心填-基本信息&审核标准'!$D$4="是","无",IF(INT(H32/100)>9,"9F",INT(H32/100)&"F")) -> 无 | S32: =VLOOKUP(R32,【1】定价因子!D:F,3,0) -> 1 | T32: =IF('【2】运营中心填-基本信息&审核标准'!$D$4="否","无",IF(INT(H32/100)=1,"1F",IF(AND(INT(H32/100)>=2,INT(H32/100)<=3),"2-3F",IF(INT(H32/100)=4,"4F",IF(AND(INT(H32/100)>=5,INT(H32/100)<=6),"5-6F",IF(AND(INT(H32/100)>=7,INT(H32/100)<=8),"7-8F",IF(AND(INT(H32/100)>=9,INT(H32/100)<=10),"9-10F",IF(AND(INT(H32/100)>=11,INT(H32/100)<=12),"11-12F",IF(INT(H32/100)>=13,"13以上F",""))))))))) -> 4F | U32: =VLOOKUP($T$1&T32,【1】定价因子!E:F,2,0) -> 1 | V32: =IF(COUNTIFS(户型资产表!E:E,I32,户型资产表!H:H,"操作台")>0,"有","无") -> 有 | W32: =IF(COUNTIFS(户型资产表!E:E,I32,户型资产表!H:H,"书桌")>0,"有","无") -> 无 | X32: {=IF(SUMPRODUCT((户型资产表!E:E=I32)*((户型资产表!I:I="沙发01单人")+(户型资产表!I:I="单人沙发02")))>0,"有","无")} -> 无 | Y32: {=IF(SUMPRODUCT((户型资产表!E:E=I32)*((户型资产表!I:I="沙发02两人")+(户型资产表!I:I="双人沙发01")))>0,"有","无")} -> 有 | Z32: =IF(COUNTIFS(户型资产表!E:E,I32,户型资产表!H:H,"餐桌")>0,"有","无") -> 有 | AA32: =IF(COUNTIFS(户型资产表!E:E,I32,户型资产表!H:H,"吸油烟机")>0,"有","无") -> 有 | AB32: =IF(COUNTIFS(户型资产表!E:E,I32,户型资产表!H:H,"冰箱")>0,"有","无") -> 无 | AC32: =IF(COUNTIFS(户型资产表!E:E,I32,户型资产表!H:H,"电视柜")>0,"有","无") -> 无 | AD32: =IF(J32="开间",IF(AND(V32="无",W32="无"),"缺失",IF(AND(V32="无",W32="有"),"缺失（操作台）",IF(AND(V32="有",W32="无"),"缺失（书桌）",IF(AND(V32="有",W32="有"),IF(OR(AA32="有",Y32="有"),"充足（油烟机/双人沙发）",IF(OR(X32="有",Z32="有"),"充足（单人沙发/餐桌）",IF(AND(OR(X32="有",Y32="有"),Z32="有"),"非常充足","适中"))),"")))),"适中") -> 适中 | AE32: =VLOOKUP($AD$1&AD32,【1】定价因子!E:F,2,0) -> 1 | AF32: 适中 | AG32: =VLOOKUP($AF$1&AF32,【1】定价因子!E:F,2,0) -> 1 | AH32: =IF(J32="二居室",IF(AND(Y32="无",Z32="无",AC32="无",V32="无"),"缺失",IF(OR(AND(Y32="无",Z32="无",AC32="有"),AND(Y32="无",Z32="无",V32="有"),AND(Y32="无",Z32="无",AC32="有",V32="有"),AND(Y32="无",Z32="有",AC32="无"),AND(Y32="无",Z32="有",V32="无"),AND(Y32="无",Z32="有",AC32="有"),AND(Y32="无",Z32="有",V32="有"),AND(Y32="有",Z32="无",AC32="无"),AND(Y32="有",Z32="无",V32="无"),AND(Y32="有",Z32="无",AC32="有"),AND(Y32="有",Z32="无",V32="有")),"缺失（沙发/餐桌）",IF(AND(Y32="有",Z32="有",OR(AC32="无",V32="无")),"缺失（电视柜/操作台）",IF(AND(Y32="有",Z32="有",AC32="有",V32="有"),IF(OR(AA32="有",AB32="有"),"充配（油烟机/冰箱）",IF(AND(AA32="无",AB32="无"),"适中","")),"")))),"适中") -> 适中 | AI32: =VLOOKUP($AH$1&AH32,【1】定价因子!E:F,2,0) -> 1 | AJ32: =VLOOKUP(H32,'【3-1】大区填-采光基本要素'!A:H,8,0) -> 2 | AK32: =VLOOKUP($AJ$1&AJ32,【1】定价因子!E:F,2,0) -> 0.96 | AL32: =L32*PRODUCT(AG32,AK32,AE32,U32,S32,Q32,O32) -> 2230.304 | AM32: 2180 | AN32: =AM32/AL32-1 -> -0.022554784
A33: ='【2】运营中心填-基本信息&审核标准'!$E$2 -> 兴围西4-11栋 | B33: =INT(H33/100) -> 5 | C33: =COUNTIF($B$2:$B$72,B33) -> 8 | D33: =COUNTIF(C$2:C$72,C33) -> 64 | F33: =IF(D33=$E$2,C33,"") -> 8 | H33: 501 | I33: N | J33: 开间 | L33: =VLOOKUP(J33,'【3】大区填-楼栋基准格局定价'!B:H,7,0) -> 1647.8784 | M33: =IF(OR(J33="开间",J33="二人宿舍"),IF(N33<10,"很狭小",IF(N33<13,"较狭小",IF(N33<17,"适中",IF(N33<20,"较宽敞","很宽敞")))),IF(OR(J33="一居室",J33="四人宿舍"),IF(N33<20,"很狭小",IF(N33<23,"较狭小",IF(N33<26,"适中",IF(N33<28,"较宽敞","很宽敞")))),IF(OR(J33="二居室",J33="六人宿舍"),IF(N33<30,"很狭小",IF(N33<35,"较狭小",IF(N33<40,"适中",IF(N33<45,"较宽敞","很宽敞")))),""))) -> 较狭小 | N33: 10.96 | O33: =VLOOKUP($M$1&M33,【1】定价因子!E:F,2,0) -> 0.95 | P33: =IF(COUNTIFS(户型资产表!E:E,I33,户型资产表!H:H,"阳台门")>0,"有","无") -> 无 | Q33: =VLOOKUP($P$1&P33,【1】定价因子!E:F,2,0) -> 1 | R33: =IF('【2】运营中心填-基本信息&审核标准'!$D$4="是","无",IF(INT(H33/100)>9,"9F",INT(H33/100)&"F")) -> 无 | S33: =VLOOKUP(R33,【1】定价因子!D:F,3,0) -> 1 | T33: =IF('【2】运营中心填-基本信息&审核标准'!$D$4="否","无",IF(INT(H33/100)=1,"1F",IF(AND(INT(H33/100)>=2,INT(H33/100)<=3),"2-3F",IF(INT(H33/100)=4,"4F",IF(AND(INT(H33/100)>=5,INT(H33/100)<=6),"5-6F",IF(AND(INT(H33/100)>=7,INT(H33/100)<=8),"7-8F",IF(AND(INT(H33/100)>=9,INT(H33/100)<=10),"9-10F",IF(AND(INT(H33/100)>=11,INT(H33/100)<=12),"11-12F",IF(INT(H33/100)>=13,"13以上F",""))))))))) -> 5-6F | U33: =VLOOKUP($T$1&T33,【1】定价因子!E:F,2,0) -> 1.01 | V33: =IF(COUNTIFS(户型资产表!E:E,I33,户型资产表!H:H,"操作台")>0,"有","无") -> 有 | W33: =IF(COUNTIFS(户型资产表!E:E,I33,户型资产表!H:H,"书桌")>0,"有","无") -> 有 | X33: {=IF(SUMPRODUCT((户型资产表!E:E=I33)*((户型资产表!I:I="沙发01单人")+(户型资产表!I:I="单人沙发02")))>0,"有","无")} -> 无 | Y33: {=IF(SUMPRODUCT((户型资产表!E:E=I33)*((户型资产表!I:I="沙发02两人")+(户型资产表!I:I="双人沙发01")))>0,"有","无")} -> 无 | Z33: =IF(COUNTIFS(户型资产表!E:E,I33,户型资产表!H:H,"餐桌")>0,"有","无") -> 无 | AA33: =IF(COUNTIFS(户型资产表!E:E,I33,户型资产表!H:H,"吸油烟机")>0,"有","无") -> 无 | AB33: =IF(COUNTIFS(户型资产表!E:E,I33,户型资产表!H:H,"冰箱")>0,"有","无") -> 无 | AC33: =IF(COUNTIFS(户型资产表!E:E,I33,户型资产表!H:H,"电视柜")>0,"有","无") -> 无 | AD33: =IF(J33="开间",IF(AND(V33="无",W33="无"),"缺失",IF(AND(V33="无",W33="有"),"缺失（操作台）",IF(AND(V33="有",W33="无"),"缺失（书桌）",IF(AND(V33="有",W33="有"),IF(OR(AA33="有",Y33="有"),"充足（油烟机/双人沙发）",IF(OR(X33="有",Z33="有"),"充足（单人沙发/餐桌）",IF(AND(OR(X33="有",Y33="有"),Z33="有"),"非常充足","适中"))),"")))),"适中") -> 适中 | AE33: =VLOOKUP($AD$1&AD33,【1】定价因子!E:F,2,0) -> 1 | AF33: =IF(J33="一居室",IF(AND(V33="无",Y33="无",Z33="无"),"缺失",IF(OR(AND(Z33="有",V33="无",Y33="无"),AND(Z33="有",V33="无",Y33="有"),AND(Z33="有",V33="有",Y33="无"),AND(Z33="无",V33="有",Y33="无"),AND(Z33="无",V33="无",Y33="有")),"缺失（操作台/双人沙发）",IF(AND(V33="有",Y33="有",Z33="无"),"缺失（餐桌）",IF(AND(V33="有",Y33="有",Z33="有"),IF(AND(W33="无",AA33="有"),"充配（油烟机）",IF(AND(W33="有",AA33="无"),"充配（书桌）",IF(AND(W33="有",AA33="有"),"非常充配","适中"))),"")))),"适中") -> 适中 | AG33: =VLOOKUP($AF$1&AF33,【1】定价因子!E:F,2,0) -> 1 | AH33: =IF(J33="二居室",IF(AND(Y33="无",Z33="无",AC33="无",V33="无"),"缺失",IF(OR(AND(Y33="无",Z33="无",AC33="有"),AND(Y33="无",Z33="无",V33="有"),AND(Y33="无",Z33="无",AC33="有",V33="有"),AND(Y33="无",Z33="有",AC33="无"),AND(Y33="无",Z33="有",V33="无"),AND(Y33="无",Z33="有",AC33="有"),AND(Y33="无",Z33="有",V33="有"),AND(Y33="有",Z33="无",AC33="无"),AND(Y33="有",Z33="无",V33="无"),AND(Y33="有",Z33="无",AC33="有"),AND(Y33="有",Z33="无",V33="有")),"缺失（沙发/餐桌）",IF(AND(Y33="有",Z33="有",OR(AC33="无",V33="无")),"缺失（电视柜/操作台）",IF(AND(Y33="有",Z33="有",AC33="有",V33="有"),IF(OR(AA33="有",AB33="有"),"充配（油烟机/冰箱）",IF(AND(AA33="无",AB33="无"),"适中","")),"")))),"适中") -> 适中 | AI33: =VLOOKUP($AH$1&AH33,【1】定价因子!E:F,2,0) -> 1 | AJ33: =VLOOKUP(H33,'【3-1】大区填-采光基本要素'!A:H,8,0) -> 5 | AK33: =VLOOKUP($AJ$1&AJ33,【1】定价因子!E:F,2,0) -> 1.06 | AL33: =L33*PRODUCT(AG33,AK33,AE33,U33,S33,Q33,O33) -> 1676.0077 | AM33: 1530 | AN33: =AM33/AL33-1 -> -0.087116357
A34: ='【2】运营中心填-基本信息&审核标准'!$E$2 -> 兴围西4-11栋 | B34: =INT(H34/100) -> 5 | C34: =COUNTIF($B$2:$B$72,B34) -> 8 | D34: =COUNTIF(C$2:C$72,C34) -> 64 | F34: =IF(D34=$E$2,C34,"") -> 8 | H34: 502 | I34: H | J34: 一居室 | L34: =VLOOKUP(J34,'【3】大区填-楼栋基准格局定价'!B:H,7,0) -> 2445.5088 | M34: =IF(OR(J34="开间",J34="二人宿舍"),IF(N34<10,"很狭小",IF(N34<13,"较狭小",IF(N34<17,"适中",IF(N34<20,"较宽敞","很宽敞")))),IF(OR(J34="一居室",J34="四人宿舍"),IF(N34<20,"很狭小",IF(N34<23,"较狭小",IF(N34<26,"适中",IF(N34<28,"较宽敞","很宽敞")))),IF(OR(J34="二居室",J34="六人宿舍"),IF(N34<30,"很狭小",IF(N34<35,"较狭小",IF(N34<40,"适中",IF(N34<45,"较宽敞","很宽敞")))),""))) -> 很狭小 | N34: 18.86 | O34: =VLOOKUP($M$1&M34,【1】定价因子!E:F,2,0) -> 0.9 | P34: =IF(COUNTIFS(户型资产表!E:E,I34,户型资产表!H:H,"阳台门")>0,"有","无") -> 无 | Q34: =VLOOKUP($P$1&P34,【1】定价因子!E:F,2,0) -> 1 | R34: =IF('【2】运营中心填-基本信息&审核标准'!$D$4="是","无",IF(INT(H34/100)>9,"9F",INT(H34/100)&"F")) -> 无 | S34: =VLOOKUP(R34,【1】定价因子!D:F,3,0) -> 1 | T34: =IF('【2】运营中心填-基本信息&审核标准'!$D$4="否","无",IF(INT(H34/100)=1,"1F",IF(AND(INT(H34/100)>=2,INT(H34/100)<=3),"2-3F",IF(INT(H34/100)=4,"4F",IF(AND(INT(H34/100)>=5,INT(H34/100)<=6),"5-6F",IF(AND(INT(H34/100)>=7,INT(H34/100)<=8),"7-8F",IF(AND(INT(H34/100)>=9,INT(H34/100)<=10),"9-10F",IF(AND(INT(H34/100)>=11,INT(H34/100)<=12),"11-12F",IF(INT(H34/100)>=13,"13以上F",""))))))))) -> 5-6F | U34: =VLOOKUP($T$1&T34,【1】定价因子!E:F,2,0) -> 1.01 | V34: =IF(COUNTIFS(户型资产表!E:E,I34,户型资产表!H:H,"操作台")>0,"有","无") -> 有 | W34: =IF(COUNTIFS(户型资产表!E:E,I34,户型资产表!H:H,"书桌")>0,"有","无") -> 有 | X34: {=IF(SUMPRODUCT((户型资产表!E:E=I34)*((户型资产表!I:I="沙发01单人")+(户型资产表!I:I="单人沙发02")))>0,"有","无")} -> 无 | Y34: {=IF(SUMPRODUCT((户型资产表!E:E=I34)*((户型资产表!I:I="沙发02两人")+(户型资产表!I:I="双人沙发01")))>0,"有","无")} -> 有 | Z34: =IF(COUNTIFS(户型资产表!E:E,I34,户型资产表!H:H,"餐桌")>0,"有","无") -> 有 | AA34: =IF(COUNTIFS(户型资产表!E:E,I34,户型资产表!H:H,"吸油烟机")>0,"有","无") -> 无 | AB34: =IF(COUNTIFS(户型资产表!E:E,I34,户型资产表!H:H,"冰箱")>0,"有","无") -> 无 | AC34: =IF(COUNTIFS(户型资产表!E:E,I34,户型资产表!H:H,"电视柜")>0,"有","无") -> 无 | AD34: =IF(J34="开间",IF(AND(V34="无",W34="无"),"缺失",IF(AND(V34="无",W34="有"),"缺失（操作台）",IF(AND(V34="有",W34="无"),"缺失（书桌）",IF(AND(V34="有",W34="有"),IF(OR(AA34="有",Y34="有"),"充足（油烟机/双人沙发）",IF(OR(X34="有",Z34="有"),"充足（单人沙发/餐桌）",IF(AND(OR(X34="有",Y34="有"),Z34="有"),"非常充足","适中"))),"")))),"适中") -> 适中 | AE34: =VLOOKUP($AD$1&AD34,【1】定价因子!E:F,2,0) -> 1 | AF34: 适中 | AG34: =VLOOKUP($AF$1&AF34,【1】定价因子!E:F,2,0) -> 1 | AH34: =IF(J34="二居室",IF(AND(Y34="无",Z34="无",AC34="无",V34="无"),"缺失",IF(OR(AND(Y34="无",Z34="无",AC34="有"),AND(Y34="无",Z34="无",V34="有"),AND(Y34="无",Z34="无",AC34="有",V34="有"),AND(Y34="无",Z34="有",AC34="无"),AND(Y34="无",Z34="有",V34="无"),AND(Y34="无",Z34="有",AC34="有"),AND(Y34="无",Z34="有",V34="有"),AND(Y34="有",Z34="无",AC34="无"),AND(Y34="有",Z34="无",V34="无"),AND(Y34="有",Z34="无",AC34="有"),AND(Y34="有",Z34="无",V34="有")),"缺失（沙发/餐桌）",IF(AND(Y34="有",Z34="有",OR(AC34="无",V34="无")),"缺失（电视柜/操作台）",IF(AND(Y34="有",Z34="有",AC34="有",V34="有"),IF(OR(AA34="有",AB34="有"),"充配（油烟机/冰箱）",IF(AND(AA34="无",AB34="无"),"适中","")),"")))),"适中") -> 适中 | AI34: =VLOOKUP($AH$1&AH34,【1】定价因子!E:F,2,0) -> 1 | AJ34: =VLOOKUP(H34,'【3-1】大区填-采光基本要素'!A:H,8,0) -> 2 | AK34: =VLOOKUP($AJ$1&AJ34,【1】定价因子!E:F,2,0) -> 0.96 | AL34: =L34*PRODUCT(AG34,AK34,AE34,U34,S34,Q34,O34) -> 2134.0488 | AM34: 2080 | AN34: =AM34/AL34-1 -> -0.025326881
A35: ='【2】运营中心填-基本信息&审核标准'!$E$2 -> 兴围西4-11栋 | B35: =INT(H35/100) -> 5 | C35: =COUNTIF($B$2:$B$72,B35) -> 8 | D35: =COUNTIF(C$2:C$72,C35) -> 64 | F35: =IF(D35=$E$2,C35,"") -> 8 | H35: 503 | I35: O | J35: 开间 | L35: =VLOOKUP(J35,'【3】大区填-楼栋基准格局定价'!B:H,7,0) -> 1647.8784 | M35: =IF(OR(J35="开间",J35="二人宿舍"),IF(N35<10,"很狭小",IF(N35<13,"较狭小",IF(N35<17,"适中",IF(N35<20,"较宽敞","很宽敞")))),IF(OR(J35="一居室",J35="四人宿舍"),IF(N35<20,"很狭小",IF(N35<23,"较狭小",IF(N35<26,"适中",IF(N35<28,"较宽敞","很宽敞")))),IF(OR(J35="二居室",J35="六人宿舍"),IF(N35<30,"很狭小",IF(N35<35,"较狭小",IF(N35<40,"适中",IF(N35<45,"较宽敞","很宽敞")))),""))) -> 适中 | N35: 13.87 | O35: =VLOOKUP($M$1&M35,【1】定价因子!E:F,2,0) -> 1 | P35: =IF(COUNTIFS(户型资产表!E:E,I35,户型资产表!H:H,"阳台门")>0,"有","无") -> 有 | Q35: =VLOOKUP($P$1&P35,【1】定价因子!E:F,2,0) -> 1.07 | R35: =IF('【2】运营中心填-基本信息&审核标准'!$D$4="是","无",IF(INT(H35/100)>9,"9F",INT(H35/100)&"F")) -> 无 | S35: =VLOOKUP(R35,【1】定价因子!D:F,3,0) -> 1 | T35: =IF('【2】运营中心填-基本信息&审核标准'!$D$4="否","无",IF(INT(H35/100)=1,"1F",IF(AND(INT(H35/100)>=2,INT(H35/100)<=3),"2-3F",IF(INT(H35/100)=4,"4F",IF(AND(INT(H35/100)>=5,INT(H35/100)<=6),"5-6F",IF(AND(INT(H35/100)>=7,INT(H35/100)<=8),"7-8F",IF(AND(INT(H35/100)>=9,INT(H35/100)<=10),"9-10F",IF(AND(INT(H35/100)>=11,INT(H35/100)<=12),"11-12F",IF(INT(H35/100)>=13,"13以上F",""))))))))) -> 5-6F | U35: =VLOOKUP($T$1&T35,【1】定价因子!E:F,2,0) -> 1.01 | V35: =IF(COUNTIFS(户型资产表!E:E,I35,户型资产表!H:H,"操作台")>0,"有","无") -> 有 | W35: =IF(COUNTIFS(户型资产表!E:E,I35,户型资产表!H:H,"书桌")>0,"有","无") -> 有 | X35: {=IF(SUMPRODUCT((户型资产表!E:E=I35)*((户型资产表!I:I="沙发01单人")+(户型资产表!I:I="单人沙发02")))>0,"有","无")} -> 无 | Y35: {=IF(SUMPRODUCT((户型资产表!E:E=I35)*((户型资产表!I:I="沙发02两人")+(户型资产表!I:I="双人沙发01")))>0,"有","无")} -> 无 | Z35: =IF(COUNTIFS(户型资产表!E:E,I35,户型资产表!H:H,"餐桌")>0,"有","无") -> 无 | AA35: =IF(COUNTIFS(户型资产表!E:E,I35,户型资产表!H:H,"吸油烟机")>0,"有","无") -> 无 | AB35: =IF(COUNTIFS(户型资产表!E:E,I35,户型资产表!H:H,"冰箱")>0,"有","无") -> 无 | AC35: =IF(COUNTIFS(户型资产表!E:E,I35,户型资产表!H:H,"电视柜")>0,"有","无") -> 无 | AD35: =IF(J35="开间",IF(AND(V35="无",W35="无"),"缺失",IF(AND(V35="无",W35="有"),"缺失（操作台）",IF(AND(V35="有",W35="无"),"缺失（书桌）",IF(AND(V35="有",W35="有"),IF(OR(AA35="有",Y35="有"),"充足（油烟机/双人沙发）",IF(OR(X35="有",Z35="有"),"充足（单人沙发/餐桌）",IF(AND(OR(X35="有",Y35="有"),Z35="有"),"非常充足","适中"))),"")))),"适中") -> 适中 | AE35: =VLOOKUP($AD$1&AD35,【1】定价因子!E:F,2,0) -> 1 | AF35: =IF(J35="一居室",IF(AND(V35="无",Y35="无",Z35="无"),"缺失",IF(OR(AND(Z35="有",V35="无",Y35="无"),AND(Z35="有",V35="无",Y35="有"),AND(Z35="有",V35="有",Y35="无"),AND(Z35="无",V35="有",Y35="无"),AND(Z35="无",V35="无",Y35="有")),"缺失（操作台/双人沙发）",IF(AND(V35="有",Y35="有",Z35="无"),"缺失（餐桌）",IF(AND(V35="有",Y35="有",Z35="有"),IF(AND(W35="无",AA35="有"),"充配（油烟机）",IF(AND(W35="有",AA35="无"),"充配（书桌）",IF(AND(W35="有",AA35="有"),"非常充配","适中"))),"")))),"适中") -> 适中 | AG35: =VLOOKUP($AF$1&AF35,【1】定价因子!E:F,2,0) -> 1 | AH35: =IF(J35="二居室",IF(AND(Y35="无",Z35="无",AC35="无",V35="无"),"缺失",IF(OR(AND(Y35="无",Z35="无",AC35="有"),AND(Y35="无",Z35="无",V35="有"),AND(Y35="无",Z35="无",AC35="有",V35="有"),AND(Y35="无",Z35="有",AC35="无"),AND(Y35="无",Z35="有",V35="无"),AND(Y35="无",Z35="有",AC35="有"),AND(Y35="无",Z35="有",V35="有"),AND(Y35="有",Z35="无",AC35="无"),AND(Y35="有",Z35="无",V35="无"),AND(Y35="有",Z35="无",AC35="有"),AND(Y35="有",Z35="无",V35="有")),"缺失（沙发/餐桌）",IF(AND(Y35="有",Z35="有",OR(AC35="无",V35="无")),"缺失（电视柜/操作台）",IF(AND(Y35="有",Z35="有",AC35="有",V35="有"),IF(OR(AA35="有",AB35="有"),"充配（油烟机/冰箱）",IF(AND(AA35="无",AB35="无"),"适中","")),"")))),"适中") -> 适中 | AI35: =VLOOKUP($AH$1&AH35,【1】定价因子!E:F,2,0) -> 1 | AJ35: =VLOOKUP(H35,'【3-1】大区填-采光基本要素'!A:H,8,0) -> 4 | AK35: =VLOOKUP($AJ$1&AJ35,【1】定价因子!E:F,2,0) -> 1.03 | AL35: =L35*PRODUCT(AG35,AK35,AE35,U35,S35,Q35,O35) -> 1834.2881 | AM35: 1660 | AN35: =AM35/AL35-1 -> -0.09501673
A36: ='【2】运营中心填-基本信息&审核标准'!$E$2 -> 兴围西4-11栋 | B36: =INT(H36/100) -> 5 | C36: =COUNTIF($B$2:$B$72,B36) -> 8 | D36: =COUNTIF(C$2:C$72,C36) -> 64 | F36: =IF(D36=$E$2,C36,"") -> 8 | H36: 504 | I36: P | J36: 开间 | L36: =VLOOKUP(J36,'【3】大区填-楼栋基准格局定价'!B:H,7,0) -> 1647.8784 | M36: 适中 | N36: 19.76 | O36: =VLOOKUP($M$1&M36,【1】定价因子!E:F,2,0) -> 1 | P36: =IF(COUNTIFS(户型资产表!E:E,I36,户型资产表!H:H,"阳台门")>0,"有","无") -> 无 | Q36: =VLOOKUP($P$1&P36,【1】定价因子!E:F,2,0) -> 1 | R36: =IF('【2】运营中心填-基本信息&审核标准'!$D$4="是","无",IF(INT(H36/100)>9,"9F",INT(H36/100)&"F")) -> 无 | S36: =VLOOKUP(R36,【1】定价因子!D:F,3,0) -> 1 | T36: =IF('【2】运营中心填-基本信息&审核标准'!$D$4="否","无",IF(INT(H36/100)=1,"1F",IF(AND(INT(H36/100)>=2,INT(H36/100)<=3),"2-3F",IF(INT(H36/100)=4,"4F",IF(AND(INT(H36/100)>=5,INT(H36/100)<=6),"5-6F",IF(AND(INT(H36/100)>=7,INT(H36/100)<=8),"7-8F",IF(AND(INT(H36/100)>=9,INT(H36/100)<=10),"9-10F",IF(AND(INT(H36/100)>=11,INT(H36/100)<=12),"11-12F",IF(INT(H36/100)>=13,"13以上F",""))))))))) -> 5-6F | U36: =VLOOKUP($T$1&T36,【1】定价因子!E:F,2,0) -> 1.01 | V36: =IF(COUNTIFS(户型资产表!E:E,I36,户型资产表!H:H,"操作台")>0,"有","无") -> 有 | W36: =IF(COUNTIFS(户型资产表!E:E,I36,户型资产表!H:H,"书桌")>0,"有","无") -> 有 | X36: {=IF(SUMPRODUCT((户型资产表!E:E=I36)*((户型资产表!I:I="沙发01单人")+(户型资产表!I:I="单人沙发02")))>0,"有","无")} -> 无 | Y36: {=IF(SUMPRODUCT((户型资产表!E:E=I36)*((户型资产表!I:I="沙发02两人")+(户型资产表!I:I="双人沙发01")))>0,"有","无")} -> 无 | Z36: =IF(COUNTIFS(户型资产表!E:E,I36,户型资产表!H:H,"餐桌")>0,"有","无") -> 无 | AA36: =IF(COUNTIFS(户型资产表!E:E,I36,户型资产表!H:H,"吸油烟机")>0,"有","无") -> 无 | AB36: =IF(COUNTIFS(户型资产表!E:E,I36,户型资产表!H:H,"冰箱")>0,"有","无") -> 无 | AC36: =IF(COUNTIFS(户型资产表!E:E,I36,户型资产表!H:H,"电视柜")>0,"有","无") -> 无 | AD36: =IF(J36="开间",IF(AND(V36="无",W36="无"),"缺失",IF(AND(V36="无",W36="有"),"缺失（操作台）",IF(AND(V36="有",W36="无"),"缺失（书桌）",IF(AND(V36="有",W36="有"),IF(OR(AA36="有",Y36="有"),"充足（油烟机/双人沙发）",IF(OR(X36="有",Z36="有"),"充足（单人沙发/餐桌）",IF(AND(OR(X36="有",Y36="有"),Z36="有"),"非常充足","适中"))),"")))),"适中") -> 适中 | AE36: =VLOOKUP($AD$1&AD36,【1】定价因子!E:F,2,0) -> 1 | AF36: =IF(J36="一居室",IF(AND(V36="无",Y36="无",Z36="无"),"缺失",IF(OR(AND(Z36="有",V36="无",Y36="无"),AND(Z36="有",V36="无",Y36="有"),AND(Z36="有",V36="有",Y36="无"),AND(Z36="无",V36="有",Y36="无"),AND(Z36="无",V36="无",Y36="有")),"缺失（操作台/双人沙发）",IF(AND(V36="有",Y36="有",Z36="无"),"缺失（餐桌）",IF(AND(V36="有",Y36="有",Z36="有"),IF(AND(W36="无",AA36="有"),"充配（油烟机）",IF(AND(W36="有",AA36="无"),"充配（书桌）",IF(AND(W36="有",AA36="有"),"非常充配","适中"))),"")))),"适中") -> 适中 | AG36: =VLOOKUP($AF$1&AF36,【1】定价因子!E:F,2,0) -> 1 | AH36: =IF(J36="二居室",IF(AND(Y36="无",Z36="无",AC36="无",V36="无"),"缺失",IF(OR(AND(Y36="无",Z36="无",AC36="有"),AND(Y36="无",Z36="无",V36="有"),AND(Y36="无",Z36="无",AC36="有",V36="有"),AND(Y36="无",Z36="有",AC36="无"),AND(Y36="无",Z36="有",V36="无"),AND(Y36="无",Z36="有",AC36="有"),AND(Y36="无",Z36="有",V36="有"),AND(Y36="有",Z36="无",AC36="无"),AND(Y36="有",Z36="无",V36="无"),AND(Y36="有",Z36="无",AC36="有"),AND(Y36="有",Z36="无",V36="有")),"缺失（沙发/餐桌）",IF(AND(Y36="有",Z36="有",OR(AC36="无",V36="无")),"缺失（电视柜/操作台）",IF(AND(Y36="有",Z36="有",AC36="有",V36="有"),IF(OR(AA36="有",AB36="有"),"充配（油烟机/冰箱）",IF(AND(AA36="无",AB36="无"),"适中","")),"")))),"适中") -> 适中 | AI36: =VLOOKUP($AH$1&AH36,【1】定价因子!E:F,2,0) -> 1 | AJ36: =VLOOKUP(H36,'【3-1】大区填-采光基本要素'!A:H,8,0) -> 2 | AK36: =VLOOKUP($AJ$1&AJ36,【1】定价因子!E:F,2,0) -> 0.96 | AL36: =L36*PRODUCT(AG36,AK36,AE36,U36,S36,Q36,O36) -> 1597.7829 | AM36: 1460 | AN36: =AM36/AL36-1 -> -0.086233804
A37: ='【2】运营中心填-基本信息&审核标准'!$E$2 -> 兴围西4-11栋 | B37: =INT(H37/100) -> 5 | C37: =COUNTIF($B$2:$B$72,B37) -> 8 | D37: =COUNTIF(C$2:C$72,C37) -> 64 | F37: =IF(D37=$E$2,C37,"") -> 8 | H37: 505 | I37: K | J37: 开间 | L37: =VLOOKUP(J37,'【3】大区填-楼栋基准格局定价'!B:H,7,0) -> 1647.8784 | M37: =IF(OR(J37="开间",J37="二人宿舍"),IF(N37<10,"很狭小",IF(N37<13,"较狭小",IF(N37<17,"适中",IF(N37<20,"较宽敞","很宽敞")))),IF(OR(J37="一居室",J37="四人宿舍"),IF(N37<20,"很狭小",IF(N37<23,"较狭小",IF(N37<26,"适中",IF(N37<28,"较宽敞","很宽敞")))),IF(OR(J37="二居室",J37="六人宿舍"),IF(N37<30,"很狭小",IF(N37<35,"较狭小",IF(N37<40,"适中",IF(N37<45,"较宽敞","很宽敞")))),""))) -> 适中 | N37: 13.79 | O37: =VLOOKUP($M$1&M37,【1】定价因子!E:F,2,0) -> 1 | P37: =IF(COUNTIFS(户型资产表!E:E,I37,户型资产表!H:H,"阳台门")>0,"有","无") -> 无 | Q37: =VLOOKUP($P$1&P37,【1】定价因子!E:F,2,0) -> 1 | R37: =IF('【2】运营中心填-基本信息&审核标准'!$D$4="是","无",IF(INT(H37/100)>9,"9F",INT(H37/100)&"F")) -> 无 | S37: =VLOOKUP(R37,【1】定价因子!D:F,3,0) -> 1 | T37: =IF('【2】运营中心填-基本信息&审核标准'!$D$4="否","无",IF(INT(H37/100)=1,"1F",IF(AND(INT(H37/100)>=2,INT(H37/100)<=3),"2-3F",IF(INT(H37/100)=4,"4F",IF(AND(INT(H37/100)>=5,INT(H37/100)<=6),"5-6F",IF(AND(INT(H37/100)>=7,INT(H37/100)<=8),"7-8F",IF(AND(INT(H37/100)>=9,INT(H37/100)<=10),"9-10F",IF(AND(INT(H37/100)>=11,INT(H37/100)<=12),"11-12F",IF(INT(H37/100)>=13,"13以上F",""))))))))) -> 5-6F | U37: =VLOOKUP($T$1&T37,【1】定价因子!E:F,2,0) -> 1.01 | V37: =IF(COUNTIFS(户型资产表!E:E,I37,户型资产表!H:H,"操作台")>0,"有","无") -> 有 | W37: =IF(COUNTIFS(户型资产表!E:E,I37,户型资产表!H:H,"书桌")>0,"有","无") -> 有 | X37: {=IF(SUMPRODUCT((户型资产表!E:E=I37)*((户型资产表!I:I="沙发01单人")+(户型资产表!I:I="单人沙发02")))>0,"有","无")} -> 无 | Y37: {=IF(SUMPRODUCT((户型资产表!E:E=I37)*((户型资产表!I:I="沙发02两人")+(户型资产表!I:I="双人沙发01")))>0,"有","无")} -> 无 | Z37: =IF(COUNTIFS(户型资产表!E:E,I37,户型资产表!H:H,"餐桌")>0,"有","无") -> 无 | AA37: =IF(COUNTIFS(户型资产表!E:E,I37,户型资产表!H:H,"吸油烟机")>0,"有","无") -> 无 | AB37: =IF(COUNTIFS(户型资产表!E:E,I37,户型资产表!H:H,"冰箱")>0,"有","无") -> 无 | AC37: =IF(COUNTIFS(户型资产表!E:E,I37,户型资产表!H:H,"电视柜")>0,"有","无") -> 无 | AD37: =IF(J37="开间",IF(AND(V37="无",W37="无"),"缺失",IF(AND(V37="无",W37="有"),"缺失（操作台）",IF(AND(V37="有",W37="无"),"缺失（书桌）",IF(AND(V37="有",W37="有"),IF(OR(AA37="有",Y37="有"),"充足（油烟机/双人沙发）",IF(OR(X37="有",Z37="有"),"充足（单人沙发/餐桌）",IF(AND(OR(X37="有",Y37="有"),Z37="有"),"非常充足","适中"))),"")))),"适中") -> 适中 | AE37: =VLOOKUP($AD$1&AD37,【1】定价因子!E:F,2,0) -> 1 | AF37: =IF(J37="一居室",IF(AND(V37="无",Y37="无",Z37="无"),"缺失",IF(OR(AND(Z37="有",V37="无",Y37="无"),AND(Z37="有",V37="无",Y37="有"),AND(Z37="有",V37="有",Y37="无"),AND(Z37="无",V37="有",Y37="无"),AND(Z37="无",V37="无",Y37="有")),"缺失（操作台/双人沙发）",IF(AND(V37="有",Y37="有",Z37="无"),"缺失（餐桌）",IF(AND(V37="有",Y37="有",Z37="有"),IF(AND(W37="无",AA37="有"),"充配（油烟机）",IF(AND(W37="有",AA37="无"),"充配（书桌）",IF(AND(W37="有",AA37="有"),"非常充配","适中"))),"")))),"适中") -> 适中 | AG37: =VLOOKUP($AF$1&AF37,【1】定价因子!E:F,2,0) -> 1 | AH37: =IF(J37="二居室",IF(AND(Y37="无",Z37="无",AC37="无",V37="无"),"缺失",IF(OR(AND(Y37="无",Z37="无",AC37="有"),AND(Y37="无",Z37="无",V37="有"),AND(Y37="无",Z37="无",AC37="有",V37="有"),AND(Y37="无",Z37="有",AC37="无"),AND(Y37="无",Z37="有",V37="无"),AND(Y37="无",Z37="有",AC37="有"),AND(Y37="无",Z37="有",V37="有"),AND(Y37="有",Z37="无",AC37="无"),AND(Y37="有",Z37="无",V37="无"),AND(Y37="有",Z37="无",AC37="有"),AND(Y37="有",Z37="无",V37="有")),"缺失（沙发/餐桌）",IF(AND(Y37="有",Z37="有",OR(AC37="无",V37="无")),"缺失（电视柜/操作台）",IF(AND(Y37="有",Z37="有",AC37="有",V37="有"),IF(OR(AA37="有",AB37="有"),"充配（油烟机/冰箱）",IF(AND(AA37="无",AB37="无"),"适中","")),"")))),"适中") -> 适中 | AI37: =VLOOKUP($AH$1&AH37,【1】定价因子!E:F,2,0) -> 1 | AJ37: =VLOOKUP(H37,'【3-1】大区填-采光基本要素'!A:H,8,0) -> 4 | AK37: =VLOOKUP($AJ$1&AJ37,【1】定价因子!E:F,2,0) -> 1.03 | AL37: =L37*PRODUCT(AG37,AK37,AE37,U37,S37,Q37,O37) -> 1714.2879 | AM37: 1560 | AN37: =AM37/AL37-1 -> -0.09000116
A38: ='【2】运营中心填-基本信息&审核标准'!$E$2 -> 兴围西4-11栋 | B38: =INT(H38/100) -> 5 | C38: =COUNTIF($B$2:$B$72,B38) -> 8 | D38: =COUNTIF(C$2:C$72,C38) -> 64 | F38: =IF(D38=$E$2,C38,"") -> 8 | H38: 506 | I38: L | J38: 一居室 | L38: =VLOOKUP(J38,'【3】大区填-楼栋基准格局定价'!B:H,7,0) -> 2445.5088 | M38: =IF(OR(J38="开间",J38="二人宿舍"),IF(N38<10,"很狭小",IF(N38<13,"较狭小",IF(N38<17,"适中",IF(N38<20,"较宽敞","很宽敞")))),IF(OR(J38="一居室",J38="四人宿舍"),IF(N38<20,"很狭小",IF(N38<23,"较狭小",IF(N38<26,"适中",IF(N38<28,"较宽敞","很宽敞")))),IF(OR(J38="二居室",J38="六人宿舍"),IF(N38<30,"很狭小",IF(N38<35,"较狭小",IF(N38<40,"适中",IF(N38<45,"较宽敞","很宽敞")))),""))) -> 很狭小 | N38: 11.35 | O38: =VLOOKUP($M$1&M38,【1】定价因子!E:F,2,0) -> 0.9 | P38: =IF(COUNTIFS(户型资产表!E:E,I38,户型资产表!H:H,"阳台门")>0,"有","无") -> 无 | Q38: =VLOOKUP($P$1&P38,【1】定价因子!E:F,2,0) -> 1 | R38: =IF('【2】运营中心填-基本信息&审核标准'!$D$4="是","无",IF(INT(H38/100)>9,"9F",INT(H38/100)&"F")) -> 无 | S38: =VLOOKUP(R38,【1】定价因子!D:F,3,0) -> 1 | T38: =IF('【2】运营中心填-基本信息&审核标准'!$D$4="否","无",IF(INT(H38/100)=1,"1F",IF(AND(INT(H38/100)>=2,INT(H38/100)<=3),"2-3F",IF(INT(H38/100)=4,"4F",IF(AND(INT(H38/100)>=5,INT(H38/100)<=6),"5-6F",IF(AND(INT(H38/100)>=7,INT(H38/100)<=8),"7-8F",IF(AND(INT(H38/100)>=9,INT(H38/100)<=10),"9-10F",IF(AND(INT(H38/100)>=11,INT(H38/100)<=12),"11-12F",IF(INT(H38/100)>=13,"13以上F",""))))))))) -> 5-6F | U38: =VLOOKUP($T$1&T38,【1】定价因子!E:F,2,0) -> 1.01 | V38: =IF(COUNTIFS(户型资产表!E:E,I38,户型资产表!H:H,"操作台")>0,"有","无") -> 有 | W38: =IF(COUNTIFS(户型资产表!E:E,I38,户型资产表!H:H,"书桌")>0,"有","无") -> 无 | X38: {=IF(SUMPRODUCT((户型资产表!E:E=I38)*((户型资产表!I:I="沙发01单人")+(户型资产表!I:I="单人沙发02")))>0,"有","无")} -> 无 | Y38: {=IF(SUMPRODUCT((户型资产表!E:E=I38)*((户型资产表!I:I="沙发02两人")+(户型资产表!I:I="双人沙发01")))>0,"有","无")} -> 有 | Z38: =IF(COUNTIFS(户型资产表!E:E,I38,户型资产表!H:H,"餐桌")>0,"有","无") -> 有 | AA38: =IF(COUNTIFS(户型资产表!E:E,I38,户型资产表!H:H,"吸油烟机")>0,"有","无") -> 无 | AB38: =IF(COUNTIFS(户型资产表!E:E,I38,户型资产表!H:H,"冰箱")>0,"有","无") -> 无 | AC38: =IF(COUNTIFS(户型资产表!E:E,I38,户型资产表!H:H,"电视柜")>0,"有","无") -> 无 | AD38: =IF(J38="开间",IF(AND(V38="无",W38="无"),"缺失",IF(AND(V38="无",W38="有"),"缺失（操作台）",IF(AND(V38="有",W38="无"),"缺失（书桌）",IF(AND(V38="有",W38="有"),IF(OR(AA38="有",Y38="有"),"充足（油烟机/双人沙发）",IF(OR(X38="有",Z38="有"),"充足（单人沙发/餐桌）",IF(AND(OR(X38="有",Y38="有"),Z38="有"),"非常充足","适中"))),"")))),"适中") -> 适中 | AE38: =VLOOKUP($AD$1&AD38,【1】定价因子!E:F,2,0) -> 1 | AF38: =IF(J38="一居室",IF(AND(V38="无",Y38="无",Z38="无"),"缺失",IF(OR(AND(Z38="有",V38="无",Y38="无"),AND(Z38="有",V38="无",Y38="有"),AND(Z38="有",V38="有",Y38="无"),AND(Z38="无",V38="有",Y38="无"),AND(Z38="无",V38="无",Y38="有")),"缺失（操作台/双人沙发）",IF(AND(V38="有",Y38="有",Z38="无"),"缺失（餐桌）",IF(AND(V38="有",Y38="有",Z38="有"),IF(AND(W38="无",AA38="有"),"充配（油烟机）",IF(AND(W38="有",AA38="无"),"充配（书桌）",IF(AND(W38="有",AA38="有"),"非常充配","适中"))),"")))),"适中") -> 适中 | AG38: =VLOOKUP($AF$1&AF38,【1】定价因子!E:F,2,0) -> 1 | AH38: =IF(J38="二居室",IF(AND(Y38="无",Z38="无",AC38="无",V38="无"),"缺失",IF(OR(AND(Y38="无",Z38="无",AC38="有"),AND(Y38="无",Z38="无",V38="有"),AND(Y38="无",Z38="无",AC38="有",V38="有"),AND(Y38="无",Z38="有",AC38="无"),AND(Y38="无",Z38="有",V38="无"),AND(Y38="无",Z38="有",AC38="有"),AND(Y38="无",Z38="有",V38="有"),AND(Y38="有",Z38="无",AC38="无"),AND(Y38="有",Z38="无",V38="无"),AND(Y38="有",Z38="无",AC38="有"),AND(Y38="有",Z38="无",V38="有")),"缺失（沙发/餐桌）",IF(AND(Y38="有",Z38="有",OR(AC38="无",V38="无")),"缺失（电视柜/操作台）",IF(AND(Y38="有",Z38="有",AC38="有",V38="有"),IF(OR(AA38="有",AB38="有"),"充配（油烟机/冰箱）",IF(AND(AA38="无",AB38="无"),"适中","")),"")))),"适中") -> 适中 | AI38: =VLOOKUP($AH$1&AH38,【1】定价因子!E:F,2,0) -> 1 | AJ38: =VLOOKUP(H38,'【3-1】大区填-采光基本要素'!A:H,8,0) -> 1 | AK38: =VLOOKUP($AJ$1&AJ38,【1】定价因子!E:F,2,0) -> 0.91 | AL38: =L38*PRODUCT(AG38,AK38,AE38,U38,S38,Q38,O38) -> 2022.9004 | AM38: 2000 | AN38: =AM38/AL38-1 -> -0.011320589
